Workbook

Sheet Start
A1: Monthly close workbook
A3: How this workbook works
A4: 1. Numbers enter only through the grey Data_ tabs. The runner fills them from your sources; you can also paste query results by hand.
A5: 2. Every other tab is formulas reading the Data_ tabs for a 12-month window ending at the as-of month.
A6: 3. Judgment inputs (forecast and capacity) live on the Overrides tab, seeded from config.yaml. Type an override in a yellow cell to test a scenario.
A7: Bad entries are ignored, not fatal: a word, an error or an out-of-range number falls back to the model value. Set the switch on Overrides to OFF to undo every override at once.
A8: 4. Grey-shaded cells on Checks and Summary are for people and the agent: owners, explanations, commentary.
A10: This close
A11: As-of month | B11: =Data_Params!$B$2
A12: Generated | B12: =Data_Params!$B$13
A13: Usage grain | B13: =Data_Params!$B$9
A14: Sources connected | B14: =Data_Params!$B$12
A15: Usage data from | B15: =Data_Params!$B$10
A16: Usage data to | B16: =Data_Params!$B$11
A17: Checks flagged | B17: =COUNTIF(Checks!$G$5:$G$154,"FLAG")
A18: Overrides | B18: =Overrides!$C$5
A20: Color key: blue = input, black = formula, green = link to another tab, yellow = key assumption, grey tab = data.

Sheet Summary
A1: =Data_Params!$B$14&" | Monthly close"
A2: Formulas only. Start here, then Checks. Every figure traces to a Data_ sheet and from there to a query in /sql.
A3: As-of month | B3: =Data_Params!$B$2 | C3: Sources | D3: =Data_Params!$B$12 | F3: Overrides | G3: =Overrides!$C$5
A5: Metric | B5: =Monthly!H4 | C5: =Monthly!I4 | D5: =Monthly!J4 | E5: =Monthly!K4 | F5: =Monthly!L4 | G5: =Monthly!M4
A6: Billable tokens per day (B) | B6: =Monthly!H12 | C6: =Monthly!I12 | D6: =Monthly!J12 | E6: =Monthly!K12 | F6: =Monthly!L12 | G6: =Monthly!M12
A7: Growth in tokens per day | B7: =Monthly!H16 | C7: =Monthly!I16 | D7: =Monthly!J16 | E7: =Monthly!K16 | F7: =Monthly!L16 | G7: =Monthly!M16
A8: Net revenue ($k) | B8: =Monthly!H34 | C8: =Monthly!I34 | D8: =Monthly!J34 | E8: =Monthly!K34 | F8: =Monthly!L34 | G8: =Monthly!M34
A9: Annualized run-rate ($k) | B9: =Monthly!H36 | C9: =Monthly!I36 | D9: =Monthly!J36 | E9: =Monthly!K36 | F9: =Monthly!L36 | G9: =Monthly!M36
A10: Enterprise share of revenue | B10: =Monthly!H37 | C10: =Monthly!I37 | D10: =Monthly!J37 | E10: =Monthly!K37 | F10: =Monthly!L37 | G10: =Monthly!M37
A11: Realized net price per M tokens | B11: =Monthly!H38 | C11: =Monthly!I38 | D11: =Monthly!J38 | E11: =Monthly!K38 | F11: =Monthly!L38 | G11: =Monthly!M38
A12: Active accounts | B12: =Monthly!H44 | C12: =Monthly!I44 | D12: =Monthly!J44 | E12: =Monthly!K44 | F12: =Monthly!L44 | G12: =Monthly!M44
A13: Paying accounts | B13: =Monthly!H45 | C13: =Monthly!I45 | D13: =Monthly!J45 | E13: =Monthly!K45 | F13: =Monthly!L45 | G13: =Monthly!M45
A14: Failed calls (not billed) | B14: =Monthly!H46 | C14: =Monthly!I46 | D14: =Monthly!J46 | E14: =Monthly!K46 | F14: =Monthly!L46 | G14: =Monthly!M46
A16: Close checks
A17: Flagged for review | B17: =COUNTIF(Checks!$G$5:$G$154,"FLAG")
A18: Informational | B18: =COUNTIF(Checks!$G$5:$G$154,"INFO")
A19: Skipped (source not connected) | B19: =COUNTIF(Checks!$G$5:$G$154,"SKIP")
A20: Passed | B20: =COUNTIF(Checks!$G$5:$G$154,"PASS")
A21: $ impact of flagged items | B21: =SUMIF(Checks!$G$5:$G$154,"FLAG",Checks!$F$5:$F$154)
A23: Forecast, tokens per day (B)
A24: Scenario | B24: =EDATE(Data_Params!$B$2,1) | C24: =EDATE(Data_Params!$B$2,2) | D24: =EDATE(Data_Params!$B$2,3)
A25: Low | B25: =Forecast!B127 | C25: =Forecast!C127 | D25: =Forecast!D127
A26: Base | B26: =Forecast!E127 | C26: =Forecast!F127 | D26: =Forecast!G127
A27: High | B27: =Forecast!H127 | C27: =Forecast!I127 | D27: =Forecast!J127
A28: Net revenue, base ($k) | B28: =Forecast!E135 | C28: =Forecast!F135 | D28: =Forecast!G135
A29: Last month's forecast vs actual (total) | B29: =IF(Forecast!E143="","no forecast on file",Forecast!E143)
A30: GPUs to reserve for serving | B30: =Capacity!B27
A32: Commentary (written by finance, or drafted by the agent per AGENT_BRIEF.md and reviewed before it goes anywhere)

Sheet Checks
A1: =Data_Params!$B$14&" | Close checks"
A2: Rules in sql/50_checks.sql (Data_Checks). FLAG = a person must look. Columns I-L are for people and the agent; they are not overwritten by formulas.
A4: # | B4: Check | C4: Scope | D4: Expected | E4: Actual | F4: $ impact | G4: Status | H4: Detail | I4: Owner | J4: Next step | K4: Explanation (agent draft) | L4: Reviewed by
A5: =IF(INDEX(Data_Checks!$A:$A,1+1)="","",INDEX(Data_Checks!$A:$A,1+1)) | B5: =IF(INDEX(Data_Checks!$B:$B,1+1)="","",INDEX(Data_Checks!$B:$B,1+1)) | C5: =IF(INDEX(Data_Checks!$C:$C,1+1)="","",INDEX(Data_Checks!$C:$C,1+1)) | D5: =IF(INDEX(Data_Checks!$D:$D,1+1)="","",INDEX(Data_Checks!$D:$D,1+1)) | E5: =IF(INDEX(Data_Checks!$E:$E,1+1)="","",INDEX(Data_Checks!$E:$E,1+1)) | F5: =IF(INDEX(Data_Checks!$F:$F,1+1)="","",INDEX(Data_Checks!$F:$F,1+1)) | G5: =IF(INDEX(Data_Checks!$G:$G,1+1)="","",INDEX(Data_Checks!$G:$G,1+1)) | H5: =IF(INDEX(Data_Checks!$H:$H,1+1)="","",INDEX(Data_Checks!$H:$H,1+1))
A6: =IF(INDEX(Data_Checks!$A:$A,2+1)="","",INDEX(Data_Checks!$A:$A,2+1)) | B6: =IF(INDEX(Data_Checks!$B:$B,2+1)="","",INDEX(Data_Checks!$B:$B,2+1)) | C6: =IF(INDEX(Data_Checks!$C:$C,2+1)="","",INDEX(Data_Checks!$C:$C,2+1)) | D6: =IF(INDEX(Data_Checks!$D:$D,2+1)="","",INDEX(Data_Checks!$D:$D,2+1)) | E6: =IF(INDEX(Data_Checks!$E:$E,2+1)="","",INDEX(Data_Checks!$E:$E,2+1)) | F6: =IF(INDEX(Data_Checks!$F:$F,2+1)="","",INDEX(Data_Checks!$F:$F,2+1)) | G6: =IF(INDEX(Data_Checks!$G:$G,2+1)="","",INDEX(Data_Checks!$G:$G,2+1)) | H6: =IF(INDEX(Data_Checks!$H:$H,2+1)="","",INDEX(Data_Checks!$H:$H,2+1))
A7: =IF(INDEX(Data_Checks!$A:$A,3+1)="","",INDEX(Data_Checks!$A:$A,3+1)) | B7: =IF(INDEX(Data_Checks!$B:$B,3+1)="","",INDEX(Data_Checks!$B:$B,3+1)) | C7: =IF(INDEX(Data_Checks!$C:$C,3+1)="","",INDEX(Data_Checks!$C:$C,3+1)) | D7: =IF(INDEX(Data_Checks!$D:$D,3+1)="","",INDEX(Data_Checks!$D:$D,3+1)) | E7: =IF(INDEX(Data_Checks!$E:$E,3+1)="","",INDEX(Data_Checks!$E:$E,3+1)) | F7: =IF(INDEX(Data_Checks!$F:$F,3+1)="","",INDEX(Data_Checks!$F:$F,3+1)) | G7: =IF(INDEX(Data_Checks!$G:$G,3+1)="","",INDEX(Data_Checks!$G:$G,3+1)) | H7: =IF(INDEX(Data_Checks!$H:$H,3+1)="","",INDEX(Data_Checks!$H:$H,3+1))
A8: =IF(INDEX(Data_Checks!$A:$A,4+1)="","",INDEX(Data_Checks!$A:$A,4+1)) | B8: =IF(INDEX(Data_Checks!$B:$B,4+1)="","",INDEX(Data_Checks!$B:$B,4+1)) | C8: =IF(INDEX(Data_Checks!$C:$C,4+1)="","",INDEX(Data_Checks!$C:$C,4+1)) | D8: =IF(INDEX(Data_Checks!$D:$D,4+1)="","",INDEX(Data_Checks!$D:$D,4+1)) | E8: =IF(INDEX(Data_Checks!$E:$E,4+1)="","",INDEX(Data_Checks!$E:$E,4+1)) | F8: =IF(INDEX(Data_Checks!$F:$F,4+1)="","",INDEX(Data_Checks!$F:$F,4+1)) | G8: =IF(INDEX(Data_Checks!$G:$G,4+1)="","",INDEX(Data_Checks!$G:$G,4+1)) | H8: =IF(INDEX(Data_Checks!$H:$H,4+1)="","",INDEX(Data_Checks!$H:$H,4+1))
A9: =IF(INDEX(Data_Checks!$A:$A,5+1)="","",INDEX(Data_Checks!$A:$A,5+1)) | B9: =IF(INDEX(Data_Checks!$B:$B,5+1)="","",INDEX(Data_Checks!$B:$B,5+1)) | C9: =IF(INDEX(Data_Checks!$C:$C,5+1)="","",INDEX(Data_Checks!$C:$C,5+1)) | D9: =IF(INDEX(Data_Checks!$D:$D,5+1)="","",INDEX(Data_Checks!$D:$D,5+1)) | E9: =IF(INDEX(Data_Checks!$E:$E,5+1)="","",INDEX(Data_Checks!$E:$E,5+1)) | F9: =IF(INDEX(Data_Checks!$F:$F,5+1)="","",INDEX(Data_Checks!$F:$F,5+1)) | G9: =IF(INDEX(Data_Checks!$G:$G,5+1)="","",INDEX(Data_Checks!$G:$G,5+1)) | H9: =IF(INDEX(Data_Checks!$H:$H,5+1)="","",INDEX(Data_Checks!$H:$H,5+1))
A10: =IF(INDEX(Data_Checks!$A:$A,6+1)="","",INDEX(Data_Checks!$A:$A,6+1)) | B10: =IF(INDEX(Data_Checks!$B:$B,6+1)="","",INDEX(Data_Checks!$B:$B,6+1)) | C10: =IF(INDEX(Data_Checks!$C:$C,6+1)="","",INDEX(Data_Checks!$C:$C,6+1)) | D10: =IF(INDEX(Data_Checks!$D:$D,6+1)="","",INDEX(Data_Checks!$D:$D,6+1)) | E10: =IF(INDEX(Data_Checks!$E:$E,6+1)="","",INDEX(Data_Checks!$E:$E,6+1)) | F10: =IF(INDEX(Data_Checks!$F:$F,6+1)="","",INDEX(Data_Checks!$F:$F,6+1)) | G10: =IF(INDEX(Data_Checks!$G:$G,6+1)="","",INDEX(Data_Checks!$G:$G,6+1)) | H10: =IF(INDEX(Data_Checks!$H:$H,6+1)="","",INDEX(Data_Checks!$H:$H,6+1))
A11: =IF(INDEX(Data_Checks!$A:$A,7+1)="","",INDEX(Data_Checks!$A:$A,7+1)) | B11: =IF(INDEX(Data_Checks!$B:$B,7+1)="","",INDEX(Data_Checks!$B:$B,7+1)) | C11: =IF(INDEX(Data_Checks!$C:$C,7+1)="","",INDEX(Data_Checks!$C:$C,7+1)) | D11: =IF(INDEX(Data_Checks!$D:$D,7+1)="","",INDEX(Data_Checks!$D:$D,7+1)) | E11: =IF(INDEX(Data_Checks!$E:$E,7+1)="","",INDEX(Data_Checks!$E:$E,7+1)) | F11: =IF(INDEX(Data_Checks!$F:$F,7+1)="","",INDEX(Data_Checks!$F:$F,7+1)) | G11: =IF(INDEX(Data_Checks!$G:$G,7+1)="","",INDEX(Data_Checks!$G:$G,7+1)) | H11: =IF(INDEX(Data_Checks!$H:$H,7+1)="","",INDEX(Data_Checks!$H:$H,7+1))
A12: =IF(INDEX(Data_Checks!$A:$A,8+1)="","",INDEX(Data_Checks!$A:$A,8+1)) | B12: =IF(INDEX(Data_Checks!$B:$B,8+1)="","",INDEX(Data_Checks!$B:$B,8+1)) | C12: =IF(INDEX(Data_Checks!$C:$C,8+1)="","",INDEX(Data_Checks!$C:$C,8+1)) | D12: =IF(INDEX(Data_Checks!$D:$D,8+1)="","",INDEX(Data_Checks!$D:$D,8+1)) | E12: =IF(INDEX(Data_Checks!$E:$E,8+1)="","",INDEX(Data_Checks!$E:$E,8+1)) | F12: =IF(INDEX(Data_Checks!$F:$F,8+1)="","",INDEX(Data_Checks!$F:$F,8+1)) | G12: =IF(INDEX(Data_Checks!$G:$G,8+1)="","",INDEX(Data_Checks!$G:$G,8+1)) | H12: =IF(INDEX(Data_Checks!$H:$H,8+1)="","",INDEX(Data_Checks!$H:$H,8+1))
A13: =IF(INDEX(Data_Checks!$A:$A,9+1)="","",INDEX(Data_Checks!$A:$A,9+1)) | B13: =IF(INDEX(Data_Checks!$B:$B,9+1)="","",INDEX(Data_Checks!$B:$B,9+1)) | C13: =IF(INDEX(Data_Checks!$C:$C,9+1)="","",INDEX(Data_Checks!$C:$C,9+1)) | D13: =IF(INDEX(Data_Checks!$D:$D,9+1)="","",INDEX(Data_Checks!$D:$D,9+1)) | E13: =IF(INDEX(Data_Checks!$E:$E,9+1)="","",INDEX(Data_Checks!$E:$E,9+1)) | F13: =IF(INDEX(Data_Checks!$F:$F,9+1)="","",INDEX(Data_Checks!$F:$F,9+1)) | G13: =IF(INDEX(Data_Checks!$G:$G,9+1)="","",INDEX(Data_Checks!$G:$G,9+1)) | H13: =IF(INDEX(Data_Checks!$H:$H,9+1)="","",INDEX(Data_Checks!$H:$H,9+1))
A14: =IF(INDEX(Data_Checks!$A:$A,10+1)="","",INDEX(Data_Checks!$A:$A,10+1)) | B14: =IF(INDEX(Data_Checks!$B:$B,10+1)="","",INDEX(Data_Checks!$B:$B,10+1)) | C14: =IF(INDEX(Data_Checks!$C:$C,10+1)="","",INDEX(Data_Checks!$C:$C,10+1)) | D14: =IF(INDEX(Data_Checks!$D:$D,10+1)="","",INDEX(Data_Checks!$D:$D,10+1)) | E14: =IF(INDEX(Data_Checks!$E:$E,10+1)="","",INDEX(Data_Checks!$E:$E,10+1)) | F14: =IF(INDEX(Data_Checks!$F:$F,10+1)="","",INDEX(Data_Checks!$F:$F,10+1)) | G14: =IF(INDEX(Data_Checks!$G:$G,10+1)="","",INDEX(Data_Checks!$G:$G,10+1)) | H14: =IF(INDEX(Data_Checks!$H:$H,10+1)="","",INDEX(Data_Checks!$H:$H,10+1))
A15: =IF(INDEX(Data_Checks!$A:$A,11+1)="","",INDEX(Data_Checks!$A:$A,11+1)) | B15: =IF(INDEX(Data_Checks!$B:$B,11+1)="","",INDEX(Data_Checks!$B:$B,11+1)) | C15: =IF(INDEX(Data_Checks!$C:$C,11+1)="","",INDEX(Data_Checks!$C:$C,11+1)) | D15: =IF(INDEX(Data_Checks!$D:$D,11+1)="","",INDEX(Data_Checks!$D:$D,11+1)) | E15: =IF(INDEX(Data_Checks!$E:$E,11+1)="","",INDEX(Data_Checks!$E:$E,11+1)) | F15: =IF(INDEX(Data_Checks!$F:$F,11+1)="","",INDEX(Data_Checks!$F:$F,11+1)) | G15: =IF(INDEX(Data_Checks!$G:$G,11+1)="","",INDEX(Data_Checks!$G:$G,11+1)) | H15: =IF(INDEX(Data_Checks!$H:$H,11+1)="","",INDEX(Data_Checks!$H:$H,11+1))
A16: =IF(INDEX(Data_Checks!$A:$A,12+1)="","",INDEX(Data_Checks!$A:$A,12+1)) | B16: =IF(INDEX(Data_Checks!$B:$B,12+1)="","",INDEX(Data_Checks!$B:$B,12+1)) | C16: =IF(INDEX(Data_Checks!$C:$C,12+1)="","",INDEX(Data_Checks!$C:$C,12+1)) | D16: =IF(INDEX(Data_Checks!$D:$D,12+1)="","",INDEX(Data_Checks!$D:$D,12+1)) | E16: =IF(INDEX(Data_Checks!$E:$E,12+1)="","",INDEX(Data_Checks!$E:$E,12+1)) | F16: =IF(INDEX(Data_Checks!$F:$F,12+1)="","",INDEX(Data_Checks!$F:$F,12+1)) | G16: =IF(INDEX(Data_Checks!$G:$G,12+1)="","",INDEX(Data_Checks!$G:$G,12+1)) | H16: =IF(INDEX(Data_Checks!$H:$H,12+1)="","",INDEX(Data_Checks!$H:$H,12+1))
A17: =IF(INDEX(Data_Checks!$A:$A,13+1)="","",INDEX(Data_Checks!$A:$A,13+1)) | B17: =IF(INDEX(Data_Checks!$B:$B,13+1)="","",INDEX(Data_Checks!$B:$B,13+1)) | C17: =IF(INDEX(Data_Checks!$C:$C,13+1)="","",INDEX(Data_Checks!$C:$C,13+1)) | D17: =IF(INDEX(Data_Checks!$D:$D,13+1)="","",INDEX(Data_Checks!$D:$D,13+1)) | E17: =IF(INDEX(Data_Checks!$E:$E,13+1)="","",INDEX(Data_Checks!$E:$E,13+1)) | F17: =IF(INDEX(Data_Checks!$F:$F,13+1)="","",INDEX(Data_Checks!$F:$F,13+1)) | G17: =IF(INDEX(Data_Checks!$G:$G,13+1)="","",INDEX(Data_Checks!$G:$G,13+1)) | H17: =IF(INDEX(Data_Checks!$H:$H,13+1)="","",INDEX(Data_Checks!$H:$H,13+1))
A18: =IF(INDEX(Data_Checks!$A:$A,14+1)="","",INDEX(Data_Checks!$A:$A,14+1)) | B18: =IF(INDEX(Data_Checks!$B:$B,14+1)="","",INDEX(Data_Checks!$B:$B,14+1)) | C18: =IF(INDEX(Data_Checks!$C:$C,14+1)="","",INDEX(Data_Checks!$C:$C,14+1)) | D18: =IF(INDEX(Data_Checks!$D:$D,14+1)="","",INDEX(Data_Checks!$D:$D,14+1)) | E18: =IF(INDEX(Data_Checks!$E:$E,14+1)="","",INDEX(Data_Checks!$E:$E,14+1)) | F18: =IF(INDEX(Data_Checks!$F:$F,14+1)="","",INDEX(Data_Checks!$F:$F,14+1)) | G18: =IF(INDEX(Data_Checks!$G:$G,14+1)="","",INDEX(Data_Checks!$G:$G,14+1)) | H18: =IF(INDEX(Data_Checks!$H:$H,14+1)="","",INDEX(Data_Checks!$H:$H,14+1))
A19: =IF(INDEX(Data_Checks!$A:$A,15+1)="","",INDEX(Data_Checks!$A:$A,15+1)) | B19: =IF(INDEX(Data_Checks!$B:$B,15+1)="","",INDEX(Data_Checks!$B:$B,15+1)) | C19: =IF(INDEX(Data_Checks!$C:$C,15+1)="","",INDEX(Data_Checks!$C:$C,15+1)) | D19: =IF(INDEX(Data_Checks!$D:$D,15+1)="","",INDEX(Data_Checks!$D:$D,15+1)) | E19: =IF(INDEX(Data_Checks!$E:$E,15+1)="","",INDEX(Data_Checks!$E:$E,15+1)) | F19: =IF(INDEX(Data_Checks!$F:$F,15+1)="","",INDEX(Data_Checks!$F:$F,15+1)) | G19: =IF(INDEX(Data_Checks!$G:$G,15+1)="","",INDEX(Data_Checks!$G:$G,15+1)) | H19: =IF(INDEX(Data_Checks!$H:$H,15+1)="","",INDEX(Data_Checks!$H:$H,15+1))
A20: =IF(INDEX(Data_Checks!$A:$A,16+1)="","",INDEX(Data_Checks!$A:$A,16+1)) | B20: =IF(INDEX(Data_Checks!$B:$B,16+1)="","",INDEX(Data_Checks!$B:$B,16+1)) | C20: =IF(INDEX(Data_Checks!$C:$C,16+1)="","",INDEX(Data_Checks!$C:$C,16+1)) | D20: =IF(INDEX(Data_Checks!$D:$D,16+1)="","",INDEX(Data_Checks!$D:$D,16+1)) | E20: =IF(INDEX(Data_Checks!$E:$E,16+1)="","",INDEX(Data_Checks!$E:$E,16+1)) | F20: =IF(INDEX(Data_Checks!$F:$F,16+1)="","",INDEX(Data_Checks!$F:$F,16+1)) | G20: =IF(INDEX(Data_Checks!$G:$G,16+1)="","",INDEX(Data_Checks!$G:$G,16+1)) | H20: =IF(INDEX(Data_Checks!$H:$H,16+1)="","",INDEX(Data_Checks!$H:$H,16+1))
A21: =IF(INDEX(Data_Checks!$A:$A,17+1)="","",INDEX(Data_Checks!$A:$A,17+1)) | B21: =IF(INDEX(Data_Checks!$B:$B,17+1)="","",INDEX(Data_Checks!$B:$B,17+1)) | C21: =IF(INDEX(Data_Checks!$C:$C,17+1)="","",INDEX(Data_Checks!$C:$C,17+1)) | D21: =IF(INDEX(Data_Checks!$D:$D,17+1)="","",INDEX(Data_Checks!$D:$D,17+1)) | E21: =IF(INDEX(Data_Checks!$E:$E,17+1)="","",INDEX(Data_Checks!$E:$E,17+1)) | F21: =IF(INDEX(Data_Checks!$F:$F,17+1)="","",INDEX(Data_Checks!$F:$F,17+1)) | G21: =IF(INDEX(Data_Checks!$G:$G,17+1)="","",INDEX(Data_Checks!$G:$G,17+1)) | H21: =IF(INDEX(Data_Checks!$H:$H,17+1)="","",INDEX(Data_Checks!$H:$H,17+1))
A22: =IF(INDEX(Data_Checks!$A:$A,18+1)="","",INDEX(Data_Checks!$A:$A,18+1)) | B22: =IF(INDEX(Data_Checks!$B:$B,18+1)="","",INDEX(Data_Checks!$B:$B,18+1)) | C22: =IF(INDEX(Data_Checks!$C:$C,18+1)="","",INDEX(Data_Checks!$C:$C,18+1)) | D22: =IF(INDEX(Data_Checks!$D:$D,18+1)="","",INDEX(Data_Checks!$D:$D,18+1)) | E22: =IF(INDEX(Data_Checks!$E:$E,18+1)="","",INDEX(Data_Checks!$E:$E,18+1)) | F22: =IF(INDEX(Data_Checks!$F:$F,18+1)="","",INDEX(Data_Checks!$F:$F,18+1)) | G22: =IF(INDEX(Data_Checks!$G:$G,18+1)="","",INDEX(Data_Checks!$G:$G,18+1)) | H22: =IF(INDEX(Data_Checks!$H:$H,18+1)="","",INDEX(Data_Checks!$H:$H,18+1))
A23: =IF(INDEX(Data_Checks!$A:$A,19+1)="","",INDEX(Data_Checks!$A:$A,19+1)) | B23: =IF(INDEX(Data_Checks!$B:$B,19+1)="","",INDEX(Data_Checks!$B:$B,19+1)) | C23: =IF(INDEX(Data_Checks!$C:$C,19+1)="","",INDEX(Data_Checks!$C:$C,19+1)) | D23: =IF(INDEX(Data_Checks!$D:$D,19+1)="","",INDEX(Data_Checks!$D:$D,19+1)) | E23: =IF(INDEX(Data_Checks!$E:$E,19+1)="","",INDEX(Data_Checks!$E:$E,19+1)) | F23: =IF(INDEX(Data_Checks!$F:$F,19+1)="","",INDEX(Data_Checks!$F:$F,19+1)) | G23: =IF(INDEX(Data_Checks!$G:$G,19+1)="","",INDEX(Data_Checks!$G:$G,19+1)) | H23: =IF(INDEX(Data_Checks!$H:$H,19+1)="","",INDEX(Data_Checks!$H:$H,19+1))
A24: =IF(INDEX(Data_Checks!$A:$A,20+1)="","",INDEX(Data_Checks!$A:$A,20+1)) | B24: =IF(INDEX(Data_Checks!$B:$B,20+1)="","",INDEX(Data_Checks!$B:$B,20+1)) | C24: =IF(INDEX(Data_Checks!$C:$C,20+1)="","",INDEX(Data_Checks!$C:$C,20+1)) | D24: =IF(INDEX(Data_Checks!$D:$D,20+1)="","",INDEX(Data_Checks!$D:$D,20+1)) | E24: =IF(INDEX(Data_Checks!$E:$E,20+1)="","",INDEX(Data_Checks!$E:$E,20+1)) | F24: =IF(INDEX(Data_Checks!$F:$F,20+1)="","",INDEX(Data_Checks!$F:$F,20+1)) | G24: =IF(INDEX(Data_Checks!$G:$G,20+1)="","",INDEX(Data_Checks!$G:$G,20+1)) | H24: =IF(INDEX(Data_Checks!$H:$H,20+1)="","",INDEX(Data_Checks!$H:$H,20+1))
A25: =IF(INDEX(Data_Checks!$A:$A,21+1)="","",INDEX(Data_Checks!$A:$A,21+1)) | B25: =IF(INDEX(Data_Checks!$B:$B,21+1)="","",INDEX(Data_Checks!$B:$B,21+1)) | C25: =IF(INDEX(Data_Checks!$C:$C,21+1)="","",INDEX(Data_Checks!$C:$C,21+1)) | D25: =IF(INDEX(Data_Checks!$D:$D,21+1)="","",INDEX(Data_Checks!$D:$D,21+1)) | E25: =IF(INDEX(Data_Checks!$E:$E,21+1)="","",INDEX(Data_Checks!$E:$E,21+1)) | F25: =IF(INDEX(Data_Checks!$F:$F,21+1)="","",INDEX(Data_Checks!$F:$F,21+1)) | G25: =IF(INDEX(Data_Checks!$G:$G,21+1)="","",INDEX(Data_Checks!$G:$G,21+1)) | H25: =IF(INDEX(Data_Checks!$H:$H,21+1)="","",INDEX(Data_Checks!$H:$H,21+1))
A26: =IF(INDEX(Data_Checks!$A:$A,22+1)="","",INDEX(Data_Checks!$A:$A,22+1)) | B26: =IF(INDEX(Data_Checks!$B:$B,22+1)="","",INDEX(Data_Checks!$B:$B,22+1)) | C26: =IF(INDEX(Data_Checks!$C:$C,22+1)="","",INDEX(Data_Checks!$C:$C,22+1)) | D26: =IF(INDEX(Data_Checks!$D:$D,22+1)="","",INDEX(Data_Checks!$D:$D,22+1)) | E26: =IF(INDEX(Data_Checks!$E:$E,22+1)="","",INDEX(Data_Checks!$E:$E,22+1)) | F26: =IF(INDEX(Data_Checks!$F:$F,22+1)="","",INDEX(Data_Checks!$F:$F,22+1)) | G26: =IF(INDEX(Data_Checks!$G:$G,22+1)="","",INDEX(Data_Checks!$G:$G,22+1)) | H26: =IF(INDEX(Data_Checks!$H:$H,22+1)="","",INDEX(Data_Checks!$H:$H,22+1))
A27: =IF(INDEX(Data_Checks!$A:$A,23+1)="","",INDEX(Data_Checks!$A:$A,23+1)) | B27: =IF(INDEX(Data_Checks!$B:$B,23+1)="","",INDEX(Data_Checks!$B:$B,23+1)) | C27: =IF(INDEX(Data_Checks!$C:$C,23+1)="","",INDEX(Data_Checks!$C:$C,23+1)) | D27: =IF(INDEX(Data_Checks!$D:$D,23+1)="","",INDEX(Data_Checks!$D:$D,23+1)) | E27: =IF(INDEX(Data_Checks!$E:$E,23+1)="","",INDEX(Data_Checks!$E:$E,23+1)) | F27: =IF(INDEX(Data_Checks!$F:$F,23+1)="","",INDEX(Data_Checks!$F:$F,23+1)) | G27: =IF(INDEX(Data_Checks!$G:$G,23+1)="","",INDEX(Data_Checks!$G:$G,23+1)) | H27: =IF(INDEX(Data_Checks!$H:$H,23+1)="","",INDEX(Data_Checks!$H:$H,23+1))
A28: =IF(INDEX(Data_Checks!$A:$A,24+1)="","",INDEX(Data_Checks!$A:$A,24+1)) | B28: =IF(INDEX(Data_Checks!$B:$B,24+1)="","",INDEX(Data_Checks!$B:$B,24+1)) | C28: =IF(INDEX(Data_Checks!$C:$C,24+1)="","",INDEX(Data_Checks!$C:$C,24+1)) | D28: =IF(INDEX(Data_Checks!$D:$D,24+1)="","",INDEX(Data_Checks!$D:$D,24+1)) | E28: =IF(INDEX(Data_Checks!$E:$E,24+1)="","",INDEX(Data_Checks!$E:$E,24+1)) | F28: =IF(INDEX(Data_Checks!$F:$F,24+1)="","",INDEX(Data_Checks!$F:$F,24+1)) | G28: =IF(INDEX(Data_Checks!$G:$G,24+1)="","",INDEX(Data_Checks!$G:$G,24+1)) | H28: =IF(INDEX(Data_Checks!$H:$H,24+1)="","",INDEX(Data_Checks!$H:$H,24+1))
A29: =IF(INDEX(Data_Checks!$A:$A,25+1)="","",INDEX(Data_Checks!$A:$A,25+1)) | B29: =IF(INDEX(Data_Checks!$B:$B,25+1)="","",INDEX(Data_Checks!$B:$B,25+1)) | C29: =IF(INDEX(Data_Checks!$C:$C,25+1)="","",INDEX(Data_Checks!$C:$C,25+1)) | D29: =IF(INDEX(Data_Checks!$D:$D,25+1)="","",INDEX(Data_Checks!$D:$D,25+1)) | E29: =IF(INDEX(Data_Checks!$E:$E,25+1)="","",INDEX(Data_Checks!$E:$E,25+1)) | F29: =IF(INDEX(Data_Checks!$F:$F,25+1)="","",INDEX(Data_Checks!$F:$F,25+1)) | G29: =IF(INDEX(Data_Checks!$G:$G,25+1)="","",INDEX(Data_Checks!$G:$G,25+1)) | H29: =IF(INDEX(Data_Checks!$H:$H,25+1)="","",INDEX(Data_Checks!$H:$H,25+1))
A30: =IF(INDEX(Data_Checks!$A:$A,26+1)="","",INDEX(Data_Checks!$A:$A,26+1)) | B30: =IF(INDEX(Data_Checks!$B:$B,26+1)="","",INDEX(Data_Checks!$B:$B,26+1)) | C30: =IF(INDEX(Data_Checks!$C:$C,26+1)="","",INDEX(Data_Checks!$C:$C,26+1)) | D30: =IF(INDEX(Data_Checks!$D:$D,26+1)="","",INDEX(Data_Checks!$D:$D,26+1)) | E30: =IF(INDEX(Data_Checks!$E:$E,26+1)="","",INDEX(Data_Checks!$E:$E,26+1)) | F30: =IF(INDEX(Data_Checks!$F:$F,26+1)="","",INDEX(Data_Checks!$F:$F,26+1)) | G30: =IF(INDEX(Data_Checks!$G:$G,26+1)="","",INDEX(Data_Checks!$G:$G,26+1)) | H30: =IF(INDEX(Data_Checks!$H:$H,26+1)="","",INDEX(Data_Checks!$H:$H,26+1))
A31: =IF(INDEX(Data_Checks!$A:$A,27+1)="","",INDEX(Data_Checks!$A:$A,27+1)) | B31: =IF(INDEX(Data_Checks!$B:$B,27+1)="","",INDEX(Data_Checks!$B:$B,27+1)) | C31: =IF(INDEX(Data_Checks!$C:$C,27+1)="","",INDEX(Data_Checks!$C:$C,27+1)) | D31: =IF(INDEX(Data_Checks!$D:$D,27+1)="","",INDEX(Data_Checks!$D:$D,27+1)) | E31: =IF(INDEX(Data_Checks!$E:$E,27+1)="","",INDEX(Data_Checks!$E:$E,27+1)) | F31: =IF(INDEX(Data_Checks!$F:$F,27+1)="","",INDEX(Data_Checks!$F:$F,27+1)) | G31: =IF(INDEX(Data_Checks!$G:$G,27+1)="","",INDEX(Data_Checks!$G:$G,27+1)) | H31: =IF(INDEX(Data_Checks!$H:$H,27+1)="","",INDEX(Data_Checks!$H:$H,27+1))
A32: =IF(INDEX(Data_Checks!$A:$A,28+1)="","",INDEX(Data_Checks!$A:$A,28+1)) | B32: =IF(INDEX(Data_Checks!$B:$B,28+1)="","",INDEX(Data_Checks!$B:$B,28+1)) | C32: =IF(INDEX(Data_Checks!$C:$C,28+1)="","",INDEX(Data_Checks!$C:$C,28+1)) | D32: =IF(INDEX(Data_Checks!$D:$D,28+1)="","",INDEX(Data_Checks!$D:$D,28+1)) | E32: =IF(INDEX(Data_Checks!$E:$E,28+1)="","",INDEX(Data_Checks!$E:$E,28+1)) | F32: =IF(INDEX(Data_Checks!$F:$F,28+1)="","",INDEX(Data_Checks!$F:$F,28+1)) | G32: =IF(INDEX(Data_Checks!$G:$G,28+1)="","",INDEX(Data_Checks!$G:$G,28+1)) | H32: =IF(INDEX(Data_Checks!$H:$H,28+1)="","",INDEX(Data_Checks!$H:$H,28+1))
A33: =IF(INDEX(Data_Checks!$A:$A,29+1)="","",INDEX(Data_Checks!$A:$A,29+1)) | B33: =IF(INDEX(Data_Checks!$B:$B,29+1)="","",INDEX(Data_Checks!$B:$B,29+1)) | C33: =IF(INDEX(Data_Checks!$C:$C,29+1)="","",INDEX(Data_Checks!$C:$C,29+1)) | D33: =IF(INDEX(Data_Checks!$D:$D,29+1)="","",INDEX(Data_Checks!$D:$D,29+1)) | E33: =IF(INDEX(Data_Checks!$E:$E,29+1)="","",INDEX(Data_Checks!$E:$E,29+1)) | F33: =IF(INDEX(Data_Checks!$F:$F,29+1)="","",INDEX(Data_Checks!$F:$F,29+1)) | G33: =IF(INDEX(Data_Checks!$G:$G,29+1)="","",INDEX(Data_Checks!$G:$G,29+1)) | H33: =IF(INDEX(Data_Checks!$H:$H,29+1)="","",INDEX(Data_Checks!$H:$H,29+1))
A34: =IF(INDEX(Data_Checks!$A:$A,30+1)="","",INDEX(Data_Checks!$A:$A,30+1)) | B34: =IF(INDEX(Data_Checks!$B:$B,30+1)="","",INDEX(Data_Checks!$B:$B,30+1)) | C34: =IF(INDEX(Data_Checks!$C:$C,30+1)="","",INDEX(Data_Checks!$C:$C,30+1)) | D34: =IF(INDEX(Data_Checks!$D:$D,30+1)="","",INDEX(Data_Checks!$D:$D,30+1)) | E34: =IF(INDEX(Data_Checks!$E:$E,30+1)="","",INDEX(Data_Checks!$E:$E,30+1)) | F34: =IF(INDEX(Data_Checks!$F:$F,30+1)="","",INDEX(Data_Checks!$F:$F,30+1)) | G34: =IF(INDEX(Data_Checks!$G:$G,30+1)="","",INDEX(Data_Checks!$G:$G,30+1)) | H34: =IF(INDEX(Data_Checks!$H:$H,30+1)="","",INDEX(Data_Checks!$H:$H,30+1))
A35: =IF(INDEX(Data_Checks!$A:$A,31+1)="","",INDEX(Data_Checks!$A:$A,31+1)) | B35: =IF(INDEX(Data_Checks!$B:$B,31+1)="","",INDEX(Data_Checks!$B:$B,31+1)) | C35: =IF(INDEX(Data_Checks!$C:$C,31+1)="","",INDEX(Data_Checks!$C:$C,31+1)) | D35: =IF(INDEX(Data_Checks!$D:$D,31+1)="","",INDEX(Data_Checks!$D:$D,31+1)) | E35: =IF(INDEX(Data_Checks!$E:$E,31+1)="","",INDEX(Data_Checks!$E:$E,31+1)) | F35: =IF(INDEX(Data_Checks!$F:$F,31+1)="","",INDEX(Data_Checks!$F:$F,31+1)) | G35: =IF(INDEX(Data_Checks!$G:$G,31+1)="","",INDEX(Data_Checks!$G:$G,31+1)) | H35: =IF(INDEX(Data_Checks!$H:$H,31+1)="","",INDEX(Data_Checks!$H:$H,31+1))
A36: =IF(INDEX(Data_Checks!$A:$A,32+1)="","",INDEX(Data_Checks!$A:$A,32+1)) | B36: =IF(INDEX(Data_Checks!$B:$B,32+1)="","",INDEX(Data_Checks!$B:$B,32+1)) | C36: =IF(INDEX(Data_Checks!$C:$C,32+1)="","",INDEX(Data_Checks!$C:$C,32+1)) | D36: =IF(INDEX(Data_Checks!$D:$D,32+1)="","",INDEX(Data_Checks!$D:$D,32+1)) | E36: =IF(INDEX(Data_Checks!$E:$E,32+1)="","",INDEX(Data_Checks!$E:$E,32+1)) | F36: =IF(INDEX(Data_Checks!$F:$F,32+1)="","",INDEX(Data_Checks!$F:$F,32+1)) | G36: =IF(INDEX(Data_Checks!$G:$G,32+1)="","",INDEX(Data_Checks!$G:$G,32+1)) | H36: =IF(INDEX(Data_Checks!$H:$H,32+1)="","",INDEX(Data_Checks!$H:$H,32+1))
A37: =IF(INDEX(Data_Checks!$A:$A,33+1)="","",INDEX(Data_Checks!$A:$A,33+1)) | B37: =IF(INDEX(Data_Checks!$B:$B,33+1)="","",INDEX(Data_Checks!$B:$B,33+1)) | C37: =IF(INDEX(Data_Checks!$C:$C,33+1)="","",INDEX(Data_Checks!$C:$C,33+1)) | D37: =IF(INDEX(Data_Checks!$D:$D,33+1)="","",INDEX(Data_Checks!$D:$D,33+1)) | E37: =IF(INDEX(Data_Checks!$E:$E,33+1)="","",INDEX(Data_Checks!$E:$E,33+1)) | F37: =IF(INDEX(Data_Checks!$F:$F,33+1)="","",INDEX(Data_Checks!$F:$F,33+1)) | G37: =IF(INDEX(Data_Checks!$G:$G,33+1)="","",INDEX(Data_Checks!$G:$G,33+1)) | H37: =IF(INDEX(Data_Checks!$H:$H,33+1)="","",INDEX(Data_Checks!$H:$H,33+1))
A38: =IF(INDEX(Data_Checks!$A:$A,34+1)="","",INDEX(Data_Checks!$A:$A,34+1)) | B38: =IF(INDEX(Data_Checks!$B:$B,34+1)="","",INDEX(Data_Checks!$B:$B,34+1)) | C38: =IF(INDEX(Data_Checks!$C:$C,34+1)="","",INDEX(Data_Checks!$C:$C,34+1)) | D38: =IF(INDEX(Data_Checks!$D:$D,34+1)="","",INDEX(Data_Checks!$D:$D,34+1)) | E38: =IF(INDEX(Data_Checks!$E:$E,34+1)="","",INDEX(Data_Checks!$E:$E,34+1)) | F38: =IF(INDEX(Data_Checks!$F:$F,34+1)="","",INDEX(Data_Checks!$F:$F,34+1)) | G38: =IF(INDEX(Data_Checks!$G:$G,34+1)="","",INDEX(Data_Checks!$G:$G,34+1)) | H38: =IF(INDEX(Data_Checks!$H:$H,34+1)="","",INDEX(Data_Checks!$H:$H,34+1))
A39: =IF(INDEX(Data_Checks!$A:$A,35+1)="","",INDEX(Data_Checks!$A:$A,35+1)) | B39: =IF(INDEX(Data_Checks!$B:$B,35+1)="","",INDEX(Data_Checks!$B:$B,35+1)) | C39: =IF(INDEX(Data_Checks!$C:$C,35+1)="","",INDEX(Data_Checks!$C:$C,35+1)) | D39: =IF(INDEX(Data_Checks!$D:$D,35+1)="","",INDEX(Data_Checks!$D:$D,35+1)) | E39: =IF(INDEX(Data_Checks!$E:$E,35+1)="","",INDEX(Data_Checks!$E:$E,35+1)) | F39: =IF(INDEX(Data_Checks!$F:$F,35+1)="","",INDEX(Data_Checks!$F:$F,35+1)) | G39: =IF(INDEX(Data_Checks!$G:$G,35+1)="","",INDEX(Data_Checks!$G:$G,35+1)) | H39: =IF(INDEX(Data_Checks!$H:$H,35+1)="","",INDEX(Data_Checks!$H:$H,35+1))
A40: =IF(INDEX(Data_Checks!$A:$A,36+1)="","",INDEX(Data_Checks!$A:$A,36+1)) | B40: =IF(INDEX(Data_Checks!$B:$B,36+1)="","",INDEX(Data_Checks!$B:$B,36+1)) | C40: =IF(INDEX(Data_Checks!$C:$C,36+1)="","",INDEX(Data_Checks!$C:$C,36+1)) | D40: =IF(INDEX(Data_Checks!$D:$D,36+1)="","",INDEX(Data_Checks!$D:$D,36+1)) | E40: =IF(INDEX(Data_Checks!$E:$E,36+1)="","",INDEX(Data_Checks!$E:$E,36+1)) | F40: =IF(INDEX(Data_Checks!$F:$F,36+1)="","",INDEX(Data_Checks!$F:$F,36+1)) | G40: =IF(INDEX(Data_Checks!$G:$G,36+1)="","",INDEX(Data_Checks!$G:$G,36+1)) | H40: =IF(INDEX(Data_Checks!$H:$H,36+1)="","",INDEX(Data_Checks!$H:$H,36+1))
A41: =IF(INDEX(Data_Checks!$A:$A,37+1)="","",INDEX(Data_Checks!$A:$A,37+1)) | B41: =IF(INDEX(Data_Checks!$B:$B,37+1)="","",INDEX(Data_Checks!$B:$B,37+1)) | C41: =IF(INDEX(Data_Checks!$C:$C,37+1)="","",INDEX(Data_Checks!$C:$C,37+1)) | D41: =IF(INDEX(Data_Checks!$D:$D,37+1)="","",INDEX(Data_Checks!$D:$D,37+1)) | E41: =IF(INDEX(Data_Checks!$E:$E,37+1)="","",INDEX(Data_Checks!$E:$E,37+1)) | F41: =IF(INDEX(Data_Checks!$F:$F,37+1)="","",INDEX(Data_Checks!$F:$F,37+1)) | G41: =IF(INDEX(Data_Checks!$G:$G,37+1)="","",INDEX(Data_Checks!$G:$G,37+1)) | H41: =IF(INDEX(Data_Checks!$H:$H,37+1)="","",INDEX(Data_Checks!$H:$H,37+1))
A42: =IF(INDEX(Data_Checks!$A:$A,38+1)="","",INDEX(Data_Checks!$A:$A,38+1)) | B42: =IF(INDEX(Data_Checks!$B:$B,38+1)="","",INDEX(Data_Checks!$B:$B,38+1)) | C42: =IF(INDEX(Data_Checks!$C:$C,38+1)="","",INDEX(Data_Checks!$C:$C,38+1)) | D42: =IF(INDEX(Data_Checks!$D:$D,38+1)="","",INDEX(Data_Checks!$D:$D,38+1)) | E42: =IF(INDEX(Data_Checks!$E:$E,38+1)="","",INDEX(Data_Checks!$E:$E,38+1)) | F42: =IF(INDEX(Data_Checks!$F:$F,38+1)="","",INDEX(Data_Checks!$F:$F,38+1)) | G42: =IF(INDEX(Data_Checks!$G:$G,38+1)="","",INDEX(Data_Checks!$G:$G,38+1)) | H42: =IF(INDEX(Data_Checks!$H:$H,38+1)="","",INDEX(Data_Checks!$H:$H,38+1))
A43: =IF(INDEX(Data_Checks!$A:$A,39+1)="","",INDEX(Data_Checks!$A:$A,39+1)) | B43: =IF(INDEX(Data_Checks!$B:$B,39+1)="","",INDEX(Data_Checks!$B:$B,39+1)) | C43: =IF(INDEX(Data_Checks!$C:$C,39+1)="","",INDEX(Data_Checks!$C:$C,39+1)) | D43: =IF(INDEX(Data_Checks!$D:$D,39+1)="","",INDEX(Data_Checks!$D:$D,39+1)) | E43: =IF(INDEX(Data_Checks!$E:$E,39+1)="","",INDEX(Data_Checks!$E:$E,39+1)) | F43: =IF(INDEX(Data_Checks!$F:$F,39+1)="","",INDEX(Data_Checks!$F:$F,39+1)) | G43: =IF(INDEX(Data_Checks!$G:$G,39+1)="","",INDEX(Data_Checks!$G:$G,39+1)) | H43: =IF(INDEX(Data_Checks!$H:$H,39+1)="","",INDEX(Data_Checks!$H:$H,39+1))
A44: =IF(INDEX(Data_Checks!$A:$A,40+1)="","",INDEX(Data_Checks!$A:$A,40+1)) | B44: =IF(INDEX(Data_Checks!$B:$B,40+1)="","",INDEX(Data_Checks!$B:$B,40+1)) | C44: =IF(INDEX(Data_Checks!$C:$C,40+1)="","",INDEX(Data_Checks!$C:$C,40+1)) | D44: =IF(INDEX(Data_Checks!$D:$D,40+1)="","",INDEX(Data_Checks!$D:$D,40+1)) | E44: =IF(INDEX(Data_Checks!$E:$E,40+1)="","",INDEX(Data_Checks!$E:$E,40+1)) | F44: =IF(INDEX(Data_Checks!$F:$F,40+1)="","",INDEX(Data_Checks!$F:$F,40+1)) | G44: =IF(INDEX(Data_Checks!$G:$G,40+1)="","",INDEX(Data_Checks!$G:$G,40+1)) | H44: =IF(INDEX(Data_Checks!$H:$H,40+1)="","",INDEX(Data_Checks!$H:$H,40+1))
A45: =IF(INDEX(Data_Checks!$A:$A,41+1)="","",INDEX(Data_Checks!$A:$A,41+1)) | B45: =IF(INDEX(Data_Checks!$B:$B,41+1)="","",INDEX(Data_Checks!$B:$B,41+1)) | C45: =IF(INDEX(Data_Checks!$C:$C,41+1)="","",INDEX(Data_Checks!$C:$C,41+1)) | D45: =IF(INDEX(Data_Checks!$D:$D,41+1)="","",INDEX(Data_Checks!$D:$D,41+1)) | E45: =IF(INDEX(Data_Checks!$E:$E,41+1)="","",INDEX(Data_Checks!$E:$E,41+1)) | F45: =IF(INDEX(Data_Checks!$F:$F,41+1)="","",INDEX(Data_Checks!$F:$F,41+1)) | G45: =IF(INDEX(Data_Checks!$G:$G,41+1)="","",INDEX(Data_Checks!$G:$G,41+1)) | H45: =IF(INDEX(Data_Checks!$H:$H,41+1)="","",INDEX(Data_Checks!$H:$H,41+1))
A46: =IF(INDEX(Data_Checks!$A:$A,42+1)="","",INDEX(Data_Checks!$A:$A,42+1)) | B46: =IF(INDEX(Data_Checks!$B:$B,42+1)="","",INDEX(Data_Checks!$B:$B,42+1)) | C46: =IF(INDEX(Data_Checks!$C:$C,42+1)="","",INDEX(Data_Checks!$C:$C,42+1)) | D46: =IF(INDEX(Data_Checks!$D:$D,42+1)="","",INDEX(Data_Checks!$D:$D,42+1)) | E46: =IF(INDEX(Data_Checks!$E:$E,42+1)="","",INDEX(Data_Checks!$E:$E,42+1)) | F46: =IF(INDEX(Data_Checks!$F:$F,42+1)="","",INDEX(Data_Checks!$F:$F,42+1)) | G46: =IF(INDEX(Data_Checks!$G:$G,42+1)="","",INDEX(Data_Checks!$G:$G,42+1)) | H46: =IF(INDEX(Data_Checks!$H:$H,42+1)="","",INDEX(Data_Checks!$H:$H,42+1))
A47: =IF(INDEX(Data_Checks!$A:$A,43+1)="","",INDEX(Data_Checks!$A:$A,43+1)) | B47: =IF(INDEX(Data_Checks!$B:$B,43+1)="","",INDEX(Data_Checks!$B:$B,43+1)) | C47: =IF(INDEX(Data_Checks!$C:$C,43+1)="","",INDEX(Data_Checks!$C:$C,43+1)) | D47: =IF(INDEX(Data_Checks!$D:$D,43+1)="","",INDEX(Data_Checks!$D:$D,43+1)) | E47: =IF(INDEX(Data_Checks!$E:$E,43+1)="","",INDEX(Data_Checks!$E:$E,43+1)) | F47: =IF(INDEX(Data_Checks!$F:$F,43+1)="","",INDEX(Data_Checks!$F:$F,43+1)) | G47: =IF(INDEX(Data_Checks!$G:$G,43+1)="","",INDEX(Data_Checks!$G:$G,43+1)) | H47: =IF(INDEX(Data_Checks!$H:$H,43+1)="","",INDEX(Data_Checks!$H:$H,43+1))
A48: =IF(INDEX(Data_Checks!$A:$A,44+1)="","",INDEX(Data_Checks!$A:$A,44+1)) | B48: =IF(INDEX(Data_Checks!$B:$B,44+1)="","",INDEX(Data_Checks!$B:$B,44+1)) | C48: =IF(INDEX(Data_Checks!$C:$C,44+1)="","",INDEX(Data_Checks!$C:$C,44+1)) | D48: =IF(INDEX(Data_Checks!$D:$D,44+1)="","",INDEX(Data_Checks!$D:$D,44+1)) | E48: =IF(INDEX(Data_Checks!$E:$E,44+1)="","",INDEX(Data_Checks!$E:$E,44+1)) | F48: =IF(INDEX(Data_Checks!$F:$F,44+1)="","",INDEX(Data_Checks!$F:$F,44+1)) | G48: =IF(INDEX(Data_Checks!$G:$G,44+1)="","",INDEX(Data_Checks!$G:$G,44+1)) | H48: =IF(INDEX(Data_Checks!$H:$H,44+1)="","",INDEX(Data_Checks!$H:$H,44+1))
A49: =IF(INDEX(Data_Checks!$A:$A,45+1)="","",INDEX(Data_Checks!$A:$A,45+1)) | B49: =IF(INDEX(Data_Checks!$B:$B,45+1)="","",INDEX(Data_Checks!$B:$B,45+1)) | C49: =IF(INDEX(Data_Checks!$C:$C,45+1)="","",INDEX(Data_Checks!$C:$C,45+1)) | D49: =IF(INDEX(Data_Checks!$D:$D,45+1)="","",INDEX(Data_Checks!$D:$D,45+1)) | E49: =IF(INDEX(Data_Checks!$E:$E,45+1)="","",INDEX(Data_Checks!$E:$E,45+1)) | F49: =IF(INDEX(Data_Checks!$F:$F,45+1)="","",INDEX(Data_Checks!$F:$F,45+1)) | G49: =IF(INDEX(Data_Checks!$G:$G,45+1)="","",INDEX(Data_Checks!$G:$G,45+1)) | H49: =IF(INDEX(Data_Checks!$H:$H,45+1)="","",INDEX(Data_Checks!$H:$H,45+1))
A50: =IF(INDEX(Data_Checks!$A:$A,46+1)="","",INDEX(Data_Checks!$A:$A,46+1)) | B50: =IF(INDEX(Data_Checks!$B:$B,46+1)="","",INDEX(Data_Checks!$B:$B,46+1)) | C50: =IF(INDEX(Data_Checks!$C:$C,46+1)="","",INDEX(Data_Checks!$C:$C,46+1)) | D50: =IF(INDEX(Data_Checks!$D:$D,46+1)="","",INDEX(Data_Checks!$D:$D,46+1)) | E50: =IF(INDEX(Data_Checks!$E:$E,46+1)="","",INDEX(Data_Checks!$E:$E,46+1)) | F50: =IF(INDEX(Data_Checks!$F:$F,46+1)="","",INDEX(Data_Checks!$F:$F,46+1)) | G50: =IF(INDEX(Data_Checks!$G:$G,46+1)="","",INDEX(Data_Checks!$G:$G,46+1)) | H50: =IF(INDEX(Data_Checks!$H:$H,46+1)="","",INDEX(Data_Checks!$H:$H,46+1))
A51: =IF(INDEX(Data_Checks!$A:$A,47+1)="","",INDEX(Data_Checks!$A:$A,47+1)) | B51: =IF(INDEX(Data_Checks!$B:$B,47+1)="","",INDEX(Data_Checks!$B:$B,47+1)) | C51: =IF(INDEX(Data_Checks!$C:$C,47+1)="","",INDEX(Data_Checks!$C:$C,47+1)) | D51: =IF(INDEX(Data_Checks!$D:$D,47+1)="","",INDEX(Data_Checks!$D:$D,47+1)) | E51: =IF(INDEX(Data_Checks!$E:$E,47+1)="","",INDEX(Data_Checks!$E:$E,47+1)) | F51: =IF(INDEX(Data_Checks!$F:$F,47+1)="","",INDEX(Data_Checks!$F:$F,47+1)) | G51: =IF(INDEX(Data_Checks!$G:$G,47+1)="","",INDEX(Data_Checks!$G:$G,47+1)) | H51: =IF(INDEX(Data_Checks!$H:$H,47+1)="","",INDEX(Data_Checks!$H:$H,47+1))
A52: =IF(INDEX(Data_Checks!$A:$A,48+1)="","",INDEX(Data_Checks!$A:$A,48+1)) | B52: =IF(INDEX(Data_Checks!$B:$B,48+1)="","",INDEX(Data_Checks!$B:$B,48+1)) | C52: =IF(INDEX(Data_Checks!$C:$C,48+1)="","",INDEX(Data_Checks!$C:$C,48+1)) | D52: =IF(INDEX(Data_Checks!$D:$D,48+1)="","",INDEX(Data_Checks!$D:$D,48+1)) | E52: =IF(INDEX(Data_Checks!$E:$E,48+1)="","",INDEX(Data_Checks!$E:$E,48+1)) | F52: =IF(INDEX(Data_Checks!$F:$F,48+1)="","",INDEX(Data_Checks!$F:$F,48+1)) | G52: =IF(INDEX(Data_Checks!$G:$G,48+1)="","",INDEX(Data_Checks!$G:$G,48+1)) | H52: =IF(INDEX(Data_Checks!$H:$H,48+1)="","",INDEX(Data_Checks!$H:$H,48+1))
A53: =IF(INDEX(Data_Checks!$A:$A,49+1)="","",INDEX(Data_Checks!$A:$A,49+1)) | B53: =IF(INDEX(Data_Checks!$B:$B,49+1)="","",INDEX(Data_Checks!$B:$B,49+1)) | C53: =IF(INDEX(Data_Checks!$C:$C,49+1)="","",INDEX(Data_Checks!$C:$C,49+1)) | D53: =IF(INDEX(Data_Checks!$D:$D,49+1)="","",INDEX(Data_Checks!$D:$D,49+1)) | E53: =IF(INDEX(Data_Checks!$E:$E,49+1)="","",INDEX(Data_Checks!$E:$E,49+1)) | F53: =IF(INDEX(Data_Checks!$F:$F,49+1)="","",INDEX(Data_Checks!$F:$F,49+1)) | G53: =IF(INDEX(Data_Checks!$G:$G,49+1)="","",INDEX(Data_Checks!$G:$G,49+1)) | H53: =IF(INDEX(Data_Checks!$H:$H,49+1)="","",INDEX(Data_Checks!$H:$H,49+1))
A54: =IF(INDEX(Data_Checks!$A:$A,50+1)="","",INDEX(Data_Checks!$A:$A,50+1)) | B54: =IF(INDEX(Data_Checks!$B:$B,50+1)="","",INDEX(Data_Checks!$B:$B,50+1)) | C54: =IF(INDEX(Data_Checks!$C:$C,50+1)="","",INDEX(Data_Checks!$C:$C,50+1)) | D54: =IF(INDEX(Data_Checks!$D:$D,50+1)="","",INDEX(Data_Checks!$D:$D,50+1)) | E54: =IF(INDEX(Data_Checks!$E:$E,50+1)="","",INDEX(Data_Checks!$E:$E,50+1)) | F54: =IF(INDEX(Data_Checks!$F:$F,50+1)="","",INDEX(Data_Checks!$F:$F,50+1)) | G54: =IF(INDEX(Data_Checks!$G:$G,50+1)="","",INDEX(Data_Checks!$G:$G,50+1)) | H54: =IF(INDEX(Data_Checks!$H:$H,50+1)="","",INDEX(Data_Checks!$H:$H,50+1))
A55: =IF(INDEX(Data_Checks!$A:$A,51+1)="","",INDEX(Data_Checks!$A:$A,51+1)) | B55: =IF(INDEX(Data_Checks!$B:$B,51+1)="","",INDEX(Data_Checks!$B:$B,51+1)) | C55: =IF(INDEX(Data_Checks!$C:$C,51+1)="","",INDEX(Data_Checks!$C:$C,51+1)) | D55: =IF(INDEX(Data_Checks!$D:$D,51+1)="","",INDEX(Data_Checks!$D:$D,51+1)) | E55: =IF(INDEX(Data_Checks!$E:$E,51+1)="","",INDEX(Data_Checks!$E:$E,51+1)) | F55: =IF(INDEX(Data_Checks!$F:$F,51+1)="","",INDEX(Data_Checks!$F:$F,51+1)) | G55: =IF(INDEX(Data_Checks!$G:$G,51+1)="","",INDEX(Data_Checks!$G:$G,51+1)) | H55: =IF(INDEX(Data_Checks!$H:$H,51+1)="","",INDEX(Data_Checks!$H:$H,51+1))
A56: =IF(INDEX(Data_Checks!$A:$A,52+1)="","",INDEX(Data_Checks!$A:$A,52+1)) | B56: =IF(INDEX(Data_Checks!$B:$B,52+1)="","",INDEX(Data_Checks!$B:$B,52+1)) | C56: =IF(INDEX(Data_Checks!$C:$C,52+1)="","",INDEX(Data_Checks!$C:$C,52+1)) | D56: =IF(INDEX(Data_Checks!$D:$D,52+1)="","",INDEX(Data_Checks!$D:$D,52+1)) | E56: =IF(INDEX(Data_Checks!$E:$E,52+1)="","",INDEX(Data_Checks!$E:$E,52+1)) | F56: =IF(INDEX(Data_Checks!$F:$F,52+1)="","",INDEX(Data_Checks!$F:$F,52+1)) | G56: =IF(INDEX(Data_Checks!$G:$G,52+1)="","",INDEX(Data_Checks!$G:$G,52+1)) | H56: =IF(INDEX(Data_Checks!$H:$H,52+1)="","",INDEX(Data_Checks!$H:$H,52+1))
A57: =IF(INDEX(Data_Checks!$A:$A,53+1)="","",INDEX(Data_Checks!$A:$A,53+1)) | B57: =IF(INDEX(Data_Checks!$B:$B,53+1)="","",INDEX(Data_Checks!$B:$B,53+1)) | C57: =IF(INDEX(Data_Checks!$C:$C,53+1)="","",INDEX(Data_Checks!$C:$C,53+1)) | D57: =IF(INDEX(Data_Checks!$D:$D,53+1)="","",INDEX(Data_Checks!$D:$D,53+1)) | E57: =IF(INDEX(Data_Checks!$E:$E,53+1)="","",INDEX(Data_Checks!$E:$E,53+1)) | F57: =IF(INDEX(Data_Checks!$F:$F,53+1)="","",INDEX(Data_Checks!$F:$F,53+1)) | G57: =IF(INDEX(Data_Checks!$G:$G,53+1)="","",INDEX(Data_Checks!$G:$G,53+1)) | H57: =IF(INDEX(Data_Checks!$H:$H,53+1)="","",INDEX(Data_Checks!$H:$H,53+1))
A58: =IF(INDEX(Data_Checks!$A:$A,54+1)="","",INDEX(Data_Checks!$A:$A,54+1)) | B58: =IF(INDEX(Data_Checks!$B:$B,54+1)="","",INDEX(Data_Checks!$B:$B,54+1)) | C58: =IF(INDEX(Data_Checks!$C:$C,54+1)="","",INDEX(Data_Checks!$C:$C,54+1)) | D58: =IF(INDEX(Data_Checks!$D:$D,54+1)="","",INDEX(Data_Checks!$D:$D,54+1)) | E58: =IF(INDEX(Data_Checks!$E:$E,54+1)="","",INDEX(Data_Checks!$E:$E,54+1)) | F58: =IF(INDEX(Data_Checks!$F:$F,54+1)="","",INDEX(Data_Checks!$F:$F,54+1)) | G58: =IF(INDEX(Data_Checks!$G:$G,54+1)="","",INDEX(Data_Checks!$G:$G,54+1)) | H58: =IF(INDEX(Data_Checks!$H:$H,54+1)="","",INDEX(Data_Checks!$H:$H,54+1))
A59: =IF(INDEX(Data_Checks!$A:$A,55+1)="","",INDEX(Data_Checks!$A:$A,55+1)) | B59: =IF(INDEX(Data_Checks!$B:$B,55+1)="","",INDEX(Data_Checks!$B:$B,55+1)) | C59: =IF(INDEX(Data_Checks!$C:$C,55+1)="","",INDEX(Data_Checks!$C:$C,55+1)) | D59: =IF(INDEX(Data_Checks!$D:$D,55+1)="","",INDEX(Data_Checks!$D:$D,55+1)) | E59: =IF(INDEX(Data_Checks!$E:$E,55+1)="","",INDEX(Data_Checks!$E:$E,55+1)) | F59: =IF(INDEX(Data_Checks!$F:$F,55+1)="","",INDEX(Data_Checks!$F:$F,55+1)) | G59: =IF(INDEX(Data_Checks!$G:$G,55+1)="","",INDEX(Data_Checks!$G:$G,55+1)) | H59: =IF(INDEX(Data_Checks!$H:$H,55+1)="","",INDEX(Data_Checks!$H:$H,55+1))
A60: =IF(INDEX(Data_Checks!$A:$A,56+1)="","",INDEX(Data_Checks!$A:$A,56+1)) | B60: =IF(INDEX(Data_Checks!$B:$B,56+1)="","",INDEX(Data_Checks!$B:$B,56+1)) | C60: =IF(INDEX(Data_Checks!$C:$C,56+1)="","",INDEX(Data_Checks!$C:$C,56+1)) | D60: =IF(INDEX(Data_Checks!$D:$D,56+1)="","",INDEX(Data_Checks!$D:$D,56+1)) | E60: =IF(INDEX(Data_Checks!$E:$E,56+1)="","",INDEX(Data_Checks!$E:$E,56+1)) | F60: =IF(INDEX(Data_Checks!$F:$F,56+1)="","",INDEX(Data_Checks!$F:$F,56+1)) | G60: =IF(INDEX(Data_Checks!$G:$G,56+1)="","",INDEX(Data_Checks!$G:$G,56+1)) | H60: =IF(INDEX(Data_Checks!$H:$H,56+1)="","",INDEX(Data_Checks!$H:$H,56+1))
A61: =IF(INDEX(Data_Checks!$A:$A,57+1)="","",INDEX(Data_Checks!$A:$A,57+1)) | B61: =IF(INDEX(Data_Checks!$B:$B,57+1)="","",INDEX(Data_Checks!$B:$B,57+1)) | C61: =IF(INDEX(Data_Checks!$C:$C,57+1)="","",INDEX(Data_Checks!$C:$C,57+1)) | D61: =IF(INDEX(Data_Checks!$D:$D,57+1)="","",INDEX(Data_Checks!$D:$D,57+1)) | E61: =IF(INDEX(Data_Checks!$E:$E,57+1)="","",INDEX(Data_Checks!$E:$E,57+1)) | F61: =IF(INDEX(Data_Checks!$F:$F,57+1)="","",INDEX(Data_Checks!$F:$F,57+1)) | G61: =IF(INDEX(Data_Checks!$G:$G,57+1)="","",INDEX(Data_Checks!$G:$G,57+1)) | H61: =IF(INDEX(Data_Checks!$H:$H,57+1)="","",INDEX(Data_Checks!$H:$H,57+1))
A62: =IF(INDEX(Data_Checks!$A:$A,58+1)="","",INDEX(Data_Checks!$A:$A,58+1)) | B62: =IF(INDEX(Data_Checks!$B:$B,58+1)="","",INDEX(Data_Checks!$B:$B,58+1)) | C62: =IF(INDEX(Data_Checks!$C:$C,58+1)="","",INDEX(Data_Checks!$C:$C,58+1)) | D62: =IF(INDEX(Data_Checks!$D:$D,58+1)="","",INDEX(Data_Checks!$D:$D,58+1)) | E62: =IF(INDEX(Data_Checks!$E:$E,58+1)="","",INDEX(Data_Checks!$E:$E,58+1)) | F62: =IF(INDEX(Data_Checks!$F:$F,58+1)="","",INDEX(Data_Checks!$F:$F,58+1)) | G62: =IF(INDEX(Data_Checks!$G:$G,58+1)="","",INDEX(Data_Checks!$G:$G,58+1)) | H62: =IF(INDEX(Data_Checks!$H:$H,58+1)="","",INDEX(Data_Checks!$H:$H,58+1))
A63: =IF(INDEX(Data_Checks!$A:$A,59+1)="","",INDEX(Data_Checks!$A:$A,59+1)) | B63: =IF(INDEX(Data_Checks!$B:$B,59+1)="","",INDEX(Data_Checks!$B:$B,59+1)) | C63: =IF(INDEX(Data_Checks!$C:$C,59+1)="","",INDEX(Data_Checks!$C:$C,59+1)) | D63: =IF(INDEX(Data_Checks!$D:$D,59+1)="","",INDEX(Data_Checks!$D:$D,59+1)) | E63: =IF(INDEX(Data_Checks!$E:$E,59+1)="","",INDEX(Data_Checks!$E:$E,59+1)) | F63: =IF(INDEX(Data_Checks!$F:$F,59+1)="","",INDEX(Data_Checks!$F:$F,59+1)) | G63: =IF(INDEX(Data_Checks!$G:$G,59+1)="","",INDEX(Data_Checks!$G:$G,59+1)) | H63: =IF(INDEX(Data_Checks!$H:$H,59+1)="","",INDEX(Data_Checks!$H:$H,59+1))
A64: =IF(INDEX(Data_Checks!$A:$A,60+1)="","",INDEX(Data_Checks!$A:$A,60+1)) | B64: =IF(INDEX(Data_Checks!$B:$B,60+1)="","",INDEX(Data_Checks!$B:$B,60+1)) | C64: =IF(INDEX(Data_Checks!$C:$C,60+1)="","",INDEX(Data_Checks!$C:$C,60+1)) | D64: =IF(INDEX(Data_Checks!$D:$D,60+1)="","",INDEX(Data_Checks!$D:$D,60+1)) | E64: =IF(INDEX(Data_Checks!$E:$E,60+1)="","",INDEX(Data_Checks!$E:$E,60+1)) | F64: =IF(INDEX(Data_Checks!$F:$F,60+1)="","",INDEX(Data_Checks!$F:$F,60+1)) | G64: =IF(INDEX(Data_Checks!$G:$G,60+1)="","",INDEX(Data_Checks!$G:$G,60+1)) | H64: =IF(INDEX(Data_Checks!$H:$H,60+1)="","",INDEX(Data_Checks!$H:$H,60+1))
A65: =IF(INDEX(Data_Checks!$A:$A,61+1)="","",INDEX(Data_Checks!$A:$A,61+1)) | B65: =IF(INDEX(Data_Checks!$B:$B,61+1)="","",INDEX(Data_Checks!$B:$B,61+1)) | C65: =IF(INDEX(Data_Checks!$C:$C,61+1)="","",INDEX(Data_Checks!$C:$C,61+1)) | D65: =IF(INDEX(Data_Checks!$D:$D,61+1)="","",INDEX(Data_Checks!$D:$D,61+1)) | E65: =IF(INDEX(Data_Checks!$E:$E,61+1)="","",INDEX(Data_Checks!$E:$E,61+1)) | F65: =IF(INDEX(Data_Checks!$F:$F,61+1)="","",INDEX(Data_Checks!$F:$F,61+1)) | G65: =IF(INDEX(Data_Checks!$G:$G,61+1)="","",INDEX(Data_Checks!$G:$G,61+1)) | H65: =IF(INDEX(Data_Checks!$H:$H,61+1)="","",INDEX(Data_Checks!$H:$H,61+1))
A66: =IF(INDEX(Data_Checks!$A:$A,62+1)="","",INDEX(Data_Checks!$A:$A,62+1)) | B66: =IF(INDEX(Data_Checks!$B:$B,62+1)="","",INDEX(Data_Checks!$B:$B,62+1)) | C66: =IF(INDEX(Data_Checks!$C:$C,62+1)="","",INDEX(Data_Checks!$C:$C,62+1)) | D66: =IF(INDEX(Data_Checks!$D:$D,62+1)="","",INDEX(Data_Checks!$D:$D,62+1)) | E66: =IF(INDEX(Data_Checks!$E:$E,62+1)="","",INDEX(Data_Checks!$E:$E,62+1)) | F66: =IF(INDEX(Data_Checks!$F:$F,62+1)="","",INDEX(Data_Checks!$F:$F,62+1)) | G66: =IF(INDEX(Data_Checks!$G:$G,62+1)="","",INDEX(Data_Checks!$G:$G,62+1)) | H66: =IF(INDEX(Data_Checks!$H:$H,62+1)="","",INDEX(Data_Checks!$H:$H,62+1))
A67: =IF(INDEX(Data_Checks!$A:$A,63+1)="","",INDEX(Data_Checks!$A:$A,63+1)) | B67: =IF(INDEX(Data_Checks!$B:$B,63+1)="","",INDEX(Data_Checks!$B:$B,63+1)) | C67: =IF(INDEX(Data_Checks!$C:$C,63+1)="","",INDEX(Data_Checks!$C:$C,63+1)) | D67: =IF(INDEX(Data_Checks!$D:$D,63+1)="","",INDEX(Data_Checks!$D:$D,63+1)) | E67: =IF(INDEX(Data_Checks!$E:$E,63+1)="","",INDEX(Data_Checks!$E:$E,63+1)) | F67: =IF(INDEX(Data_Checks!$F:$F,63+1)="","",INDEX(Data_Checks!$F:$F,63+1)) | G67: =IF(INDEX(Data_Checks!$G:$G,63+1)="","",INDEX(Data_Checks!$G:$G,63+1)) | H67: =IF(INDEX(Data_Checks!$H:$H,63+1)="","",INDEX(Data_Checks!$H:$H,63+1))
A68: =IF(INDEX(Data_Checks!$A:$A,64+1)="","",INDEX(Data_Checks!$A:$A,64+1)) | B68: =IF(INDEX(Data_Checks!$B:$B,64+1)="","",INDEX(Data_Checks!$B:$B,64+1)) | C68: =IF(INDEX(Data_Checks!$C:$C,64+1)="","",INDEX(Data_Checks!$C:$C,64+1)) | D68: =IF(INDEX(Data_Checks!$D:$D,64+1)="","",INDEX(Data_Checks!$D:$D,64+1)) | E68: =IF(INDEX(Data_Checks!$E:$E,64+1)="","",INDEX(Data_Checks!$E:$E,64+1)) | F68: =IF(INDEX(Data_Checks!$F:$F,64+1)="","",INDEX(Data_Checks!$F:$F,64+1)) | G68: =IF(INDEX(Data_Checks!$G:$G,64+1)="","",INDEX(Data_Checks!$G:$G,64+1)) | H68: =IF(INDEX(Data_Checks!$H:$H,64+1)="","",INDEX(Data_Checks!$H:$H,64+1))
A69: =IF(INDEX(Data_Checks!$A:$A,65+1)="","",INDEX(Data_Checks!$A:$A,65+1)) | B69: =IF(INDEX(Data_Checks!$B:$B,65+1)="","",INDEX(Data_Checks!$B:$B,65+1)) | C69: =IF(INDEX(Data_Checks!$C:$C,65+1)="","",INDEX(Data_Checks!$C:$C,65+1)) | D69: =IF(INDEX(Data_Checks!$D:$D,65+1)="","",INDEX(Data_Checks!$D:$D,65+1)) | E69: =IF(INDEX(Data_Checks!$E:$E,65+1)="","",INDEX(Data_Checks!$E:$E,65+1)) | F69: =IF(INDEX(Data_Checks!$F:$F,65+1)="","",INDEX(Data_Checks!$F:$F,65+1)) | G69: =IF(INDEX(Data_Checks!$G:$G,65+1)="","",INDEX(Data_Checks!$G:$G,65+1)) | H69: =IF(INDEX(Data_Checks!$H:$H,65+1)="","",INDEX(Data_Checks!$H:$H,65+1))
A70: =IF(INDEX(Data_Checks!$A:$A,66+1)="","",INDEX(Data_Checks!$A:$A,66+1)) | B70: =IF(INDEX(Data_Checks!$B:$B,66+1)="","",INDEX(Data_Checks!$B:$B,66+1)) | C70: =IF(INDEX(Data_Checks!$C:$C,66+1)="","",INDEX(Data_Checks!$C:$C,66+1)) | D70: =IF(INDEX(Data_Checks!$D:$D,66+1)="","",INDEX(Data_Checks!$D:$D,66+1)) | E70: =IF(INDEX(Data_Checks!$E:$E,66+1)="","",INDEX(Data_Checks!$E:$E,66+1)) | F70: =IF(INDEX(Data_Checks!$F:$F,66+1)="","",INDEX(Data_Checks!$F:$F,66+1)) | G70: =IF(INDEX(Data_Checks!$G:$G,66+1)="","",INDEX(Data_Checks!$G:$G,66+1)) | H70: =IF(INDEX(Data_Checks!$H:$H,66+1)="","",INDEX(Data_Checks!$H:$H,66+1))
A71: =IF(INDEX(Data_Checks!$A:$A,67+1)="","",INDEX(Data_Checks!$A:$A,67+1)) | B71: =IF(INDEX(Data_Checks!$B:$B,67+1)="","",INDEX(Data_Checks!$B:$B,67+1)) | C71: =IF(INDEX(Data_Checks!$C:$C,67+1)="","",INDEX(Data_Checks!$C:$C,67+1)) | D71: =IF(INDEX(Data_Checks!$D:$D,67+1)="","",INDEX(Data_Checks!$D:$D,67+1)) | E71: =IF(INDEX(Data_Checks!$E:$E,67+1)="","",INDEX(Data_Checks!$E:$E,67+1)) | F71: =IF(INDEX(Data_Checks!$F:$F,67+1)="","",INDEX(Data_Checks!$F:$F,67+1)) | G71: =IF(INDEX(Data_Checks!$G:$G,67+1)="","",INDEX(Data_Checks!$G:$G,67+1)) | H71: =IF(INDEX(Data_Checks!$H:$H,67+1)="","",INDEX(Data_Checks!$H:$H,67+1))
A72: =IF(INDEX(Data_Checks!$A:$A,68+1)="","",INDEX(Data_Checks!$A:$A,68+1)) | B72: =IF(INDEX(Data_Checks!$B:$B,68+1)="","",INDEX(Data_Checks!$B:$B,68+1)) | C72: =IF(INDEX(Data_Checks!$C:$C,68+1)="","",INDEX(Data_Checks!$C:$C,68+1)) | D72: =IF(INDEX(Data_Checks!$D:$D,68+1)="","",INDEX(Data_Checks!$D:$D,68+1)) | E72: =IF(INDEX(Data_Checks!$E:$E,68+1)="","",INDEX(Data_Checks!$E:$E,68+1)) | F72: =IF(INDEX(Data_Checks!$F:$F,68+1)="","",INDEX(Data_Checks!$F:$F,68+1)) | G72: =IF(INDEX(Data_Checks!$G:$G,68+1)="","",INDEX(Data_Checks!$G:$G,68+1)) | H72: =IF(INDEX(Data_Checks!$H:$H,68+1)="","",INDEX(Data_Checks!$H:$H,68+1))
A73: =IF(INDEX(Data_Checks!$A:$A,69+1)="","",INDEX(Data_Checks!$A:$A,69+1)) | B73: =IF(INDEX(Data_Checks!$B:$B,69+1)="","",INDEX(Data_Checks!$B:$B,69+1)) | C73: =IF(INDEX(Data_Checks!$C:$C,69+1)="","",INDEX(Data_Checks!$C:$C,69+1)) | D73: =IF(INDEX(Data_Checks!$D:$D,69+1)="","",INDEX(Data_Checks!$D:$D,69+1)) | E73: =IF(INDEX(Data_Checks!$E:$E,69+1)="","",INDEX(Data_Checks!$E:$E,69+1)) | F73: =IF(INDEX(Data_Checks!$F:$F,69+1)="","",INDEX(Data_Checks!$F:$F,69+1)) | G73: =IF(INDEX(Data_Checks!$G:$G,69+1)="","",INDEX(Data_Checks!$G:$G,69+1)) | H73: =IF(INDEX(Data_Checks!$H:$H,69+1)="","",INDEX(Data_Checks!$H:$H,69+1))
A74: =IF(INDEX(Data_Checks!$A:$A,70+1)="","",INDEX(Data_Checks!$A:$A,70+1)) | B74: =IF(INDEX(Data_Checks!$B:$B,70+1)="","",INDEX(Data_Checks!$B:$B,70+1)) | C74: =IF(INDEX(Data_Checks!$C:$C,70+1)="","",INDEX(Data_Checks!$C:$C,70+1)) | D74: =IF(INDEX(Data_Checks!$D:$D,70+1)="","",INDEX(Data_Checks!$D:$D,70+1)) | E74: =IF(INDEX(Data_Checks!$E:$E,70+1)="","",INDEX(Data_Checks!$E:$E,70+1)) | F74: =IF(INDEX(Data_Checks!$F:$F,70+1)="","",INDEX(Data_Checks!$F:$F,70+1)) | G74: =IF(INDEX(Data_Checks!$G:$G,70+1)="","",INDEX(Data_Checks!$G:$G,70+1)) | H74: =IF(INDEX(Data_Checks!$H:$H,70+1)="","",INDEX(Data_Checks!$H:$H,70+1))
A75: =IF(INDEX(Data_Checks!$A:$A,71+1)="","",INDEX(Data_Checks!$A:$A,71+1)) | B75: =IF(INDEX(Data_Checks!$B:$B,71+1)="","",INDEX(Data_Checks!$B:$B,71+1)) | C75: =IF(INDEX(Data_Checks!$C:$C,71+1)="","",INDEX(Data_Checks!$C:$C,71+1)) | D75: =IF(INDEX(Data_Checks!$D:$D,71+1)="","",INDEX(Data_Checks!$D:$D,71+1)) | E75: =IF(INDEX(Data_Checks!$E:$E,71+1)="","",INDEX(Data_Checks!$E:$E,71+1)) | F75: =IF(INDEX(Data_Checks!$F:$F,71+1)="","",INDEX(Data_Checks!$F:$F,71+1)) | G75: =IF(INDEX(Data_Checks!$G:$G,71+1)="","",INDEX(Data_Checks!$G:$G,71+1)) | H75: =IF(INDEX(Data_Checks!$H:$H,71+1)="","",INDEX(Data_Checks!$H:$H,71+1))
A76: =IF(INDEX(Data_Checks!$A:$A,72+1)="","",INDEX(Data_Checks!$A:$A,72+1)) | B76: =IF(INDEX(Data_Checks!$B:$B,72+1)="","",INDEX(Data_Checks!$B:$B,72+1)) | C76: =IF(INDEX(Data_Checks!$C:$C,72+1)="","",INDEX(Data_Checks!$C:$C,72+1)) | D76: =IF(INDEX(Data_Checks!$D:$D,72+1)="","",INDEX(Data_Checks!$D:$D,72+1)) | E76: =IF(INDEX(Data_Checks!$E:$E,72+1)="","",INDEX(Data_Checks!$E:$E,72+1)) | F76: =IF(INDEX(Data_Checks!$F:$F,72+1)="","",INDEX(Data_Checks!$F:$F,72+1)) | G76: =IF(INDEX(Data_Checks!$G:$G,72+1)="","",INDEX(Data_Checks!$G:$G,72+1)) | H76: =IF(INDEX(Data_Checks!$H:$H,72+1)="","",INDEX(Data_Checks!$H:$H,72+1))
A77: =IF(INDEX(Data_Checks!$A:$A,73+1)="","",INDEX(Data_Checks!$A:$A,73+1)) | B77: =IF(INDEX(Data_Checks!$B:$B,73+1)="","",INDEX(Data_Checks!$B:$B,73+1)) | C77: =IF(INDEX(Data_Checks!$C:$C,73+1)="","",INDEX(Data_Checks!$C:$C,73+1)) | D77: =IF(INDEX(Data_Checks!$D:$D,73+1)="","",INDEX(Data_Checks!$D:$D,73+1)) | E77: =IF(INDEX(Data_Checks!$E:$E,73+1)="","",INDEX(Data_Checks!$E:$E,73+1)) | F77: =IF(INDEX(Data_Checks!$F:$F,73+1)="","",INDEX(Data_Checks!$F:$F,73+1)) | G77: =IF(INDEX(Data_Checks!$G:$G,73+1)="","",INDEX(Data_Checks!$G:$G,73+1)) | H77: =IF(INDEX(Data_Checks!$H:$H,73+1)="","",INDEX(Data_Checks!$H:$H,73+1))
A78: =IF(INDEX(Data_Checks!$A:$A,74+1)="","",INDEX(Data_Checks!$A:$A,74+1)) | B78: =IF(INDEX(Data_Checks!$B:$B,74+1)="","",INDEX(Data_Checks!$B:$B,74+1)) | C78: =IF(INDEX(Data_Checks!$C:$C,74+1)="","",INDEX(Data_Checks!$C:$C,74+1)) | D78: =IF(INDEX(Data_Checks!$D:$D,74+1)="","",INDEX(Data_Checks!$D:$D,74+1)) | E78: =IF(INDEX(Data_Checks!$E:$E,74+1)="","",INDEX(Data_Checks!$E:$E,74+1)) | F78: =IF(INDEX(Data_Checks!$F:$F,74+1)="","",INDEX(Data_Checks!$F:$F,74+1)) | G78: =IF(INDEX(Data_Checks!$G:$G,74+1)="","",INDEX(Data_Checks!$G:$G,74+1)) | H78: =IF(INDEX(Data_Checks!$H:$H,74+1)="","",INDEX(Data_Checks!$H:$H,74+1))
A79: =IF(INDEX(Data_Checks!$A:$A,75+1)="","",INDEX(Data_Checks!$A:$A,75+1)) | B79: =IF(INDEX(Data_Checks!$B:$B,75+1)="","",INDEX(Data_Checks!$B:$B,75+1)) | C79: =IF(INDEX(Data_Checks!$C:$C,75+1)="","",INDEX(Data_Checks!$C:$C,75+1)) | D79: =IF(INDEX(Data_Checks!$D:$D,75+1)="","",INDEX(Data_Checks!$D:$D,75+1)) | E79: =IF(INDEX(Data_Checks!$E:$E,75+1)="","",INDEX(Data_Checks!$E:$E,75+1)) | F79: =IF(INDEX(Data_Checks!$F:$F,75+1)="","",INDEX(Data_Checks!$F:$F,75+1)) | G79: =IF(INDEX(Data_Checks!$G:$G,75+1)="","",INDEX(Data_Checks!$G:$G,75+1)) | H79: =IF(INDEX(Data_Checks!$H:$H,75+1)="","",INDEX(Data_Checks!$H:$H,75+1))
A80: =IF(INDEX(Data_Checks!$A:$A,76+1)="","",INDEX(Data_Checks!$A:$A,76+1)) | B80: =IF(INDEX(Data_Checks!$B:$B,76+1)="","",INDEX(Data_Checks!$B:$B,76+1)) | C80: =IF(INDEX(Data_Checks!$C:$C,76+1)="","",INDEX(Data_Checks!$C:$C,76+1)) | D80: =IF(INDEX(Data_Checks!$D:$D,76+1)="","",INDEX(Data_Checks!$D:$D,76+1)) | E80: =IF(INDEX(Data_Checks!$E:$E,76+1)="","",INDEX(Data_Checks!$E:$E,76+1)) | F80: =IF(INDEX(Data_Checks!$F:$F,76+1)="","",INDEX(Data_Checks!$F:$F,76+1)) | G80: =IF(INDEX(Data_Checks!$G:$G,76+1)="","",INDEX(Data_Checks!$G:$G,76+1)) | H80: =IF(INDEX(Data_Checks!$H:$H,76+1)="","",INDEX(Data_Checks!$H:$H,76+1))
A81: =IF(INDEX(Data_Checks!$A:$A,77+1)="","",INDEX(Data_Checks!$A:$A,77+1)) | B81: =IF(INDEX(Data_Checks!$B:$B,77+1)="","",INDEX(Data_Checks!$B:$B,77+1)) | C81: =IF(INDEX(Data_Checks!$C:$C,77+1)="","",INDEX(Data_Checks!$C:$C,77+1)) | D81: =IF(INDEX(Data_Checks!$D:$D,77+1)="","",INDEX(Data_Checks!$D:$D,77+1)) | E81: =IF(INDEX(Data_Checks!$E:$E,77+1)="","",INDEX(Data_Checks!$E:$E,77+1)) | F81: =IF(INDEX(Data_Checks!$F:$F,77+1)="","",INDEX(Data_Checks!$F:$F,77+1)) | G81: =IF(INDEX(Data_Checks!$G:$G,77+1)="","",INDEX(Data_Checks!$G:$G,77+1)) | H81: =IF(INDEX(Data_Checks!$H:$H,77+1)="","",INDEX(Data_Checks!$H:$H,77+1))
A82: =IF(INDEX(Data_Checks!$A:$A,78+1)="","",INDEX(Data_Checks!$A:$A,78+1)) | B82: =IF(INDEX(Data_Checks!$B:$B,78+1)="","",INDEX(Data_Checks!$B:$B,78+1)) | C82: =IF(INDEX(Data_Checks!$C:$C,78+1)="","",INDEX(Data_Checks!$C:$C,78+1)) | D82: =IF(INDEX(Data_Checks!$D:$D,78+1)="","",INDEX(Data_Checks!$D:$D,78+1)) | E82: =IF(INDEX(Data_Checks!$E:$E,78+1)="","",INDEX(Data_Checks!$E:$E,78+1)) | F82: =IF(INDEX(Data_Checks!$F:$F,78+1)="","",INDEX(Data_Checks!$F:$F,78+1)) | G82: =IF(INDEX(Data_Checks!$G:$G,78+1)="","",INDEX(Data_Checks!$G:$G,78+1)) | H82: =IF(INDEX(Data_Checks!$H:$H,78+1)="","",INDEX(Data_Checks!$H:$H,78+1))
A83: =IF(INDEX(Data_Checks!$A:$A,79+1)="","",INDEX(Data_Checks!$A:$A,79+1)) | B83: =IF(INDEX(Data_Checks!$B:$B,79+1)="","",INDEX(Data_Checks!$B:$B,79+1)) | C83: =IF(INDEX(Data_Checks!$C:$C,79+1)="","",INDEX(Data_Checks!$C:$C,79+1)) | D83: =IF(INDEX(Data_Checks!$D:$D,79+1)="","",INDEX(Data_Checks!$D:$D,79+1)) | E83: =IF(INDEX(Data_Checks!$E:$E,79+1)="","",INDEX(Data_Checks!$E:$E,79+1)) | F83: =IF(INDEX(Data_Checks!$F:$F,79+1)="","",INDEX(Data_Checks!$F:$F,79+1)) | G83: =IF(INDEX(Data_Checks!$G:$G,79+1)="","",INDEX(Data_Checks!$G:$G,79+1)) | H83: =IF(INDEX(Data_Checks!$H:$H,79+1)="","",INDEX(Data_Checks!$H:$H,79+1))
A84: =IF(INDEX(Data_Checks!$A:$A,80+1)="","",INDEX(Data_Checks!$A:$A,80+1)) | B84: =IF(INDEX(Data_Checks!$B:$B,80+1)="","",INDEX(Data_Checks!$B:$B,80+1)) | C84: =IF(INDEX(Data_Checks!$C:$C,80+1)="","",INDEX(Data_Checks!$C:$C,80+1)) | D84: =IF(INDEX(Data_Checks!$D:$D,80+1)="","",INDEX(Data_Checks!$D:$D,80+1)) | E84: =IF(INDEX(Data_Checks!$E:$E,80+1)="","",INDEX(Data_Checks!$E:$E,80+1)) | F84: =IF(INDEX(Data_Checks!$F:$F,80+1)="","",INDEX(Data_Checks!$F:$F,80+1)) | G84: =IF(INDEX(Data_Checks!$G:$G,80+1)="","",INDEX(Data_Checks!$G:$G,80+1)) | H84: =IF(INDEX(Data_Checks!$H:$H,80+1)="","",INDEX(Data_Checks!$H:$H,80+1))
A85: =IF(INDEX(Data_Checks!$A:$A,81+1)="","",INDEX(Data_Checks!$A:$A,81+1)) | B85: =IF(INDEX(Data_Checks!$B:$B,81+1)="","",INDEX(Data_Checks!$B:$B,81+1)) | C85: =IF(INDEX(Data_Checks!$C:$C,81+1)="","",INDEX(Data_Checks!$C:$C,81+1)) | D85: =IF(INDEX(Data_Checks!$D:$D,81+1)="","",INDEX(Data_Checks!$D:$D,81+1)) | E85: =IF(INDEX(Data_Checks!$E:$E,81+1)="","",INDEX(Data_Checks!$E:$E,81+1)) | F85: =IF(INDEX(Data_Checks!$F:$F,81+1)="","",INDEX(Data_Checks!$F:$F,81+1)) | G85: =IF(INDEX(Data_Checks!$G:$G,81+1)="","",INDEX(Data_Checks!$G:$G,81+1)) | H85: =IF(INDEX(Data_Checks!$H:$H,81+1)="","",INDEX(Data_Checks!$H:$H,81+1))
A86: =IF(INDEX(Data_Checks!$A:$A,82+1)="","",INDEX(Data_Checks!$A:$A,82+1)) | B86: =IF(INDEX(Data_Checks!$B:$B,82+1)="","",INDEX(Data_Checks!$B:$B,82+1)) | C86: =IF(INDEX(Data_Checks!$C:$C,82+1)="","",INDEX(Data_Checks!$C:$C,82+1)) | D86: =IF(INDEX(Data_Checks!$D:$D,82+1)="","",INDEX(Data_Checks!$D:$D,82+1)) | E86: =IF(INDEX(Data_Checks!$E:$E,82+1)="","",INDEX(Data_Checks!$E:$E,82+1)) | F86: =IF(INDEX(Data_Checks!$F:$F,82+1)="","",INDEX(Data_Checks!$F:$F,82+1)) | G86: =IF(INDEX(Data_Checks!$G:$G,82+1)="","",INDEX(Data_Checks!$G:$G,82+1)) | H86: =IF(INDEX(Data_Checks!$H:$H,82+1)="","",INDEX(Data_Checks!$H:$H,82+1))
A87: =IF(INDEX(Data_Checks!$A:$A,83+1)="","",INDEX(Data_Checks!$A:$A,83+1)) | B87: =IF(INDEX(Data_Checks!$B:$B,83+1)="","",INDEX(Data_Checks!$B:$B,83+1)) | C87: =IF(INDEX(Data_Checks!$C:$C,83+1)="","",INDEX(Data_Checks!$C:$C,83+1)) | D87: =IF(INDEX(Data_Checks!$D:$D,83+1)="","",INDEX(Data_Checks!$D:$D,83+1)) | E87: =IF(INDEX(Data_Checks!$E:$E,83+1)="","",INDEX(Data_Checks!$E:$E,83+1)) | F87: =IF(INDEX(Data_Checks!$F:$F,83+1)="","",INDEX(Data_Checks!$F:$F,83+1)) | G87: =IF(INDEX(Data_Checks!$G:$G,83+1)="","",INDEX(Data_Checks!$G:$G,83+1)) | H87: =IF(INDEX(Data_Checks!$H:$H,83+1)="","",INDEX(Data_Checks!$H:$H,83+1))
A88: =IF(INDEX(Data_Checks!$A:$A,84+1)="","",INDEX(Data_Checks!$A:$A,84+1)) | B88: =IF(INDEX(Data_Checks!$B:$B,84+1)="","",INDEX(Data_Checks!$B:$B,84+1)) | C88: =IF(INDEX(Data_Checks!$C:$C,84+1)="","",INDEX(Data_Checks!$C:$C,84+1)) | D88: =IF(INDEX(Data_Checks!$D:$D,84+1)="","",INDEX(Data_Checks!$D:$D,84+1)) | E88: =IF(INDEX(Data_Checks!$E:$E,84+1)="","",INDEX(Data_Checks!$E:$E,84+1)) | F88: =IF(INDEX(Data_Checks!$F:$F,84+1)="","",INDEX(Data_Checks!$F:$F,84+1)) | G88: =IF(INDEX(Data_Checks!$G:$G,84+1)="","",INDEX(Data_Checks!$G:$G,84+1)) | H88: =IF(INDEX(Data_Checks!$H:$H,84+1)="","",INDEX(Data_Checks!$H:$H,84+1))
A89: =IF(INDEX(Data_Checks!$A:$A,85+1)="","",INDEX(Data_Checks!$A:$A,85+1)) | B89: =IF(INDEX(Data_Checks!$B:$B,85+1)="","",INDEX(Data_Checks!$B:$B,85+1)) | C89: =IF(INDEX(Data_Checks!$C:$C,85+1)="","",INDEX(Data_Checks!$C:$C,85+1)) | D89: =IF(INDEX(Data_Checks!$D:$D,85+1)="","",INDEX(Data_Checks!$D:$D,85+1)) | E89: =IF(INDEX(Data_Checks!$E:$E,85+1)="","",INDEX(Data_Checks!$E:$E,85+1)) | F89: =IF(INDEX(Data_Checks!$F:$F,85+1)="","",INDEX(Data_Checks!$F:$F,85+1)) | G89: =IF(INDEX(Data_Checks!$G:$G,85+1)="","",INDEX(Data_Checks!$G:$G,85+1)) | H89: =IF(INDEX(Data_Checks!$H:$H,85+1)="","",INDEX(Data_Checks!$H:$H,85+1))
A90: =IF(INDEX(Data_Checks!$A:$A,86+1)="","",INDEX(Data_Checks!$A:$A,86+1)) | B90: =IF(INDEX(Data_Checks!$B:$B,86+1)="","",INDEX(Data_Checks!$B:$B,86+1)) | C90: =IF(INDEX(Data_Checks!$C:$C,86+1)="","",INDEX(Data_Checks!$C:$C,86+1)) | D90: =IF(INDEX(Data_Checks!$D:$D,86+1)="","",INDEX(Data_Checks!$D:$D,86+1)) | E90: =IF(INDEX(Data_Checks!$E:$E,86+1)="","",INDEX(Data_Checks!$E:$E,86+1)) | F90: =IF(INDEX(Data_Checks!$F:$F,86+1)="","",INDEX(Data_Checks!$F:$F,86+1)) | G90: =IF(INDEX(Data_Checks!$G:$G,86+1)="","",INDEX(Data_Checks!$G:$G,86+1)) | H90: =IF(INDEX(Data_Checks!$H:$H,86+1)="","",INDEX(Data_Checks!$H:$H,86+1))
A91: =IF(INDEX(Data_Checks!$A:$A,87+1)="","",INDEX(Data_Checks!$A:$A,87+1)) | B91: =IF(INDEX(Data_Checks!$B:$B,87+1)="","",INDEX(Data_Checks!$B:$B,87+1)) | C91: =IF(INDEX(Data_Checks!$C:$C,87+1)="","",INDEX(Data_Checks!$C:$C,87+1)) | D91: =IF(INDEX(Data_Checks!$D:$D,87+1)="","",INDEX(Data_Checks!$D:$D,87+1)) | E91: =IF(INDEX(Data_Checks!$E:$E,87+1)="","",INDEX(Data_Checks!$E:$E,87+1)) | F91: =IF(INDEX(Data_Checks!$F:$F,87+1)="","",INDEX(Data_Checks!$F:$F,87+1)) | G91: =IF(INDEX(Data_Checks!$G:$G,87+1)="","",INDEX(Data_Checks!$G:$G,87+1)) | H91: =IF(INDEX(Data_Checks!$H:$H,87+1)="","",INDEX(Data_Checks!$H:$H,87+1))
A92: =IF(INDEX(Data_Checks!$A:$A,88+1)="","",INDEX(Data_Checks!$A:$A,88+1)) | B92: =IF(INDEX(Data_Checks!$B:$B,88+1)="","",INDEX(Data_Checks!$B:$B,88+1)) | C92: =IF(INDEX(Data_Checks!$C:$C,88+1)="","",INDEX(Data_Checks!$C:$C,88+1)) | D92: =IF(INDEX(Data_Checks!$D:$D,88+1)="","",INDEX(Data_Checks!$D:$D,88+1)) | E92: =IF(INDEX(Data_Checks!$E:$E,88+1)="","",INDEX(Data_Checks!$E:$E,88+1)) | F92: =IF(INDEX(Data_Checks!$F:$F,88+1)="","",INDEX(Data_Checks!$F:$F,88+1)) | G92: =IF(INDEX(Data_Checks!$G:$G,88+1)="","",INDEX(Data_Checks!$G:$G,88+1)) | H92: =IF(INDEX(Data_Checks!$H:$H,88+1)="","",INDEX(Data_Checks!$H:$H,88+1))
A93: =IF(INDEX(Data_Checks!$A:$A,89+1)="","",INDEX(Data_Checks!$A:$A,89+1)) | B93: =IF(INDEX(Data_Checks!$B:$B,89+1)="","",INDEX(Data_Checks!$B:$B,89+1)) | C93: =IF(INDEX(Data_Checks!$C:$C,89+1)="","",INDEX(Data_Checks!$C:$C,89+1)) | D93: =IF(INDEX(Data_Checks!$D:$D,89+1)="","",INDEX(Data_Checks!$D:$D,89+1)) | E93: =IF(INDEX(Data_Checks!$E:$E,89+1)="","",INDEX(Data_Checks!$E:$E,89+1)) | F93: =IF(INDEX(Data_Checks!$F:$F,89+1)="","",INDEX(Data_Checks!$F:$F,89+1)) | G93: =IF(INDEX(Data_Checks!$G:$G,89+1)="","",INDEX(Data_Checks!$G:$G,89+1)) | H93: =IF(INDEX(Data_Checks!$H:$H,89+1)="","",INDEX(Data_Checks!$H:$H,89+1))
A94: =IF(INDEX(Data_Checks!$A:$A,90+1)="","",INDEX(Data_Checks!$A:$A,90+1)) | B94: =IF(INDEX(Data_Checks!$B:$B,90+1)="","",INDEX(Data_Checks!$B:$B,90+1)) | C94: =IF(INDEX(Data_Checks!$C:$C,90+1)="","",INDEX(Data_Checks!$C:$C,90+1)) | D94: =IF(INDEX(Data_Checks!$D:$D,90+1)="","",INDEX(Data_Checks!$D:$D,90+1)) | E94: =IF(INDEX(Data_Checks!$E:$E,90+1)="","",INDEX(Data_Checks!$E:$E,90+1)) | F94: =IF(INDEX(Data_Checks!$F:$F,90+1)="","",INDEX(Data_Checks!$F:$F,90+1)) | G94: =IF(INDEX(Data_Checks!$G:$G,90+1)="","",INDEX(Data_Checks!$G:$G,90+1)) | H94: =IF(INDEX(Data_Checks!$H:$H,90+1)="","",INDEX(Data_Checks!$H:$H,90+1))
A95: =IF(INDEX(Data_Checks!$A:$A,91+1)="","",INDEX(Data_Checks!$A:$A,91+1)) | B95: =IF(INDEX(Data_Checks!$B:$B,91+1)="","",INDEX(Data_Checks!$B:$B,91+1)) | C95: =IF(INDEX(Data_Checks!$C:$C,91+1)="","",INDEX(Data_Checks!$C:$C,91+1)) | D95: =IF(INDEX(Data_Checks!$D:$D,91+1)="","",INDEX(Data_Checks!$D:$D,91+1)) | E95: =IF(INDEX(Data_Checks!$E:$E,91+1)="","",INDEX(Data_Checks!$E:$E,91+1)) | F95: =IF(INDEX(Data_Checks!$F:$F,91+1)="","",INDEX(Data_Checks!$F:$F,91+1)) | G95: =IF(INDEX(Data_Checks!$G:$G,91+1)="","",INDEX(Data_Checks!$G:$G,91+1)) | H95: =IF(INDEX(Data_Checks!$H:$H,91+1)="","",INDEX(Data_Checks!$H:$H,91+1))
A96: =IF(INDEX(Data_Checks!$A:$A,92+1)="","",INDEX(Data_Checks!$A:$A,92+1)) | B96: =IF(INDEX(Data_Checks!$B:$B,92+1)="","",INDEX(Data_Checks!$B:$B,92+1)) | C96: =IF(INDEX(Data_Checks!$C:$C,92+1)="","",INDEX(Data_Checks!$C:$C,92+1)) | D96: =IF(INDEX(Data_Checks!$D:$D,92+1)="","",INDEX(Data_Checks!$D:$D,92+1)) | E96: =IF(INDEX(Data_Checks!$E:$E,92+1)="","",INDEX(Data_Checks!$E:$E,92+1)) | F96: =IF(INDEX(Data_Checks!$F:$F,92+1)="","",INDEX(Data_Checks!$F:$F,92+1)) | G96: =IF(INDEX(Data_Checks!$G:$G,92+1)="","",INDEX(Data_Checks!$G:$G,92+1)) | H96: =IF(INDEX(Data_Checks!$H:$H,92+1)="","",INDEX(Data_Checks!$H:$H,92+1))
A97: =IF(INDEX(Data_Checks!$A:$A,93+1)="","",INDEX(Data_Checks!$A:$A,93+1)) | B97: =IF(INDEX(Data_Checks!$B:$B,93+1)="","",INDEX(Data_Checks!$B:$B,93+1)) | C97: =IF(INDEX(Data_Checks!$C:$C,93+1)="","",INDEX(Data_Checks!$C:$C,93+1)) | D97: =IF(INDEX(Data_Checks!$D:$D,93+1)="","",INDEX(Data_Checks!$D:$D,93+1)) | E97: =IF(INDEX(Data_Checks!$E:$E,93+1)="","",INDEX(Data_Checks!$E:$E,93+1)) | F97: =IF(INDEX(Data_Checks!$F:$F,93+1)="","",INDEX(Data_Checks!$F:$F,93+1)) | G97: =IF(INDEX(Data_Checks!$G:$G,93+1)="","",INDEX(Data_Checks!$G:$G,93+1)) | H97: =IF(INDEX(Data_Checks!$H:$H,93+1)="","",INDEX(Data_Checks!$H:$H,93+1))
A98: =IF(INDEX(Data_Checks!$A:$A,94+1)="","",INDEX(Data_Checks!$A:$A,94+1)) | B98: =IF(INDEX(Data_Checks!$B:$B,94+1)="","",INDEX(Data_Checks!$B:$B,94+1)) | C98: =IF(INDEX(Data_Checks!$C:$C,94+1)="","",INDEX(Data_Checks!$C:$C,94+1)) | D98: =IF(INDEX(Data_Checks!$D:$D,94+1)="","",INDEX(Data_Checks!$D:$D,94+1)) | E98: =IF(INDEX(Data_Checks!$E:$E,94+1)="","",INDEX(Data_Checks!$E:$E,94+1)) | F98: =IF(INDEX(Data_Checks!$F:$F,94+1)="","",INDEX(Data_Checks!$F:$F,94+1)) | G98: =IF(INDEX(Data_Checks!$G:$G,94+1)="","",INDEX(Data_Checks!$G:$G,94+1)) | H98: =IF(INDEX(Data_Checks!$H:$H,94+1)="","",INDEX(Data_Checks!$H:$H,94+1))
A99: =IF(INDEX(Data_Checks!$A:$A,95+1)="","",INDEX(Data_Checks!$A:$A,95+1)) | B99: =IF(INDEX(Data_Checks!$B:$B,95+1)="","",INDEX(Data_Checks!$B:$B,95+1)) | C99: =IF(INDEX(Data_Checks!$C:$C,95+1)="","",INDEX(Data_Checks!$C:$C,95+1)) | D99: =IF(INDEX(Data_Checks!$D:$D,95+1)="","",INDEX(Data_Checks!$D:$D,95+1)) | E99: =IF(INDEX(Data_Checks!$E:$E,95+1)="","",INDEX(Data_Checks!$E:$E,95+1)) | F99: =IF(INDEX(Data_Checks!$F:$F,95+1)="","",INDEX(Data_Checks!$F:$F,95+1)) | G99: =IF(INDEX(Data_Checks!$G:$G,95+1)="","",INDEX(Data_Checks!$G:$G,95+1)) | H99: =IF(INDEX(Data_Checks!$H:$H,95+1)="","",INDEX(Data_Checks!$H:$H,95+1))
A100: =IF(INDEX(Data_Checks!$A:$A,96+1)="","",INDEX(Data_Checks!$A:$A,96+1)) | B100: =IF(INDEX(Data_Checks!$B:$B,96+1)="","",INDEX(Data_Checks!$B:$B,96+1)) | C100: =IF(INDEX(Data_Checks!$C:$C,96+1)="","",INDEX(Data_Checks!$C:$C,96+1)) | D100: =IF(INDEX(Data_Checks!$D:$D,96+1)="","",INDEX(Data_Checks!$D:$D,96+1)) | E100: =IF(INDEX(Data_Checks!$E:$E,96+1)="","",INDEX(Data_Checks!$E:$E,96+1)) | F100: =IF(INDEX(Data_Checks!$F:$F,96+1)="","",INDEX(Data_Checks!$F:$F,96+1)) | G100: =IF(INDEX(Data_Checks!$G:$G,96+1)="","",INDEX(Data_Checks!$G:$G,96+1)) | H100: =IF(INDEX(Data_Checks!$H:$H,96+1)="","",INDEX(Data_Checks!$H:$H,96+1))
A101: =IF(INDEX(Data_Checks!$A:$A,97+1)="","",INDEX(Data_Checks!$A:$A,97+1)) | B101: =IF(INDEX(Data_Checks!$B:$B,97+1)="","",INDEX(Data_Checks!$B:$B,97+1)) | C101: =IF(INDEX(Data_Checks!$C:$C,97+1)="","",INDEX(Data_Checks!$C:$C,97+1)) | D101: =IF(INDEX(Data_Checks!$D:$D,97+1)="","",INDEX(Data_Checks!$D:$D,97+1)) | E101: =IF(INDEX(Data_Checks!$E:$E,97+1)="","",INDEX(Data_Checks!$E:$E,97+1)) | F101: =IF(INDEX(Data_Checks!$F:$F,97+1)="","",INDEX(Data_Checks!$F:$F,97+1)) | G101: =IF(INDEX(Data_Checks!$G:$G,97+1)="","",INDEX(Data_Checks!$G:$G,97+1)) | H101: =IF(INDEX(Data_Checks!$H:$H,97+1)="","",INDEX(Data_Checks!$H:$H,97+1))
...

Sheet Monthly
A1: =Data_Params!$B$14&" | Usage and revenue by month"
A2: Formulas only: every number reads the Data_ sheets. Tokens in billions, $ in thousands.
A4: Line | B4: =EDATE(Data_Params!$B$3,0) | C4: =EDATE(Data_Params!$B$3,1) | D4: =EDATE(Data_Params!$B$3,2) | E4: =EDATE(Data_Params!$B$3,3) | F4: =EDATE(Data_Params!$B$3,4) | G4: =EDATE(Data_Params!$B$3,5) | H4: =EDATE(Data_Params!$B$3,6) | I4: =EDATE(Data_Params!$B$3,7) | J4: =EDATE(Data_Params!$B$3,8) | K4: =EDATE(Data_Params!$B$3,9) | L4: =EDATE(Data_Params!$B$3,10) | M4: =EDATE(Data_Params!$B$3,11)
A5: Billable tokens (B)
A6: Enterprise | B6: =SUMIFS(Data_Monthly!$F:$F,Data_Monthly!$A:$A,B$4,Data_Monthly!$B:$B,"enterprise")/1E9 | C6: =SUMIFS(Data_Monthly!$F:$F,Data_Monthly!$A:$A,C$4,Data_Monthly!$B:$B,"enterprise")/1E9 | D6: =SUMIFS(Data_Monthly!$F:$F,Data_Monthly!$A:$A,D$4,Data_Monthly!$B:$B,"enterprise")/1E9 | E6: =SUMIFS(Data_Monthly!$F:$F,Data_Monthly!$A:$A,E$4,Data_Monthly!$B:$B,"enterprise")/1E9 | F6: =SUMIFS(Data_Monthly!$F:$F,Data_Monthly!$A:$A,F$4,Data_Monthly!$B:$B,"enterprise")/1E9 | G6: =SUMIFS(Data_Monthly!$F:$F,Data_Monthly!$A:$A,G$4,Data_Monthly!$B:$B,"enterprise")/1E9 | H6: =SUMIFS(Data_Monthly!$F:$F,Data_Monthly!$A:$A,H$4,Data_Monthly!$B:$B,"enterprise")/1E9 | I6: =SUMIFS(Data_Monthly!$F:$F,Data_Monthly!$A:$A,I$4,Data_Monthly!$B:$B,"enterprise")/1E9 | ... M6: =SUMIFS(Data_Monthly!$F:$F,Data_Monthly!$A:$A,M$4,Data_Monthly!$B:$B,"enterprise")/1E9
A7: Self-serve | B7: =SUMIFS(Data_Monthly!$F:$F,Data_Monthly!$A:$A,B$4,Data_Monthly!$B:$B,"self_serve")/1E9 | C7: =SUMIFS(Data_Monthly!$F:$F,Data_Monthly!$A:$A,C$4,Data_Monthly!$B:$B,"self_serve")/1E9 | D7: =SUMIFS(Data_Monthly!$F:$F,Data_Monthly!$A:$A,D$4,Data_Monthly!$B:$B,"self_serve")/1E9 | E7: =SUMIFS(Data_Monthly!$F:$F,Data_Monthly!$A:$A,E$4,Data_Monthly!$B:$B,"self_serve")/1E9 | F7: =SUMIFS(Data_Monthly!$F:$F,Data_Monthly!$A:$A,F$4,Data_Monthly!$B:$B,"self_serve")/1E9 | G7: =SUMIFS(Data_Monthly!$F:$F,Data_Monthly!$A:$A,G$4,Data_Monthly!$B:$B,"self_serve")/1E9 | H7: =SUMIFS(Data_Monthly!$F:$F,Data_Monthly!$A:$A,H$4,Data_Monthly!$B:$B,"self_serve")/1E9 | I7: =SUMIFS(Data_Monthly!$F:$F,Data_Monthly!$A:$A,I$4,Data_Monthly!$B:$B,"self_serve")/1E9 | ... M7: =SUMIFS(Data_Monthly!$F:$F,Data_Monthly!$A:$A,M$4,Data_Monthly!$B:$B,"self_serve")/1E9
A8: Gateways that don't pass customer IDs | B8: =SUMIFS(Data_Monthly!$F:$F,Data_Monthly!$A:$A,B$4,Data_Monthly!$B:$B,"gateway_aggregate")/1E9 | C8: =SUMIFS(Data_Monthly!$F:$F,Data_Monthly!$A:$A,C$4,Data_Monthly!$B:$B,"gateway_aggregate")/1E9 | D8: =SUMIFS(Data_Monthly!$F:$F,Data_Monthly!$A:$A,D$4,Data_Monthly!$B:$B,"gateway_aggregate")/1E9 | E8: =SUMIFS(Data_Monthly!$F:$F,Data_Monthly!$A:$A,E$4,Data_Monthly!$B:$B,"gateway_aggregate")/1E9 | F8: =SUMIFS(Data_Monthly!$F:$F,Data_Monthly!$A:$A,F$4,Data_Monthly!$B:$B,"gateway_aggregate")/1E9 | G8: =SUMIFS(Data_Monthly!$F:$F,Data_Monthly!$A:$A,G$4,Data_Monthly!$B:$B,"gateway_aggregate")/1E9 | H8: =SUMIFS(Data_Monthly!$F:$F,Data_Monthly!$A:$A,H$4,Data_Monthly!$B:$B,"gateway_aggregate")/1E9 | I8: =SUMIFS(Data_Monthly!$F:$F,Data_Monthly!$A:$A,I$4,Data_Monthly!$B:$B,"gateway_aggregate")/1E9 | ... M8: =SUMIFS(Data_Monthly!$F:$F,Data_Monthly!$A:$A,M$4,Data_Monthly!$B:$B,"gateway_aggregate")/1E9
A9: Unmatched accounts (fix the accounts source) | B9: =SUMIFS(Data_Monthly!$F:$F,Data_Monthly!$A:$A,B$4,Data_Monthly!$B:$B,"unmatched")/1E9 | C9: =SUMIFS(Data_Monthly!$F:$F,Data_Monthly!$A:$A,C$4,Data_Monthly!$B:$B,"unmatched")/1E9 | D9: =SUMIFS(Data_Monthly!$F:$F,Data_Monthly!$A:$A,D$4,Data_Monthly!$B:$B,"unmatched")/1E9 | E9: =SUMIFS(Data_Monthly!$F:$F,Data_Monthly!$A:$A,E$4,Data_Monthly!$B:$B,"unmatched")/1E9 | F9: =SUMIFS(Data_Monthly!$F:$F,Data_Monthly!$A:$A,F$4,Data_Monthly!$B:$B,"unmatched")/1E9 | G9: =SUMIFS(Data_Monthly!$F:$F,Data_Monthly!$A:$A,G$4,Data_Monthly!$B:$B,"unmatched")/1E9 | H9: =SUMIFS(Data_Monthly!$F:$F,Data_Monthly!$A:$A,H$4,Data_Monthly!$B:$B,"unmatched")/1E9 | I9: =SUMIFS(Data_Monthly!$F:$F,Data_Monthly!$A:$A,I$4,Data_Monthly!$B:$B,"unmatched")/1E9 | ... M9: =SUMIFS(Data_Monthly!$F:$F,Data_Monthly!$A:$A,M$4,Data_Monthly!$B:$B,"unmatched")/1E9
A10: Total billable tokens | B10: =SUM(B6:B9) | C10: =SUM(C6:C9) | D10: =SUM(D6:D9) | E10: =SUM(E6:E9) | F10: =SUM(F6:F9) | G10: =SUM(G6:G9) | H10: =SUM(H6:H9) | I10: =SUM(I6:I9) | ... M10: =SUM(M6:M9)
A11: Days of data in month | B11: =SUMIFS(Data_Months!$B:$B,Data_Months!$A:$A,B$4) | C11: =SUMIFS(Data_Months!$B:$B,Data_Months!$A:$A,C$4) | D11: =SUMIFS(Data_Months!$B:$B,Data_Months!$A:$A,D$4) | E11: =SUMIFS(Data_Months!$B:$B,Data_Months!$A:$A,E$4) | F11: =SUMIFS(Data_Months!$B:$B,Data_Months!$A:$A,F$4) | G11: =SUMIFS(Data_Months!$B:$B,Data_Months!$A:$A,G$4) | H11: =SUMIFS(Data_Months!$B:$B,Data_Months!$A:$A,H$4) | I11: =SUMIFS(Data_Months!$B:$B,Data_Months!$A:$A,I$4) | ... M11: =SUMIFS(Data_Months!$B:$B,Data_Months!$A:$A,M$4)
A12: Tokens per day (B) | B12: =IF(B11=0,0,B10/B11) | C12: =IF(C11=0,0,C10/C11) | D12: =IF(D11=0,0,D10/D11) | E12: =IF(E11=0,0,E10/E11) | F12: =IF(F11=0,0,F10/F11) | G12: =IF(G11=0,0,G10/G11) | H12: =IF(H11=0,0,H10/H11) | I12: =IF(I11=0,0,I10/I11) | ... M12: =IF(M11=0,0,M10/M11)
A13: Enterprise, per day | B13: =IF(B11=0,0,B6/B11) | C13: =IF(C11=0,0,C6/C11) | D13: =IF(D11=0,0,D6/D11) | E13: =IF(E11=0,0,E6/E11) | F13: =IF(F11=0,0,F6/F11) | G13: =IF(G11=0,0,G6/G11) | H13: =IF(H11=0,0,H6/H11) | I13: =IF(I11=0,0,I6/I11) | ... M13: =IF(M11=0,0,M6/M11)
A14: Self-serve, per day | B14: =IF(B11=0,0,B7/B11) | C14: =IF(C11=0,0,C7/C11) | D14: =IF(D11=0,0,D7/D11) | E14: =IF(E11=0,0,E7/E11) | F14: =IF(F11=0,0,F7/F11) | G14: =IF(G11=0,0,G7/G11) | H14: =IF(H11=0,0,H7/H11) | I14: =IF(I11=0,0,I7/I11) | ... M14: =IF(M11=0,0,M7/M11)
A15: Gateways that don't pass customer IDs, per day | B15: =IF(B11=0,0,B8/B11) | C15: =IF(C11=0,0,C8/C11) | D15: =IF(D11=0,0,D8/D11) | E15: =IF(E11=0,0,E8/E11) | F15: =IF(F11=0,0,F8/F11) | G15: =IF(G11=0,0,G8/G11) | H15: =IF(H11=0,0,H8/H11) | I15: =IF(I11=0,0,I8/I11) | ... M15: =IF(M11=0,0,M8/M11)
A16: Growth in tokens per day vs prior month | C16: =IF(B12=0,0,C12/B12-1) | D16: =IF(C12=0,0,D12/C12-1) | E16: =IF(D12=0,0,E12/D12-1) | F16: =IF(E12=0,0,F12/E12-1) | G16: =IF(F12=0,0,G12/F12-1) | H16: =IF(G12=0,0,H12/G12-1) | I16: =IF(H12=0,0,I12/H12-1) | J16: =IF(I12=0,0,J12/I12-1) | ... M16: =IF(L12=0,0,M12/L12-1)
A18: Billable tokens by channel (B)
A19: =IF(INDEX(Data_Lists!$B:$B,1+1)="","",INDEX(Data_Lists!$B:$B,1+1)) | B19: =IF($A19="","",SUMIFS(Data_Monthly!$F:$F,Data_Monthly!$A:$A,B$4,Data_Monthly!$C:$C,$A19)/1E9) | C19: =IF($A19="","",SUMIFS(Data_Monthly!$F:$F,Data_Monthly!$A:$A,C$4,Data_Monthly!$C:$C,$A19)/1E9) | D19: =IF($A19="","",SUMIFS(Data_Monthly!$F:$F,Data_Monthly!$A:$A,D$4,Data_Monthly!$C:$C,$A19)/1E9) | E19: =IF($A19="","",SUMIFS(Data_Monthly!$F:$F,Data_Monthly!$A:$A,E$4,Data_Monthly!$C:$C,$A19)/1E9) | F19: =IF($A19="","",SUMIFS(Data_Monthly!$F:$F,Data_Monthly!$A:$A,F$4,Data_Monthly!$C:$C,$A19)/1E9) | G19: =IF($A19="","",SUMIFS(Data_Monthly!$F:$F,Data_Monthly!$A:$A,G$4,Data_Monthly!$C:$C,$A19)/1E9) | H19: =IF($A19="","",SUMIFS(Data_Monthly!$F:$F,Data_Monthly!$A:$A,H$4,Data_Monthly!$C:$C,$A19)/1E9) | I19: =IF($A19="","",SUMIFS(Data_Monthly!$F:$F,Data_Monthly!$A:$A,I$4,Data_Monthly!$C:$C,$A19)/1E9) | ... M19: =IF($A19="","",SUMIFS(Data_Monthly!$F:$F,Data_Monthly!$A:$A,M$4,Data_Monthly!$C:$C,$A19)/1E9)
A20: =IF(INDEX(Data_Lists!$B:$B,2+1)="","",INDEX(Data_Lists!$B:$B,2+1)) | B20: =IF($A20="","",SUMIFS(Data_Monthly!$F:$F,Data_Monthly!$A:$A,B$4,Data_Monthly!$C:$C,$A20)/1E9) | C20: =IF($A20="","",SUMIFS(Data_Monthly!$F:$F,Data_Monthly!$A:$A,C$4,Data_Monthly!$C:$C,$A20)/1E9) | D20: =IF($A20="","",SUMIFS(Data_Monthly!$F:$F,Data_Monthly!$A:$A,D$4,Data_Monthly!$C:$C,$A20)/1E9) | E20: =IF($A20="","",SUMIFS(Data_Monthly!$F:$F,Data_Monthly!$A:$A,E$4,Data_Monthly!$C:$C,$A20)/1E9) | F20: =IF($A20="","",SUMIFS(Data_Monthly!$F:$F,Data_Monthly!$A:$A,F$4,Data_Monthly!$C:$C,$A20)/1E9) | G20: =IF($A20="","",SUMIFS(Data_Monthly!$F:$F,Data_Monthly!$A:$A,G$4,Data_Monthly!$C:$C,$A20)/1E9) | H20: =IF($A20="","",SUMIFS(Data_Monthly!$F:$F,Data_Monthly!$A:$A,H$4,Data_Monthly!$C:$C,$A20)/1E9) | I20: =IF($A20="","",SUMIFS(Data_Monthly!$F:$F,Data_Monthly!$A:$A,I$4,Data_Monthly!$C:$C,$A20)/1E9) | ... M20: =IF($A20="","",SUMIFS(Data_Monthly!$F:$F,Data_Monthly!$A:$A,M$4,Data_Monthly!$C:$C,$A20)/1E9)
A21: =IF(INDEX(Data_Lists!$B:$B,3+1)="","",INDEX(Data_Lists!$B:$B,3+1)) | B21: =IF($A21="","",SUMIFS(Data_Monthly!$F:$F,Data_Monthly!$A:$A,B$4,Data_Monthly!$C:$C,$A21)/1E9) | C21: =IF($A21="","",SUMIFS(Data_Monthly!$F:$F,Data_Monthly!$A:$A,C$4,Data_Monthly!$C:$C,$A21)/1E9) | D21: =IF($A21="","",SUMIFS(Data_Monthly!$F:$F,Data_Monthly!$A:$A,D$4,Data_Monthly!$C:$C,$A21)/1E9) | E21: =IF($A21="","",SUMIFS(Data_Monthly!$F:$F,Data_Monthly!$A:$A,E$4,Data_Monthly!$C:$C,$A21)/1E9) | F21: =IF($A21="","",SUMIFS(Data_Monthly!$F:$F,Data_Monthly!$A:$A,F$4,Data_Monthly!$C:$C,$A21)/1E9) | G21: =IF($A21="","",SUMIFS(Data_Monthly!$F:$F,Data_Monthly!$A:$A,G$4,Data_Monthly!$C:$C,$A21)/1E9) | H21: =IF($A21="","",SUMIFS(Data_Monthly!$F:$F,Data_Monthly!$A:$A,H$4,Data_Monthly!$C:$C,$A21)/1E9) | I21: =IF($A21="","",SUMIFS(Data_Monthly!$F:$F,Data_Monthly!$A:$A,I$4,Data_Monthly!$C:$C,$A21)/1E9) | ... M21: =IF($A21="","",SUMIFS(Data_Monthly!$F:$F,Data_Monthly!$A:$A,M$4,Data_Monthly!$C:$C,$A21)/1E9)
A22: =IF(INDEX(Data_Lists!$B:$B,4+1)="","",INDEX(Data_Lists!$B:$B,4+1)) | B22: =IF($A22="","",SUMIFS(Data_Monthly!$F:$F,Data_Monthly!$A:$A,B$4,Data_Monthly!$C:$C,$A22)/1E9) | C22: =IF($A22="","",SUMIFS(Data_Monthly!$F:$F,Data_Monthly!$A:$A,C$4,Data_Monthly!$C:$C,$A22)/1E9) | D22: =IF($A22="","",SUMIFS(Data_Monthly!$F:$F,Data_Monthly!$A:$A,D$4,Data_Monthly!$C:$C,$A22)/1E9) | E22: =IF($A22="","",SUMIFS(Data_Monthly!$F:$F,Data_Monthly!$A:$A,E$4,Data_Monthly!$C:$C,$A22)/1E9) | F22: =IF($A22="","",SUMIFS(Data_Monthly!$F:$F,Data_Monthly!$A:$A,F$4,Data_Monthly!$C:$C,$A22)/1E9) | G22: =IF($A22="","",SUMIFS(Data_Monthly!$F:$F,Data_Monthly!$A:$A,G$4,Data_Monthly!$C:$C,$A22)/1E9) | H22: =IF($A22="","",SUMIFS(Data_Monthly!$F:$F,Data_Monthly!$A:$A,H$4,Data_Monthly!$C:$C,$A22)/1E9) | I22: =IF($A22="","",SUMIFS(Data_Monthly!$F:$F,Data_Monthly!$A:$A,I$4,Data_Monthly!$C:$C,$A22)/1E9) | ... M22: =IF($A22="","",SUMIFS(Data_Monthly!$F:$F,Data_Monthly!$A:$A,M$4,Data_Monthly!$C:$C,$A22)/1E9)
A23: =IF(INDEX(Data_Lists!$B:$B,5+1)="","",INDEX(Data_Lists!$B:$B,5+1)) | B23: =IF($A23="","",SUMIFS(Data_Monthly!$F:$F,Data_Monthly!$A:$A,B$4,Data_Monthly!$C:$C,$A23)/1E9) | C23: =IF($A23="","",SUMIFS(Data_Monthly!$F:$F,Data_Monthly!$A:$A,C$4,Data_Monthly!$C:$C,$A23)/1E9) | D23: =IF($A23="","",SUMIFS(Data_Monthly!$F:$F,Data_Monthly!$A:$A,D$4,Data_Monthly!$C:$C,$A23)/1E9) | E23: =IF($A23="","",SUMIFS(Data_Monthly!$F:$F,Data_Monthly!$A:$A,E$4,Data_Monthly!$C:$C,$A23)/1E9) | F23: =IF($A23="","",SUMIFS(Data_Monthly!$F:$F,Data_Monthly!$A:$A,F$4,Data_Monthly!$C:$C,$A23)/1E9) | G23: =IF($A23="","",SUMIFS(Data_Monthly!$F:$F,Data_Monthly!$A:$A,G$4,Data_Monthly!$C:$C,$A23)/1E9) | H23: =IF($A23="","",SUMIFS(Data_Monthly!$F:$F,Data_Monthly!$A:$A,H$4,Data_Monthly!$C:$C,$A23)/1E9) | I23: =IF($A23="","",SUMIFS(Data_Monthly!$F:$F,Data_Monthly!$A:$A,I$4,Data_Monthly!$C:$C,$A23)/1E9) | ... M23: =IF($A23="","",SUMIFS(Data_Monthly!$F:$F,Data_Monthly!$A:$A,M$4,Data_Monthly!$C:$C,$A23)/1E9)
A24: =IF(INDEX(Data_Lists!$B:$B,6+1)="","",INDEX(Data_Lists!$B:$B,6+1)) | B24: =IF($A24="","",SUMIFS(Data_Monthly!$F:$F,Data_Monthly!$A:$A,B$4,Data_Monthly!$C:$C,$A24)/1E9) | C24: =IF($A24="","",SUMIFS(Data_Monthly!$F:$F,Data_Monthly!$A:$A,C$4,Data_Monthly!$C:$C,$A24)/1E9) | D24: =IF($A24="","",SUMIFS(Data_Monthly!$F:$F,Data_Monthly!$A:$A,D$4,Data_Monthly!$C:$C,$A24)/1E9) | E24: =IF($A24="","",SUMIFS(Data_Monthly!$F:$F,Data_Monthly!$A:$A,E$4,Data_Monthly!$C:$C,$A24)/1E9) | F24: =IF($A24="","",SUMIFS(Data_Monthly!$F:$F,Data_Monthly!$A:$A,F$4,Data_Monthly!$C:$C,$A24)/1E9) | G24: =IF($A24="","",SUMIFS(Data_Monthly!$F:$F,Data_Monthly!$A:$A,G$4,Data_Monthly!$C:$C,$A24)/1E9) | H24: =IF($A24="","",SUMIFS(Data_Monthly!$F:$F,Data_Monthly!$A:$A,H$4,Data_Monthly!$C:$C,$A24)/1E9) | I24: =IF($A24="","",SUMIFS(Data_Monthly!$F:$F,Data_Monthly!$A:$A,I$4,Data_Monthly!$C:$C,$A24)/1E9) | ... M24: =IF($A24="","",SUMIFS(Data_Monthly!$F:$F,Data_Monthly!$A:$A,M$4,Data_Monthly!$C:$C,$A24)/1E9)
A25: =IF(INDEX(Data_Lists!$B:$B,7+1)="","",INDEX(Data_Lists!$B:$B,7+1)) | B25: =IF($A25="","",SUMIFS(Data_Monthly!$F:$F,Data_Monthly!$A:$A,B$4,Data_Monthly!$C:$C,$A25)/1E9) | C25: =IF($A25="","",SUMIFS(Data_Monthly!$F:$F,Data_Monthly!$A:$A,C$4,Data_Monthly!$C:$C,$A25)/1E9) | D25: =IF($A25="","",SUMIFS(Data_Monthly!$F:$F,Data_Monthly!$A:$A,D$4,Data_Monthly!$C:$C,$A25)/1E9) | E25: =IF($A25="","",SUMIFS(Data_Monthly!$F:$F,Data_Monthly!$A:$A,E$4,Data_Monthly!$C:$C,$A25)/1E9) | F25: =IF($A25="","",SUMIFS(Data_Monthly!$F:$F,Data_Monthly!$A:$A,F$4,Data_Monthly!$C:$C,$A25)/1E9) | G25: =IF($A25="","",SUMIFS(Data_Monthly!$F:$F,Data_Monthly!$A:$A,G$4,Data_Monthly!$C:$C,$A25)/1E9) | H25: =IF($A25="","",SUMIFS(Data_Monthly!$F:$F,Data_Monthly!$A:$A,H$4,Data_Monthly!$C:$C,$A25)/1E9) | I25: =IF($A25="","",SUMIFS(Data_Monthly!$F:$F,Data_Monthly!$A:$A,I$4,Data_Monthly!$C:$C,$A25)/1E9) | ... M25: =IF($A25="","",SUMIFS(Data_Monthly!$F:$F,Data_Monthly!$A:$A,M$4,Data_Monthly!$C:$C,$A25)/1E9)
A26: =IF(INDEX(Data_Lists!$B:$B,8+1)="","",INDEX(Data_Lists!$B:$B,8+1)) | B26: =IF($A26="","",SUMIFS(Data_Monthly!$F:$F,Data_Monthly!$A:$A,B$4,Data_Monthly!$C:$C,$A26)/1E9) | C26: =IF($A26="","",SUMIFS(Data_Monthly!$F:$F,Data_Monthly!$A:$A,C$4,Data_Monthly!$C:$C,$A26)/1E9) | D26: =IF($A26="","",SUMIFS(Data_Monthly!$F:$F,Data_Monthly!$A:$A,D$4,Data_Monthly!$C:$C,$A26)/1E9) | E26: =IF($A26="","",SUMIFS(Data_Monthly!$F:$F,Data_Monthly!$A:$A,E$4,Data_Monthly!$C:$C,$A26)/1E9) | F26: =IF($A26="","",SUMIFS(Data_Monthly!$F:$F,Data_Monthly!$A:$A,F$4,Data_Monthly!$C:$C,$A26)/1E9) | G26: =IF($A26="","",SUMIFS(Data_Monthly!$F:$F,Data_Monthly!$A:$A,G$4,Data_Monthly!$C:$C,$A26)/1E9) | H26: =IF($A26="","",SUMIFS(Data_Monthly!$F:$F,Data_Monthly!$A:$A,H$4,Data_Monthly!$C:$C,$A26)/1E9) | I26: =IF($A26="","",SUMIFS(Data_Monthly!$F:$F,Data_Monthly!$A:$A,I$4,Data_Monthly!$C:$C,$A26)/1E9) | ... M26: =IF($A26="","",SUMIFS(Data_Monthly!$F:$F,Data_Monthly!$A:$A,M$4,Data_Monthly!$C:$C,$A26)/1E9)
A28: Net revenue ($k)
A29: Enterprise | B29: =SUMIFS(Data_Monthly!$L:$L,Data_Monthly!$A:$A,B$4,Data_Monthly!$B:$B,"enterprise")/1E3 | C29: =SUMIFS(Data_Monthly!$L:$L,Data_Monthly!$A:$A,C$4,Data_Monthly!$B:$B,"enterprise")/1E3 | D29: =SUMIFS(Data_Monthly!$L:$L,Data_Monthly!$A:$A,D$4,Data_Monthly!$B:$B,"enterprise")/1E3 | E29: =SUMIFS(Data_Monthly!$L:$L,Data_Monthly!$A:$A,E$4,Data_Monthly!$B:$B,"enterprise")/1E3 | F29: =SUMIFS(Data_Monthly!$L:$L,Data_Monthly!$A:$A,F$4,Data_Monthly!$B:$B,"enterprise")/1E3 | G29: =SUMIFS(Data_Monthly!$L:$L,Data_Monthly!$A:$A,G$4,Data_Monthly!$B:$B,"enterprise")/1E3 | H29: =SUMIFS(Data_Monthly!$L:$L,Data_Monthly!$A:$A,H$4,Data_Monthly!$B:$B,"enterprise")/1E3 | I29: =SUMIFS(Data_Monthly!$L:$L,Data_Monthly!$A:$A,I$4,Data_Monthly!$B:$B,"enterprise")/1E3 | ... M29: =SUMIFS(Data_Monthly!$L:$L,Data_Monthly!$A:$A,M$4,Data_Monthly!$B:$B,"enterprise")/1E3
A30: Self-serve | B30: =SUMIFS(Data_Monthly!$L:$L,Data_Monthly!$A:$A,B$4,Data_Monthly!$B:$B,"self_serve")/1E3 | C30: =SUMIFS(Data_Monthly!$L:$L,Data_Monthly!$A:$A,C$4,Data_Monthly!$B:$B,"self_serve")/1E3 | D30: =SUMIFS(Data_Monthly!$L:$L,Data_Monthly!$A:$A,D$4,Data_Monthly!$B:$B,"self_serve")/1E3 | E30: =SUMIFS(Data_Monthly!$L:$L,Data_Monthly!$A:$A,E$4,Data_Monthly!$B:$B,"self_serve")/1E3 | F30: =SUMIFS(Data_Monthly!$L:$L,Data_Monthly!$A:$A,F$4,Data_Monthly!$B:$B,"self_serve")/1E3 | G30: =SUMIFS(Data_Monthly!$L:$L,Data_Monthly!$A:$A,G$4,Data_Monthly!$B:$B,"self_serve")/1E3 | H30: =SUMIFS(Data_Monthly!$L:$L,Data_Monthly!$A:$A,H$4,Data_Monthly!$B:$B,"self_serve")/1E3 | I30: =SUMIFS(Data_Monthly!$L:$L,Data_Monthly!$A:$A,I$4,Data_Monthly!$B:$B,"self_serve")/1E3 | ... M30: =SUMIFS(Data_Monthly!$L:$L,Data_Monthly!$A:$A,M$4,Data_Monthly!$B:$B,"self_serve")/1E3
A31: Gateways that don't pass customer IDs | B31: =SUMIFS(Data_Monthly!$L:$L,Data_Monthly!$A:$A,B$4,Data_Monthly!$B:$B,"gateway_aggregate")/1E3 | C31: =SUMIFS(Data_Monthly!$L:$L,Data_Monthly!$A:$A,C$4,Data_Monthly!$B:$B,"gateway_aggregate")/1E3 | D31: =SUMIFS(Data_Monthly!$L:$L,Data_Monthly!$A:$A,D$4,Data_Monthly!$B:$B,"gateway_aggregate")/1E3 | E31: =SUMIFS(Data_Monthly!$L:$L,Data_Monthly!$A:$A,E$4,Data_Monthly!$B:$B,"gateway_aggregate")/1E3 | F31: =SUMIFS(Data_Monthly!$L:$L,Data_Monthly!$A:$A,F$4,Data_Monthly!$B:$B,"gateway_aggregate")/1E3 | G31: =SUMIFS(Data_Monthly!$L:$L,Data_Monthly!$A:$A,G$4,Data_Monthly!$B:$B,"gateway_aggregate")/1E3 | H31: =SUMIFS(Data_Monthly!$L:$L,Data_Monthly!$A:$A,H$4,Data_Monthly!$B:$B,"gateway_aggregate")/1E3 | I31: =SUMIFS(Data_Monthly!$L:$L,Data_Monthly!$A:$A,I$4,Data_Monthly!$B:$B,"gateway_aggregate")/1E3 | ... M31: =SUMIFS(Data_Monthly!$L:$L,Data_Monthly!$A:$A,M$4,Data_Monthly!$B:$B,"gateway_aggregate")/1E3
A32: Unmatched accounts (fix the accounts source) | B32: =SUMIFS(Data_Monthly!$L:$L,Data_Monthly!$A:$A,B$4,Data_Monthly!$B:$B,"unmatched")/1E3 | C32: =SUMIFS(Data_Monthly!$L:$L,Data_Monthly!$A:$A,C$4,Data_Monthly!$B:$B,"unmatched")/1E3 | D32: =SUMIFS(Data_Monthly!$L:$L,Data_Monthly!$A:$A,D$4,Data_Monthly!$B:$B,"unmatched")/1E3 | E32: =SUMIFS(Data_Monthly!$L:$L,Data_Monthly!$A:$A,E$4,Data_Monthly!$B:$B,"unmatched")/1E3 | F32: =SUMIFS(Data_Monthly!$L:$L,Data_Monthly!$A:$A,F$4,Data_Monthly!$B:$B,"unmatched")/1E3 | G32: =SUMIFS(Data_Monthly!$L:$L,Data_Monthly!$A:$A,G$4,Data_Monthly!$B:$B,"unmatched")/1E3 | H32: =SUMIFS(Data_Monthly!$L:$L,Data_Monthly!$A:$A,H$4,Data_Monthly!$B:$B,"unmatched")/1E3 | I32: =SUMIFS(Data_Monthly!$L:$L,Data_Monthly!$A:$A,I$4,Data_Monthly!$B:$B,"unmatched")/1E3 | ... M32: =SUMIFS(Data_Monthly!$L:$L,Data_Monthly!$A:$A,M$4,Data_Monthly!$B:$B,"unmatched")/1E3
A33: Manual adjustments (Overrides tab) | B33: =SUMIFS(Overrides!$G$46:$G$75,Overrides!$F$46:$F$75,B$4)/1E3 | C33: =SUMIFS(Overrides!$G$46:$G$75,Overrides!$F$46:$F$75,C$4)/1E3 | D33: =SUMIFS(Overrides!$G$46:$G$75,Overrides!$F$46:$F$75,D$4)/1E3 | E33: =SUMIFS(Overrides!$G$46:$G$75,Overrides!$F$46:$F$75,E$4)/1E3 | F33: =SUMIFS(Overrides!$G$46:$G$75,Overrides!$F$46:$F$75,F$4)/1E3 | G33: =SUMIFS(Overrides!$G$46:$G$75,Overrides!$F$46:$F$75,G$4)/1E3 | H33: =SUMIFS(Overrides!$G$46:$G$75,Overrides!$F$46:$F$75,H$4)/1E3 | I33: =SUMIFS(Overrides!$G$46:$G$75,Overrides!$F$46:$F$75,I$4)/1E3 | ... M33: =SUMIFS(Overrides!$G$46:$G$75,Overrides!$F$46:$F$75,M$4)/1E3
A34: Total net revenue | B34: =SUM(B29:B33) | C34: =SUM(C29:C33) | D34: =SUM(D29:D33) | E34: =SUM(E29:E33) | F34: =SUM(F29:F33) | G34: =SUM(G29:G33) | H34: =SUM(H29:H33) | I34: =SUM(I29:I33) | ... M34: =SUM(M29:M33)
A35: of which enterprise true-ups | B35: =SUMIFS(Data_Monthly!$K:$K,Data_Monthly!$A:$A,B$4)/1E3 | C35: =SUMIFS(Data_Monthly!$K:$K,Data_Monthly!$A:$A,C$4)/1E3 | D35: =SUMIFS(Data_Monthly!$K:$K,Data_Monthly!$A:$A,D$4)/1E3 | E35: =SUMIFS(Data_Monthly!$K:$K,Data_Monthly!$A:$A,E$4)/1E3 | F35: =SUMIFS(Data_Monthly!$K:$K,Data_Monthly!$A:$A,F$4)/1E3 | G35: =SUMIFS(Data_Monthly!$K:$K,Data_Monthly!$A:$A,G$4)/1E3 | H35: =SUMIFS(Data_Monthly!$K:$K,Data_Monthly!$A:$A,H$4)/1E3 | I35: =SUMIFS(Data_Monthly!$K:$K,Data_Monthly!$A:$A,I$4)/1E3 | ... M35: =SUMIFS(Data_Monthly!$K:$K,Data_Monthly!$A:$A,M$4)/1E3
A36: Annualized run-rate ($k) | B36: =IF(B11=0,0,B34/B11*365) | C36: =IF(C11=0,0,C34/C11*365) | D36: =IF(D11=0,0,D34/D11*365) | E36: =IF(E11=0,0,E34/E11*365) | F36: =IF(F11=0,0,F34/F11*365) | G36: =IF(G11=0,0,G34/G11*365) | H36: =IF(H11=0,0,H34/H11*365) | I36: =IF(I11=0,0,I34/I11*365) | ... M36: =IF(M11=0,0,M34/M11*365)
A37: Enterprise share of net revenue | B37: =IF(B34=0,0,B29/B34) | C37: =IF(C34=0,0,C29/C34) | D37: =IF(D34=0,0,D29/D34) | E37: =IF(E34=0,0,E29/E34) | F37: =IF(F34=0,0,F29/F34) | G37: =IF(G34=0,0,G29/G34) | H37: =IF(H34=0,0,H29/H34) | I37: =IF(I34=0,0,I29/I34) | ... M37: =IF(M34=0,0,M29/M34)
A38: Realized net price per M tokens ($) | B38: =IF(B10=0,0,B34/B10) | C38: =IF(C10=0,0,C34/C10) | D38: =IF(D10=0,0,D34/D10) | E38: =IF(E10=0,0,E34/E10) | F38: =IF(F10=0,0,F34/F10) | G38: =IF(G10=0,0,G34/G10) | H38: =IF(H10=0,0,H34/H10) | I38: =IF(I10=0,0,I34/I10) | ... M38: =IF(M10=0,0,M34/M10)
A40: Other lines
A41: List value of tokens ($k) | B41: =SUMIFS(Data_Monthly!$I:$I,Data_Monthly!$A:$A,B$4)/1000 | C41: =SUMIFS(Data_Monthly!$I:$I,Data_Monthly!$A:$A,C$4)/1000 | D41: =SUMIFS(Data_Monthly!$I:$I,Data_Monthly!$A:$A,D$4)/1000 | E41: =SUMIFS(Data_Monthly!$I:$I,Data_Monthly!$A:$A,E$4)/1000 | F41: =SUMIFS(Data_Monthly!$I:$I,Data_Monthly!$A:$A,F$4)/1000 | G41: =SUMIFS(Data_Monthly!$I:$I,Data_Monthly!$A:$A,G$4)/1000 | H41: =SUMIFS(Data_Monthly!$I:$I,Data_Monthly!$A:$A,H$4)/1000 | I41: =SUMIFS(Data_Monthly!$I:$I,Data_Monthly!$A:$A,I$4)/1000 | ... M41: =SUMIFS(Data_Monthly!$I:$I,Data_Monthly!$A:$A,M$4)/1000
A42: Free credit used ($k) | B42: =SUMIFS(Data_Monthly!$H:$H,Data_Monthly!$A:$A,B$4)/1000 | C42: =SUMIFS(Data_Monthly!$H:$H,Data_Monthly!$A:$A,C$4)/1000 | D42: =SUMIFS(Data_Monthly!$H:$H,Data_Monthly!$A:$A,D$4)/1000 | E42: =SUMIFS(Data_Monthly!$H:$H,Data_Monthly!$A:$A,E$4)/1000 | F42: =SUMIFS(Data_Monthly!$H:$H,Data_Monthly!$A:$A,F$4)/1000 | G42: =SUMIFS(Data_Monthly!$H:$H,Data_Monthly!$A:$A,G$4)/1000 | H42: =SUMIFS(Data_Monthly!$H:$H,Data_Monthly!$A:$A,H$4)/1000 | I42: =SUMIFS(Data_Monthly!$H:$H,Data_Monthly!$A:$A,I$4)/1000 | ... M42: =SUMIFS(Data_Monthly!$H:$H,Data_Monthly!$A:$A,M$4)/1000
A43: Gateway fees ($k) | B43: =SUMIFS(Data_Monthly!$M:$M,Data_Monthly!$A:$A,B$4)/1000 | C43: =SUMIFS(Data_Monthly!$M:$M,Data_Monthly!$A:$A,C$4)/1000 | D43: =SUMIFS(Data_Monthly!$M:$M,Data_Monthly!$A:$A,D$4)/1000 | E43: =SUMIFS(Data_Monthly!$M:$M,Data_Monthly!$A:$A,E$4)/1000 | F43: =SUMIFS(Data_Monthly!$M:$M,Data_Monthly!$A:$A,F$4)/1000 | G43: =SUMIFS(Data_Monthly!$M:$M,Data_Monthly!$A:$A,G$4)/1000 | H43: =SUMIFS(Data_Monthly!$M:$M,Data_Monthly!$A:$A,H$4)/1000 | I43: =SUMIFS(Data_Monthly!$M:$M,Data_Monthly!$A:$A,I$4)/1000 | ... M43: =SUMIFS(Data_Monthly!$M:$M,Data_Monthly!$A:$A,M$4)/1000
A44: Active accounts (gateways counted once) | B44: =SUMIFS(Data_Monthly!$D:$D,Data_Monthly!$A:$A,B$4) | C44: =SUMIFS(Data_Monthly!$D:$D,Data_Monthly!$A:$A,C$4) | D44: =SUMIFS(Data_Monthly!$D:$D,Data_Monthly!$A:$A,D$4) | E44: =SUMIFS(Data_Monthly!$D:$D,Data_Monthly!$A:$A,E$4) | F44: =SUMIFS(Data_Monthly!$D:$D,Data_Monthly!$A:$A,F$4) | G44: =SUMIFS(Data_Monthly!$D:$D,Data_Monthly!$A:$A,G$4) | H44: =SUMIFS(Data_Monthly!$D:$D,Data_Monthly!$A:$A,H$4) | I44: =SUMIFS(Data_Monthly!$D:$D,Data_Monthly!$A:$A,I$4) | ... M44: =SUMIFS(Data_Monthly!$D:$D,Data_Monthly!$A:$A,M$4)
A45: Paying accounts | B45: =SUMIFS(Data_Monthly!$E:$E,Data_Monthly!$A:$A,B$4) | C45: =SUMIFS(Data_Monthly!$E:$E,Data_Monthly!$A:$A,C$4) | D45: =SUMIFS(Data_Monthly!$E:$E,Data_Monthly!$A:$A,D$4) | E45: =SUMIFS(Data_Monthly!$E:$E,Data_Monthly!$A:$A,E$4) | F45: =SUMIFS(Data_Monthly!$E:$E,Data_Monthly!$A:$A,F$4) | G45: =SUMIFS(Data_Monthly!$E:$E,Data_Monthly!$A:$A,G$4) | H45: =SUMIFS(Data_Monthly!$E:$E,Data_Monthly!$A:$A,H$4) | I45: =SUMIFS(Data_Monthly!$E:$E,Data_Monthly!$A:$A,I$4) | ... M45: =SUMIFS(Data_Monthly!$E:$E,Data_Monthly!$A:$A,M$4)
A46: Failed calls as % of all calls (not billed) | B46: =IF(SUMIFS(Data_Reliability!$B:$B,Data_Reliability!$A:$A,B$4)+SUMIFS(Data_Reliability!$C:$C,Data_Reliability!$A:$A,B$4)=0,0,SUMIFS(Data_Reliability!$C:$C,Data_Reliability!$A:$A,B$4)/(SUMIFS(Data_Reliability!$B:$B,Data_Reliability!$A:$A,B$4)+SUMIFS(Data_Reliability!$C:$C,Data_Reliability!$A:$A,B$4))) | C46: =IF(SUMIFS(Data_Reliability!$B:$B,Data_Reliability!$A:$A,C$4)+SUMIFS(Data_Reliability!$C:$C,Data_Reliability!$A:$A,C$4)=0,0,SUMIFS(Data_Reliability!$C:$C,Data_Reliability!$A:$A,C$4)/(SUMIFS(Data_Reliability!$B:$B,Data_Reliability!$A:$A,C$4)+SUMIFS(Data_Reliability!$C:$C,Data_Reliability!$A:$A,C$4))) | D46: =IF(SUMIFS(Data_Reliability!$B:$B,Data_Reliability!$A:$A,D$4)+SUMIFS(Data_Reliability!$C:$C,Data_Reliability!$A:$A,D$4)=0,0,SUMIFS(Data_Reliability!$C:$C,Data_Reliability!$A:$A,D$4)/(SUMIFS(Data_Reliability!$B:$B,Data_Reliability!$A:$A,D$4)+SUMIFS(Data_Reliability!$C:$C,Data_Reliability!$A:$A,D$4))) | E46: =IF(SUMIFS(Data_Reliability!$B:$B,Data_Reliability!$A:$A,E$4)+SUMIFS(Data_Reliability!$C:$C,Data_Reliability!$A:$A,E$4)=0,0,SUMIFS(Data_Reliability!$C:$C,Data_Reliability!$A:$A,E$4)/(SUMIFS(Data_Reliability!$B:$B,Data_Reliability!$A:$A,E$4)+SUMIFS(Data_Reliability!$C:$C,Data_Reliability!$A:$A,E$4))) | F46: =IF(SUMIFS(Data_Reliability!$B:$B,Data_Reliability!$A:$A,F$4)+SUMIFS(Data_Reliability!$C:$C,Data_Reliability!$A:$A,F$4)=0,0,SUMIFS(Data_Reliability!$C:$C,Data_Reliability!$A:$A,F$4)/(SUMIFS(Data_Reliability!$B:$B,Data_Reliability!$A:$A,F$4)+SUMIFS(Data_Reliability!$C:$C,Data_Reliability!$A:$A,F$4))) | G46: =IF(SUMIFS(Data_Reliability!$B:$B,Data_Reliability!$A:$A,G$4)+SUMIFS(Data_Reliability!$C:$C,Data_Reliability!$A:$A,G$4)=0,0,SUMIFS(Data_Reliability!$C:$C,Data_Reliability!$A:$A,G$4)/(SUMIFS(Data_Reliability!$B:$B,Data_Reliability!$A:$A,G$4)+SUMIFS(Data_Reliability!$C:$C,Data_Reliability!$A:$A,G$4))) | H46: =IF(SUMIFS(Data_Reliability!$B:$B,Data_Reliability!$A:$A,H$4)+SUMIFS(Data_Reliability!$C:$C,Data_Reliability!$A:$A,H$4)=0,0,SUMIFS(Data_Reliability!$C:$C,Data_Reliability!$A:$A,H$4)/(SUMIFS(Data_Reliability!$B:$B,Data_Reliability!$A:$A,H$4)+SUMIFS(Data_Reliability!$C:$C,Data_Reliability!$A:$A,H$4))) | I46: =IF(SUMIFS(Data_Reliability!$B:$B,Data_Reliability!$A:$A,I$4)+SUMIFS(Data_Reliability!$C:$C,Data_Reliability!$A:$A,I$4)=0,0,SUMIFS(Data_Reliability!$C:$C,Data_Reliability!$A:$A,I$4)/(SUMIFS(Data_Reliability!$B:$B,Data_Reliability!$A:$A,I$4)+SUMIFS(Data_Reliability!$C:$C,Data_Reliability!$A:$A,I$4))) | ... M46: =IF(SUMIFS(Data_Reliability!$B:$B,Data_Reliability!$A:$A,M$4)+SUMIFS(Data_Reliability!$C:$C,Data_Reliability!$A:$A,M$4)=0,0,SUMIFS(Data_Reliability!$C:$C,Data_Reliability!$A:$A,M$4)/(SUMIFS(Data_Reliability!$B:$B,Data_Reliability!$A:$A,M$4)+SUMIFS(Data_Reliability!$C:$C,Data_Reliability!$A:$A,M$4)))

Sheet UseCases
A1: =Data_Params!$B$14&" | Where usage comes from"
A2: Use case from the customer's project label when mapped (label_map), otherwise inferred from traffic shape (sql/20_use_case_rules.sql).
A4: Use case (B tokens) | B4: =EDATE(Data_Params!$B$3,0) | C4: =EDATE(Data_Params!$B$3,1) | D4: =EDATE(Data_Params!$B$3,2) | E4: =EDATE(Data_Params!$B$3,3) | F4: =EDATE(Data_Params!$B$3,4) | G4: =EDATE(Data_Params!$B$3,5) | H4: =EDATE(Data_Params!$B$3,6) | I4: =EDATE(Data_Params!$B$3,7) | J4: =EDATE(Data_Params!$B$3,8) | K4: =EDATE(Data_Params!$B$3,9) | L4: =EDATE(Data_Params!$B$3,10) | M4: =EDATE(Data_Params!$B$3,11) | N4: Share of latest month | O4: From label, latest month
A5: =IF(INDEX(Data_Lists!$C:$C,1+1)="","",INDEX(Data_Lists!$C:$C,1+1)) | B5: =IF($A5="","",SUMIFS(Data_UseCase!$C:$C,Data_UseCase!$A:$A,B$4,Data_UseCase!$B:$B,$A5)/1E9) | C5: =IF($A5="","",SUMIFS(Data_UseCase!$C:$C,Data_UseCase!$A:$A,C$4,Data_UseCase!$B:$B,$A5)/1E9) | D5: =IF($A5="","",SUMIFS(Data_UseCase!$C:$C,Data_UseCase!$A:$A,D$4,Data_UseCase!$B:$B,$A5)/1E9) | E5: =IF($A5="","",SUMIFS(Data_UseCase!$C:$C,Data_UseCase!$A:$A,E$4,Data_UseCase!$B:$B,$A5)/1E9) | F5: =IF($A5="","",SUMIFS(Data_UseCase!$C:$C,Data_UseCase!$A:$A,F$4,Data_UseCase!$B:$B,$A5)/1E9) | G5: =IF($A5="","",SUMIFS(Data_UseCase!$C:$C,Data_UseCase!$A:$A,G$4,Data_UseCase!$B:$B,$A5)/1E9) | H5: =IF($A5="","",SUMIFS(Data_UseCase!$C:$C,Data_UseCase!$A:$A,H$4,Data_UseCase!$B:$B,$A5)/1E9) | I5: =IF($A5="","",SUMIFS(Data_UseCase!$C:$C,Data_UseCase!$A:$A,I$4,Data_UseCase!$B:$B,$A5)/1E9) | ... M5: =IF($A5="","",SUMIFS(Data_UseCase!$C:$C,Data_UseCase!$A:$A,M$4,Data_UseCase!$B:$B,$A5)/1E9) | N5: =IF($A5="","",IF(M$20=0,0,M5/M$20)) | O5: =IF(OR($A5="",N(M5)=0),"",SUMIFS(Data_UseCase!$D:$D,Data_UseCase!$A:$A,M$4,Data_UseCase!$B:$B,$A5)/1E9/M5)
A6: =IF(INDEX(Data_Lists!$C:$C,2+1)="","",INDEX(Data_Lists!$C:$C,2+1)) | B6: =IF($A6="","",SUMIFS(Data_UseCase!$C:$C,Data_UseCase!$A:$A,B$4,Data_UseCase!$B:$B,$A6)/1E9) | C6: =IF($A6="","",SUMIFS(Data_UseCase!$C:$C,Data_UseCase!$A:$A,C$4,Data_UseCase!$B:$B,$A6)/1E9) | D6: =IF($A6="","",SUMIFS(Data_UseCase!$C:$C,Data_UseCase!$A:$A,D$4,Data_UseCase!$B:$B,$A6)/1E9) | E6: =IF($A6="","",SUMIFS(Data_UseCase!$C:$C,Data_UseCase!$A:$A,E$4,Data_UseCase!$B:$B,$A6)/1E9) | F6: =IF($A6="","",SUMIFS(Data_UseCase!$C:$C,Data_UseCase!$A:$A,F$4,Data_UseCase!$B:$B,$A6)/1E9) | G6: =IF($A6="","",SUMIFS(Data_UseCase!$C:$C,Data_UseCase!$A:$A,G$4,Data_UseCase!$B:$B,$A6)/1E9) | H6: =IF($A6="","",SUMIFS(Data_UseCase!$C:$C,Data_UseCase!$A:$A,H$4,Data_UseCase!$B:$B,$A6)/1E9) | I6: =IF($A6="","",SUMIFS(Data_UseCase!$C:$C,Data_UseCase!$A:$A,I$4,Data_UseCase!$B:$B,$A6)/1E9) | ... M6: =IF($A6="","",SUMIFS(Data_UseCase!$C:$C,Data_UseCase!$A:$A,M$4,Data_UseCase!$B:$B,$A6)/1E9) | N6: =IF($A6="","",IF(M$20=0,0,M6/M$20)) | O6: =IF(OR($A6="",N(M6)=0),"",SUMIFS(Data_UseCase!$D:$D,Data_UseCase!$A:$A,M$4,Data_UseCase!$B:$B,$A6)/1E9/M6)
A7: =IF(INDEX(Data_Lists!$C:$C,3+1)="","",INDEX(Data_Lists!$C:$C,3+1)) | B7: =IF($A7="","",SUMIFS(Data_UseCase!$C:$C,Data_UseCase!$A:$A,B$4,Data_UseCase!$B:$B,$A7)/1E9) | C7: =IF($A7="","",SUMIFS(Data_UseCase!$C:$C,Data_UseCase!$A:$A,C$4,Data_UseCase!$B:$B,$A7)/1E9) | D7: =IF($A7="","",SUMIFS(Data_UseCase!$C:$C,Data_UseCase!$A:$A,D$4,Data_UseCase!$B:$B,$A7)/1E9) | E7: =IF($A7="","",SUMIFS(Data_UseCase!$C:$C,Data_UseCase!$A:$A,E$4,Data_UseCase!$B:$B,$A7)/1E9) | F7: =IF($A7="","",SUMIFS(Data_UseCase!$C:$C,Data_UseCase!$A:$A,F$4,Data_UseCase!$B:$B,$A7)/1E9) | G7: =IF($A7="","",SUMIFS(Data_UseCase!$C:$C,Data_UseCase!$A:$A,G$4,Data_UseCase!$B:$B,$A7)/1E9) | H7: =IF($A7="","",SUMIFS(Data_UseCase!$C:$C,Data_UseCase!$A:$A,H$4,Data_UseCase!$B:$B,$A7)/1E9) | I7: =IF($A7="","",SUMIFS(Data_UseCase!$C:$C,Data_UseCase!$A:$A,I$4,Data_UseCase!$B:$B,$A7)/1E9) | ... M7: =IF($A7="","",SUMIFS(Data_UseCase!$C:$C,Data_UseCase!$A:$A,M$4,Data_UseCase!$B:$B,$A7)/1E9) | N7: =IF($A7="","",IF(M$20=0,0,M7/M$20)) | O7: =IF(OR($A7="",N(M7)=0),"",SUMIFS(Data_UseCase!$D:$D,Data_UseCase!$A:$A,M$4,Data_UseCase!$B:$B,$A7)/1E9/M7)
A8: =IF(INDEX(Data_Lists!$C:$C,4+1)="","",INDEX(Data_Lists!$C:$C,4+1)) | B8: =IF($A8="","",SUMIFS(Data_UseCase!$C:$C,Data_UseCase!$A:$A,B$4,Data_UseCase!$B:$B,$A8)/1E9) | C8: =IF($A8="","",SUMIFS(Data_UseCase!$C:$C,Data_UseCase!$A:$A,C$4,Data_UseCase!$B:$B,$A8)/1E9) | D8: =IF($A8="","",SUMIFS(Data_UseCase!$C:$C,Data_UseCase!$A:$A,D$4,Data_UseCase!$B:$B,$A8)/1E9) | E8: =IF($A8="","",SUMIFS(Data_UseCase!$C:$C,Data_UseCase!$A:$A,E$4,Data_UseCase!$B:$B,$A8)/1E9) | F8: =IF($A8="","",SUMIFS(Data_UseCase!$C:$C,Data_UseCase!$A:$A,F$4,Data_UseCase!$B:$B,$A8)/1E9) | G8: =IF($A8="","",SUMIFS(Data_UseCase!$C:$C,Data_UseCase!$A:$A,G$4,Data_UseCase!$B:$B,$A8)/1E9) | H8: =IF($A8="","",SUMIFS(Data_UseCase!$C:$C,Data_UseCase!$A:$A,H$4,Data_UseCase!$B:$B,$A8)/1E9) | I8: =IF($A8="","",SUMIFS(Data_UseCase!$C:$C,Data_UseCase!$A:$A,I$4,Data_UseCase!$B:$B,$A8)/1E9) | ... M8: =IF($A8="","",SUMIFS(Data_UseCase!$C:$C,Data_UseCase!$A:$A,M$4,Data_UseCase!$B:$B,$A8)/1E9) | N8: =IF($A8="","",IF(M$20=0,0,M8/M$20)) | O8: =IF(OR($A8="",N(M8)=0),"",SUMIFS(Data_UseCase!$D:$D,Data_UseCase!$A:$A,M$4,Data_UseCase!$B:$B,$A8)/1E9/M8)
A9: =IF(INDEX(Data_Lists!$C:$C,5+1)="","",INDEX(Data_Lists!$C:$C,5+1)) | B9: =IF($A9="","",SUMIFS(Data_UseCase!$C:$C,Data_UseCase!$A:$A,B$4,Data_UseCase!$B:$B,$A9)/1E9) | C9: =IF($A9="","",SUMIFS(Data_UseCase!$C:$C,Data_UseCase!$A:$A,C$4,Data_UseCase!$B:$B,$A9)/1E9) | D9: =IF($A9="","",SUMIFS(Data_UseCase!$C:$C,Data_UseCase!$A:$A,D$4,Data_UseCase!$B:$B,$A9)/1E9) | E9: =IF($A9="","",SUMIFS(Data_UseCase!$C:$C,Data_UseCase!$A:$A,E$4,Data_UseCase!$B:$B,$A9)/1E9) | F9: =IF($A9="","",SUMIFS(Data_UseCase!$C:$C,Data_UseCase!$A:$A,F$4,Data_UseCase!$B:$B,$A9)/1E9) | G9: =IF($A9="","",SUMIFS(Data_UseCase!$C:$C,Data_UseCase!$A:$A,G$4,Data_UseCase!$B:$B,$A9)/1E9) | H9: =IF($A9="","",SUMIFS(Data_UseCase!$C:$C,Data_UseCase!$A:$A,H$4,Data_UseCase!$B:$B,$A9)/1E9) | I9: =IF($A9="","",SUMIFS(Data_UseCase!$C:$C,Data_UseCase!$A:$A,I$4,Data_UseCase!$B:$B,$A9)/1E9) | ... M9: =IF($A9="","",SUMIFS(Data_UseCase!$C:$C,Data_UseCase!$A:$A,M$4,Data_UseCase!$B:$B,$A9)/1E9) | N9: =IF($A9="","",IF(M$20=0,0,M9/M$20)) | O9: =IF(OR($A9="",N(M9)=0),"",SUMIFS(Data_UseCase!$D:$D,Data_UseCase!$A:$A,M$4,Data_UseCase!$B:$B,$A9)/1E9/M9)
A10: =IF(INDEX(Data_Lists!$C:$C,6+1)="","",INDEX(Data_Lists!$C:$C,6+1)) | B10: =IF($A10="","",SUMIFS(Data_UseCase!$C:$C,Data_UseCase!$A:$A,B$4,Data_UseCase!$B:$B,$A10)/1E9) | C10: =IF($A10="","",SUMIFS(Data_UseCase!$C:$C,Data_UseCase!$A:$A,C$4,Data_UseCase!$B:$B,$A10)/1E9) | D10: =IF($A10="","",SUMIFS(Data_UseCase!$C:$C,Data_UseCase!$A:$A,D$4,Data_UseCase!$B:$B,$A10)/1E9) | E10: =IF($A10="","",SUMIFS(Data_UseCase!$C:$C,Data_UseCase!$A:$A,E$4,Data_UseCase!$B:$B,$A10)/1E9) | F10: =IF($A10="","",SUMIFS(Data_UseCase!$C:$C,Data_UseCase!$A:$A,F$4,Data_UseCase!$B:$B,$A10)/1E9) | G10: =IF($A10="","",SUMIFS(Data_UseCase!$C:$C,Data_UseCase!$A:$A,G$4,Data_UseCase!$B:$B,$A10)/1E9) | H10: =IF($A10="","",SUMIFS(Data_UseCase!$C:$C,Data_UseCase!$A:$A,H$4,Data_UseCase!$B:$B,$A10)/1E9) | I10: =IF($A10="","",SUMIFS(Data_UseCase!$C:$C,Data_UseCase!$A:$A,I$4,Data_UseCase!$B:$B,$A10)/1E9) | ... M10: =IF($A10="","",SUMIFS(Data_UseCase!$C:$C,Data_UseCase!$A:$A,M$4,Data_UseCase!$B:$B,$A10)/1E9) | N10: =IF($A10="","",IF(M$20=0,0,M10/M$20)) | O10: =IF(OR($A10="",N(M10)=0),"",SUMIFS(Data_UseCase!$D:$D,Data_UseCase!$A:$A,M$4,Data_UseCase!$B:$B,$A10)/1E9/M10)
A11: =IF(INDEX(Data_Lists!$C:$C,7+1)="","",INDEX(Data_Lists!$C:$C,7+1)) | B11: =IF($A11="","",SUMIFS(Data_UseCase!$C:$C,Data_UseCase!$A:$A,B$4,Data_UseCase!$B:$B,$A11)/1E9) | C11: =IF($A11="","",SUMIFS(Data_UseCase!$C:$C,Data_UseCase!$A:$A,C$4,Data_UseCase!$B:$B,$A11)/1E9) | D11: =IF($A11="","",SUMIFS(Data_UseCase!$C:$C,Data_UseCase!$A:$A,D$4,Data_UseCase!$B:$B,$A11)/1E9) | E11: =IF($A11="","",SUMIFS(Data_UseCase!$C:$C,Data_UseCase!$A:$A,E$4,Data_UseCase!$B:$B,$A11)/1E9) | F11: =IF($A11="","",SUMIFS(Data_UseCase!$C:$C,Data_UseCase!$A:$A,F$4,Data_UseCase!$B:$B,$A11)/1E9) | G11: =IF($A11="","",SUMIFS(Data_UseCase!$C:$C,Data_UseCase!$A:$A,G$4,Data_UseCase!$B:$B,$A11)/1E9) | H11: =IF($A11="","",SUMIFS(Data_UseCase!$C:$C,Data_UseCase!$A:$A,H$4,Data_UseCase!$B:$B,$A11)/1E9) | I11: =IF($A11="","",SUMIFS(Data_UseCase!$C:$C,Data_UseCase!$A:$A,I$4,Data_UseCase!$B:$B,$A11)/1E9) | ... M11: =IF($A11="","",SUMIFS(Data_UseCase!$C:$C,Data_UseCase!$A:$A,M$4,Data_UseCase!$B:$B,$A11)/1E9) | N11: =IF($A11="","",IF(M$20=0,0,M11/M$20)) | O11: =IF(OR($A11="",N(M11)=0),"",SUMIFS(Data_UseCase!$D:$D,Data_UseCase!$A:$A,M$4,Data_UseCase!$B:$B,$A11)/1E9/M11)
A12: =IF(INDEX(Data_Lists!$C:$C,8+1)="","",INDEX(Data_Lists!$C:$C,8+1)) | B12: =IF($A12="","",SUMIFS(Data_UseCase!$C:$C,Data_UseCase!$A:$A,B$4,Data_UseCase!$B:$B,$A12)/1E9) | C12: =IF($A12="","",SUMIFS(Data_UseCase!$C:$C,Data_UseCase!$A:$A,C$4,Data_UseCase!$B:$B,$A12)/1E9) | D12: =IF($A12="","",SUMIFS(Data_UseCase!$C:$C,Data_UseCase!$A:$A,D$4,Data_UseCase!$B:$B,$A12)/1E9) | E12: =IF($A12="","",SUMIFS(Data_UseCase!$C:$C,Data_UseCase!$A:$A,E$4,Data_UseCase!$B:$B,$A12)/1E9) | F12: =IF($A12="","",SUMIFS(Data_UseCase!$C:$C,Data_UseCase!$A:$A,F$4,Data_UseCase!$B:$B,$A12)/1E9) | G12: =IF($A12="","",SUMIFS(Data_UseCase!$C:$C,Data_UseCase!$A:$A,G$4,Data_UseCase!$B:$B,$A12)/1E9) | H12: =IF($A12="","",SUMIFS(Data_UseCase!$C:$C,Data_UseCase!$A:$A,H$4,Data_UseCase!$B:$B,$A12)/1E9) | I12: =IF($A12="","",SUMIFS(Data_UseCase!$C:$C,Data_UseCase!$A:$A,I$4,Data_UseCase!$B:$B,$A12)/1E9) | ... M12: =IF($A12="","",SUMIFS(Data_UseCase!$C:$C,Data_UseCase!$A:$A,M$4,Data_UseCase!$B:$B,$A12)/1E9) | N12: =IF($A12="","",IF(M$20=0,0,M12/M$20)) | O12: =IF(OR($A12="",N(M12)=0),"",SUMIFS(Data_UseCase!$D:$D,Data_UseCase!$A:$A,M$4,Data_UseCase!$B:$B,$A12)/1E9/M12)
A13: =IF(INDEX(Data_Lists!$C:$C,9+1)="","",INDEX(Data_Lists!$C:$C,9+1)) | B13: =IF($A13="","",SUMIFS(Data_UseCase!$C:$C,Data_UseCase!$A:$A,B$4,Data_UseCase!$B:$B,$A13)/1E9) | C13: =IF($A13="","",SUMIFS(Data_UseCase!$C:$C,Data_UseCase!$A:$A,C$4,Data_UseCase!$B:$B,$A13)/1E9) | D13: =IF($A13="","",SUMIFS(Data_UseCase!$C:$C,Data_UseCase!$A:$A,D$4,Data_UseCase!$B:$B,$A13)/1E9) | E13: =IF($A13="","",SUMIFS(Data_UseCase!$C:$C,Data_UseCase!$A:$A,E$4,Data_UseCase!$B:$B,$A13)/1E9) | F13: =IF($A13="","",SUMIFS(Data_UseCase!$C:$C,Data_UseCase!$A:$A,F$4,Data_UseCase!$B:$B,$A13)/1E9) | G13: =IF($A13="","",SUMIFS(Data_UseCase!$C:$C,Data_UseCase!$A:$A,G$4,Data_UseCase!$B:$B,$A13)/1E9) | H13: =IF($A13="","",SUMIFS(Data_UseCase!$C:$C,Data_UseCase!$A:$A,H$4,Data_UseCase!$B:$B,$A13)/1E9) | I13: =IF($A13="","",SUMIFS(Data_UseCase!$C:$C,Data_UseCase!$A:$A,I$4,Data_UseCase!$B:$B,$A13)/1E9) | ... M13: =IF($A13="","",SUMIFS(Data_UseCase!$C:$C,Data_UseCase!$A:$A,M$4,Data_UseCase!$B:$B,$A13)/1E9) | N13: =IF($A13="","",IF(M$20=0,0,M13/M$20)) | O13: =IF(OR($A13="",N(M13)=0),"",SUMIFS(Data_UseCase!$D:$D,Data_UseCase!$A:$A,M$4,Data_UseCase!$B:$B,$A13)/1E9/M13)
A14: =IF(INDEX(Data_Lists!$C:$C,10+1)="","",INDEX(Data_Lists!$C:$C,10+1)) | B14: =IF($A14="","",SUMIFS(Data_UseCase!$C:$C,Data_UseCase!$A:$A,B$4,Data_UseCase!$B:$B,$A14)/1E9) | C14: =IF($A14="","",SUMIFS(Data_UseCase!$C:$C,Data_UseCase!$A:$A,C$4,Data_UseCase!$B:$B,$A14)/1E9) | D14: =IF($A14="","",SUMIFS(Data_UseCase!$C:$C,Data_UseCase!$A:$A,D$4,Data_UseCase!$B:$B,$A14)/1E9) | E14: =IF($A14="","",SUMIFS(Data_UseCase!$C:$C,Data_UseCase!$A:$A,E$4,Data_UseCase!$B:$B,$A14)/1E9) | F14: =IF($A14="","",SUMIFS(Data_UseCase!$C:$C,Data_UseCase!$A:$A,F$4,Data_UseCase!$B:$B,$A14)/1E9) | G14: =IF($A14="","",SUMIFS(Data_UseCase!$C:$C,Data_UseCase!$A:$A,G$4,Data_UseCase!$B:$B,$A14)/1E9) | H14: =IF($A14="","",SUMIFS(Data_UseCase!$C:$C,Data_UseCase!$A:$A,H$4,Data_UseCase!$B:$B,$A14)/1E9) | I14: =IF($A14="","",SUMIFS(Data_UseCase!$C:$C,Data_UseCase!$A:$A,I$4,Data_UseCase!$B:$B,$A14)/1E9) | ... M14: =IF($A14="","",SUMIFS(Data_UseCase!$C:$C,Data_UseCase!$A:$A,M$4,Data_UseCase!$B:$B,$A14)/1E9) | N14: =IF($A14="","",IF(M$20=0,0,M14/M$20)) | O14: =IF(OR($A14="",N(M14)=0),"",SUMIFS(Data_UseCase!$D:$D,Data_UseCase!$A:$A,M$4,Data_UseCase!$B:$B,$A14)/1E9/M14)
A15: =IF(INDEX(Data_Lists!$C:$C,11+1)="","",INDEX(Data_Lists!$C:$C,11+1)) | B15: =IF($A15="","",SUMIFS(Data_UseCase!$C:$C,Data_UseCase!$A:$A,B$4,Data_UseCase!$B:$B,$A15)/1E9) | C15: =IF($A15="","",SUMIFS(Data_UseCase!$C:$C,Data_UseCase!$A:$A,C$4,Data_UseCase!$B:$B,$A15)/1E9) | D15: =IF($A15="","",SUMIFS(Data_UseCase!$C:$C,Data_UseCase!$A:$A,D$4,Data_UseCase!$B:$B,$A15)/1E9) | E15: =IF($A15="","",SUMIFS(Data_UseCase!$C:$C,Data_UseCase!$A:$A,E$4,Data_UseCase!$B:$B,$A15)/1E9) | F15: =IF($A15="","",SUMIFS(Data_UseCase!$C:$C,Data_UseCase!$A:$A,F$4,Data_UseCase!$B:$B,$A15)/1E9) | G15: =IF($A15="","",SUMIFS(Data_UseCase!$C:$C,Data_UseCase!$A:$A,G$4,Data_UseCase!$B:$B,$A15)/1E9) | H15: =IF($A15="","",SUMIFS(Data_UseCase!$C:$C,Data_UseCase!$A:$A,H$4,Data_UseCase!$B:$B,$A15)/1E9) | I15: =IF($A15="","",SUMIFS(Data_UseCase!$C:$C,Data_UseCase!$A:$A,I$4,Data_UseCase!$B:$B,$A15)/1E9) | ... M15: =IF($A15="","",SUMIFS(Data_UseCase!$C:$C,Data_UseCase!$A:$A,M$4,Data_UseCase!$B:$B,$A15)/1E9) | N15: =IF($A15="","",IF(M$20=0,0,M15/M$20)) | O15: =IF(OR($A15="",N(M15)=0),"",SUMIFS(Data_UseCase!$D:$D,Data_UseCase!$A:$A,M$4,Data_UseCase!$B:$B,$A15)/1E9/M15)
A16: =IF(INDEX(Data_Lists!$C:$C,12+1)="","",INDEX(Data_Lists!$C:$C,12+1)) | B16: =IF($A16="","",SUMIFS(Data_UseCase!$C:$C,Data_UseCase!$A:$A,B$4,Data_UseCase!$B:$B,$A16)/1E9) | C16: =IF($A16="","",SUMIFS(Data_UseCase!$C:$C,Data_UseCase!$A:$A,C$4,Data_UseCase!$B:$B,$A16)/1E9) | D16: =IF($A16="","",SUMIFS(Data_UseCase!$C:$C,Data_UseCase!$A:$A,D$4,Data_UseCase!$B:$B,$A16)/1E9) | E16: =IF($A16="","",SUMIFS(Data_UseCase!$C:$C,Data_UseCase!$A:$A,E$4,Data_UseCase!$B:$B,$A16)/1E9) | F16: =IF($A16="","",SUMIFS(Data_UseCase!$C:$C,Data_UseCase!$A:$A,F$4,Data_UseCase!$B:$B,$A16)/1E9) | G16: =IF($A16="","",SUMIFS(Data_UseCase!$C:$C,Data_UseCase!$A:$A,G$4,Data_UseCase!$B:$B,$A16)/1E9) | H16: =IF($A16="","",SUMIFS(Data_UseCase!$C:$C,Data_UseCase!$A:$A,H$4,Data_UseCase!$B:$B,$A16)/1E9) | I16: =IF($A16="","",SUMIFS(Data_UseCase!$C:$C,Data_UseCase!$A:$A,I$4,Data_UseCase!$B:$B,$A16)/1E9) | ... M16: =IF($A16="","",SUMIFS(Data_UseCase!$C:$C,Data_UseCase!$A:$A,M$4,Data_UseCase!$B:$B,$A16)/1E9) | N16: =IF($A16="","",IF(M$20=0,0,M16/M$20)) | O16: =IF(OR($A16="",N(M16)=0),"",SUMIFS(Data_UseCase!$D:$D,Data_UseCase!$A:$A,M$4,Data_UseCase!$B:$B,$A16)/1E9/M16)
A17: =IF(INDEX(Data_Lists!$C:$C,13+1)="","",INDEX(Data_Lists!$C:$C,13+1)) | B17: =IF($A17="","",SUMIFS(Data_UseCase!$C:$C,Data_UseCase!$A:$A,B$4,Data_UseCase!$B:$B,$A17)/1E9) | C17: =IF($A17="","",SUMIFS(Data_UseCase!$C:$C,Data_UseCase!$A:$A,C$4,Data_UseCase!$B:$B,$A17)/1E9) | D17: =IF($A17="","",SUMIFS(Data_UseCase!$C:$C,Data_UseCase!$A:$A,D$4,Data_UseCase!$B:$B,$A17)/1E9) | E17: =IF($A17="","",SUMIFS(Data_UseCase!$C:$C,Data_UseCase!$A:$A,E$4,Data_UseCase!$B:$B,$A17)/1E9) | F17: =IF($A17="","",SUMIFS(Data_UseCase!$C:$C,Data_UseCase!$A:$A,F$4,Data_UseCase!$B:$B,$A17)/1E9) | G17: =IF($A17="","",SUMIFS(Data_UseCase!$C:$C,Data_UseCase!$A:$A,G$4,Data_UseCase!$B:$B,$A17)/1E9) | H17: =IF($A17="","",SUMIFS(Data_UseCase!$C:$C,Data_UseCase!$A:$A,H$4,Data_UseCase!$B:$B,$A17)/1E9) | I17: =IF($A17="","",SUMIFS(Data_UseCase!$C:$C,Data_UseCase!$A:$A,I$4,Data_UseCase!$B:$B,$A17)/1E9) | ... M17: =IF($A17="","",SUMIFS(Data_UseCase!$C:$C,Data_UseCase!$A:$A,M$4,Data_UseCase!$B:$B,$A17)/1E9) | N17: =IF($A17="","",IF(M$20=0,0,M17/M$20)) | O17: =IF(OR($A17="",N(M17)=0),"",SUMIFS(Data_UseCase!$D:$D,Data_UseCase!$A:$A,M$4,Data_UseCase!$B:$B,$A17)/1E9/M17)
A18: =IF(INDEX(Data_Lists!$C:$C,14+1)="","",INDEX(Data_Lists!$C:$C,14+1)) | B18: =IF($A18="","",SUMIFS(Data_UseCase!$C:$C,Data_UseCase!$A:$A,B$4,Data_UseCase!$B:$B,$A18)/1E9) | C18: =IF($A18="","",SUMIFS(Data_UseCase!$C:$C,Data_UseCase!$A:$A,C$4,Data_UseCase!$B:$B,$A18)/1E9) | D18: =IF($A18="","",SUMIFS(Data_UseCase!$C:$C,Data_UseCase!$A:$A,D$4,Data_UseCase!$B:$B,$A18)/1E9) | E18: =IF($A18="","",SUMIFS(Data_UseCase!$C:$C,Data_UseCase!$A:$A,E$4,Data_UseCase!$B:$B,$A18)/1E9) | F18: =IF($A18="","",SUMIFS(Data_UseCase!$C:$C,Data_UseCase!$A:$A,F$4,Data_UseCase!$B:$B,$A18)/1E9) | G18: =IF($A18="","",SUMIFS(Data_UseCase!$C:$C,Data_UseCase!$A:$A,G$4,Data_UseCase!$B:$B,$A18)/1E9) | H18: =IF($A18="","",SUMIFS(Data_UseCase!$C:$C,Data_UseCase!$A:$A,H$4,Data_UseCase!$B:$B,$A18)/1E9) | I18: =IF($A18="","",SUMIFS(Data_UseCase!$C:$C,Data_UseCase!$A:$A,I$4,Data_UseCase!$B:$B,$A18)/1E9) | ... M18: =IF($A18="","",SUMIFS(Data_UseCase!$C:$C,Data_UseCase!$A:$A,M$4,Data_UseCase!$B:$B,$A18)/1E9) | N18: =IF($A18="","",IF(M$20=0,0,M18/M$20)) | O18: =IF(OR($A18="",N(M18)=0),"",SUMIFS(Data_UseCase!$D:$D,Data_UseCase!$A:$A,M$4,Data_UseCase!$B:$B,$A18)/1E9/M18)
A19: =IF(INDEX(Data_Lists!$C:$C,15+1)="","",INDEX(Data_Lists!$C:$C,15+1)) | B19: =IF($A19="","",SUMIFS(Data_UseCase!$C:$C,Data_UseCase!$A:$A,B$4,Data_UseCase!$B:$B,$A19)/1E9) | C19: =IF($A19="","",SUMIFS(Data_UseCase!$C:$C,Data_UseCase!$A:$A,C$4,Data_UseCase!$B:$B,$A19)/1E9) | D19: =IF($A19="","",SUMIFS(Data_UseCase!$C:$C,Data_UseCase!$A:$A,D$4,Data_UseCase!$B:$B,$A19)/1E9) | E19: =IF($A19="","",SUMIFS(Data_UseCase!$C:$C,Data_UseCase!$A:$A,E$4,Data_UseCase!$B:$B,$A19)/1E9) | F19: =IF($A19="","",SUMIFS(Data_UseCase!$C:$C,Data_UseCase!$A:$A,F$4,Data_UseCase!$B:$B,$A19)/1E9) | G19: =IF($A19="","",SUMIFS(Data_UseCase!$C:$C,Data_UseCase!$A:$A,G$4,Data_UseCase!$B:$B,$A19)/1E9) | H19: =IF($A19="","",SUMIFS(Data_UseCase!$C:$C,Data_UseCase!$A:$A,H$4,Data_UseCase!$B:$B,$A19)/1E9) | I19: =IF($A19="","",SUMIFS(Data_UseCase!$C:$C,Data_UseCase!$A:$A,I$4,Data_UseCase!$B:$B,$A19)/1E9) | ... M19: =IF($A19="","",SUMIFS(Data_UseCase!$C:$C,Data_UseCase!$A:$A,M$4,Data_UseCase!$B:$B,$A19)/1E9) | N19: =IF($A19="","",IF(M$20=0,0,M19/M$20)) | O19: =IF(OR($A19="",N(M19)=0),"",SUMIFS(Data_UseCase!$D:$D,Data_UseCase!$A:$A,M$4,Data_UseCase!$B:$B,$A19)/1E9/M19)
A20: Total | B20: =SUM(B5:B19) | C20: =SUM(C5:C19) | D20: =SUM(D5:D19) | E20: =SUM(E5:E19) | F20: =SUM(F5:F19) | G20: =SUM(G5:G19) | H20: =SUM(H5:H19) | I20: =SUM(I5:I19) | ... M20: =SUM(M5:M19)
A22: How reliable is the inferred use case? Rules scored on traffic whose label we know
A23: Use case | B23: Labelled tokens (B) | C23: Inferred correctly (B) | D23: Accuracy
A24: =IF(INDEX(Data_InferenceAcc!$A:$A,1+1)="","",INDEX(Data_InferenceAcc!$A:$A,1+1)) | B24: =IF($A24="","",INDEX(Data_InferenceAcc!$B:$B,1+1)/1E9) | C24: =IF($A24="","",INDEX(Data_InferenceAcc!$C:$C,1+1)/1E9) | D24: =IF(OR($A24="",N(B24)=0),"",C24/B24)
A25: =IF(INDEX(Data_InferenceAcc!$A:$A,2+1)="","",INDEX(Data_InferenceAcc!$A:$A,2+1)) | B25: =IF($A25="","",INDEX(Data_InferenceAcc!$B:$B,2+1)/1E9) | C25: =IF($A25="","",INDEX(Data_InferenceAcc!$C:$C,2+1)/1E9) | D25: =IF(OR($A25="",N(B25)=0),"",C25/B25)
A26: =IF(INDEX(Data_InferenceAcc!$A:$A,3+1)="","",INDEX(Data_InferenceAcc!$A:$A,3+1)) | B26: =IF($A26="","",INDEX(Data_InferenceAcc!$B:$B,3+1)/1E9) | C26: =IF($A26="","",INDEX(Data_InferenceAcc!$C:$C,3+1)/1E9) | D26: =IF(OR($A26="",N(B26)=0),"",C26/B26)
A27: =IF(INDEX(Data_InferenceAcc!$A:$A,4+1)="","",INDEX(Data_InferenceAcc!$A:$A,4+1)) | B27: =IF($A27="","",INDEX(Data_InferenceAcc!$B:$B,4+1)/1E9) | C27: =IF($A27="","",INDEX(Data_InferenceAcc!$C:$C,4+1)/1E9) | D27: =IF(OR($A27="",N(B27)=0),"",C27/B27)
A28: =IF(INDEX(Data_InferenceAcc!$A:$A,5+1)="","",INDEX(Data_InferenceAcc!$A:$A,5+1)) | B28: =IF($A28="","",INDEX(Data_InferenceAcc!$B:$B,5+1)/1E9) | C28: =IF($A28="","",INDEX(Data_InferenceAcc!$C:$C,5+1)/1E9) | D28: =IF(OR($A28="",N(B28)=0),"",C28/B28)
A29: =IF(INDEX(Data_InferenceAcc!$A:$A,6+1)="","",INDEX(Data_InferenceAcc!$A:$A,6+1)) | B29: =IF($A29="","",INDEX(Data_InferenceAcc!$B:$B,6+1)/1E9) | C29: =IF($A29="","",INDEX(Data_InferenceAcc!$C:$C,6+1)/1E9) | D29: =IF(OR($A29="",N(B29)=0),"",C29/B29)
A30: =IF(INDEX(Data_InferenceAcc!$A:$A,7+1)="","",INDEX(Data_InferenceAcc!$A:$A,7+1)) | B30: =IF($A30="","",INDEX(Data_InferenceAcc!$B:$B,7+1)/1E9) | C30: =IF($A30="","",INDEX(Data_InferenceAcc!$C:$C,7+1)/1E9) | D30: =IF(OR($A30="",N(B30)=0),"",C30/B30)
A31: =IF(INDEX(Data_InferenceAcc!$A:$A,8+1)="","",INDEX(Data_InferenceAcc!$A:$A,8+1)) | B31: =IF($A31="","",INDEX(Data_InferenceAcc!$B:$B,8+1)/1E9) | C31: =IF($A31="","",INDEX(Data_InferenceAcc!$C:$C,8+1)/1E9) | D31: =IF(OR($A31="",N(B31)=0),"",C31/B31)
A32: =IF(INDEX(Data_InferenceAcc!$A:$A,9+1)="","",INDEX(Data_InferenceAcc!$A:$A,9+1)) | B32: =IF($A32="","",INDEX(Data_InferenceAcc!$B:$B,9+1)/1E9) | C32: =IF($A32="","",INDEX(Data_InferenceAcc!$C:$C,9+1)/1E9) | D32: =IF(OR($A32="",N(B32)=0),"",C32/B32)
A33: =IF(INDEX(Data_InferenceAcc!$A:$A,10+1)="","",INDEX(Data_InferenceAcc!$A:$A,10+1)) | B33: =IF($A33="","",INDEX(Data_InferenceAcc!$B:$B,10+1)/1E9) | C33: =IF($A33="","",INDEX(Data_InferenceAcc!$C:$C,10+1)/1E9) | D33: =IF(OR($A33="",N(B33)=0),"",C33/B33)
A34: =IF(INDEX(Data_InferenceAcc!$A:$A,11+1)="","",INDEX(Data_InferenceAcc!$A:$A,11+1)) | B34: =IF($A34="","",INDEX(Data_InferenceAcc!$B:$B,11+1)/1E9) | C34: =IF($A34="","",INDEX(Data_InferenceAcc!$C:$C,11+1)/1E9) | D34: =IF(OR($A34="",N(B34)=0),"",C34/B34)
A35: =IF(INDEX(Data_InferenceAcc!$A:$A,12+1)="","",INDEX(Data_InferenceAcc!$A:$A,12+1)) | B35: =IF($A35="","",INDEX(Data_InferenceAcc!$B:$B,12+1)/1E9) | C35: =IF($A35="","",INDEX(Data_InferenceAcc!$C:$C,12+1)/1E9) | D35: =IF(OR($A35="",N(B35)=0),"",C35/B35)
A36: =IF(INDEX(Data_InferenceAcc!$A:$A,13+1)="","",INDEX(Data_InferenceAcc!$A:$A,13+1)) | B36: =IF($A36="","",INDEX(Data_InferenceAcc!$B:$B,13+1)/1E9) | C36: =IF($A36="","",INDEX(Data_InferenceAcc!$C:$C,13+1)/1E9) | D36: =IF(OR($A36="",N(B36)=0),"",C36/B36)
A37: =IF(INDEX(Data_InferenceAcc!$A:$A,14+1)="","",INDEX(Data_InferenceAcc!$A:$A,14+1)) | B37: =IF($A37="","",INDEX(Data_InferenceAcc!$B:$B,14+1)/1E9) | C37: =IF($A37="","",INDEX(Data_InferenceAcc!$C:$C,14+1)/1E9) | D37: =IF(OR($A37="",N(B37)=0),"",C37/B37)
A38: =IF(INDEX(Data_InferenceAcc!$A:$A,15+1)="","",INDEX(Data_InferenceAcc!$A:$A,15+1)) | B38: =IF($A38="","",INDEX(Data_InferenceAcc!$B:$B,15+1)/1E9) | C38: =IF($A38="","",INDEX(Data_InferenceAcc!$C:$C,15+1)/1E9) | D38: =IF(OR($A38="",N(B38)=0),"",C38/B38)
A39: All labelled traffic | B39: =SUM(B24:B38) | C39: =SUM(C24:C38) | D39: =IF(B39=0,"no labelled traffic",C39/B39)
A41: Low accuracy means the rules in sql/20_use_case_rules.sql don't fit your traffic yet. Recalibrate them, or map more labels.

Sheet Cohorts
A1: =Data_Params!$B$14&" | Self-serve cohorts"
A2: Accounts grouped by signup month. Tokens per day (B) so partial months compare fairly. Older cohorts are combined on the Forecast tab.
A4: Signup cohort | B4: Signups | C4: Added payment method | D4: Month 0 | E4: Month 1 | F4: Month 2 | G4: Month 3 | H4: Month 4 | I4: Month 5 | J4: Month 6 | K4: Month 7 | L4: Month 8 | M4: Month 9 | N4: Month 10 | O4: Month 11
A5: =EDATE(Data_Params!$B$3,0) | B5: =SUMIFS(Data_Signups!$B:$B,Data_Signups!$A:$A,$A5) | C5: =IF(SUMIFS(Data_Signups!$D:$D,Data_Signups!$A:$A,$A5)=0,"n/a",SUMIFS(Data_Signups!$C:$C,Data_Signups!$A:$A,$A5)) | D5: =SUMIFS(Data_Cohort!$C:$C,Data_Cohort!$A:$A,$A5,Data_Cohort!$B:$B,0)/MAX(1,SUMIFS(Data_Months!$B:$B,Data_Months!$A:$A,EDATE($A5,0)))/1E9 | E5: =SUMIFS(Data_Cohort!$C:$C,Data_Cohort!$A:$A,$A5,Data_Cohort!$B:$B,1)/MAX(1,SUMIFS(Data_Months!$B:$B,Data_Months!$A:$A,EDATE($A5,1)))/1E9 | F5: =SUMIFS(Data_Cohort!$C:$C,Data_Cohort!$A:$A,$A5,Data_Cohort!$B:$B,2)/MAX(1,SUMIFS(Data_Months!$B:$B,Data_Months!$A:$A,EDATE($A5,2)))/1E9 | G5: =SUMIFS(Data_Cohort!$C:$C,Data_Cohort!$A:$A,$A5,Data_Cohort!$B:$B,3)/MAX(1,SUMIFS(Data_Months!$B:$B,Data_Months!$A:$A,EDATE($A5,3)))/1E9 | H5: =SUMIFS(Data_Cohort!$C:$C,Data_Cohort!$A:$A,$A5,Data_Cohort!$B:$B,4)/MAX(1,SUMIFS(Data_Months!$B:$B,Data_Months!$A:$A,EDATE($A5,4)))/1E9 | I5: =SUMIFS(Data_Cohort!$C:$C,Data_Cohort!$A:$A,$A5,Data_Cohort!$B:$B,5)/MAX(1,SUMIFS(Data_Months!$B:$B,Data_Months!$A:$A,EDATE($A5,5)))/1E9 | J5: =SUMIFS(Data_Cohort!$C:$C,Data_Cohort!$A:$A,$A5,Data_Cohort!$B:$B,6)/MAX(1,SUMIFS(Data_Months!$B:$B,Data_Months!$A:$A,EDATE($A5,6)))/1E9 | K5: =SUMIFS(Data_Cohort!$C:$C,Data_Cohort!$A:$A,$A5,Data_Cohort!$B:$B,7)/MAX(1,SUMIFS(Data_Months!$B:$B,Data_Months!$A:$A,EDATE($A5,7)))/1E9 | L5: =SUMIFS(Data_Cohort!$C:$C,Data_Cohort!$A:$A,$A5,Data_Cohort!$B:$B,8)/MAX(1,SUMIFS(Data_Months!$B:$B,Data_Months!$A:$A,EDATE($A5,8)))/1E9 | M5: =SUMIFS(Data_Cohort!$C:$C,Data_Cohort!$A:$A,$A5,Data_Cohort!$B:$B,9)/MAX(1,SUMIFS(Data_Months!$B:$B,Data_Months!$A:$A,EDATE($A5,9)))/1E9 | N5: =SUMIFS(Data_Cohort!$C:$C,Data_Cohort!$A:$A,$A5,Data_Cohort!$B:$B,10)/MAX(1,SUMIFS(Data_Months!$B:$B,Data_Months!$A:$A,EDATE($A5,10)))/1E9 | O5: =SUMIFS(Data_Cohort!$C:$C,Data_Cohort!$A:$A,$A5,Data_Cohort!$B:$B,11)/MAX(1,SUMIFS(Data_Months!$B:$B,Data_Months!$A:$A,EDATE($A5,11)))/1E9
A6: =EDATE(Data_Params!$B$3,1) | B6: =SUMIFS(Data_Signups!$B:$B,Data_Signups!$A:$A,$A6) | C6: =IF(SUMIFS(Data_Signups!$D:$D,Data_Signups!$A:$A,$A6)=0,"n/a",SUMIFS(Data_Signups!$C:$C,Data_Signups!$A:$A,$A6)) | D6: =SUMIFS(Data_Cohort!$C:$C,Data_Cohort!$A:$A,$A6,Data_Cohort!$B:$B,0)/MAX(1,SUMIFS(Data_Months!$B:$B,Data_Months!$A:$A,EDATE($A6,0)))/1E9 | E6: =SUMIFS(Data_Cohort!$C:$C,Data_Cohort!$A:$A,$A6,Data_Cohort!$B:$B,1)/MAX(1,SUMIFS(Data_Months!$B:$B,Data_Months!$A:$A,EDATE($A6,1)))/1E9 | F6: =SUMIFS(Data_Cohort!$C:$C,Data_Cohort!$A:$A,$A6,Data_Cohort!$B:$B,2)/MAX(1,SUMIFS(Data_Months!$B:$B,Data_Months!$A:$A,EDATE($A6,2)))/1E9 | G6: =SUMIFS(Data_Cohort!$C:$C,Data_Cohort!$A:$A,$A6,Data_Cohort!$B:$B,3)/MAX(1,SUMIFS(Data_Months!$B:$B,Data_Months!$A:$A,EDATE($A6,3)))/1E9 | H6: =SUMIFS(Data_Cohort!$C:$C,Data_Cohort!$A:$A,$A6,Data_Cohort!$B:$B,4)/MAX(1,SUMIFS(Data_Months!$B:$B,Data_Months!$A:$A,EDATE($A6,4)))/1E9 | I6: =SUMIFS(Data_Cohort!$C:$C,Data_Cohort!$A:$A,$A6,Data_Cohort!$B:$B,5)/MAX(1,SUMIFS(Data_Months!$B:$B,Data_Months!$A:$A,EDATE($A6,5)))/1E9 | J6: =SUMIFS(Data_Cohort!$C:$C,Data_Cohort!$A:$A,$A6,Data_Cohort!$B:$B,6)/MAX(1,SUMIFS(Data_Months!$B:$B,Data_Months!$A:$A,EDATE($A6,6)))/1E9 | K6: =SUMIFS(Data_Cohort!$C:$C,Data_Cohort!$A:$A,$A6,Data_Cohort!$B:$B,7)/MAX(1,SUMIFS(Data_Months!$B:$B,Data_Months!$A:$A,EDATE($A6,7)))/1E9 | L6: =SUMIFS(Data_Cohort!$C:$C,Data_Cohort!$A:$A,$A6,Data_Cohort!$B:$B,8)/MAX(1,SUMIFS(Data_Months!$B:$B,Data_Months!$A:$A,EDATE($A6,8)))/1E9 | M6: =SUMIFS(Data_Cohort!$C:$C,Data_Cohort!$A:$A,$A6,Data_Cohort!$B:$B,9)/MAX(1,SUMIFS(Data_Months!$B:$B,Data_Months!$A:$A,EDATE($A6,9)))/1E9 | N6: =SUMIFS(Data_Cohort!$C:$C,Data_Cohort!$A:$A,$A6,Data_Cohort!$B:$B,10)/MAX(1,SUMIFS(Data_Months!$B:$B,Data_Months!$A:$A,EDATE($A6,10)))/1E9
A7: =EDATE(Data_Params!$B$3,2) | B7: =SUMIFS(Data_Signups!$B:$B,Data_Signups!$A:$A,$A7) | C7: =IF(SUMIFS(Data_Signups!$D:$D,Data_Signups!$A:$A,$A7)=0,"n/a",SUMIFS(Data_Signups!$C:$C,Data_Signups!$A:$A,$A7)) | D7: =SUMIFS(Data_Cohort!$C:$C,Data_Cohort!$A:$A,$A7,Data_Cohort!$B:$B,0)/MAX(1,SUMIFS(Data_Months!$B:$B,Data_Months!$A:$A,EDATE($A7,0)))/1E9 | E7: =SUMIFS(Data_Cohort!$C:$C,Data_Cohort!$A:$A,$A7,Data_Cohort!$B:$B,1)/MAX(1,SUMIFS(Data_Months!$B:$B,Data_Months!$A:$A,EDATE($A7,1)))/1E9 | F7: =SUMIFS(Data_Cohort!$C:$C,Data_Cohort!$A:$A,$A7,Data_Cohort!$B:$B,2)/MAX(1,SUMIFS(Data_Months!$B:$B,Data_Months!$A:$A,EDATE($A7,2)))/1E9 | G7: =SUMIFS(Data_Cohort!$C:$C,Data_Cohort!$A:$A,$A7,Data_Cohort!$B:$B,3)/MAX(1,SUMIFS(Data_Months!$B:$B,Data_Months!$A:$A,EDATE($A7,3)))/1E9 | H7: =SUMIFS(Data_Cohort!$C:$C,Data_Cohort!$A:$A,$A7,Data_Cohort!$B:$B,4)/MAX(1,SUMIFS(Data_Months!$B:$B,Data_Months!$A:$A,EDATE($A7,4)))/1E9 | I7: =SUMIFS(Data_Cohort!$C:$C,Data_Cohort!$A:$A,$A7,Data_Cohort!$B:$B,5)/MAX(1,SUMIFS(Data_Months!$B:$B,Data_Months!$A:$A,EDATE($A7,5)))/1E9 | J7: =SUMIFS(Data_Cohort!$C:$C,Data_Cohort!$A:$A,$A7,Data_Cohort!$B:$B,6)/MAX(1,SUMIFS(Data_Months!$B:$B,Data_Months!$A:$A,EDATE($A7,6)))/1E9 | K7: =SUMIFS(Data_Cohort!$C:$C,Data_Cohort!$A:$A,$A7,Data_Cohort!$B:$B,7)/MAX(1,SUMIFS(Data_Months!$B:$B,Data_Months!$A:$A,EDATE($A7,7)))/1E9 | L7: =SUMIFS(Data_Cohort!$C:$C,Data_Cohort!$A:$A,$A7,Data_Cohort!$B:$B,8)/MAX(1,SUMIFS(Data_Months!$B:$B,Data_Months!$A:$A,EDATE($A7,8)))/1E9 | M7: =SUMIFS(Data_Cohort!$C:$C,Data_Cohort!$A:$A,$A7,Data_Cohort!$B:$B,9)/MAX(1,SUMIFS(Data_Months!$B:$B,Data_Months!$A:$A,EDATE($A7,9)))/1E9
A8: =EDATE(Data_Params!$B$3,3) | B8: =SUMIFS(Data_Signups!$B:$B,Data_Signups!$A:$A,$A8) | C8: =IF(SUMIFS(Data_Signups!$D:$D,Data_Signups!$A:$A,$A8)=0,"n/a",SUMIFS(Data_Signups!$C:$C,Data_Signups!$A:$A,$A8)) | D8: =SUMIFS(Data_Cohort!$C:$C,Data_Cohort!$A:$A,$A8,Data_Cohort!$B:$B,0)/MAX(1,SUMIFS(Data_Months!$B:$B,Data_Months!$A:$A,EDATE($A8,0)))/1E9 | E8: =SUMIFS(Data_Cohort!$C:$C,Data_Cohort!$A:$A,$A8,Data_Cohort!$B:$B,1)/MAX(1,SUMIFS(Data_Months!$B:$B,Data_Months!$A:$A,EDATE($A8,1)))/1E9 | F8: =SUMIFS(Data_Cohort!$C:$C,Data_Cohort!$A:$A,$A8,Data_Cohort!$B:$B,2)/MAX(1,SUMIFS(Data_Months!$B:$B,Data_Months!$A:$A,EDATE($A8,2)))/1E9 | G8: =SUMIFS(Data_Cohort!$C:$C,Data_Cohort!$A:$A,$A8,Data_Cohort!$B:$B,3)/MAX(1,SUMIFS(Data_Months!$B:$B,Data_Months!$A:$A,EDATE($A8,3)))/1E9 | H8: =SUMIFS(Data_Cohort!$C:$C,Data_Cohort!$A:$A,$A8,Data_Cohort!$B:$B,4)/MAX(1,SUMIFS(Data_Months!$B:$B,Data_Months!$A:$A,EDATE($A8,4)))/1E9 | I8: =SUMIFS(Data_Cohort!$C:$C,Data_Cohort!$A:$A,$A8,Data_Cohort!$B:$B,5)/MAX(1,SUMIFS(Data_Months!$B:$B,Data_Months!$A:$A,EDATE($A8,5)))/1E9 | J8: =SUMIFS(Data_Cohort!$C:$C,Data_Cohort!$A:$A,$A8,Data_Cohort!$B:$B,6)/MAX(1,SUMIFS(Data_Months!$B:$B,Data_Months!$A:$A,EDATE($A8,6)))/1E9 | K8: =SUMIFS(Data_Cohort!$C:$C,Data_Cohort!$A:$A,$A8,Data_Cohort!$B:$B,7)/MAX(1,SUMIFS(Data_Months!$B:$B,Data_Months!$A:$A,EDATE($A8,7)))/1E9 | L8: =SUMIFS(Data_Cohort!$C:$C,Data_Cohort!$A:$A,$A8,Data_Cohort!$B:$B,8)/MAX(1,SUMIFS(Data_Months!$B:$B,Data_Months!$A:$A,EDATE($A8,8)))/1E9
A9: =EDATE(Data_Params!$B$3,4) | B9: =SUMIFS(Data_Signups!$B:$B,Data_Signups!$A:$A,$A9) | C9: =IF(SUMIFS(Data_Signups!$D:$D,Data_Signups!$A:$A,$A9)=0,"n/a",SUMIFS(Data_Signups!$C:$C,Data_Signups!$A:$A,$A9)) | D9: =SUMIFS(Data_Cohort!$C:$C,Data_Cohort!$A:$A,$A9,Data_Cohort!$B:$B,0)/MAX(1,SUMIFS(Data_Months!$B:$B,Data_Months!$A:$A,EDATE($A9,0)))/1E9 | E9: =SUMIFS(Data_Cohort!$C:$C,Data_Cohort!$A:$A,$A9,Data_Cohort!$B:$B,1)/MAX(1,SUMIFS(Data_Months!$B:$B,Data_Months!$A:$A,EDATE($A9,1)))/1E9 | F9: =SUMIFS(Data_Cohort!$C:$C,Data_Cohort!$A:$A,$A9,Data_Cohort!$B:$B,2)/MAX(1,SUMIFS(Data_Months!$B:$B,Data_Months!$A:$A,EDATE($A9,2)))/1E9 | G9: =SUMIFS(Data_Cohort!$C:$C,Data_Cohort!$A:$A,$A9,Data_Cohort!$B:$B,3)/MAX(1,SUMIFS(Data_Months!$B:$B,Data_Months!$A:$A,EDATE($A9,3)))/1E9 | H9: =SUMIFS(Data_Cohort!$C:$C,Data_Cohort!$A:$A,$A9,Data_Cohort!$B:$B,4)/MAX(1,SUMIFS(Data_Months!$B:$B,Data_Months!$A:$A,EDATE($A9,4)))/1E9 | I9: =SUMIFS(Data_Cohort!$C:$C,Data_Cohort!$A:$A,$A9,Data_Cohort!$B:$B,5)/MAX(1,SUMIFS(Data_Months!$B:$B,Data_Months!$A:$A,EDATE($A9,5)))/1E9 | J9: =SUMIFS(Data_Cohort!$C:$C,Data_Cohort!$A:$A,$A9,Data_Cohort!$B:$B,6)/MAX(1,SUMIFS(Data_Months!$B:$B,Data_Months!$A:$A,EDATE($A9,6)))/1E9 | K9: =SUMIFS(Data_Cohort!$C:$C,Data_Cohort!$A:$A,$A9,Data_Cohort!$B:$B,7)/MAX(1,SUMIFS(Data_Months!$B:$B,Data_Months!$A:$A,EDATE($A9,7)))/1E9
A10: =EDATE(Data_Params!$B$3,5) | B10: =SUMIFS(Data_Signups!$B:$B,Data_Signups!$A:$A,$A10) | C10: =IF(SUMIFS(Data_Signups!$D:$D,Data_Signups!$A:$A,$A10)=0,"n/a",SUMIFS(Data_Signups!$C:$C,Data_Signups!$A:$A,$A10)) | D10: =SUMIFS(Data_Cohort!$C:$C,Data_Cohort!$A:$A,$A10,Data_Cohort!$B:$B,0)/MAX(1,SUMIFS(Data_Months!$B:$B,Data_Months!$A:$A,EDATE($A10,0)))/1E9 | E10: =SUMIFS(Data_Cohort!$C:$C,Data_Cohort!$A:$A,$A10,Data_Cohort!$B:$B,1)/MAX(1,SUMIFS(Data_Months!$B:$B,Data_Months!$A:$A,EDATE($A10,1)))/1E9 | F10: =SUMIFS(Data_Cohort!$C:$C,Data_Cohort!$A:$A,$A10,Data_Cohort!$B:$B,2)/MAX(1,SUMIFS(Data_Months!$B:$B,Data_Months!$A:$A,EDATE($A10,2)))/1E9 | G10: =SUMIFS(Data_Cohort!$C:$C,Data_Cohort!$A:$A,$A10,Data_Cohort!$B:$B,3)/MAX(1,SUMIFS(Data_Months!$B:$B,Data_Months!$A:$A,EDATE($A10,3)))/1E9 | H10: =SUMIFS(Data_Cohort!$C:$C,Data_Cohort!$A:$A,$A10,Data_Cohort!$B:$B,4)/MAX(1,SUMIFS(Data_Months!$B:$B,Data_Months!$A:$A,EDATE($A10,4)))/1E9 | I10: =SUMIFS(Data_Cohort!$C:$C,Data_Cohort!$A:$A,$A10,Data_Cohort!$B:$B,5)/MAX(1,SUMIFS(Data_Months!$B:$B,Data_Months!$A:$A,EDATE($A10,5)))/1E9 | J10: =SUMIFS(Data_Cohort!$C:$C,Data_Cohort!$A:$A,$A10,Data_Cohort!$B:$B,6)/MAX(1,SUMIFS(Data_Months!$B:$B,Data_Months!$A:$A,EDATE($A10,6)))/1E9
A11: =EDATE(Data_Params!$B$3,6) | B11: =SUMIFS(Data_Signups!$B:$B,Data_Signups!$A:$A,$A11) | C11: =IF(SUMIFS(Data_Signups!$D:$D,Data_Signups!$A:$A,$A11)=0,"n/a",SUMIFS(Data_Signups!$C:$C,Data_Signups!$A:$A,$A11)) | D11: =SUMIFS(Data_Cohort!$C:$C,Data_Cohort!$A:$A,$A11,Data_Cohort!$B:$B,0)/MAX(1,SUMIFS(Data_Months!$B:$B,Data_Months!$A:$A,EDATE($A11,0)))/1E9 | E11: =SUMIFS(Data_Cohort!$C:$C,Data_Cohort!$A:$A,$A11,Data_Cohort!$B:$B,1)/MAX(1,SUMIFS(Data_Months!$B:$B,Data_Months!$A:$A,EDATE($A11,1)))/1E9 | F11: =SUMIFS(Data_Cohort!$C:$C,Data_Cohort!$A:$A,$A11,Data_Cohort!$B:$B,2)/MAX(1,SUMIFS(Data_Months!$B:$B,Data_Months!$A:$A,EDATE($A11,2)))/1E9 | G11: =SUMIFS(Data_Cohort!$C:$C,Data_Cohort!$A:$A,$A11,Data_Cohort!$B:$B,3)/MAX(1,SUMIFS(Data_Months!$B:$B,Data_Months!$A:$A,EDATE($A11,3)))/1E9 | H11: =SUMIFS(Data_Cohort!$C:$C,Data_Cohort!$A:$A,$A11,Data_Cohort!$B:$B,4)/MAX(1,SUMIFS(Data_Months!$B:$B,Data_Months!$A:$A,EDATE($A11,4)))/1E9 | I11: =SUMIFS(Data_Cohort!$C:$C,Data_Cohort!$A:$A,$A11,Data_Cohort!$B:$B,5)/MAX(1,SUMIFS(Data_Months!$B:$B,Data_Months!$A:$A,EDATE($A11,5)))/1E9
A12: =EDATE(Data_Params!$B$3,7) | B12: =SUMIFS(Data_Signups!$B:$B,Data_Signups!$A:$A,$A12) | C12: =IF(SUMIFS(Data_Signups!$D:$D,Data_Signups!$A:$A,$A12)=0,"n/a",SUMIFS(Data_Signups!$C:$C,Data_Signups!$A:$A,$A12)) | D12: =SUMIFS(Data_Cohort!$C:$C,Data_Cohort!$A:$A,$A12,Data_Cohort!$B:$B,0)/MAX(1,SUMIFS(Data_Months!$B:$B,Data_Months!$A:$A,EDATE($A12,0)))/1E9 | E12: =SUMIFS(Data_Cohort!$C:$C,Data_Cohort!$A:$A,$A12,Data_Cohort!$B:$B,1)/MAX(1,SUMIFS(Data_Months!$B:$B,Data_Months!$A:$A,EDATE($A12,1)))/1E9 | F12: =SUMIFS(Data_Cohort!$C:$C,Data_Cohort!$A:$A,$A12,Data_Cohort!$B:$B,2)/MAX(1,SUMIFS(Data_Months!$B:$B,Data_Months!$A:$A,EDATE($A12,2)))/1E9 | G12: =SUMIFS(Data_Cohort!$C:$C,Data_Cohort!$A:$A,$A12,Data_Cohort!$B:$B,3)/MAX(1,SUMIFS(Data_Months!$B:$B,Data_Months!$A:$A,EDATE($A12,3)))/1E9 | H12: =SUMIFS(Data_Cohort!$C:$C,Data_Cohort!$A:$A,$A12,Data_Cohort!$B:$B,4)/MAX(1,SUMIFS(Data_Months!$B:$B,Data_Months!$A:$A,EDATE($A12,4)))/1E9
A13: =EDATE(Data_Params!$B$3,8) | B13: =SUMIFS(Data_Signups!$B:$B,Data_Signups!$A:$A,$A13) | C13: =IF(SUMIFS(Data_Signups!$D:$D,Data_Signups!$A:$A,$A13)=0,"n/a",SUMIFS(Data_Signups!$C:$C,Data_Signups!$A:$A,$A13)) | D13: =SUMIFS(Data_Cohort!$C:$C,Data_Cohort!$A:$A,$A13,Data_Cohort!$B:$B,0)/MAX(1,SUMIFS(Data_Months!$B:$B,Data_Months!$A:$A,EDATE($A13,0)))/1E9 | E13: =SUMIFS(Data_Cohort!$C:$C,Data_Cohort!$A:$A,$A13,Data_Cohort!$B:$B,1)/MAX(1,SUMIFS(Data_Months!$B:$B,Data_Months!$A:$A,EDATE($A13,1)))/1E9 | F13: =SUMIFS(Data_Cohort!$C:$C,Data_Cohort!$A:$A,$A13,Data_Cohort!$B:$B,2)/MAX(1,SUMIFS(Data_Months!$B:$B,Data_Months!$A:$A,EDATE($A13,2)))/1E9 | G13: =SUMIFS(Data_Cohort!$C:$C,Data_Cohort!$A:$A,$A13,Data_Cohort!$B:$B,3)/MAX(1,SUMIFS(Data_Months!$B:$B,Data_Months!$A:$A,EDATE($A13,3)))/1E9
A14: =EDATE(Data_Params!$B$3,9) | B14: =SUMIFS(Data_Signups!$B:$B,Data_Signups!$A:$A,$A14) | C14: =IF(SUMIFS(Data_Signups!$D:$D,Data_Signups!$A:$A,$A14)=0,"n/a",SUMIFS(Data_Signups!$C:$C,Data_Signups!$A:$A,$A14)) | D14: =SUMIFS(Data_Cohort!$C:$C,Data_Cohort!$A:$A,$A14,Data_Cohort!$B:$B,0)/MAX(1,SUMIFS(Data_Months!$B:$B,Data_Months!$A:$A,EDATE($A14,0)))/1E9 | E14: =SUMIFS(Data_Cohort!$C:$C,Data_Cohort!$A:$A,$A14,Data_Cohort!$B:$B,1)/MAX(1,SUMIFS(Data_Months!$B:$B,Data_Months!$A:$A,EDATE($A14,1)))/1E9 | F14: =SUMIFS(Data_Cohort!$C:$C,Data_Cohort!$A:$A,$A14,Data_Cohort!$B:$B,2)/MAX(1,SUMIFS(Data_Months!$B:$B,Data_Months!$A:$A,EDATE($A14,2)))/1E9
A15: =EDATE(Data_Params!$B$3,10) | B15: =SUMIFS(Data_Signups!$B:$B,Data_Signups!$A:$A,$A15) | C15: =IF(SUMIFS(Data_Signups!$D:$D,Data_Signups!$A:$A,$A15)=0,"n/a",SUMIFS(Data_Signups!$C:$C,Data_Signups!$A:$A,$A15)) | D15: =SUMIFS(Data_Cohort!$C:$C,Data_Cohort!$A:$A,$A15,Data_Cohort!$B:$B,0)/MAX(1,SUMIFS(Data_Months!$B:$B,Data_Months!$A:$A,EDATE($A15,0)))/1E9 | E15: =SUMIFS(Data_Cohort!$C:$C,Data_Cohort!$A:$A,$A15,Data_Cohort!$B:$B,1)/MAX(1,SUMIFS(Data_Months!$B:$B,Data_Months!$A:$A,EDATE($A15,1)))/1E9
A16: =EDATE(Data_Params!$B$3,11) | B16: =SUMIFS(Data_Signups!$B:$B,Data_Signups!$A:$A,$A16) | C16: =IF(SUMIFS(Data_Signups!$D:$D,Data_Signups!$A:$A,$A16)=0,"n/a",SUMIFS(Data_Signups!$C:$C,Data_Signups!$A:$A,$A16)) | D16: =SUMIFS(Data_Cohort!$C:$C,Data_Cohort!$A:$A,$A16,Data_Cohort!$B:$B,0)/MAX(1,SUMIFS(Data_Months!$B:$B,Data_Months!$A:$A,EDATE($A16,0)))/1E9
A18: Active accounts as % of signups (retention)
A19: Signup cohort | B19: Signups | D19: Month 0 | E19: Month 1 | F19: Month 2 | G19: Month 3 | H19: Month 4 | I19: Month 5 | J19: Month 6 | K19: Month 7 | L19: Month 8 | M19: Month 9 | N19: Month 10 | O19: Month 11
A20: =A5 | B20: =B5 | D20: =IF($B20=0,"",SUMIFS(Data_Cohort!$D:$D,Data_Cohort!$A:$A,$A20,Data_Cohort!$B:$B,0)/$B20) | E20: =IF($B20=0,"",SUMIFS(Data_Cohort!$D:$D,Data_Cohort!$A:$A,$A20,Data_Cohort!$B:$B,1)/$B20) | F20: =IF($B20=0,"",SUMIFS(Data_Cohort!$D:$D,Data_Cohort!$A:$A,$A20,Data_Cohort!$B:$B,2)/$B20) | G20: =IF($B20=0,"",SUMIFS(Data_Cohort!$D:$D,Data_Cohort!$A:$A,$A20,Data_Cohort!$B:$B,3)/$B20) | H20: =IF($B20=0,"",SUMIFS(Data_Cohort!$D:$D,Data_Cohort!$A:$A,$A20,Data_Cohort!$B:$B,4)/$B20) | I20: =IF($B20=0,"",SUMIFS(Data_Cohort!$D:$D,Data_Cohort!$A:$A,$A20,Data_Cohort!$B:$B,5)/$B20) | J20: =IF($B20=0,"",SUMIFS(Data_Cohort!$D:$D,Data_Cohort!$A:$A,$A20,Data_Cohort!$B:$B,6)/$B20) | K20: =IF($B20=0,"",SUMIFS(Data_Cohort!$D:$D,Data_Cohort!$A:$A,$A20,Data_Cohort!$B:$B,7)/$B20) | L20: =IF($B20=0,"",SUMIFS(Data_Cohort!$D:$D,Data_Cohort!$A:$A,$A20,Data_Cohort!$B:$B,8)/$B20) | M20: =IF($B20=0,"",SUMIFS(Data_Cohort!$D:$D,Data_Cohort!$A:$A,$A20,Data_Cohort!$B:$B,9)/$B20) | N20: =IF($B20=0,"",SUMIFS(Data_Cohort!$D:$D,Data_Cohort!$A:$A,$A20,Data_Cohort!$B:$B,10)/$B20) | O20: =IF($B20=0,"",SUMIFS(Data_Cohort!$D:$D,Data_Cohort!$A:$A,$A20,Data_Cohort!$B:$B,11)/$B20)
A21: =A6 | B21: =B6 | D21: =IF($B21=0,"",SUMIFS(Data_Cohort!$D:$D,Data_Cohort!$A:$A,$A21,Data_Cohort!$B:$B,0)/$B21) | E21: =IF($B21=0,"",SUMIFS(Data_Cohort!$D:$D,Data_Cohort!$A:$A,$A21,Data_Cohort!$B:$B,1)/$B21) | F21: =IF($B21=0,"",SUMIFS(Data_Cohort!$D:$D,Data_Cohort!$A:$A,$A21,Data_Cohort!$B:$B,2)/$B21) | G21: =IF($B21=0,"",SUMIFS(Data_Cohort!$D:$D,Data_Cohort!$A:$A,$A21,Data_Cohort!$B:$B,3)/$B21) | H21: =IF($B21=0,"",SUMIFS(Data_Cohort!$D:$D,Data_Cohort!$A:$A,$A21,Data_Cohort!$B:$B,4)/$B21) | I21: =IF($B21=0,"",SUMIFS(Data_Cohort!$D:$D,Data_Cohort!$A:$A,$A21,Data_Cohort!$B:$B,5)/$B21) | J21: =IF($B21=0,"",SUMIFS(Data_Cohort!$D:$D,Data_Cohort!$A:$A,$A21,Data_Cohort!$B:$B,6)/$B21) | K21: =IF($B21=0,"",SUMIFS(Data_Cohort!$D:$D,Data_Cohort!$A:$A,$A21,Data_Cohort!$B:$B,7)/$B21) | L21: =IF($B21=0,"",SUMIFS(Data_Cohort!$D:$D,Data_Cohort!$A:$A,$A21,Data_Cohort!$B:$B,8)/$B21) | M21: =IF($B21=0,"",SUMIFS(Data_Cohort!$D:$D,Data_Cohort!$A:$A,$A21,Data_Cohort!$B:$B,9)/$B21) | N21: =IF($B21=0,"",SUMIFS(Data_Cohort!$D:$D,Data_Cohort!$A:$A,$A21,Data_Cohort!$B:$B,10)/$B21)
A22: =A7 | B22: =B7 | D22: =IF($B22=0,"",SUMIFS(Data_Cohort!$D:$D,Data_Cohort!$A:$A,$A22,Data_Cohort!$B:$B,0)/$B22) | E22: =IF($B22=0,"",SUMIFS(Data_Cohort!$D:$D,Data_Cohort!$A:$A,$A22,Data_Cohort!$B:$B,1)/$B22) | F22: =IF($B22=0,"",SUMIFS(Data_Cohort!$D:$D,Data_Cohort!$A:$A,$A22,Data_Cohort!$B:$B,2)/$B22) | G22: =IF($B22=0,"",SUMIFS(Data_Cohort!$D:$D,Data_Cohort!$A:$A,$A22,Data_Cohort!$B:$B,3)/$B22) | H22: =IF($B22=0,"",SUMIFS(Data_Cohort!$D:$D,Data_Cohort!$A:$A,$A22,Data_Cohort!$B:$B,4)/$B22) | I22: =IF($B22=0,"",SUMIFS(Data_Cohort!$D:$D,Data_Cohort!$A:$A,$A22,Data_Cohort!$B:$B,5)/$B22) | J22: =IF($B22=0,"",SUMIFS(Data_Cohort!$D:$D,Data_Cohort!$A:$A,$A22,Data_Cohort!$B:$B,6)/$B22) | K22: =IF($B22=0,"",SUMIFS(Data_Cohort!$D:$D,Data_Cohort!$A:$A,$A22,Data_Cohort!$B:$B,7)/$B22) | L22: =IF($B22=0,"",SUMIFS(Data_Cohort!$D:$D,Data_Cohort!$A:$A,$A22,Data_Cohort!$B:$B,8)/$B22) | M22: =IF($B22=0,"",SUMIFS(Data_Cohort!$D:$D,Data_Cohort!$A:$A,$A22,Data_Cohort!$B:$B,9)/$B22)
A23: =A8 | B23: =B8 | D23: =IF($B23=0,"",SUMIFS(Data_Cohort!$D:$D,Data_Cohort!$A:$A,$A23,Data_Cohort!$B:$B,0)/$B23) | E23: =IF($B23=0,"",SUMIFS(Data_Cohort!$D:$D,Data_Cohort!$A:$A,$A23,Data_Cohort!$B:$B,1)/$B23) | F23: =IF($B23=0,"",SUMIFS(Data_Cohort!$D:$D,Data_Cohort!$A:$A,$A23,Data_Cohort!$B:$B,2)/$B23) | G23: =IF($B23=0,"",SUMIFS(Data_Cohort!$D:$D,Data_Cohort!$A:$A,$A23,Data_Cohort!$B:$B,3)/$B23) | H23: =IF($B23=0,"",SUMIFS(Data_Cohort!$D:$D,Data_Cohort!$A:$A,$A23,Data_Cohort!$B:$B,4)/$B23) | I23: =IF($B23=0,"",SUMIFS(Data_Cohort!$D:$D,Data_Cohort!$A:$A,$A23,Data_Cohort!$B:$B,5)/$B23) | J23: =IF($B23=0,"",SUMIFS(Data_Cohort!$D:$D,Data_Cohort!$A:$A,$A23,Data_Cohort!$B:$B,6)/$B23) | K23: =IF($B23=0,"",SUMIFS(Data_Cohort!$D:$D,Data_Cohort!$A:$A,$A23,Data_Cohort!$B:$B,7)/$B23) | L23: =IF($B23=0,"",SUMIFS(Data_Cohort!$D:$D,Data_Cohort!$A:$A,$A23,Data_Cohort!$B:$B,8)/$B23)
A24: =A9 | B24: =B9 | D24: =IF($B24=0,"",SUMIFS(Data_Cohort!$D:$D,Data_Cohort!$A:$A,$A24,Data_Cohort!$B:$B,0)/$B24) | E24: =IF($B24=0,"",SUMIFS(Data_Cohort!$D:$D,Data_Cohort!$A:$A,$A24,Data_Cohort!$B:$B,1)/$B24) | F24: =IF($B24=0,"",SUMIFS(Data_Cohort!$D:$D,Data_Cohort!$A:$A,$A24,Data_Cohort!$B:$B,2)/$B24) | G24: =IF($B24=0,"",SUMIFS(Data_Cohort!$D:$D,Data_Cohort!$A:$A,$A24,Data_Cohort!$B:$B,3)/$B24) | H24: =IF($B24=0,"",SUMIFS(Data_Cohort!$D:$D,Data_Cohort!$A:$A,$A24,Data_Cohort!$B:$B,4)/$B24) | I24: =IF($B24=0,"",SUMIFS(Data_Cohort!$D:$D,Data_Cohort!$A:$A,$A24,Data_Cohort!$B:$B,5)/$B24) | J24: =IF($B24=0,"",SUMIFS(Data_Cohort!$D:$D,Data_Cohort!$A:$A,$A24,Data_Cohort!$B:$B,6)/$B24) | K24: =IF($B24=0,"",SUMIFS(Data_Cohort!$D:$D,Data_Cohort!$A:$A,$A24,Data_Cohort!$B:$B,7)/$B24)
A25: =A10 | B25: =B10 | D25: =IF($B25=0,"",SUMIFS(Data_Cohort!$D:$D,Data_Cohort!$A:$A,$A25,Data_Cohort!$B:$B,0)/$B25) | E25: =IF($B25=0,"",SUMIFS(Data_Cohort!$D:$D,Data_Cohort!$A:$A,$A25,Data_Cohort!$B:$B,1)/$B25) | F25: =IF($B25=0,"",SUMIFS(Data_Cohort!$D:$D,Data_Cohort!$A:$A,$A25,Data_Cohort!$B:$B,2)/$B25) | G25: =IF($B25=0,"",SUMIFS(Data_Cohort!$D:$D,Data_Cohort!$A:$A,$A25,Data_Cohort!$B:$B,3)/$B25) | H25: =IF($B25=0,"",SUMIFS(Data_Cohort!$D:$D,Data_Cohort!$A:$A,$A25,Data_Cohort!$B:$B,4)/$B25) | I25: =IF($B25=0,"",SUMIFS(Data_Cohort!$D:$D,Data_Cohort!$A:$A,$A25,Data_Cohort!$B:$B,5)/$B25) | J25: =IF($B25=0,"",SUMIFS(Data_Cohort!$D:$D,Data_Cohort!$A:$A,$A25,Data_Cohort!$B:$B,6)/$B25)
A26: =A11 | B26: =B11 | D26: =IF($B26=0,"",SUMIFS(Data_Cohort!$D:$D,Data_Cohort!$A:$A,$A26,Data_Cohort!$B:$B,0)/$B26) | E26: =IF($B26=0,"",SUMIFS(Data_Cohort!$D:$D,Data_Cohort!$A:$A,$A26,Data_Cohort!$B:$B,1)/$B26) | F26: =IF($B26=0,"",SUMIFS(Data_Cohort!$D:$D,Data_Cohort!$A:$A,$A26,Data_Cohort!$B:$B,2)/$B26) | G26: =IF($B26=0,"",SUMIFS(Data_Cohort!$D:$D,Data_Cohort!$A:$A,$A26,Data_Cohort!$B:$B,3)/$B26) | H26: =IF($B26=0,"",SUMIFS(Data_Cohort!$D:$D,Data_Cohort!$A:$A,$A26,Data_Cohort!$B:$B,4)/$B26) | I26: =IF($B26=0,"",SUMIFS(Data_Cohort!$D:$D,Data_Cohort!$A:$A,$A26,Data_Cohort!$B:$B,5)/$B26)
A27: =A12 | B27: =B12 | D27: =IF($B27=0,"",SUMIFS(Data_Cohort!$D:$D,Data_Cohort!$A:$A,$A27,Data_Cohort!$B:$B,0)/$B27) | E27: =IF($B27=0,"",SUMIFS(Data_Cohort!$D:$D,Data_Cohort!$A:$A,$A27,Data_Cohort!$B:$B,1)/$B27) | F27: =IF($B27=0,"",SUMIFS(Data_Cohort!$D:$D,Data_Cohort!$A:$A,$A27,Data_Cohort!$B:$B,2)/$B27) | G27: =IF($B27=0,"",SUMIFS(Data_Cohort!$D:$D,Data_Cohort!$A:$A,$A27,Data_Cohort!$B:$B,3)/$B27) | H27: =IF($B27=0,"",SUMIFS(Data_Cohort!$D:$D,Data_Cohort!$A:$A,$A27,Data_Cohort!$B:$B,4)/$B27)
A28: =A13 | B28: =B13 | D28: =IF($B28=0,"",SUMIFS(Data_Cohort!$D:$D,Data_Cohort!$A:$A,$A28,Data_Cohort!$B:$B,0)/$B28) | E28: =IF($B28=0,"",SUMIFS(Data_Cohort!$D:$D,Data_Cohort!$A:$A,$A28,Data_Cohort!$B:$B,1)/$B28) | F28: =IF($B28=0,"",SUMIFS(Data_Cohort!$D:$D,Data_Cohort!$A:$A,$A28,Data_Cohort!$B:$B,2)/$B28) | G28: =IF($B28=0,"",SUMIFS(Data_Cohort!$D:$D,Data_Cohort!$A:$A,$A28,Data_Cohort!$B:$B,3)/$B28)
A29: =A14 | B29: =B14 | D29: =IF($B29=0,"",SUMIFS(Data_Cohort!$D:$D,Data_Cohort!$A:$A,$A29,Data_Cohort!$B:$B,0)/$B29) | E29: =IF($B29=0,"",SUMIFS(Data_Cohort!$D:$D,Data_Cohort!$A:$A,$A29,Data_Cohort!$B:$B,1)/$B29) | F29: =IF($B29=0,"",SUMIFS(Data_Cohort!$D:$D,Data_Cohort!$A:$A,$A29,Data_Cohort!$B:$B,2)/$B29)
A30: =A15 | B30: =B15 | D30: =IF($B30=0,"",SUMIFS(Data_Cohort!$D:$D,Data_Cohort!$A:$A,$A30,Data_Cohort!$B:$B,0)/$B30) | E30: =IF($B30=0,"",SUMIFS(Data_Cohort!$D:$D,Data_Cohort!$A:$A,$A30,Data_Cohort!$B:$B,1)/$B30)
A31: =A16 | B31: =B16 | D31: =IF($B31=0,"",SUMIFS(Data_Cohort!$D:$D,Data_Cohort!$A:$A,$A31,Data_Cohort!$B:$B,0)/$B31)
A33: Read across a row to follow one cohort; read down a column to compare cohorts at the same age.

Sheet Enterprise
A1: =Data_Params!$B$14&" | Enterprise: usage vs commitment"
A2: Contracts live at the close (Data_Contracts) and usage revenue by month (Data_EntMonth). True-up = commitment minus usage when usage falls short.
A4: Customer | B4: Start | C4: End | D4: Monthly commit ($) | E4: Price ($/M) | F4: Latest month vs commit | G4: Latest month true-up ($) | H4: =EDATE(Data_Params!$B$3,0) | I4: =EDATE(Data_Params!$B$3,1) | J4: =EDATE(Data_Params!$B$3,2) | K4: =EDATE(Data_Params!$B$3,3) | L4: =EDATE(Data_Params!$B$3,4) | M4: =EDATE(Data_Params!$B$3,5) | N4: =EDATE(Data_Params!$B$3,6) | O4: =EDATE(Data_Params!$B$3,7) | P4: =EDATE(Data_Params!$B$3,8) | Q4: =EDATE(Data_Params!$B$3,9) | R4: =EDATE(Data_Params!$B$3,10) | S4: =EDATE(Data_Params!$B$3,11)
A5: =IF(INDEX(Data_Contracts!$A:$A,1+1)="","",INDEX(Data_Contracts!$A:$A,1+1)) | B5: =IF(INDEX(Data_Contracts!$C:$C,1+1)="","",INDEX(Data_Contracts!$C:$C,1+1)) | C5: =IF(INDEX(Data_Contracts!$D:$D,1+1)="","",INDEX(Data_Contracts!$D:$D,1+1)) | D5: =IF(INDEX(Data_Contracts!$E:$E,1+1)="","",INDEX(Data_Contracts!$E:$E,1+1)) | E5: =IF(INDEX(Data_Contracts!$F:$F,1+1)="","",INDEX(Data_Contracts!$F:$F,1+1)) | F5: =IF(OR($A5="",N($D5)=0),"",S5/$D5) | G5: =IF($A5="","",SUMIFS(Data_EntMonth!$F:$F,Data_EntMonth!$A:$A,$A5,Data_EntMonth!$B:$B,S$4)) | H5: =IF($A5="","",SUMIFS(Data_EntMonth!$D:$D,Data_EntMonth!$A:$A,$A5,Data_EntMonth!$B:$B,H$4)) | I5: =IF($A5="","",SUMIFS(Data_EntMonth!$D:$D,Data_EntMonth!$A:$A,$A5,Data_EntMonth!$B:$B,I$4)) | J5: =IF($A5="","",SUMIFS(Data_EntMonth!$D:$D,Data_EntMonth!$A:$A,$A5,Data_EntMonth!$B:$B,J$4)) | K5: =IF($A5="","",SUMIFS(Data_EntMonth!$D:$D,Data_EntMonth!$A:$A,$A5,Data_EntMonth!$B:$B,K$4)) | L5: =IF($A5="","",SUMIFS(Data_EntMonth!$D:$D,Data_EntMonth!$A:$A,$A5,Data_EntMonth!$B:$B,L$4)) | M5: =IF($A5="","",SUMIFS(Data_EntMonth!$D:$D,Data_EntMonth!$A:$A,$A5,Data_EntMonth!$B:$B,M$4)) | N5: =IF($A5="","",SUMIFS(Data_EntMonth!$D:$D,Data_EntMonth!$A:$A,$A5,Data_EntMonth!$B:$B,N$4)) | O5: =IF($A5="","",SUMIFS(Data_EntMonth!$D:$D,Data_EntMonth!$A:$A,$A5,Data_EntMonth!$B:$B,O$4)) | ... S5: =IF($A5="","",SUMIFS(Data_EntMonth!$D:$D,Data_EntMonth!$A:$A,$A5,Data_EntMonth!$B:$B,S$4))
A6: =IF(INDEX(Data_Contracts!$A:$A,2+1)="","",INDEX(Data_Contracts!$A:$A,2+1)) | B6: =IF(INDEX(Data_Contracts!$C:$C,2+1)="","",INDEX(Data_Contracts!$C:$C,2+1)) | C6: =IF(INDEX(Data_Contracts!$D:$D,2+1)="","",INDEX(Data_Contracts!$D:$D,2+1)) | D6: =IF(INDEX(Data_Contracts!$E:$E,2+1)="","",INDEX(Data_Contracts!$E:$E,2+1)) | E6: =IF(INDEX(Data_Contracts!$F:$F,2+1)="","",INDEX(Data_Contracts!$F:$F,2+1)) | F6: =IF(OR($A6="",N($D6)=0),"",S6/$D6) | G6: =IF($A6="","",SUMIFS(Data_EntMonth!$F:$F,Data_EntMonth!$A:$A,$A6,Data_EntMonth!$B:$B,S$4)) | H6: =IF($A6="","",SUMIFS(Data_EntMonth!$D:$D,Data_EntMonth!$A:$A,$A6,Data_EntMonth!$B:$B,H$4)) | I6: =IF($A6="","",SUMIFS(Data_EntMonth!$D:$D,Data_EntMonth!$A:$A,$A6,Data_EntMonth!$B:$B,I$4)) | J6: =IF($A6="","",SUMIFS(Data_EntMonth!$D:$D,Data_EntMonth!$A:$A,$A6,Data_EntMonth!$B:$B,J$4)) | K6: =IF($A6="","",SUMIFS(Data_EntMonth!$D:$D,Data_EntMonth!$A:$A,$A6,Data_EntMonth!$B:$B,K$4)) | L6: =IF($A6="","",SUMIFS(Data_EntMonth!$D:$D,Data_EntMonth!$A:$A,$A6,Data_EntMonth!$B:$B,L$4)) | M6: =IF($A6="","",SUMIFS(Data_EntMonth!$D:$D,Data_EntMonth!$A:$A,$A6,Data_EntMonth!$B:$B,M$4)) | N6: =IF($A6="","",SUMIFS(Data_EntMonth!$D:$D,Data_EntMonth!$A:$A,$A6,Data_EntMonth!$B:$B,N$4)) | O6: =IF($A6="","",SUMIFS(Data_EntMonth!$D:$D,Data_EntMonth!$A:$A,$A6,Data_EntMonth!$B:$B,O$4)) | ... S6: =IF($A6="","",SUMIFS(Data_EntMonth!$D:$D,Data_EntMonth!$A:$A,$A6,Data_EntMonth!$B:$B,S$4))
A7: =IF(INDEX(Data_Contracts!$A:$A,3+1)="","",INDEX(Data_Contracts!$A:$A,3+1)) | B7: =IF(INDEX(Data_Contracts!$C:$C,3+1)="","",INDEX(Data_Contracts!$C:$C,3+1)) | C7: =IF(INDEX(Data_Contracts!$D:$D,3+1)="","",INDEX(Data_Contracts!$D:$D,3+1)) | D7: =IF(INDEX(Data_Contracts!$E:$E,3+1)="","",INDEX(Data_Contracts!$E:$E,3+1)) | E7: =IF(INDEX(Data_Contracts!$F:$F,3+1)="","",INDEX(Data_Contracts!$F:$F,3+1)) | F7: =IF(OR($A7="",N($D7)=0),"",S7/$D7) | G7: =IF($A7="","",SUMIFS(Data_EntMonth!$F:$F,Data_EntMonth!$A:$A,$A7,Data_EntMonth!$B:$B,S$4)) | H7: =IF($A7="","",SUMIFS(Data_EntMonth!$D:$D,Data_EntMonth!$A:$A,$A7,Data_EntMonth!$B:$B,H$4)) | I7: =IF($A7="","",SUMIFS(Data_EntMonth!$D:$D,Data_EntMonth!$A:$A,$A7,Data_EntMonth!$B:$B,I$4)) | J7: =IF($A7="","",SUMIFS(Data_EntMonth!$D:$D,Data_EntMonth!$A:$A,$A7,Data_EntMonth!$B:$B,J$4)) | K7: =IF($A7="","",SUMIFS(Data_EntMonth!$D:$D,Data_EntMonth!$A:$A,$A7,Data_EntMonth!$B:$B,K$4)) | L7: =IF($A7="","",SUMIFS(Data_EntMonth!$D:$D,Data_EntMonth!$A:$A,$A7,Data_EntMonth!$B:$B,L$4)) | M7: =IF($A7="","",SUMIFS(Data_EntMonth!$D:$D,Data_EntMonth!$A:$A,$A7,Data_EntMonth!$B:$B,M$4)) | N7: =IF($A7="","",SUMIFS(Data_EntMonth!$D:$D,Data_EntMonth!$A:$A,$A7,Data_EntMonth!$B:$B,N$4)) | O7: =IF($A7="","",SUMIFS(Data_EntMonth!$D:$D,Data_EntMonth!$A:$A,$A7,Data_EntMonth!$B:$B,O$4)) | ... S7: =IF($A7="","",SUMIFS(Data_EntMonth!$D:$D,Data_EntMonth!$A:$A,$A7,Data_EntMonth!$B:$B,S$4))
A8: =IF(INDEX(Data_Contracts!$A:$A,4+1)="","",INDEX(Data_Contracts!$A:$A,4+1)) | B8: =IF(INDEX(Data_Contracts!$C:$C,4+1)="","",INDEX(Data_Contracts!$C:$C,4+1)) | C8: =IF(INDEX(Data_Contracts!$D:$D,4+1)="","",INDEX(Data_Contracts!$D:$D,4+1)) | D8: =IF(INDEX(Data_Contracts!$E:$E,4+1)="","",INDEX(Data_Contracts!$E:$E,4+1)) | E8: =IF(INDEX(Data_Contracts!$F:$F,4+1)="","",INDEX(Data_Contracts!$F:$F,4+1)) | F8: =IF(OR($A8="",N($D8)=0),"",S8/$D8) | G8: =IF($A8="","",SUMIFS(Data_EntMonth!$F:$F,Data_EntMonth!$A:$A,$A8,Data_EntMonth!$B:$B,S$4)) | H8: =IF($A8="","",SUMIFS(Data_EntMonth!$D:$D,Data_EntMonth!$A:$A,$A8,Data_EntMonth!$B:$B,H$4)) | I8: =IF($A8="","",SUMIFS(Data_EntMonth!$D:$D,Data_EntMonth!$A:$A,$A8,Data_EntMonth!$B:$B,I$4)) | J8: =IF($A8="","",SUMIFS(Data_EntMonth!$D:$D,Data_EntMonth!$A:$A,$A8,Data_EntMonth!$B:$B,J$4)) | K8: =IF($A8="","",SUMIFS(Data_EntMonth!$D:$D,Data_EntMonth!$A:$A,$A8,Data_EntMonth!$B:$B,K$4)) | L8: =IF($A8="","",SUMIFS(Data_EntMonth!$D:$D,Data_EntMonth!$A:$A,$A8,Data_EntMonth!$B:$B,L$4)) | M8: =IF($A8="","",SUMIFS(Data_EntMonth!$D:$D,Data_EntMonth!$A:$A,$A8,Data_EntMonth!$B:$B,M$4)) | N8: =IF($A8="","",SUMIFS(Data_EntMonth!$D:$D,Data_EntMonth!$A:$A,$A8,Data_EntMonth!$B:$B,N$4)) | O8: =IF($A8="","",SUMIFS(Data_EntMonth!$D:$D,Data_EntMonth!$A:$A,$A8,Data_EntMonth!$B:$B,O$4)) | ... S8: =IF($A8="","",SUMIFS(Data_EntMonth!$D:$D,Data_EntMonth!$A:$A,$A8,Data_EntMonth!$B:$B,S$4))
A9: =IF(INDEX(Data_Contracts!$A:$A,5+1)="","",INDEX(Data_Contracts!$A:$A,5+1)) | B9: =IF(INDEX(Data_Contracts!$C:$C,5+1)="","",INDEX(Data_Contracts!$C:$C,5+1)) | C9: =IF(INDEX(Data_Contracts!$D:$D,5+1)="","",INDEX(Data_Contracts!$D:$D,5+1)) | D9: =IF(INDEX(Data_Contracts!$E:$E,5+1)="","",INDEX(Data_Contracts!$E:$E,5+1)) | E9: =IF(INDEX(Data_Contracts!$F:$F,5+1)="","",INDEX(Data_Contracts!$F:$F,5+1)) | F9: =IF(OR($A9="",N($D9)=0),"",S9/$D9) | G9: =IF($A9="","",SUMIFS(Data_EntMonth!$F:$F,Data_EntMonth!$A:$A,$A9,Data_EntMonth!$B:$B,S$4)) | H9: =IF($A9="","",SUMIFS(Data_EntMonth!$D:$D,Data_EntMonth!$A:$A,$A9,Data_EntMonth!$B:$B,H$4)) | I9: =IF($A9="","",SUMIFS(Data_EntMonth!$D:$D,Data_EntMonth!$A:$A,$A9,Data_EntMonth!$B:$B,I$4)) | J9: =IF($A9="","",SUMIFS(Data_EntMonth!$D:$D,Data_EntMonth!$A:$A,$A9,Data_EntMonth!$B:$B,J$4)) | K9: =IF($A9="","",SUMIFS(Data_EntMonth!$D:$D,Data_EntMonth!$A:$A,$A9,Data_EntMonth!$B:$B,K$4)) | L9: =IF($A9="","",SUMIFS(Data_EntMonth!$D:$D,Data_EntMonth!$A:$A,$A9,Data_EntMonth!$B:$B,L$4)) | M9: =IF($A9="","",SUMIFS(Data_EntMonth!$D:$D,Data_EntMonth!$A:$A,$A9,Data_EntMonth!$B:$B,M$4)) | N9: =IF($A9="","",SUMIFS(Data_EntMonth!$D:$D,Data_EntMonth!$A:$A,$A9,Data_EntMonth!$B:$B,N$4)) | O9: =IF($A9="","",SUMIFS(Data_EntMonth!$D:$D,Data_EntMonth!$A:$A,$A9,Data_EntMonth!$B:$B,O$4)) | ... S9: =IF($A9="","",SUMIFS(Data_EntMonth!$D:$D,Data_EntMonth!$A:$A,$A9,Data_EntMonth!$B:$B,S$4))
A10: =IF(INDEX(Data_Contracts!$A:$A,6+1)="","",INDEX(Data_Contracts!$A:$A,6+1)) | B10: =IF(INDEX(Data_Contracts!$C:$C,6+1)="","",INDEX(Data_Contracts!$C:$C,6+1)) | C10: =IF(INDEX(Data_Contracts!$D:$D,6+1)="","",INDEX(Data_Contracts!$D:$D,6+1)) | D10: =IF(INDEX(Data_Contracts!$E:$E,6+1)="","",INDEX(Data_Contracts!$E:$E,6+1)) | E10: =IF(INDEX(Data_Contracts!$F:$F,6+1)="","",INDEX(Data_Contracts!$F:$F,6+1)) | F10: =IF(OR($A10="",N($D10)=0),"",S10/$D10) | G10: =IF($A10="","",SUMIFS(Data_EntMonth!$F:$F,Data_EntMonth!$A:$A,$A10,Data_EntMonth!$B:$B,S$4)) | H10: =IF($A10="","",SUMIFS(Data_EntMonth!$D:$D,Data_EntMonth!$A:$A,$A10,Data_EntMonth!$B:$B,H$4)) | I10: =IF($A10="","",SUMIFS(Data_EntMonth!$D:$D,Data_EntMonth!$A:$A,$A10,Data_EntMonth!$B:$B,I$4)) | J10: =IF($A10="","",SUMIFS(Data_EntMonth!$D:$D,Data_EntMonth!$A:$A,$A10,Data_EntMonth!$B:$B,J$4)) | K10: =IF($A10="","",SUMIFS(Data_EntMonth!$D:$D,Data_EntMonth!$A:$A,$A10,Data_EntMonth!$B:$B,K$4)) | L10: =IF($A10="","",SUMIFS(Data_EntMonth!$D:$D,Data_EntMonth!$A:$A,$A10,Data_EntMonth!$B:$B,L$4)) | M10: =IF($A10="","",SUMIFS(Data_EntMonth!$D:$D,Data_EntMonth!$A:$A,$A10,Data_EntMonth!$B:$B,M$4)) | N10: =IF($A10="","",SUMIFS(Data_EntMonth!$D:$D,Data_EntMonth!$A:$A,$A10,Data_EntMonth!$B:$B,N$4)) | O10: =IF($A10="","",SUMIFS(Data_EntMonth!$D:$D,Data_EntMonth!$A:$A,$A10,Data_EntMonth!$B:$B,O$4)) | ... S10: =IF($A10="","",SUMIFS(Data_EntMonth!$D:$D,Data_EntMonth!$A:$A,$A10,Data_EntMonth!$B:$B,S$4))
A11: =IF(INDEX(Data_Contracts!$A:$A,7+1)="","",INDEX(Data_Contracts!$A:$A,7+1)) | B11: =IF(INDEX(Data_Contracts!$C:$C,7+1)="","",INDEX(Data_Contracts!$C:$C,7+1)) | C11: =IF(INDEX(Data_Contracts!$D:$D,7+1)="","",INDEX(Data_Contracts!$D:$D,7+1)) | D11: =IF(INDEX(Data_Contracts!$E:$E,7+1)="","",INDEX(Data_Contracts!$E:$E,7+1)) | E11: =IF(INDEX(Data_Contracts!$F:$F,7+1)="","",INDEX(Data_Contracts!$F:$F,7+1)) | F11: =IF(OR($A11="",N($D11)=0),"",S11/$D11) | G11: =IF($A11="","",SUMIFS(Data_EntMonth!$F:$F,Data_EntMonth!$A:$A,$A11,Data_EntMonth!$B:$B,S$4)) | H11: =IF($A11="","",SUMIFS(Data_EntMonth!$D:$D,Data_EntMonth!$A:$A,$A11,Data_EntMonth!$B:$B,H$4)) | I11: =IF($A11="","",SUMIFS(Data_EntMonth!$D:$D,Data_EntMonth!$A:$A,$A11,Data_EntMonth!$B:$B,I$4)) | J11: =IF($A11="","",SUMIFS(Data_EntMonth!$D:$D,Data_EntMonth!$A:$A,$A11,Data_EntMonth!$B:$B,J$4)) | K11: =IF($A11="","",SUMIFS(Data_EntMonth!$D:$D,Data_EntMonth!$A:$A,$A11,Data_EntMonth!$B:$B,K$4)) | L11: =IF($A11="","",SUMIFS(Data_EntMonth!$D:$D,Data_EntMonth!$A:$A,$A11,Data_EntMonth!$B:$B,L$4)) | M11: =IF($A11="","",SUMIFS(Data_EntMonth!$D:$D,Data_EntMonth!$A:$A,$A11,Data_EntMonth!$B:$B,M$4)) | N11: =IF($A11="","",SUMIFS(Data_EntMonth!$D:$D,Data_EntMonth!$A:$A,$A11,Data_EntMonth!$B:$B,N$4)) | O11: =IF($A11="","",SUMIFS(Data_EntMonth!$D:$D,Data_EntMonth!$A:$A,$A11,Data_EntMonth!$B:$B,O$4)) | ... S11: =IF($A11="","",SUMIFS(Data_EntMonth!$D:$D,Data_EntMonth!$A:$A,$A11,Data_EntMonth!$B:$B,S$4))
A12: =IF(INDEX(Data_Contracts!$A:$A,8+1)="","",INDEX(Data_Contracts!$A:$A,8+1)) | B12: =IF(INDEX(Data_Contracts!$C:$C,8+1)="","",INDEX(Data_Contracts!$C:$C,8+1)) | C12: =IF(INDEX(Data_Contracts!$D:$D,8+1)="","",INDEX(Data_Contracts!$D:$D,8+1)) | D12: =IF(INDEX(Data_Contracts!$E:$E,8+1)="","",INDEX(Data_Contracts!$E:$E,8+1)) | E12: =IF(INDEX(Data_Contracts!$F:$F,8+1)="","",INDEX(Data_Contracts!$F:$F,8+1)) | F12: =IF(OR($A12="",N($D12)=0),"",S12/$D12) | G12: =IF($A12="","",SUMIFS(Data_EntMonth!$F:$F,Data_EntMonth!$A:$A,$A12,Data_EntMonth!$B:$B,S$4)) | H12: =IF($A12="","",SUMIFS(Data_EntMonth!$D:$D,Data_EntMonth!$A:$A,$A12,Data_EntMonth!$B:$B,H$4)) | I12: =IF($A12="","",SUMIFS(Data_EntMonth!$D:$D,Data_EntMonth!$A:$A,$A12,Data_EntMonth!$B:$B,I$4)) | J12: =IF($A12="","",SUMIFS(Data_EntMonth!$D:$D,Data_EntMonth!$A:$A,$A12,Data_EntMonth!$B:$B,J$4)) | K12: =IF($A12="","",SUMIFS(Data_EntMonth!$D:$D,Data_EntMonth!$A:$A,$A12,Data_EntMonth!$B:$B,K$4)) | L12: =IF($A12="","",SUMIFS(Data_EntMonth!$D:$D,Data_EntMonth!$A:$A,$A12,Data_EntMonth!$B:$B,L$4)) | M12: =IF($A12="","",SUMIFS(Data_EntMonth!$D:$D,Data_EntMonth!$A:$A,$A12,Data_EntMonth!$B:$B,M$4)) | N12: =IF($A12="","",SUMIFS(Data_EntMonth!$D:$D,Data_EntMonth!$A:$A,$A12,Data_EntMonth!$B:$B,N$4)) | O12: =IF($A12="","",SUMIFS(Data_EntMonth!$D:$D,Data_EntMonth!$A:$A,$A12,Data_EntMonth!$B:$B,O$4)) | ... S12: =IF($A12="","",SUMIFS(Data_EntMonth!$D:$D,Data_EntMonth!$A:$A,$A12,Data_EntMonth!$B:$B,S$4))
A13: =IF(INDEX(Data_Contracts!$A:$A,9+1)="","",INDEX(Data_Contracts!$A:$A,9+1)) | B13: =IF(INDEX(Data_Contracts!$C:$C,9+1)="","",INDEX(Data_Contracts!$C:$C,9+1)) | C13: =IF(INDEX(Data_Contracts!$D:$D,9+1)="","",INDEX(Data_Contracts!$D:$D,9+1)) | D13: =IF(INDEX(Data_Contracts!$E:$E,9+1)="","",INDEX(Data_Contracts!$E:$E,9+1)) | E13: =IF(INDEX(Data_Contracts!$F:$F,9+1)="","",INDEX(Data_Contracts!$F:$F,9+1)) | F13: =IF(OR($A13="",N($D13)=0),"",S13/$D13) | G13: =IF($A13="","",SUMIFS(Data_EntMonth!$F:$F,Data_EntMonth!$A:$A,$A13,Data_EntMonth!$B:$B,S$4)) | H13: =IF($A13="","",SUMIFS(Data_EntMonth!$D:$D,Data_EntMonth!$A:$A,$A13,Data_EntMonth!$B:$B,H$4)) | I13: =IF($A13="","",SUMIFS(Data_EntMonth!$D:$D,Data_EntMonth!$A:$A,$A13,Data_EntMonth!$B:$B,I$4)) | J13: =IF($A13="","",SUMIFS(Data_EntMonth!$D:$D,Data_EntMonth!$A:$A,$A13,Data_EntMonth!$B:$B,J$4)) | K13: =IF($A13="","",SUMIFS(Data_EntMonth!$D:$D,Data_EntMonth!$A:$A,$A13,Data_EntMonth!$B:$B,K$4)) | L13: =IF($A13="","",SUMIFS(Data_EntMonth!$D:$D,Data_EntMonth!$A:$A,$A13,Data_EntMonth!$B:$B,L$4)) | M13: =IF($A13="","",SUMIFS(Data_EntMonth!$D:$D,Data_EntMonth!$A:$A,$A13,Data_EntMonth!$B:$B,M$4)) | N13: =IF($A13="","",SUMIFS(Data_EntMonth!$D:$D,Data_EntMonth!$A:$A,$A13,Data_EntMonth!$B:$B,N$4)) | O13: =IF($A13="","",SUMIFS(Data_EntMonth!$D:$D,Data_EntMonth!$A:$A,$A13,Data_EntMonth!$B:$B,O$4)) | ... S13: =IF($A13="","",SUMIFS(Data_EntMonth!$D:$D,Data_EntMonth!$A:$A,$A13,Data_EntMonth!$B:$B,S$4))
A14: =IF(INDEX(Data_Contracts!$A:$A,10+1)="","",INDEX(Data_Contracts!$A:$A,10+1)) | B14: =IF(INDEX(Data_Contracts!$C:$C,10+1)="","",INDEX(Data_Contracts!$C:$C,10+1)) | C14: =IF(INDEX(Data_Contracts!$D:$D,10+1)="","",INDEX(Data_Contracts!$D:$D,10+1)) | D14: =IF(INDEX(Data_Contracts!$E:$E,10+1)="","",INDEX(Data_Contracts!$E:$E,10+1)) | E14: =IF(INDEX(Data_Contracts!$F:$F,10+1)="","",INDEX(Data_Contracts!$F:$F,10+1)) | F14: =IF(OR($A14="",N($D14)=0),"",S14/$D14) | G14: =IF($A14="","",SUMIFS(Data_EntMonth!$F:$F,Data_EntMonth!$A:$A,$A14,Data_EntMonth!$B:$B,S$4)) | H14: =IF($A14="","",SUMIFS(Data_EntMonth!$D:$D,Data_EntMonth!$A:$A,$A14,Data_EntMonth!$B:$B,H$4)) | I14: =IF($A14="","",SUMIFS(Data_EntMonth!$D:$D,Data_EntMonth!$A:$A,$A14,Data_EntMonth!$B:$B,I$4)) | J14: =IF($A14="","",SUMIFS(Data_EntMonth!$D:$D,Data_EntMonth!$A:$A,$A14,Data_EntMonth!$B:$B,J$4)) | K14: =IF($A14="","",SUMIFS(Data_EntMonth!$D:$D,Data_EntMonth!$A:$A,$A14,Data_EntMonth!$B:$B,K$4)) | L14: =IF($A14="","",SUMIFS(Data_EntMonth!$D:$D,Data_EntMonth!$A:$A,$A14,Data_EntMonth!$B:$B,L$4)) | M14: =IF($A14="","",SUMIFS(Data_EntMonth!$D:$D,Data_EntMonth!$A:$A,$A14,Data_EntMonth!$B:$B,M$4)) | N14: =IF($A14="","",SUMIFS(Data_EntMonth!$D:$D,Data_EntMonth!$A:$A,$A14,Data_EntMonth!$B:$B,N$4)) | O14: =IF($A14="","",SUMIFS(Data_EntMonth!$D:$D,Data_EntMonth!$A:$A,$A14,Data_EntMonth!$B:$B,O$4)) | ... S14: =IF($A14="","",SUMIFS(Data_EntMonth!$D:$D,Data_EntMonth!$A:$A,$A14,Data_EntMonth!$B:$B,S$4))
A15: =IF(INDEX(Data_Contracts!$A:$A,11+1)="","",INDEX(Data_Contracts!$A:$A,11+1)) | B15: =IF(INDEX(Data_Contracts!$C:$C,11+1)="","",INDEX(Data_Contracts!$C:$C,11+1)) | C15: =IF(INDEX(Data_Contracts!$D:$D,11+1)="","",INDEX(Data_Contracts!$D:$D,11+1)) | D15: =IF(INDEX(Data_Contracts!$E:$E,11+1)="","",INDEX(Data_Contracts!$E:$E,11+1)) | E15: =IF(INDEX(Data_Contracts!$F:$F,11+1)="","",INDEX(Data_Contracts!$F:$F,11+1)) | F15: =IF(OR($A15="",N($D15)=0),"",S15/$D15) | G15: =IF($A15="","",SUMIFS(Data_EntMonth!$F:$F,Data_EntMonth!$A:$A,$A15,Data_EntMonth!$B:$B,S$4)) | H15: =IF($A15="","",SUMIFS(Data_EntMonth!$D:$D,Data_EntMonth!$A:$A,$A15,Data_EntMonth!$B:$B,H$4)) | I15: =IF($A15="","",SUMIFS(Data_EntMonth!$D:$D,Data_EntMonth!$A:$A,$A15,Data_EntMonth!$B:$B,I$4)) | J15: =IF($A15="","",SUMIFS(Data_EntMonth!$D:$D,Data_EntMonth!$A:$A,$A15,Data_EntMonth!$B:$B,J$4)) | K15: =IF($A15="","",SUMIFS(Data_EntMonth!$D:$D,Data_EntMonth!$A:$A,$A15,Data_EntMonth!$B:$B,K$4)) | L15: =IF($A15="","",SUMIFS(Data_EntMonth!$D:$D,Data_EntMonth!$A:$A,$A15,Data_EntMonth!$B:$B,L$4)) | M15: =IF($A15="","",SUMIFS(Data_EntMonth!$D:$D,Data_EntMonth!$A:$A,$A15,Data_EntMonth!$B:$B,M$4)) | N15: =IF($A15="","",SUMIFS(Data_EntMonth!$D:$D,Data_EntMonth!$A:$A,$A15,Data_EntMonth!$B:$B,N$4)) | O15: =IF($A15="","",SUMIFS(Data_EntMonth!$D:$D,Data_EntMonth!$A:$A,$A15,Data_EntMonth!$B:$B,O$4)) | ... S15: =IF($A15="","",SUMIFS(Data_EntMonth!$D:$D,Data_EntMonth!$A:$A,$A15,Data_EntMonth!$B:$B,S$4))
A16: =IF(INDEX(Data_Contracts!$A:$A,12+1)="","",INDEX(Data_Contracts!$A:$A,12+1)) | B16: =IF(INDEX(Data_Contracts!$C:$C,12+1)="","",INDEX(Data_Contracts!$C:$C,12+1)) | C16: =IF(INDEX(Data_Contracts!$D:$D,12+1)="","",INDEX(Data_Contracts!$D:$D,12+1)) | D16: =IF(INDEX(Data_Contracts!$E:$E,12+1)="","",INDEX(Data_Contracts!$E:$E,12+1)) | E16: =IF(INDEX(Data_Contracts!$F:$F,12+1)="","",INDEX(Data_Contracts!$F:$F,12+1)) | F16: =IF(OR($A16="",N($D16)=0),"",S16/$D16) | G16: =IF($A16="","",SUMIFS(Data_EntMonth!$F:$F,Data_EntMonth!$A:$A,$A16,Data_EntMonth!$B:$B,S$4)) | H16: =IF($A16="","",SUMIFS(Data_EntMonth!$D:$D,Data_EntMonth!$A:$A,$A16,Data_EntMonth!$B:$B,H$4)) | I16: =IF($A16="","",SUMIFS(Data_EntMonth!$D:$D,Data_EntMonth!$A:$A,$A16,Data_EntMonth!$B:$B,I$4)) | J16: =IF($A16="","",SUMIFS(Data_EntMonth!$D:$D,Data_EntMonth!$A:$A,$A16,Data_EntMonth!$B:$B,J$4)) | K16: =IF($A16="","",SUMIFS(Data_EntMonth!$D:$D,Data_EntMonth!$A:$A,$A16,Data_EntMonth!$B:$B,K$4)) | L16: =IF($A16="","",SUMIFS(Data_EntMonth!$D:$D,Data_EntMonth!$A:$A,$A16,Data_EntMonth!$B:$B,L$4)) | M16: =IF($A16="","",SUMIFS(Data_EntMonth!$D:$D,Data_EntMonth!$A:$A,$A16,Data_EntMonth!$B:$B,M$4)) | N16: =IF($A16="","",SUMIFS(Data_EntMonth!$D:$D,Data_EntMonth!$A:$A,$A16,Data_EntMonth!$B:$B,N$4)) | O16: =IF($A16="","",SUMIFS(Data_EntMonth!$D:$D,Data_EntMonth!$A:$A,$A16,Data_EntMonth!$B:$B,O$4)) | ... S16: =IF($A16="","",SUMIFS(Data_EntMonth!$D:$D,Data_EntMonth!$A:$A,$A16,Data_EntMonth!$B:$B,S$4))
A17: =IF(INDEX(Data_Contracts!$A:$A,13+1)="","",INDEX(Data_Contracts!$A:$A,13+1)) | B17: =IF(INDEX(Data_Contracts!$C:$C,13+1)="","",INDEX(Data_Contracts!$C:$C,13+1)) | C17: =IF(INDEX(Data_Contracts!$D:$D,13+1)="","",INDEX(Data_Contracts!$D:$D,13+1)) | D17: =IF(INDEX(Data_Contracts!$E:$E,13+1)="","",INDEX(Data_Contracts!$E:$E,13+1)) | E17: =IF(INDEX(Data_Contracts!$F:$F,13+1)="","",INDEX(Data_Contracts!$F:$F,13+1)) | F17: =IF(OR($A17="",N($D17)=0),"",S17/$D17) | G17: =IF($A17="","",SUMIFS(Data_EntMonth!$F:$F,Data_EntMonth!$A:$A,$A17,Data_EntMonth!$B:$B,S$4)) | H17: =IF($A17="","",SUMIFS(Data_EntMonth!$D:$D,Data_EntMonth!$A:$A,$A17,Data_EntMonth!$B:$B,H$4)) | I17: =IF($A17="","",SUMIFS(Data_EntMonth!$D:$D,Data_EntMonth!$A:$A,$A17,Data_EntMonth!$B:$B,I$4)) | J17: =IF($A17="","",SUMIFS(Data_EntMonth!$D:$D,Data_EntMonth!$A:$A,$A17,Data_EntMonth!$B:$B,J$4)) | K17: =IF($A17="","",SUMIFS(Data_EntMonth!$D:$D,Data_EntMonth!$A:$A,$A17,Data_EntMonth!$B:$B,K$4)) | L17: =IF($A17="","",SUMIFS(Data_EntMonth!$D:$D,Data_EntMonth!$A:$A,$A17,Data_EntMonth!$B:$B,L$4)) | M17: =IF($A17="","",SUMIFS(Data_EntMonth!$D:$D,Data_EntMonth!$A:$A,$A17,Data_EntMonth!$B:$B,M$4)) | N17: =IF($A17="","",SUMIFS(Data_EntMonth!$D:$D,Data_EntMonth!$A:$A,$A17,Data_EntMonth!$B:$B,N$4)) | O17: =IF($A17="","",SUMIFS(Data_EntMonth!$D:$D,Data_EntMonth!$A:$A,$A17,Data_EntMonth!$B:$B,O$4)) | ... S17: =IF($A17="","",SUMIFS(Data_EntMonth!$D:$D,Data_EntMonth!$A:$A,$A17,Data_EntMonth!$B:$B,S$4))
A18: =IF(INDEX(Data_Contracts!$A:$A,14+1)="","",INDEX(Data_Contracts!$A:$A,14+1)) | B18: =IF(INDEX(Data_Contracts!$C:$C,14+1)="","",INDEX(Data_Contracts!$C:$C,14+1)) | C18: =IF(INDEX(Data_Contracts!$D:$D,14+1)="","",INDEX(Data_Contracts!$D:$D,14+1)) | D18: =IF(INDEX(Data_Contracts!$E:$E,14+1)="","",INDEX(Data_Contracts!$E:$E,14+1)) | E18: =IF(INDEX(Data_Contracts!$F:$F,14+1)="","",INDEX(Data_Contracts!$F:$F,14+1)) | F18: =IF(OR($A18="",N($D18)=0),"",S18/$D18) | G18: =IF($A18="","",SUMIFS(Data_EntMonth!$F:$F,Data_EntMonth!$A:$A,$A18,Data_EntMonth!$B:$B,S$4)) | H18: =IF($A18="","",SUMIFS(Data_EntMonth!$D:$D,Data_EntMonth!$A:$A,$A18,Data_EntMonth!$B:$B,H$4)) | I18: =IF($A18="","",SUMIFS(Data_EntMonth!$D:$D,Data_EntMonth!$A:$A,$A18,Data_EntMonth!$B:$B,I$4)) | J18: =IF($A18="","",SUMIFS(Data_EntMonth!$D:$D,Data_EntMonth!$A:$A,$A18,Data_EntMonth!$B:$B,J$4)) | K18: =IF($A18="","",SUMIFS(Data_EntMonth!$D:$D,Data_EntMonth!$A:$A,$A18,Data_EntMonth!$B:$B,K$4)) | L18: =IF($A18="","",SUMIFS(Data_EntMonth!$D:$D,Data_EntMonth!$A:$A,$A18,Data_EntMonth!$B:$B,L$4)) | M18: =IF($A18="","",SUMIFS(Data_EntMonth!$D:$D,Data_EntMonth!$A:$A,$A18,Data_EntMonth!$B:$B,M$4)) | N18: =IF($A18="","",SUMIFS(Data_EntMonth!$D:$D,Data_EntMonth!$A:$A,$A18,Data_EntMonth!$B:$B,N$4)) | O18: =IF($A18="","",SUMIFS(Data_EntMonth!$D:$D,Data_EntMonth!$A:$A,$A18,Data_EntMonth!$B:$B,O$4)) | ... S18: =IF($A18="","",SUMIFS(Data_EntMonth!$D:$D,Data_EntMonth!$A:$A,$A18,Data_EntMonth!$B:$B,S$4))
A19: =IF(INDEX(Data_Contracts!$A:$A,15+1)="","",INDEX(Data_Contracts!$A:$A,15+1)) | B19: =IF(INDEX(Data_Contracts!$C:$C,15+1)="","",INDEX(Data_Contracts!$C:$C,15+1)) | C19: =IF(INDEX(Data_Contracts!$D:$D,15+1)="","",INDEX(Data_Contracts!$D:$D,15+1)) | D19: =IF(INDEX(Data_Contracts!$E:$E,15+1)="","",INDEX(Data_Contracts!$E:$E,15+1)) | E19: =IF(INDEX(Data_Contracts!$F:$F,15+1)="","",INDEX(Data_Contracts!$F:$F,15+1)) | F19: =IF(OR($A19="",N($D19)=0),"",S19/$D19) | G19: =IF($A19="","",SUMIFS(Data_EntMonth!$F:$F,Data_EntMonth!$A:$A,$A19,Data_EntMonth!$B:$B,S$4)) | H19: =IF($A19="","",SUMIFS(Data_EntMonth!$D:$D,Data_EntMonth!$A:$A,$A19,Data_EntMonth!$B:$B,H$4)) | I19: =IF($A19="","",SUMIFS(Data_EntMonth!$D:$D,Data_EntMonth!$A:$A,$A19,Data_EntMonth!$B:$B,I$4)) | J19: =IF($A19="","",SUMIFS(Data_EntMonth!$D:$D,Data_EntMonth!$A:$A,$A19,Data_EntMonth!$B:$B,J$4)) | K19: =IF($A19="","",SUMIFS(Data_EntMonth!$D:$D,Data_EntMonth!$A:$A,$A19,Data_EntMonth!$B:$B,K$4)) | L19: =IF($A19="","",SUMIFS(Data_EntMonth!$D:$D,Data_EntMonth!$A:$A,$A19,Data_EntMonth!$B:$B,L$4)) | M19: =IF($A19="","",SUMIFS(Data_EntMonth!$D:$D,Data_EntMonth!$A:$A,$A19,Data_EntMonth!$B:$B,M$4)) | N19: =IF($A19="","",SUMIFS(Data_EntMonth!$D:$D,Data_EntMonth!$A:$A,$A19,Data_EntMonth!$B:$B,N$4)) | O19: =IF($A19="","",SUMIFS(Data_EntMonth!$D:$D,Data_EntMonth!$A:$A,$A19,Data_EntMonth!$B:$B,O$4)) | ... S19: =IF($A19="","",SUMIFS(Data_EntMonth!$D:$D,Data_EntMonth!$A:$A,$A19,Data_EntMonth!$B:$B,S$4))
A20: =IF(INDEX(Data_Contracts!$A:$A,16+1)="","",INDEX(Data_Contracts!$A:$A,16+1)) | B20: =IF(INDEX(Data_Contracts!$C:$C,16+1)="","",INDEX(Data_Contracts!$C:$C,16+1)) | C20: =IF(INDEX(Data_Contracts!$D:$D,16+1)="","",INDEX(Data_Contracts!$D:$D,16+1)) | D20: =IF(INDEX(Data_Contracts!$E:$E,16+1)="","",INDEX(Data_Contracts!$E:$E,16+1)) | E20: =IF(INDEX(Data_Contracts!$F:$F,16+1)="","",INDEX(Data_Contracts!$F:$F,16+1)) | F20: =IF(OR($A20="",N($D20)=0),"",S20/$D20) | G20: =IF($A20="","",SUMIFS(Data_EntMonth!$F:$F,Data_EntMonth!$A:$A,$A20,Data_EntMonth!$B:$B,S$4)) | H20: =IF($A20="","",SUMIFS(Data_EntMonth!$D:$D,Data_EntMonth!$A:$A,$A20,Data_EntMonth!$B:$B,H$4)) | I20: =IF($A20="","",SUMIFS(Data_EntMonth!$D:$D,Data_EntMonth!$A:$A,$A20,Data_EntMonth!$B:$B,I$4)) | J20: =IF($A20="","",SUMIFS(Data_EntMonth!$D:$D,Data_EntMonth!$A:$A,$A20,Data_EntMonth!$B:$B,J$4)) | K20: =IF($A20="","",SUMIFS(Data_EntMonth!$D:$D,Data_EntMonth!$A:$A,$A20,Data_EntMonth!$B:$B,K$4)) | L20: =IF($A20="","",SUMIFS(Data_EntMonth!$D:$D,Data_EntMonth!$A:$A,$A20,Data_EntMonth!$B:$B,L$4)) | M20: =IF($A20="","",SUMIFS(Data_EntMonth!$D:$D,Data_EntMonth!$A:$A,$A20,Data_EntMonth!$B:$B,M$4)) | N20: =IF($A20="","",SUMIFS(Data_EntMonth!$D:$D,Data_EntMonth!$A:$A,$A20,Data_EntMonth!$B:$B,N$4)) | O20: =IF($A20="","",SUMIFS(Data_EntMonth!$D:$D,Data_EntMonth!$A:$A,$A20,Data_EntMonth!$B:$B,O$4)) | ... S20: =IF($A20="","",SUMIFS(Data_EntMonth!$D:$D,Data_EntMonth!$A:$A,$A20,Data_EntMonth!$B:$B,S$4))
A21: =IF(INDEX(Data_Contracts!$A:$A,17+1)="","",INDEX(Data_Contracts!$A:$A,17+1)) | B21: =IF(INDEX(Data_Contracts!$C:$C,17+1)="","",INDEX(Data_Contracts!$C:$C,17+1)) | C21: =IF(INDEX(Data_Contracts!$D:$D,17+1)="","",INDEX(Data_Contracts!$D:$D,17+1)) | D21: =IF(INDEX(Data_Contracts!$E:$E,17+1)="","",INDEX(Data_Contracts!$E:$E,17+1)) | E21: =IF(INDEX(Data_Contracts!$F:$F,17+1)="","",INDEX(Data_Contracts!$F:$F,17+1)) | F21: =IF(OR($A21="",N($D21)=0),"",S21/$D21) | G21: =IF($A21="","",SUMIFS(Data_EntMonth!$F:$F,Data_EntMonth!$A:$A,$A21,Data_EntMonth!$B:$B,S$4)) | H21: =IF($A21="","",SUMIFS(Data_EntMonth!$D:$D,Data_EntMonth!$A:$A,$A21,Data_EntMonth!$B:$B,H$4)) | I21: =IF($A21="","",SUMIFS(Data_EntMonth!$D:$D,Data_EntMonth!$A:$A,$A21,Data_EntMonth!$B:$B,I$4)) | J21: =IF($A21="","",SUMIFS(Data_EntMonth!$D:$D,Data_EntMonth!$A:$A,$A21,Data_EntMonth!$B:$B,J$4)) | K21: =IF($A21="","",SUMIFS(Data_EntMonth!$D:$D,Data_EntMonth!$A:$A,$A21,Data_EntMonth!$B:$B,K$4)) | L21: =IF($A21="","",SUMIFS(Data_EntMonth!$D:$D,Data_EntMonth!$A:$A,$A21,Data_EntMonth!$B:$B,L$4)) | M21: =IF($A21="","",SUMIFS(Data_EntMonth!$D:$D,Data_EntMonth!$A:$A,$A21,Data_EntMonth!$B:$B,M$4)) | N21: =IF($A21="","",SUMIFS(Data_EntMonth!$D:$D,Data_EntMonth!$A:$A,$A21,Data_EntMonth!$B:$B,N$4)) | O21: =IF($A21="","",SUMIFS(Data_EntMonth!$D:$D,Data_EntMonth!$A:$A,$A21,Data_EntMonth!$B:$B,O$4)) | ... S21: =IF($A21="","",SUMIFS(Data_EntMonth!$D:$D,Data_EntMonth!$A:$A,$A21,Data_EntMonth!$B:$B,S$4))
A22: =IF(INDEX(Data_Contracts!$A:$A,18+1)="","",INDEX(Data_Contracts!$A:$A,18+1)) | B22: =IF(INDEX(Data_Contracts!$C:$C,18+1)="","",INDEX(Data_Contracts!$C:$C,18+1)) | C22: =IF(INDEX(Data_Contracts!$D:$D,18+1)="","",INDEX(Data_Contracts!$D:$D,18+1)) | D22: =IF(INDEX(Data_Contracts!$E:$E,18+1)="","",INDEX(Data_Contracts!$E:$E,18+1)) | E22: =IF(INDEX(Data_Contracts!$F:$F,18+1)="","",INDEX(Data_Contracts!$F:$F,18+1)) | F22: =IF(OR($A22="",N($D22)=0),"",S22/$D22) | G22: =IF($A22="","",SUMIFS(Data_EntMonth!$F:$F,Data_EntMonth!$A:$A,$A22,Data_EntMonth!$B:$B,S$4)) | H22: =IF($A22="","",SUMIFS(Data_EntMonth!$D:$D,Data_EntMonth!$A:$A,$A22,Data_EntMonth!$B:$B,H$4)) | I22: =IF($A22="","",SUMIFS(Data_EntMonth!$D:$D,Data_EntMonth!$A:$A,$A22,Data_EntMonth!$B:$B,I$4)) | J22: =IF($A22="","",SUMIFS(Data_EntMonth!$D:$D,Data_EntMonth!$A:$A,$A22,Data_EntMonth!$B:$B,J$4)) | K22: =IF($A22="","",SUMIFS(Data_EntMonth!$D:$D,Data_EntMonth!$A:$A,$A22,Data_EntMonth!$B:$B,K$4)) | L22: =IF($A22="","",SUMIFS(Data_EntMonth!$D:$D,Data_EntMonth!$A:$A,$A22,Data_EntMonth!$B:$B,L$4)) | M22: =IF($A22="","",SUMIFS(Data_EntMonth!$D:$D,Data_EntMonth!$A:$A,$A22,Data_EntMonth!$B:$B,M$4)) | N22: =IF($A22="","",SUMIFS(Data_EntMonth!$D:$D,Data_EntMonth!$A:$A,$A22,Data_EntMonth!$B:$B,N$4)) | O22: =IF($A22="","",SUMIFS(Data_EntMonth!$D:$D,Data_EntMonth!$A:$A,$A22,Data_EntMonth!$B:$B,O$4)) | ... S22: =IF($A22="","",SUMIFS(Data_EntMonth!$D:$D,Data_EntMonth!$A:$A,$A22,Data_EntMonth!$B:$B,S$4))
A23: =IF(INDEX(Data_Contracts!$A:$A,19+1)="","",INDEX(Data_Contracts!$A:$A,19+1)) | B23: =IF(INDEX(Data_Contracts!$C:$C,19+1)="","",INDEX(Data_Contracts!$C:$C,19+1)) | C23: =IF(INDEX(Data_Contracts!$D:$D,19+1)="","",INDEX(Data_Contracts!$D:$D,19+1)) | D23: =IF(INDEX(Data_Contracts!$E:$E,19+1)="","",INDEX(Data_Contracts!$E:$E,19+1)) | E23: =IF(INDEX(Data_Contracts!$F:$F,19+1)="","",INDEX(Data_Contracts!$F:$F,19+1)) | F23: =IF(OR($A23="",N($D23)=0),"",S23/$D23) | G23: =IF($A23="","",SUMIFS(Data_EntMonth!$F:$F,Data_EntMonth!$A:$A,$A23,Data_EntMonth!$B:$B,S$4)) | H23: =IF($A23="","",SUMIFS(Data_EntMonth!$D:$D,Data_EntMonth!$A:$A,$A23,Data_EntMonth!$B:$B,H$4)) | I23: =IF($A23="","",SUMIFS(Data_EntMonth!$D:$D,Data_EntMonth!$A:$A,$A23,Data_EntMonth!$B:$B,I$4)) | J23: =IF($A23="","",SUMIFS(Data_EntMonth!$D:$D,Data_EntMonth!$A:$A,$A23,Data_EntMonth!$B:$B,J$4)) | K23: =IF($A23="","",SUMIFS(Data_EntMonth!$D:$D,Data_EntMonth!$A:$A,$A23,Data_EntMonth!$B:$B,K$4)) | L23: =IF($A23="","",SUMIFS(Data_EntMonth!$D:$D,Data_EntMonth!$A:$A,$A23,Data_EntMonth!$B:$B,L$4)) | M23: =IF($A23="","",SUMIFS(Data_EntMonth!$D:$D,Data_EntMonth!$A:$A,$A23,Data_EntMonth!$B:$B,M$4)) | N23: =IF($A23="","",SUMIFS(Data_EntMonth!$D:$D,Data_EntMonth!$A:$A,$A23,Data_EntMonth!$B:$B,N$4)) | O23: =IF($A23="","",SUMIFS(Data_EntMonth!$D:$D,Data_EntMonth!$A:$A,$A23,Data_EntMonth!$B:$B,O$4)) | ... S23: =IF($A23="","",SUMIFS(Data_EntMonth!$D:$D,Data_EntMonth!$A:$A,$A23,Data_EntMonth!$B:$B,S$4))
A24: =IF(INDEX(Data_Contracts!$A:$A,20+1)="","",INDEX(Data_Contracts!$A:$A,20+1)) | B24: =IF(INDEX(Data_Contracts!$C:$C,20+1)="","",INDEX(Data_Contracts!$C:$C,20+1)) | C24: =IF(INDEX(Data_Contracts!$D:$D,20+1)="","",INDEX(Data_Contracts!$D:$D,20+1)) | D24: =IF(INDEX(Data_Contracts!$E:$E,20+1)="","",INDEX(Data_Contracts!$E:$E,20+1)) | E24: =IF(INDEX(Data_Contracts!$F:$F,20+1)="","",INDEX(Data_Contracts!$F:$F,20+1)) | F24: =IF(OR($A24="",N($D24)=0),"",S24/$D24) | G24: =IF($A24="","",SUMIFS(Data_EntMonth!$F:$F,Data_EntMonth!$A:$A,$A24,Data_EntMonth!$B:$B,S$4)) | H24: =IF($A24="","",SUMIFS(Data_EntMonth!$D:$D,Data_EntMonth!$A:$A,$A24,Data_EntMonth!$B:$B,H$4)) | I24: =IF($A24="","",SUMIFS(Data_EntMonth!$D:$D,Data_EntMonth!$A:$A,$A24,Data_EntMonth!$B:$B,I$4)) | J24: =IF($A24="","",SUMIFS(Data_EntMonth!$D:$D,Data_EntMonth!$A:$A,$A24,Data_EntMonth!$B:$B,J$4)) | K24: =IF($A24="","",SUMIFS(Data_EntMonth!$D:$D,Data_EntMonth!$A:$A,$A24,Data_EntMonth!$B:$B,K$4)) | L24: =IF($A24="","",SUMIFS(Data_EntMonth!$D:$D,Data_EntMonth!$A:$A,$A24,Data_EntMonth!$B:$B,L$4)) | M24: =IF($A24="","",SUMIFS(Data_EntMonth!$D:$D,Data_EntMonth!$A:$A,$A24,Data_EntMonth!$B:$B,M$4)) | N24: =IF($A24="","",SUMIFS(Data_EntMonth!$D:$D,Data_EntMonth!$A:$A,$A24,Data_EntMonth!$B:$B,N$4)) | O24: =IF($A24="","",SUMIFS(Data_EntMonth!$D:$D,Data_EntMonth!$A:$A,$A24,Data_EntMonth!$B:$B,O$4)) | ... S24: =IF($A24="","",SUMIFS(Data_EntMonth!$D:$D,Data_EntMonth!$A:$A,$A24,Data_EntMonth!$B:$B,S$4))
A25: =IF(INDEX(Data_Contracts!$A:$A,21+1)="","",INDEX(Data_Contracts!$A:$A,21+1)) | B25: =IF(INDEX(Data_Contracts!$C:$C,21+1)="","",INDEX(Data_Contracts!$C:$C,21+1)) | C25: =IF(INDEX(Data_Contracts!$D:$D,21+1)="","",INDEX(Data_Contracts!$D:$D,21+1)) | D25: =IF(INDEX(Data_Contracts!$E:$E,21+1)="","",INDEX(Data_Contracts!$E:$E,21+1)) | E25: =IF(INDEX(Data_Contracts!$F:$F,21+1)="","",INDEX(Data_Contracts!$F:$F,21+1)) | F25: =IF(OR($A25="",N($D25)=0),"",S25/$D25) | G25: =IF($A25="","",SUMIFS(Data_EntMonth!$F:$F,Data_EntMonth!$A:$A,$A25,Data_EntMonth!$B:$B,S$4)) | H25: =IF($A25="","",SUMIFS(Data_EntMonth!$D:$D,Data_EntMonth!$A:$A,$A25,Data_EntMonth!$B:$B,H$4)) | I25: =IF($A25="","",SUMIFS(Data_EntMonth!$D:$D,Data_EntMonth!$A:$A,$A25,Data_EntMonth!$B:$B,I$4)) | J25: =IF($A25="","",SUMIFS(Data_EntMonth!$D:$D,Data_EntMonth!$A:$A,$A25,Data_EntMonth!$B:$B,J$4)) | K25: =IF($A25="","",SUMIFS(Data_EntMonth!$D:$D,Data_EntMonth!$A:$A,$A25,Data_EntMonth!$B:$B,K$4)) | L25: =IF($A25="","",SUMIFS(Data_EntMonth!$D:$D,Data_EntMonth!$A:$A,$A25,Data_EntMonth!$B:$B,L$4)) | M25: =IF($A25="","",SUMIFS(Data_EntMonth!$D:$D,Data_EntMonth!$A:$A,$A25,Data_EntMonth!$B:$B,M$4)) | N25: =IF($A25="","",SUMIFS(Data_EntMonth!$D:$D,Data_EntMonth!$A:$A,$A25,Data_EntMonth!$B:$B,N$4)) | O25: =IF($A25="","",SUMIFS(Data_EntMonth!$D:$D,Data_EntMonth!$A:$A,$A25,Data_EntMonth!$B:$B,O$4)) | ... S25: =IF($A25="","",SUMIFS(Data_EntMonth!$D:$D,Data_EntMonth!$A:$A,$A25,Data_EntMonth!$B:$B,S$4))
A26: =IF(INDEX(Data_Contracts!$A:$A,22+1)="","",INDEX(Data_Contracts!$A:$A,22+1)) | B26: =IF(INDEX(Data_Contracts!$C:$C,22+1)="","",INDEX(Data_Contracts!$C:$C,22+1)) | C26: =IF(INDEX(Data_Contracts!$D:$D,22+1)="","",INDEX(Data_Contracts!$D:$D,22+1)) | D26: =IF(INDEX(Data_Contracts!$E:$E,22+1)="","",INDEX(Data_Contracts!$E:$E,22+1)) | E26: =IF(INDEX(Data_Contracts!$F:$F,22+1)="","",INDEX(Data_Contracts!$F:$F,22+1)) | F26: =IF(OR($A26="",N($D26)=0),"",S26/$D26) | G26: =IF($A26="","",SUMIFS(Data_EntMonth!$F:$F,Data_EntMonth!$A:$A,$A26,Data_EntMonth!$B:$B,S$4)) | H26: =IF($A26="","",SUMIFS(Data_EntMonth!$D:$D,Data_EntMonth!$A:$A,$A26,Data_EntMonth!$B:$B,H$4)) | I26: =IF($A26="","",SUMIFS(Data_EntMonth!$D:$D,Data_EntMonth!$A:$A,$A26,Data_EntMonth!$B:$B,I$4)) | J26: =IF($A26="","",SUMIFS(Data_EntMonth!$D:$D,Data_EntMonth!$A:$A,$A26,Data_EntMonth!$B:$B,J$4)) | K26: =IF($A26="","",SUMIFS(Data_EntMonth!$D:$D,Data_EntMonth!$A:$A,$A26,Data_EntMonth!$B:$B,K$4)) | L26: =IF($A26="","",SUMIFS(Data_EntMonth!$D:$D,Data_EntMonth!$A:$A,$A26,Data_EntMonth!$B:$B,L$4)) | M26: =IF($A26="","",SUMIFS(Data_EntMonth!$D:$D,Data_EntMonth!$A:$A,$A26,Data_EntMonth!$B:$B,M$4)) | N26: =IF($A26="","",SUMIFS(Data_EntMonth!$D:$D,Data_EntMonth!$A:$A,$A26,Data_EntMonth!$B:$B,N$4)) | O26: =IF($A26="","",SUMIFS(Data_EntMonth!$D:$D,Data_EntMonth!$A:$A,$A26,Data_EntMonth!$B:$B,O$4)) | ... S26: =IF($A26="","",SUMIFS(Data_EntMonth!$D:$D,Data_EntMonth!$A:$A,$A26,Data_EntMonth!$B:$B,S$4))
A27: =IF(INDEX(Data_Contracts!$A:$A,23+1)="","",INDEX(Data_Contracts!$A:$A,23+1)) | B27: =IF(INDEX(Data_Contracts!$C:$C,23+1)="","",INDEX(Data_Contracts!$C:$C,23+1)) | C27: =IF(INDEX(Data_Contracts!$D:$D,23+1)="","",INDEX(Data_Contracts!$D:$D,23+1)) | D27: =IF(INDEX(Data_Contracts!$E:$E,23+1)="","",INDEX(Data_Contracts!$E:$E,23+1)) | E27: =IF(INDEX(Data_Contracts!$F:$F,23+1)="","",INDEX(Data_Contracts!$F:$F,23+1)) | F27: =IF(OR($A27="",N($D27)=0),"",S27/$D27) | G27: =IF($A27="","",SUMIFS(Data_EntMonth!$F:$F,Data_EntMonth!$A:$A,$A27,Data_EntMonth!$B:$B,S$4)) | H27: =IF($A27="","",SUMIFS(Data_EntMonth!$D:$D,Data_EntMonth!$A:$A,$A27,Data_EntMonth!$B:$B,H$4)) | I27: =IF($A27="","",SUMIFS(Data_EntMonth!$D:$D,Data_EntMonth!$A:$A,$A27,Data_EntMonth!$B:$B,I$4)) | J27: =IF($A27="","",SUMIFS(Data_EntMonth!$D:$D,Data_EntMonth!$A:$A,$A27,Data_EntMonth!$B:$B,J$4)) | K27: =IF($A27="","",SUMIFS(Data_EntMonth!$D:$D,Data_EntMonth!$A:$A,$A27,Data_EntMonth!$B:$B,K$4)) | L27: =IF($A27="","",SUMIFS(Data_EntMonth!$D:$D,Data_EntMonth!$A:$A,$A27,Data_EntMonth!$B:$B,L$4)) | M27: =IF($A27="","",SUMIFS(Data_EntMonth!$D:$D,Data_EntMonth!$A:$A,$A27,Data_EntMonth!$B:$B,M$4)) | N27: =IF($A27="","",SUMIFS(Data_EntMonth!$D:$D,Data_EntMonth!$A:$A,$A27,Data_EntMonth!$B:$B,N$4)) | O27: =IF($A27="","",SUMIFS(Data_EntMonth!$D:$D,Data_EntMonth!$A:$A,$A27,Data_EntMonth!$B:$B,O$4)) | ... S27: =IF($A27="","",SUMIFS(Data_EntMonth!$D:$D,Data_EntMonth!$A:$A,$A27,Data_EntMonth!$B:$B,S$4))
A28: =IF(INDEX(Data_Contracts!$A:$A,24+1)="","",INDEX(Data_Contracts!$A:$A,24+1)) | B28: =IF(INDEX(Data_Contracts!$C:$C,24+1)="","",INDEX(Data_Contracts!$C:$C,24+1)) | C28: =IF(INDEX(Data_Contracts!$D:$D,24+1)="","",INDEX(Data_Contracts!$D:$D,24+1)) | D28: =IF(INDEX(Data_Contracts!$E:$E,24+1)="","",INDEX(Data_Contracts!$E:$E,24+1)) | E28: =IF(INDEX(Data_Contracts!$F:$F,24+1)="","",INDEX(Data_Contracts!$F:$F,24+1)) | F28: =IF(OR($A28="",N($D28)=0),"",S28/$D28) | G28: =IF($A28="","",SUMIFS(Data_EntMonth!$F:$F,Data_EntMonth!$A:$A,$A28,Data_EntMonth!$B:$B,S$4)) | H28: =IF($A28="","",SUMIFS(Data_EntMonth!$D:$D,Data_EntMonth!$A:$A,$A28,Data_EntMonth!$B:$B,H$4)) | I28: =IF($A28="","",SUMIFS(Data_EntMonth!$D:$D,Data_EntMonth!$A:$A,$A28,Data_EntMonth!$B:$B,I$4)) | J28: =IF($A28="","",SUMIFS(Data_EntMonth!$D:$D,Data_EntMonth!$A:$A,$A28,Data_EntMonth!$B:$B,J$4)) | K28: =IF($A28="","",SUMIFS(Data_EntMonth!$D:$D,Data_EntMonth!$A:$A,$A28,Data_EntMonth!$B:$B,K$4)) | L28: =IF($A28="","",SUMIFS(Data_EntMonth!$D:$D,Data_EntMonth!$A:$A,$A28,Data_EntMonth!$B:$B,L$4)) | M28: =IF($A28="","",SUMIFS(Data_EntMonth!$D:$D,Data_EntMonth!$A:$A,$A28,Data_EntMonth!$B:$B,M$4)) | N28: =IF($A28="","",SUMIFS(Data_EntMonth!$D:$D,Data_EntMonth!$A:$A,$A28,Data_EntMonth!$B:$B,N$4)) | O28: =IF($A28="","",SUMIFS(Data_EntMonth!$D:$D,Data_EntMonth!$A:$A,$A28,Data_EntMonth!$B:$B,O$4)) | ... S28: =IF($A28="","",SUMIFS(Data_EntMonth!$D:$D,Data_EntMonth!$A:$A,$A28,Data_EntMonth!$B:$B,S$4))
A29: =IF(INDEX(Data_Contracts!$A:$A,25+1)="","",INDEX(Data_Contracts!$A:$A,25+1)) | B29: =IF(INDEX(Data_Contracts!$C:$C,25+1)="","",INDEX(Data_Contracts!$C:$C,25+1)) | C29: =IF(INDEX(Data_Contracts!$D:$D,25+1)="","",INDEX(Data_Contracts!$D:$D,25+1)) | D29: =IF(INDEX(Data_Contracts!$E:$E,25+1)="","",INDEX(Data_Contracts!$E:$E,25+1)) | E29: =IF(INDEX(Data_Contracts!$F:$F,25+1)="","",INDEX(Data_Contracts!$F:$F,25+1)) | F29: =IF(OR($A29="",N($D29)=0),"",S29/$D29) | G29: =IF($A29="","",SUMIFS(Data_EntMonth!$F:$F,Data_EntMonth!$A:$A,$A29,Data_EntMonth!$B:$B,S$4)) | H29: =IF($A29="","",SUMIFS(Data_EntMonth!$D:$D,Data_EntMonth!$A:$A,$A29,Data_EntMonth!$B:$B,H$4)) | I29: =IF($A29="","",SUMIFS(Data_EntMonth!$D:$D,Data_EntMonth!$A:$A,$A29,Data_EntMonth!$B:$B,I$4)) | J29: =IF($A29="","",SUMIFS(Data_EntMonth!$D:$D,Data_EntMonth!$A:$A,$A29,Data_EntMonth!$B:$B,J$4)) | K29: =IF($A29="","",SUMIFS(Data_EntMonth!$D:$D,Data_EntMonth!$A:$A,$A29,Data_EntMonth!$B:$B,K$4)) | L29: =IF($A29="","",SUMIFS(Data_EntMonth!$D:$D,Data_EntMonth!$A:$A,$A29,Data_EntMonth!$B:$B,L$4)) | M29: =IF($A29="","",SUMIFS(Data_EntMonth!$D:$D,Data_EntMonth!$A:$A,$A29,Data_EntMonth!$B:$B,M$4)) | N29: =IF($A29="","",SUMIFS(Data_EntMonth!$D:$D,Data_EntMonth!$A:$A,$A29,Data_EntMonth!$B:$B,N$4)) | O29: =IF($A29="","",SUMIFS(Data_EntMonth!$D:$D,Data_EntMonth!$A:$A,$A29,Data_EntMonth!$B:$B,O$4)) | ... S29: =IF($A29="","",SUMIFS(Data_EntMonth!$D:$D,Data_EntMonth!$A:$A,$A29,Data_EntMonth!$B:$B,S$4))
A30: =IF(INDEX(Data_Contracts!$A:$A,26+1)="","",INDEX(Data_Contracts!$A:$A,26+1)) | B30: =IF(INDEX(Data_Contracts!$C:$C,26+1)="","",INDEX(Data_Contracts!$C:$C,26+1)) | C30: =IF(INDEX(Data_Contracts!$D:$D,26+1)="","",INDEX(Data_Contracts!$D:$D,26+1)) | D30: =IF(INDEX(Data_Contracts!$E:$E,26+1)="","",INDEX(Data_Contracts!$E:$E,26+1)) | E30: =IF(INDEX(Data_Contracts!$F:$F,26+1)="","",INDEX(Data_Contracts!$F:$F,26+1)) | F30: =IF(OR($A30="",N($D30)=0),"",S30/$D30) | G30: =IF($A30="","",SUMIFS(Data_EntMonth!$F:$F,Data_EntMonth!$A:$A,$A30,Data_EntMonth!$B:$B,S$4)) | H30: =IF($A30="","",SUMIFS(Data_EntMonth!$D:$D,Data_EntMonth!$A:$A,$A30,Data_EntMonth!$B:$B,H$4)) | I30: =IF($A30="","",SUMIFS(Data_EntMonth!$D:$D,Data_EntMonth!$A:$A,$A30,Data_EntMonth!$B:$B,I$4)) | J30: =IF($A30="","",SUMIFS(Data_EntMonth!$D:$D,Data_EntMonth!$A:$A,$A30,Data_EntMonth!$B:$B,J$4)) | K30: =IF($A30="","",SUMIFS(Data_EntMonth!$D:$D,Data_EntMonth!$A:$A,$A30,Data_EntMonth!$B:$B,K$4)) | L30: =IF($A30="","",SUMIFS(Data_EntMonth!$D:$D,Data_EntMonth!$A:$A,$A30,Data_EntMonth!$B:$B,L$4)) | M30: =IF($A30="","",SUMIFS(Data_EntMonth!$D:$D,Data_EntMonth!$A:$A,$A30,Data_EntMonth!$B:$B,M$4)) | N30: =IF($A30="","",SUMIFS(Data_EntMonth!$D:$D,Data_EntMonth!$A:$A,$A30,Data_EntMonth!$B:$B,N$4)) | O30: =IF($A30="","",SUMIFS(Data_EntMonth!$D:$D,Data_EntMonth!$A:$A,$A30,Data_EntMonth!$B:$B,O$4)) | ... S30: =IF($A30="","",SUMIFS(Data_EntMonth!$D:$D,Data_EntMonth!$A:$A,$A30,Data_EntMonth!$B:$B,S$4))
A31: =IF(INDEX(Data_Contracts!$A:$A,27+1)="","",INDEX(Data_Contracts!$A:$A,27+1)) | B31: =IF(INDEX(Data_Contracts!$C:$C,27+1)="","",INDEX(Data_Contracts!$C:$C,27+1)) | C31: =IF(INDEX(Data_Contracts!$D:$D,27+1)="","",INDEX(Data_Contracts!$D:$D,27+1)) | D31: =IF(INDEX(Data_Contracts!$E:$E,27+1)="","",INDEX(Data_Contracts!$E:$E,27+1)) | E31: =IF(INDEX(Data_Contracts!$F:$F,27+1)="","",INDEX(Data_Contracts!$F:$F,27+1)) | F31: =IF(OR($A31="",N($D31)=0),"",S31/$D31) | G31: =IF($A31="","",SUMIFS(Data_EntMonth!$F:$F,Data_EntMonth!$A:$A,$A31,Data_EntMonth!$B:$B,S$4)) | H31: =IF($A31="","",SUMIFS(Data_EntMonth!$D:$D,Data_EntMonth!$A:$A,$A31,Data_EntMonth!$B:$B,H$4)) | I31: =IF($A31="","",SUMIFS(Data_EntMonth!$D:$D,Data_EntMonth!$A:$A,$A31,Data_EntMonth!$B:$B,I$4)) | J31: =IF($A31="","",SUMIFS(Data_EntMonth!$D:$D,Data_EntMonth!$A:$A,$A31,Data_EntMonth!$B:$B,J$4)) | K31: =IF($A31="","",SUMIFS(Data_EntMonth!$D:$D,Data_EntMonth!$A:$A,$A31,Data_EntMonth!$B:$B,K$4)) | L31: =IF($A31="","",SUMIFS(Data_EntMonth!$D:$D,Data_EntMonth!$A:$A,$A31,Data_EntMonth!$B:$B,L$4)) | M31: =IF($A31="","",SUMIFS(Data_EntMonth!$D:$D,Data_EntMonth!$A:$A,$A31,Data_EntMonth!$B:$B,M$4)) | N31: =IF($A31="","",SUMIFS(Data_EntMonth!$D:$D,Data_EntMonth!$A:$A,$A31,Data_EntMonth!$B:$B,N$4)) | O31: =IF($A31="","",SUMIFS(Data_EntMonth!$D:$D,Data_EntMonth!$A:$A,$A31,Data_EntMonth!$B:$B,O$4)) | ... S31: =IF($A31="","",SUMIFS(Data_EntMonth!$D:$D,Data_EntMonth!$A:$A,$A31,Data_EntMonth!$B:$B,S$4))
A32: =IF(INDEX(Data_Contracts!$A:$A,28+1)="","",INDEX(Data_Contracts!$A:$A,28+1)) | B32: =IF(INDEX(Data_Contracts!$C:$C,28+1)="","",INDEX(Data_Contracts!$C:$C,28+1)) | C32: =IF(INDEX(Data_Contracts!$D:$D,28+1)="","",INDEX(Data_Contracts!$D:$D,28+1)) | D32: =IF(INDEX(Data_Contracts!$E:$E,28+1)="","",INDEX(Data_Contracts!$E:$E,28+1)) | E32: =IF(INDEX(Data_Contracts!$F:$F,28+1)="","",INDEX(Data_Contracts!$F:$F,28+1)) | F32: =IF(OR($A32="",N($D32)=0),"",S32/$D32) | G32: =IF($A32="","",SUMIFS(Data_EntMonth!$F:$F,Data_EntMonth!$A:$A,$A32,Data_EntMonth!$B:$B,S$4)) | H32: =IF($A32="","",SUMIFS(Data_EntMonth!$D:$D,Data_EntMonth!$A:$A,$A32,Data_EntMonth!$B:$B,H$4)) | I32: =IF($A32="","",SUMIFS(Data_EntMonth!$D:$D,Data_EntMonth!$A:$A,$A32,Data_EntMonth!$B:$B,I$4)) | J32: =IF($A32="","",SUMIFS(Data_EntMonth!$D:$D,Data_EntMonth!$A:$A,$A32,Data_EntMonth!$B:$B,J$4)) | K32: =IF($A32="","",SUMIFS(Data_EntMonth!$D:$D,Data_EntMonth!$A:$A,$A32,Data_EntMonth!$B:$B,K$4)) | L32: =IF($A32="","",SUMIFS(Data_EntMonth!$D:$D,Data_EntMonth!$A:$A,$A32,Data_EntMonth!$B:$B,L$4)) | M32: =IF($A32="","",SUMIFS(Data_EntMonth!$D:$D,Data_EntMonth!$A:$A,$A32,Data_EntMonth!$B:$B,M$4)) | N32: =IF($A32="","",SUMIFS(Data_EntMonth!$D:$D,Data_EntMonth!$A:$A,$A32,Data_EntMonth!$B:$B,N$4)) | O32: =IF($A32="","",SUMIFS(Data_EntMonth!$D:$D,Data_EntMonth!$A:$A,$A32,Data_EntMonth!$B:$B,O$4)) | ... S32: =IF($A32="","",SUMIFS(Data_EntMonth!$D:$D,Data_EntMonth!$A:$A,$A32,Data_EntMonth!$B:$B,S$4))
A33: =IF(INDEX(Data_Contracts!$A:$A,29+1)="","",INDEX(Data_Contracts!$A:$A,29+1)) | B33: =IF(INDEX(Data_Contracts!$C:$C,29+1)="","",INDEX(Data_Contracts!$C:$C,29+1)) | C33: =IF(INDEX(Data_Contracts!$D:$D,29+1)="","",INDEX(Data_Contracts!$D:$D,29+1)) | D33: =IF(INDEX(Data_Contracts!$E:$E,29+1)="","",INDEX(Data_Contracts!$E:$E,29+1)) | E33: =IF(INDEX(Data_Contracts!$F:$F,29+1)="","",INDEX(Data_Contracts!$F:$F,29+1)) | F33: =IF(OR($A33="",N($D33)=0),"",S33/$D33) | G33: =IF($A33="","",SUMIFS(Data_EntMonth!$F:$F,Data_EntMonth!$A:$A,$A33,Data_EntMonth!$B:$B,S$4)) | H33: =IF($A33="","",SUMIFS(Data_EntMonth!$D:$D,Data_EntMonth!$A:$A,$A33,Data_EntMonth!$B:$B,H$4)) | I33: =IF($A33="","",SUMIFS(Data_EntMonth!$D:$D,Data_EntMonth!$A:$A,$A33,Data_EntMonth!$B:$B,I$4)) | J33: =IF($A33="","",SUMIFS(Data_EntMonth!$D:$D,Data_EntMonth!$A:$A,$A33,Data_EntMonth!$B:$B,J$4)) | K33: =IF($A33="","",SUMIFS(Data_EntMonth!$D:$D,Data_EntMonth!$A:$A,$A33,Data_EntMonth!$B:$B,K$4)) | L33: =IF($A33="","",SUMIFS(Data_EntMonth!$D:$D,Data_EntMonth!$A:$A,$A33,Data_EntMonth!$B:$B,L$4)) | M33: =IF($A33="","",SUMIFS(Data_EntMonth!$D:$D,Data_EntMonth!$A:$A,$A33,Data_EntMonth!$B:$B,M$4)) | N33: =IF($A33="","",SUMIFS(Data_EntMonth!$D:$D,Data_EntMonth!$A:$A,$A33,Data_EntMonth!$B:$B,N$4)) | O33: =IF($A33="","",SUMIFS(Data_EntMonth!$D:$D,Data_EntMonth!$A:$A,$A33,Data_EntMonth!$B:$B,O$4)) | ... S33: =IF($A33="","",SUMIFS(Data_EntMonth!$D:$D,Data_EntMonth!$A:$A,$A33,Data_EntMonth!$B:$B,S$4))
A34: =IF(INDEX(Data_Contracts!$A:$A,30+1)="","",INDEX(Data_Contracts!$A:$A,30+1)) | B34: =IF(INDEX(Data_Contracts!$C:$C,30+1)="","",INDEX(Data_Contracts!$C:$C,30+1)) | C34: =IF(INDEX(Data_Contracts!$D:$D,30+1)="","",INDEX(Data_Contracts!$D:$D,30+1)) | D34: =IF(INDEX(Data_Contracts!$E:$E,30+1)="","",INDEX(Data_Contracts!$E:$E,30+1)) | E34: =IF(INDEX(Data_Contracts!$F:$F,30+1)="","",INDEX(Data_Contracts!$F:$F,30+1)) | F34: =IF(OR($A34="",N($D34)=0),"",S34/$D34) | G34: =IF($A34="","",SUMIFS(Data_EntMonth!$F:$F,Data_EntMonth!$A:$A,$A34,Data_EntMonth!$B:$B,S$4)) | H34: =IF($A34="","",SUMIFS(Data_EntMonth!$D:$D,Data_EntMonth!$A:$A,$A34,Data_EntMonth!$B:$B,H$4)) | I34: =IF($A34="","",SUMIFS(Data_EntMonth!$D:$D,Data_EntMonth!$A:$A,$A34,Data_EntMonth!$B:$B,I$4)) | J34: =IF($A34="","",SUMIFS(Data_EntMonth!$D:$D,Data_EntMonth!$A:$A,$A34,Data_EntMonth!$B:$B,J$4)) | K34: =IF($A34="","",SUMIFS(Data_EntMonth!$D:$D,Data_EntMonth!$A:$A,$A34,Data_EntMonth!$B:$B,K$4)) | L34: =IF($A34="","",SUMIFS(Data_EntMonth!$D:$D,Data_EntMonth!$A:$A,$A34,Data_EntMonth!$B:$B,L$4)) | M34: =IF($A34="","",SUMIFS(Data_EntMonth!$D:$D,Data_EntMonth!$A:$A,$A34,Data_EntMonth!$B:$B,M$4)) | N34: =IF($A34="","",SUMIFS(Data_EntMonth!$D:$D,Data_EntMonth!$A:$A,$A34,Data_EntMonth!$B:$B,N$4)) | O34: =IF($A34="","",SUMIFS(Data_EntMonth!$D:$D,Data_EntMonth!$A:$A,$A34,Data_EntMonth!$B:$B,O$4)) | ... S34: =IF($A34="","",SUMIFS(Data_EntMonth!$D:$D,Data_EntMonth!$A:$A,$A34,Data_EntMonth!$B:$B,S$4))
A35: =IF(INDEX(Data_Contracts!$A:$A,31+1)="","",INDEX(Data_Contracts!$A:$A,31+1)) | B35: =IF(INDEX(Data_Contracts!$C:$C,31+1)="","",INDEX(Data_Contracts!$C:$C,31+1)) | C35: =IF(INDEX(Data_Contracts!$D:$D,31+1)="","",INDEX(Data_Contracts!$D:$D,31+1)) | D35: =IF(INDEX(Data_Contracts!$E:$E,31+1)="","",INDEX(Data_Contracts!$E:$E,31+1)) | E35: =IF(INDEX(Data_Contracts!$F:$F,31+1)="","",INDEX(Data_Contracts!$F:$F,31+1)) | F35: =IF(OR($A35="",N($D35)=0),"",S35/$D35) | G35: =IF($A35="","",SUMIFS(Data_EntMonth!$F:$F,Data_EntMonth!$A:$A,$A35,Data_EntMonth!$B:$B,S$4)) | H35: =IF($A35="","",SUMIFS(Data_EntMonth!$D:$D,Data_EntMonth!$A:$A,$A35,Data_EntMonth!$B:$B,H$4)) | I35: =IF($A35="","",SUMIFS(Data_EntMonth!$D:$D,Data_EntMonth!$A:$A,$A35,Data_EntMonth!$B:$B,I$4)) | J35: =IF($A35="","",SUMIFS(Data_EntMonth!$D:$D,Data_EntMonth!$A:$A,$A35,Data_EntMonth!$B:$B,J$4)) | K35: =IF($A35="","",SUMIFS(Data_EntMonth!$D:$D,Data_EntMonth!$A:$A,$A35,Data_EntMonth!$B:$B,K$4)) | L35: =IF($A35="","",SUMIFS(Data_EntMonth!$D:$D,Data_EntMonth!$A:$A,$A35,Data_EntMonth!$B:$B,L$4)) | M35: =IF($A35="","",SUMIFS(Data_EntMonth!$D:$D,Data_EntMonth!$A:$A,$A35,Data_EntMonth!$B:$B,M$4)) | N35: =IF($A35="","",SUMIFS(Data_EntMonth!$D:$D,Data_EntMonth!$A:$A,$A35,Data_EntMonth!$B:$B,N$4)) | O35: =IF($A35="","",SUMIFS(Data_EntMonth!$D:$D,Data_EntMonth!$A:$A,$A35,Data_EntMonth!$B:$B,O$4)) | ... S35: =IF($A35="","",SUMIFS(Data_EntMonth!$D:$D,Data_EntMonth!$A:$A,$A35,Data_EntMonth!$B:$B,S$4))
A36: =IF(INDEX(Data_Contracts!$A:$A,32+1)="","",INDEX(Data_Contracts!$A:$A,32+1)) | B36: =IF(INDEX(Data_Contracts!$C:$C,32+1)="","",INDEX(Data_Contracts!$C:$C,32+1)) | C36: =IF(INDEX(Data_Contracts!$D:$D,32+1)="","",INDEX(Data_Contracts!$D:$D,32+1)) | D36: =IF(INDEX(Data_Contracts!$E:$E,32+1)="","",INDEX(Data_Contracts!$E:$E,32+1)) | E36: =IF(INDEX(Data_Contracts!$F:$F,32+1)="","",INDEX(Data_Contracts!$F:$F,32+1)) | F36: =IF(OR($A36="",N($D36)=0),"",S36/$D36) | G36: =IF($A36="","",SUMIFS(Data_EntMonth!$F:$F,Data_EntMonth!$A:$A,$A36,Data_EntMonth!$B:$B,S$4)) | H36: =IF($A36="","",SUMIFS(Data_EntMonth!$D:$D,Data_EntMonth!$A:$A,$A36,Data_EntMonth!$B:$B,H$4)) | I36: =IF($A36="","",SUMIFS(Data_EntMonth!$D:$D,Data_EntMonth!$A:$A,$A36,Data_EntMonth!$B:$B,I$4)) | J36: =IF($A36="","",SUMIFS(Data_EntMonth!$D:$D,Data_EntMonth!$A:$A,$A36,Data_EntMonth!$B:$B,J$4)) | K36: =IF($A36="","",SUMIFS(Data_EntMonth!$D:$D,Data_EntMonth!$A:$A,$A36,Data_EntMonth!$B:$B,K$4)) | L36: =IF($A36="","",SUMIFS(Data_EntMonth!$D:$D,Data_EntMonth!$A:$A,$A36,Data_EntMonth!$B:$B,L$4)) | M36: =IF($A36="","",SUMIFS(Data_EntMonth!$D:$D,Data_EntMonth!$A:$A,$A36,Data_EntMonth!$B:$B,M$4)) | N36: =IF($A36="","",SUMIFS(Data_EntMonth!$D:$D,Data_EntMonth!$A:$A,$A36,Data_EntMonth!$B:$B,N$4)) | O36: =IF($A36="","",SUMIFS(Data_EntMonth!$D:$D,Data_EntMonth!$A:$A,$A36,Data_EntMonth!$B:$B,O$4)) | ... S36: =IF($A36="","",SUMIFS(Data_EntMonth!$D:$D,Data_EntMonth!$A:$A,$A36,Data_EntMonth!$B:$B,S$4))
A37: =IF(INDEX(Data_Contracts!$A:$A,33+1)="","",INDEX(Data_Contracts!$A:$A,33+1)) | B37: =IF(INDEX(Data_Contracts!$C:$C,33+1)="","",INDEX(Data_Contracts!$C:$C,33+1)) | C37: =IF(INDEX(Data_Contracts!$D:$D,33+1)="","",INDEX(Data_Contracts!$D:$D,33+1)) | D37: =IF(INDEX(Data_Contracts!$E:$E,33+1)="","",INDEX(Data_Contracts!$E:$E,33+1)) | E37: =IF(INDEX(Data_Contracts!$F:$F,33+1)="","",INDEX(Data_Contracts!$F:$F,33+1)) | F37: =IF(OR($A37="",N($D37)=0),"",S37/$D37) | G37: =IF($A37="","",SUMIFS(Data_EntMonth!$F:$F,Data_EntMonth!$A:$A,$A37,Data_EntMonth!$B:$B,S$4)) | H37: =IF($A37="","",SUMIFS(Data_EntMonth!$D:$D,Data_EntMonth!$A:$A,$A37,Data_EntMonth!$B:$B,H$4)) | I37: =IF($A37="","",SUMIFS(Data_EntMonth!$D:$D,Data_EntMonth!$A:$A,$A37,Data_EntMonth!$B:$B,I$4)) | J37: =IF($A37="","",SUMIFS(Data_EntMonth!$D:$D,Data_EntMonth!$A:$A,$A37,Data_EntMonth!$B:$B,J$4)) | K37: =IF($A37="","",SUMIFS(Data_EntMonth!$D:$D,Data_EntMonth!$A:$A,$A37,Data_EntMonth!$B:$B,K$4)) | L37: =IF($A37="","",SUMIFS(Data_EntMonth!$D:$D,Data_EntMonth!$A:$A,$A37,Data_EntMonth!$B:$B,L$4)) | M37: =IF($A37="","",SUMIFS(Data_EntMonth!$D:$D,Data_EntMonth!$A:$A,$A37,Data_EntMonth!$B:$B,M$4)) | N37: =IF($A37="","",SUMIFS(Data_EntMonth!$D:$D,Data_EntMonth!$A:$A,$A37,Data_EntMonth!$B:$B,N$4)) | O37: =IF($A37="","",SUMIFS(Data_EntMonth!$D:$D,Data_EntMonth!$A:$A,$A37,Data_EntMonth!$B:$B,O$4)) | ... S37: =IF($A37="","",SUMIFS(Data_EntMonth!$D:$D,Data_EntMonth!$A:$A,$A37,Data_EntMonth!$B:$B,S$4))
A38: =IF(INDEX(Data_Contracts!$A:$A,34+1)="","",INDEX(Data_Contracts!$A:$A,34+1)) | B38: =IF(INDEX(Data_Contracts!$C:$C,34+1)="","",INDEX(Data_Contracts!$C:$C,34+1)) | C38: =IF(INDEX(Data_Contracts!$D:$D,34+1)="","",INDEX(Data_Contracts!$D:$D,34+1)) | D38: =IF(INDEX(Data_Contracts!$E:$E,34+1)="","",INDEX(Data_Contracts!$E:$E,34+1)) | E38: =IF(INDEX(Data_Contracts!$F:$F,34+1)="","",INDEX(Data_Contracts!$F:$F,34+1)) | F38: =IF(OR($A38="",N($D38)=0),"",S38/$D38) | G38: =IF($A38="","",SUMIFS(Data_EntMonth!$F:$F,Data_EntMonth!$A:$A,$A38,Data_EntMonth!$B:$B,S$4)) | H38: =IF($A38="","",SUMIFS(Data_EntMonth!$D:$D,Data_EntMonth!$A:$A,$A38,Data_EntMonth!$B:$B,H$4)) | I38: =IF($A38="","",SUMIFS(Data_EntMonth!$D:$D,Data_EntMonth!$A:$A,$A38,Data_EntMonth!$B:$B,I$4)) | J38: =IF($A38="","",SUMIFS(Data_EntMonth!$D:$D,Data_EntMonth!$A:$A,$A38,Data_EntMonth!$B:$B,J$4)) | K38: =IF($A38="","",SUMIFS(Data_EntMonth!$D:$D,Data_EntMonth!$A:$A,$A38,Data_EntMonth!$B:$B,K$4)) | L38: =IF($A38="","",SUMIFS(Data_EntMonth!$D:$D,Data_EntMonth!$A:$A,$A38,Data_EntMonth!$B:$B,L$4)) | M38: =IF($A38="","",SUMIFS(Data_EntMonth!$D:$D,Data_EntMonth!$A:$A,$A38,Data_EntMonth!$B:$B,M$4)) | N38: =IF($A38="","",SUMIFS(Data_EntMonth!$D:$D,Data_EntMonth!$A:$A,$A38,Data_EntMonth!$B:$B,N$4)) | O38: =IF($A38="","",SUMIFS(Data_EntMonth!$D:$D,Data_EntMonth!$A:$A,$A38,Data_EntMonth!$B:$B,O$4)) | ... S38: =IF($A38="","",SUMIFS(Data_EntMonth!$D:$D,Data_EntMonth!$A:$A,$A38,Data_EntMonth!$B:$B,S$4))
A39: =IF(INDEX(Data_Contracts!$A:$A,35+1)="","",INDEX(Data_Contracts!$A:$A,35+1)) | B39: =IF(INDEX(Data_Contracts!$C:$C,35+1)="","",INDEX(Data_Contracts!$C:$C,35+1)) | C39: =IF(INDEX(Data_Contracts!$D:$D,35+1)="","",INDEX(Data_Contracts!$D:$D,35+1)) | D39: =IF(INDEX(Data_Contracts!$E:$E,35+1)="","",INDEX(Data_Contracts!$E:$E,35+1)) | E39: =IF(INDEX(Data_Contracts!$F:$F,35+1)="","",INDEX(Data_Contracts!$F:$F,35+1)) | F39: =IF(OR($A39="",N($D39)=0),"",S39/$D39) | G39: =IF($A39="","",SUMIFS(Data_EntMonth!$F:$F,Data_EntMonth!$A:$A,$A39,Data_EntMonth!$B:$B,S$4)) | H39: =IF($A39="","",SUMIFS(Data_EntMonth!$D:$D,Data_EntMonth!$A:$A,$A39,Data_EntMonth!$B:$B,H$4)) | I39: =IF($A39="","",SUMIFS(Data_EntMonth!$D:$D,Data_EntMonth!$A:$A,$A39,Data_EntMonth!$B:$B,I$4)) | J39: =IF($A39="","",SUMIFS(Data_EntMonth!$D:$D,Data_EntMonth!$A:$A,$A39,Data_EntMonth!$B:$B,J$4)) | K39: =IF($A39="","",SUMIFS(Data_EntMonth!$D:$D,Data_EntMonth!$A:$A,$A39,Data_EntMonth!$B:$B,K$4)) | L39: =IF($A39="","",SUMIFS(Data_EntMonth!$D:$D,Data_EntMonth!$A:$A,$A39,Data_EntMonth!$B:$B,L$4)) | M39: =IF($A39="","",SUMIFS(Data_EntMonth!$D:$D,Data_EntMonth!$A:$A,$A39,Data_EntMonth!$B:$B,M$4)) | N39: =IF($A39="","",SUMIFS(Data_EntMonth!$D:$D,Data_EntMonth!$A:$A,$A39,Data_EntMonth!$B:$B,N$4)) | O39: =IF($A39="","",SUMIFS(Data_EntMonth!$D:$D,Data_EntMonth!$A:$A,$A39,Data_EntMonth!$B:$B,O$4)) | ... S39: =IF($A39="","",SUMIFS(Data_EntMonth!$D:$D,Data_EntMonth!$A:$A,$A39,Data_EntMonth!$B:$B,S$4))
A40: =IF(INDEX(Data_Contracts!$A:$A,36+1)="","",INDEX(Data_Contracts!$A:$A,36+1)) | B40: =IF(INDEX(Data_Contracts!$C:$C,36+1)="","",INDEX(Data_Contracts!$C:$C,36+1)) | C40: =IF(INDEX(Data_Contracts!$D:$D,36+1)="","",INDEX(Data_Contracts!$D:$D,36+1)) | D40: =IF(INDEX(Data_Contracts!$E:$E,36+1)="","",INDEX(Data_Contracts!$E:$E,36+1)) | E40: =IF(INDEX(Data_Contracts!$F:$F,36+1)="","",INDEX(Data_Contracts!$F:$F,36+1)) | F40: =IF(OR($A40="",N($D40)=0),"",S40/$D40) | G40: =IF($A40="","",SUMIFS(Data_EntMonth!$F:$F,Data_EntMonth!$A:$A,$A40,Data_EntMonth!$B:$B,S$4)) | H40: =IF($A40="","",SUMIFS(Data_EntMonth!$D:$D,Data_EntMonth!$A:$A,$A40,Data_EntMonth!$B:$B,H$4)) | I40: =IF($A40="","",SUMIFS(Data_EntMonth!$D:$D,Data_EntMonth!$A:$A,$A40,Data_EntMonth!$B:$B,I$4)) | J40: =IF($A40="","",SUMIFS(Data_EntMonth!$D:$D,Data_EntMonth!$A:$A,$A40,Data_EntMonth!$B:$B,J$4)) | K40: =IF($A40="","",SUMIFS(Data_EntMonth!$D:$D,Data_EntMonth!$A:$A,$A40,Data_EntMonth!$B:$B,K$4)) | L40: =IF($A40="","",SUMIFS(Data_EntMonth!$D:$D,Data_EntMonth!$A:$A,$A40,Data_EntMonth!$B:$B,L$4)) | M40: =IF($A40="","",SUMIFS(Data_EntMonth!$D:$D,Data_EntMonth!$A:$A,$A40,Data_EntMonth!$B:$B,M$4)) | N40: =IF($A40="","",SUMIFS(Data_EntMonth!$D:$D,Data_EntMonth!$A:$A,$A40,Data_EntMonth!$B:$B,N$4)) | O40: =IF($A40="","",SUMIFS(Data_EntMonth!$D:$D,Data_EntMonth!$A:$A,$A40,Data_EntMonth!$B:$B,O$4)) | ... S40: =IF($A40="","",SUMIFS(Data_EntMonth!$D:$D,Data_EntMonth!$A:$A,$A40,Data_EntMonth!$B:$B,S$4))
A41: =IF(INDEX(Data_Contracts!$A:$A,37+1)="","",INDEX(Data_Contracts!$A:$A,37+1)) | B41: =IF(INDEX(Data_Contracts!$C:$C,37+1)="","",INDEX(Data_Contracts!$C:$C,37+1)) | C41: =IF(INDEX(Data_Contracts!$D:$D,37+1)="","",INDEX(Data_Contracts!$D:$D,37+1)) | D41: =IF(INDEX(Data_Contracts!$E:$E,37+1)="","",INDEX(Data_Contracts!$E:$E,37+1)) | E41: =IF(INDEX(Data_Contracts!$F:$F,37+1)="","",INDEX(Data_Contracts!$F:$F,37+1)) | F41: =IF(OR($A41="",N($D41)=0),"",S41/$D41) | G41: =IF($A41="","",SUMIFS(Data_EntMonth!$F:$F,Data_EntMonth!$A:$A,$A41,Data_EntMonth!$B:$B,S$4)) | H41: =IF($A41="","",SUMIFS(Data_EntMonth!$D:$D,Data_EntMonth!$A:$A,$A41,Data_EntMonth!$B:$B,H$4)) | I41: =IF($A41="","",SUMIFS(Data_EntMonth!$D:$D,Data_EntMonth!$A:$A,$A41,Data_EntMonth!$B:$B,I$4)) | J41: =IF($A41="","",SUMIFS(Data_EntMonth!$D:$D,Data_EntMonth!$A:$A,$A41,Data_EntMonth!$B:$B,J$4)) | K41: =IF($A41="","",SUMIFS(Data_EntMonth!$D:$D,Data_EntMonth!$A:$A,$A41,Data_EntMonth!$B:$B,K$4)) | L41: =IF($A41="","",SUMIFS(Data_EntMonth!$D:$D,Data_EntMonth!$A:$A,$A41,Data_EntMonth!$B:$B,L$4)) | M41: =IF($A41="","",SUMIFS(Data_EntMonth!$D:$D,Data_EntMonth!$A:$A,$A41,Data_EntMonth!$B:$B,M$4)) | N41: =IF($A41="","",SUMIFS(Data_EntMonth!$D:$D,Data_EntMonth!$A:$A,$A41,Data_EntMonth!$B:$B,N$4)) | O41: =IF($A41="","",SUMIFS(Data_EntMonth!$D:$D,Data_EntMonth!$A:$A,$A41,Data_EntMonth!$B:$B,O$4)) | ... S41: =IF($A41="","",SUMIFS(Data_EntMonth!$D:$D,Data_EntMonth!$A:$A,$A41,Data_EntMonth!$B:$B,S$4))
A42: =IF(INDEX(Data_Contracts!$A:$A,38+1)="","",INDEX(Data_Contracts!$A:$A,38+1)) | B42: =IF(INDEX(Data_Contracts!$C:$C,38+1)="","",INDEX(Data_Contracts!$C:$C,38+1)) | C42: =IF(INDEX(Data_Contracts!$D:$D,38+1)="","",INDEX(Data_Contracts!$D:$D,38+1)) | D42: =IF(INDEX(Data_Contracts!$E:$E,38+1)="","",INDEX(Data_Contracts!$E:$E,38+1)) | E42: =IF(INDEX(Data_Contracts!$F:$F,38+1)="","",INDEX(Data_Contracts!$F:$F,38+1)) | F42: =IF(OR($A42="",N($D42)=0),"",S42/$D42) | G42: =IF($A42="","",SUMIFS(Data_EntMonth!$F:$F,Data_EntMonth!$A:$A,$A42,Data_EntMonth!$B:$B,S$4)) | H42: =IF($A42="","",SUMIFS(Data_EntMonth!$D:$D,Data_EntMonth!$A:$A,$A42,Data_EntMonth!$B:$B,H$4)) | I42: =IF($A42="","",SUMIFS(Data_EntMonth!$D:$D,Data_EntMonth!$A:$A,$A42,Data_EntMonth!$B:$B,I$4)) | J42: =IF($A42="","",SUMIFS(Data_EntMonth!$D:$D,Data_EntMonth!$A:$A,$A42,Data_EntMonth!$B:$B,J$4)) | K42: =IF($A42="","",SUMIFS(Data_EntMonth!$D:$D,Data_EntMonth!$A:$A,$A42,Data_EntMonth!$B:$B,K$4)) | L42: =IF($A42="","",SUMIFS(Data_EntMonth!$D:$D,Data_EntMonth!$A:$A,$A42,Data_EntMonth!$B:$B,L$4)) | M42: =IF($A42="","",SUMIFS(Data_EntMonth!$D:$D,Data_EntMonth!$A:$A,$A42,Data_EntMonth!$B:$B,M$4)) | N42: =IF($A42="","",SUMIFS(Data_EntMonth!$D:$D,Data_EntMonth!$A:$A,$A42,Data_EntMonth!$B:$B,N$4)) | O42: =IF($A42="","",SUMIFS(Data_EntMonth!$D:$D,Data_EntMonth!$A:$A,$A42,Data_EntMonth!$B:$B,O$4)) | ... S42: =IF($A42="","",SUMIFS(Data_EntMonth!$D:$D,Data_EntMonth!$A:$A,$A42,Data_EntMonth!$B:$B,S$4))
A43: =IF(INDEX(Data_Contracts!$A:$A,39+1)="","",INDEX(Data_Contracts!$A:$A,39+1)) | B43: =IF(INDEX(Data_Contracts!$C:$C,39+1)="","",INDEX(Data_Contracts!$C:$C,39+1)) | C43: =IF(INDEX(Data_Contracts!$D:$D,39+1)="","",INDEX(Data_Contracts!$D:$D,39+1)) | D43: =IF(INDEX(Data_Contracts!$E:$E,39+1)="","",INDEX(Data_Contracts!$E:$E,39+1)) | E43: =IF(INDEX(Data_Contracts!$F:$F,39+1)="","",INDEX(Data_Contracts!$F:$F,39+1)) | F43: =IF(OR($A43="",N($D43)=0),"",S43/$D43) | G43: =IF($A43="","",SUMIFS(Data_EntMonth!$F:$F,Data_EntMonth!$A:$A,$A43,Data_EntMonth!$B:$B,S$4)) | H43: =IF($A43="","",SUMIFS(Data_EntMonth!$D:$D,Data_EntMonth!$A:$A,$A43,Data_EntMonth!$B:$B,H$4)) | I43: =IF($A43="","",SUMIFS(Data_EntMonth!$D:$D,Data_EntMonth!$A:$A,$A43,Data_EntMonth!$B:$B,I$4)) | J43: =IF($A43="","",SUMIFS(Data_EntMonth!$D:$D,Data_EntMonth!$A:$A,$A43,Data_EntMonth!$B:$B,J$4)) | K43: =IF($A43="","",SUMIFS(Data_EntMonth!$D:$D,Data_EntMonth!$A:$A,$A43,Data_EntMonth!$B:$B,K$4)) | L43: =IF($A43="","",SUMIFS(Data_EntMonth!$D:$D,Data_EntMonth!$A:$A,$A43,Data_EntMonth!$B:$B,L$4)) | M43: =IF($A43="","",SUMIFS(Data_EntMonth!$D:$D,Data_EntMonth!$A:$A,$A43,Data_EntMonth!$B:$B,M$4)) | N43: =IF($A43="","",SUMIFS(Data_EntMonth!$D:$D,Data_EntMonth!$A:$A,$A43,Data_EntMonth!$B:$B,N$4)) | O43: =IF($A43="","",SUMIFS(Data_EntMonth!$D:$D,Data_EntMonth!$A:$A,$A43,Data_EntMonth!$B:$B,O$4)) | ... S43: =IF($A43="","",SUMIFS(Data_EntMonth!$D:$D,Data_EntMonth!$A:$A,$A43,Data_EntMonth!$B:$B,S$4))
A44: =IF(INDEX(Data_Contracts!$A:$A,40+1)="","",INDEX(Data_Contracts!$A:$A,40+1)) | B44: =IF(INDEX(Data_Contracts!$C:$C,40+1)="","",INDEX(Data_Contracts!$C:$C,40+1)) | C44: =IF(INDEX(Data_Contracts!$D:$D,40+1)="","",INDEX(Data_Contracts!$D:$D,40+1)) | D44: =IF(INDEX(Data_Contracts!$E:$E,40+1)="","",INDEX(Data_Contracts!$E:$E,40+1)) | E44: =IF(INDEX(Data_Contracts!$F:$F,40+1)="","",INDEX(Data_Contracts!$F:$F,40+1)) | F44: =IF(OR($A44="",N($D44)=0),"",S44/$D44) | G44: =IF($A44="","",SUMIFS(Data_EntMonth!$F:$F,Data_EntMonth!$A:$A,$A44,Data_EntMonth!$B:$B,S$4)) | H44: =IF($A44="","",SUMIFS(Data_EntMonth!$D:$D,Data_EntMonth!$A:$A,$A44,Data_EntMonth!$B:$B,H$4)) | I44: =IF($A44="","",SUMIFS(Data_EntMonth!$D:$D,Data_EntMonth!$A:$A,$A44,Data_EntMonth!$B:$B,I$4)) | J44: =IF($A44="","",SUMIFS(Data_EntMonth!$D:$D,Data_EntMonth!$A:$A,$A44,Data_EntMonth!$B:$B,J$4)) | K44: =IF($A44="","",SUMIFS(Data_EntMonth!$D:$D,Data_EntMonth!$A:$A,$A44,Data_EntMonth!$B:$B,K$4)) | L44: =IF($A44="","",SUMIFS(Data_EntMonth!$D:$D,Data_EntMonth!$A:$A,$A44,Data_EntMonth!$B:$B,L$4)) | M44: =IF($A44="","",SUMIFS(Data_EntMonth!$D:$D,Data_EntMonth!$A:$A,$A44,Data_EntMonth!$B:$B,M$4)) | N44: =IF($A44="","",SUMIFS(Data_EntMonth!$D:$D,Data_EntMonth!$A:$A,$A44,Data_EntMonth!$B:$B,N$4)) | O44: =IF($A44="","",SUMIFS(Data_EntMonth!$D:$D,Data_EntMonth!$A:$A,$A44,Data_EntMonth!$B:$B,O$4)) | ... S44: =IF($A44="","",SUMIFS(Data_EntMonth!$D:$D,Data_EntMonth!$A:$A,$A44,Data_EntMonth!$B:$B,S$4))
A45: Total | D45: =SUM(D5:D44) | G45: =SUM(G5:G44) | H45: =SUM(H5:H44) | I45: =SUM(I5:I44) | J45: =SUM(J5:J44) | K45: =SUM(K5:K44) | L45: =SUM(L5:L44) | M45: =SUM(M5:M44) | N45: =SUM(N5:N44) | ... S45: =SUM(S5:S44)
A48: Open pipeline (CRM)
A49: Deal | B49: Customer | C49: Stage | D49: Probability | E49: Expected monthly commit ($) | F49: Expected start | G49: Weighted commit ($) | H49: Use cases
A50: =IF(INDEX(Data_Pipeline!$A:$A,1+1)="","",INDEX(Data_Pipeline!$A:$A,1+1)) | B50: =IF(INDEX(Data_Pipeline!$B:$B,1+1)="","",INDEX(Data_Pipeline!$B:$B,1+1)) | C50: =IF(INDEX(Data_Pipeline!$C:$C,1+1)="","",INDEX(Data_Pipeline!$C:$C,1+1)) | D50: =IF(INDEX(Data_Pipeline!$D:$D,1+1)="","",INDEX(Data_Pipeline!$D:$D,1+1)) | E50: =IF(INDEX(Data_Pipeline!$E:$E,1+1)="","",INDEX(Data_Pipeline!$E:$E,1+1)) | F50: =IF(INDEX(Data_Pipeline!$F:$F,1+1)="","",INDEX(Data_Pipeline!$F:$F,1+1)) | G50: =IF($A50="","",D50*E50) | H50: =IF(INDEX(Data_Pipeline!$H:$H,1+1)="","",INDEX(Data_Pipeline!$H:$H,1+1))
A51: =IF(INDEX(Data_Pipeline!$A:$A,2+1)="","",INDEX(Data_Pipeline!$A:$A,2+1)) | B51: =IF(INDEX(Data_Pipeline!$B:$B,2+1)="","",INDEX(Data_Pipeline!$B:$B,2+1)) | C51: =IF(INDEX(Data_Pipeline!$C:$C,2+1)="","",INDEX(Data_Pipeline!$C:$C,2+1)) | D51: =IF(INDEX(Data_Pipeline!$D:$D,2+1)="","",INDEX(Data_Pipeline!$D:$D,2+1)) | E51: =IF(INDEX(Data_Pipeline!$E:$E,2+1)="","",INDEX(Data_Pipeline!$E:$E,2+1)) | F51: =IF(INDEX(Data_Pipeline!$F:$F,2+1)="","",INDEX(Data_Pipeline!$F:$F,2+1)) | G51: =IF($A51="","",D51*E51) | H51: =IF(INDEX(Data_Pipeline!$H:$H,2+1)="","",INDEX(Data_Pipeline!$H:$H,2+1))
A52: =IF(INDEX(Data_Pipeline!$A:$A,3+1)="","",INDEX(Data_Pipeline!$A:$A,3+1)) | B52: =IF(INDEX(Data_Pipeline!$B:$B,3+1)="","",INDEX(Data_Pipeline!$B:$B,3+1)) | C52: =IF(INDEX(Data_Pipeline!$C:$C,3+1)="","",INDEX(Data_Pipeline!$C:$C,3+1)) | D52: =IF(INDEX(Data_Pipeline!$D:$D,3+1)="","",INDEX(Data_Pipeline!$D:$D,3+1)) | E52: =IF(INDEX(Data_Pipeline!$E:$E,3+1)="","",INDEX(Data_Pipeline!$E:$E,3+1)) | F52: =IF(INDEX(Data_Pipeline!$F:$F,3+1)="","",INDEX(Data_Pipeline!$F:$F,3+1)) | G52: =IF($A52="","",D52*E52) | H52: =IF(INDEX(Data_Pipeline!$H:$H,3+1)="","",INDEX(Data_Pipeline!$H:$H,3+1))
A53: =IF(INDEX(Data_Pipeline!$A:$A,4+1)="","",INDEX(Data_Pipeline!$A:$A,4+1)) | B53: =IF(INDEX(Data_Pipeline!$B:$B,4+1)="","",INDEX(Data_Pipeline!$B:$B,4+1)) | C53: =IF(INDEX(Data_Pipeline!$C:$C,4+1)="","",INDEX(Data_Pipeline!$C:$C,4+1)) | D53: =IF(INDEX(Data_Pipeline!$D:$D,4+1)="","",INDEX(Data_Pipeline!$D:$D,4+1)) | E53: =IF(INDEX(Data_Pipeline!$E:$E,4+1)="","",INDEX(Data_Pipeline!$E:$E,4+1)) | F53: =IF(INDEX(Data_Pipeline!$F:$F,4+1)="","",INDEX(Data_Pipeline!$F:$F,4+1)) | G53: =IF($A53="","",D53*E53) | H53: =IF(INDEX(Data_Pipeline!$H:$H,4+1)="","",INDEX(Data_Pipeline!$H:$H,4+1))
A54: =IF(INDEX(Data_Pipeline!$A:$A,5+1)="","",INDEX(Data_Pipeline!$A:$A,5+1)) | B54: =IF(INDEX(Data_Pipeline!$B:$B,5+1)="","",INDEX(Data_Pipeline!$B:$B,5+1)) | C54: =IF(INDEX(Data_Pipeline!$C:$C,5+1)="","",INDEX(Data_Pipeline!$C:$C,5+1)) | D54: =IF(INDEX(Data_Pipeline!$D:$D,5+1)="","",INDEX(Data_Pipeline!$D:$D,5+1)) | E54: =IF(INDEX(Data_Pipeline!$E:$E,5+1)="","",INDEX(Data_Pipeline!$E:$E,5+1)) | F54: =IF(INDEX(Data_Pipeline!$F:$F,5+1)="","",INDEX(Data_Pipeline!$F:$F,5+1)) | G54: =IF($A54="","",D54*E54) | H54: =IF(INDEX(Data_Pipeline!$H:$H,5+1)="","",INDEX(Data_Pipeline!$H:$H,5+1))
A55: =IF(INDEX(Data_Pipeline!$A:$A,6+1)="","",INDEX(Data_Pipeline!$A:$A,6+1)) | B55: =IF(INDEX(Data_Pipeline!$B:$B,6+1)="","",INDEX(Data_Pipeline!$B:$B,6+1)) | C55: =IF(INDEX(Data_Pipeline!$C:$C,6+1)="","",INDEX(Data_Pipeline!$C:$C,6+1)) | D55: =IF(INDEX(Data_Pipeline!$D:$D,6+1)="","",INDEX(Data_Pipeline!$D:$D,6+1)) | E55: =IF(INDEX(Data_Pipeline!$E:$E,6+1)="","",INDEX(Data_Pipeline!$E:$E,6+1)) | F55: =IF(INDEX(Data_Pipeline!$F:$F,6+1)="","",INDEX(Data_Pipeline!$F:$F,6+1)) | G55: =IF($A55="","",D55*E55) | H55: =IF(INDEX(Data_Pipeline!$H:$H,6+1)="","",INDEX(Data_Pipeline!$H:$H,6+1))
A56: =IF(INDEX(Data_Pipeline!$A:$A,7+1)="","",INDEX(Data_Pipeline!$A:$A,7+1)) | B56: =IF(INDEX(Data_Pipeline!$B:$B,7+1)="","",INDEX(Data_Pipeline!$B:$B,7+1)) | C56: =IF(INDEX(Data_Pipeline!$C:$C,7+1)="","",INDEX(Data_Pipeline!$C:$C,7+1)) | D56: =IF(INDEX(Data_Pipeline!$D:$D,7+1)="","",INDEX(Data_Pipeline!$D:$D,7+1)) | E56: =IF(INDEX(Data_Pipeline!$E:$E,7+1)="","",INDEX(Data_Pipeline!$E:$E,7+1)) | F56: =IF(INDEX(Data_Pipeline!$F:$F,7+1)="","",INDEX(Data_Pipeline!$F:$F,7+1)) | G56: =IF($A56="","",D56*E56) | H56: =IF(INDEX(Data_Pipeline!$H:$H,7+1)="","",INDEX(Data_Pipeline!$H:$H,7+1))
A57: =IF(INDEX(Data_Pipeline!$A:$A,8+1)="","",INDEX(Data_Pipeline!$A:$A,8+1)) | B57: =IF(INDEX(Data_Pipeline!$B:$B,8+1)="","",INDEX(Data_Pipeline!$B:$B,8+1)) | C57: =IF(INDEX(Data_Pipeline!$C:$C,8+1)="","",INDEX(Data_Pipeline!$C:$C,8+1)) | D57: =IF(INDEX(Data_Pipeline!$D:$D,8+1)="","",INDEX(Data_Pipeline!$D:$D,8+1)) | E57: =IF(INDEX(Data_Pipeline!$E:$E,8+1)="","",INDEX(Data_Pipeline!$E:$E,8+1)) | F57: =IF(INDEX(Data_Pipeline!$F:$F,8+1)="","",INDEX(Data_Pipeline!$F:$F,8+1)) | G57: =IF($A57="","",D57*E57) | H57: =IF(INDEX(Data_Pipeline!$H:$H,8+1)="","",INDEX(Data_Pipeline!$H:$H,8+1))
