Workbook

Sheet Start
A1: Monthly close workbook
A3: How this workbook works
A4: 1. Numbers enter only through the grey Data_ tabs. The runner fills them from your sources; you can also paste query results by hand.
A5: 2. Every other tab is formulas reading the Data_ tabs for a 12-month window ending at the as-of month.
A6: 3. Judgment inputs (forecast and capacity) live on the Overrides tab, seeded from config.yaml. Type an override in a yellow cell to test a scenario.
A7: Bad entries are ignored, not fatal: a word, an error or an out-of-range number falls back to the model value. Set the switch on Overrides to OFF to undo every override at once.
A8: 4. Grey-shaded cells on Checks and Summary are for people and the agent: owners, explanations, commentary.
A10: This close
A11: As-of month | B11: =Data_Params!$B$2 -> 46419
A12: Generated | B12: =Data_Params!$B$13 -> 2026-10-08 12:54
A13: Usage grain | B13: =Data_Params!$B$9 -> daily
A14: Sources connected | B14: =Data_Params!$B$12 -> usage, accounts, contracts, pipeline, billing_ledger, gateway_statements, hourly, label_map
A15: Usage data from | B15: =Data_Params!$B$10 -> 46280
A16: Usage data to | B16: =Data_Params!$B$11 -> 46446
A17: Checks flagged | B17: =COUNTIF(Checks!$G$5:$G$154,"FLAG") -> 3
A18: Overrides | B18: =Overrides!$C$5 -> 0 input(s) and 0 adjustment(s) applied
A20: Color key: blue = input, black = formula, green = link to another tab, yellow = key assumption, grey tab = data.

Sheet Summary
A1: =Data_Params!$B$14&" | Monthly close" -> Example Co (synthetic data) | Monthly close
A2: Formulas only. Start here, then Checks. Every figure traces to a Data_ sheet and from there to a query in /sql.
A3: As-of month | B3: =Data_Params!$B$2 -> 46419 | C3: Sources | D3: =Data_Params!$B$12 -> usage, accounts, contracts, pipeline, billing_ledger, gateway_statements, hourly, label_map | F3: Overrides | G3: =Overrides!$C$5 -> 0 input(s) and 0 adjustment(s) applied
A5: Metric | B5: =Monthly!H4 -> 46266 | C5: =Monthly!I4 -> 46296 | D5: =Monthly!J4 -> 46327 | E5: =Monthly!K4 -> 46357 | F5: =Monthly!L4 -> 46388 | G5: =Monthly!M4 -> 46419
A6: Billable tokens per day (B) | B6: =Monthly!H12 -> 0.45434755 | C6: =Monthly!I12 -> 20.888752 | D6: =Monthly!J12 -> 72.944573 | E6: =Monthly!K12 -> 138.41306 | F6: =Monthly!L12 -> 182.18111 | G6: =Monthly!M12 -> 215.7228
A7: Growth in tokens per day | B7: =Monthly!H16 -> 0 | C7: =Monthly!I16 -> 44.97527 | D7: =Monthly!J16 -> 2.4920504 | E7: =Monthly!K16 -> 0.89751007 | F7: =Monthly!L16 -> 0.31621324 | G7: =Monthly!M16 -> 0.18411182
A8: Net revenue ($k) | B8: =Monthly!H34 -> 0.17380235 | C8: =Monthly!I34 -> 54.248666 | D8: =Monthly!J34 -> 114.92348 | E8: =Monthly!K34 -> 191.62524 | F8: =Monthly!L34 -> 233.34663 | G8: =Monthly!M34 -> 247.70515
A9: Annualized run-rate ($k) | B9: =Monthly!H36 -> 3.9648661 | C9: =Monthly!I36 -> 638.7343 | D9: =Monthly!J36 -> 1398.2357 | E9: =Monthly!K36 -> 2256.2327 | F9: =Monthly!L36 -> 2747.4684 | G9: =Monthly!M36 -> 3229.0135
A10: Enterprise share of revenue | B10: =Monthly!H37 -> 0 | C10: =Monthly!I37 -> 0.95735964 | D10: =Monthly!J37 -> 0.89552797 | E10: =Monthly!K37 -> 0.83387344 | F10: =Monthly!L37 -> 0.79468712 | G10: =Monthly!M37 -> 0.76750761
A11: Realized net price per M tokens | B11: =Monthly!H38 -> 0.023908232 | C11: =Monthly!I38 -> 0.083775087 | D11: =Monthly!J38 -> 0.052516349 | E11: =Monthly!K38 -> 0.04465951 | F11: =Monthly!L38 -> 0.041317734 | G11: =Monthly!M38 -> 0.041009167
A12: Active accounts | B12: =Monthly!H44 -> 205 | C12: =Monthly!I44 -> 386 | D12: =Monthly!J44 -> 448 | E12: =Monthly!K44 -> 496 | F12: =Monthly!L44 -> 576 | G12: =Monthly!M44 -> 680
A13: Paying accounts | B13: =Monthly!H45 -> 99 | C13: =Monthly!I45 -> 209 | D13: =Monthly!J45 -> 249 | E13: =Monthly!K45 -> 313 | F13: =Monthly!L45 -> 384 | G13: =Monthly!M45 -> 421
A14: Failed calls (not billed) | B14: =Monthly!H46 -> 0.0037498935 | C14: =Monthly!I46 -> 0.0058980202 | D14: =Monthly!J46 -> 0.0059310038 | E14: =Monthly!K46 -> 0.025171377 | F14: =Monthly!L46 -> 0.005939912 | G14: =Monthly!M46 -> 0.0059398741
A16: Close checks
A17: Flagged for review | B17: =COUNTIF(Checks!$G$5:$G$154,"FLAG") -> 3
A18: Informational | B18: =COUNTIF(Checks!$G$5:$G$154,"INFO") -> 8
A19: Skipped (source not connected) | B19: =COUNTIF(Checks!$G$5:$G$154,"SKIP") -> 1
A20: Passed | B20: =COUNTIF(Checks!$G$5:$G$154,"PASS") -> 51
A21: $ impact of flagged items | B21: =SUMIF(Checks!$G$5:$G$154,"FLAG",Checks!$F$5:$F$154) -> 3888.7147
A23: Forecast, tokens per day (B)
A24: Scenario | B24: =EDATE(Data_Params!$B$2,1) -> 46447 | C24: =EDATE(Data_Params!$B$2,2) -> 46478 | D24: =EDATE(Data_Params!$B$2,3) -> 46508
A25: Low | B25: =Forecast!B127 -> 226.97779 | C25: =Forecast!C127 -> 228.44125 | D25: =Forecast!D127 -> 228.44782
A26: Base | B26: =Forecast!E127 -> 248.56438 | C26: =Forecast!F127 -> 279.40283 | D26: =Forecast!G127 -> 317.13097
A27: High | B27: =Forecast!H127 -> 266.41364 | C27: =Forecast!I127 -> 323.31682 | D27: =Forecast!J127 -> 398.03836
A28: Net revenue, base ($k) | B28: =Forecast!E135 -> 294.7772 | C28: =Forecast!F135 -> 320.99496 | D28: =Forecast!G135 -> 374.31608
A29: Last month's forecast vs actual (total) | B29: =IF(Forecast!E143="","no forecast on file",Forecast!E143) -> -0.041539484
A30: GPUs to reserve for serving | B30: =Capacity!B27 -> 67
A32: Commentary (written by finance, or drafted by the agent per AGENT_BRIEF.md and reviewed before it goes anywhere)

Sheet Checks
A1: =Data_Params!$B$14&" | Close checks" -> Example Co (synthetic data) | Close checks
A2: Rules in sql/50_checks.sql (Data_Checks). FLAG = a person must look. Columns I-L are for people and the agent; they are not overwritten by formulas.
A4: # | B4: Check | C4: Scope | D4: Expected | E4: Actual | F4: $ impact | G4: Status | H4: Detail | I4: Owner | J4: Next step | K4: Explanation (agent draft) | L4: Reviewed by
A5: =IF(INDEX(Data_Checks!$A:$A,1+1)="","",INDEX(Data_Checks!$A:$A,1+1)) -> 4 | B5: =IF(INDEX(Data_Checks!$B:$B,1+1)="","",INDEX(Data_Checks!$B:$B,1+1)) -> Billed tokens tie to billable usage | C5: =IF(INDEX(Data_Checks!$C:$C,1+1)="","",INDEX(Data_Checks!$C:$C,1+1)) -> 2026-12 | D5: =IF(INDEX(Data_Checks!$D:$D,1+1)="","",INDEX(Data_Checks!$D:$D,1+1)) -> 3798184735378 | E5: =IF(INDEX(Data_Checks!$E:$E,1+1)="","",INDEX(Data_Checks!$E:$E,1+1)) -> 3875687837224 | F5: =IF(INDEX(Data_Checks!$F:$F,1+1)="","",INDEX(Data_Checks!$F:$F,1+1)) -> 2756.4944 | G5: =IF(INDEX(Data_Checks!$G:$G,1+1)="","",INDEX(Data_Checks!$G:$G,1+1)) -> FLAG | H5: =IF(INDEX(Data_Checks!$H:$H,1+1)="","",INDEX(Data_Checks!$H:$H,1+1)) -> 176 accounts billed for a different number of tokens than billable usage
A6: =IF(INDEX(Data_Checks!$A:$A,2+1)="","",INDEX(Data_Checks!$A:$A,2+1)) -> 6 | B6: =IF(INDEX(Data_Checks!$B:$B,2+1)="","",INDEX(Data_Checks!$B:$B,2+1)) -> Invoices use the right unit price | C6: =IF(INDEX(Data_Checks!$C:$C,2+1)="","",INDEX(Data_Checks!$C:$C,2+1)) -> 2027-01 | D6: =IF(INDEX(Data_Checks!$D:$D,2+1)="","",INDEX(Data_Checks!$D:$D,2+1)) -> 175335.73 | E6: =IF(INDEX(Data_Checks!$E:$E,2+1)="","",INDEX(Data_Checks!$E:$E,2+1)) -> 176794.48 | F6: =IF(INDEX(Data_Checks!$F:$F,2+1)="","",INDEX(Data_Checks!$F:$F,2+1)) -> 1458.7521 | G6: =IF(INDEX(Data_Checks!$G:$G,2+1)="","",INDEX(Data_Checks!$G:$G,2+1)) -> FLAG | H6: =IF(INDEX(Data_Checks!$H:$H,2+1)="","",INDEX(Data_Checks!$H:$H,2+1)) -> Meridian Legal at $0.042/M vs expected $0.0336/M
A7: =IF(INDEX(Data_Checks!$A:$A,3+1)="","",INDEX(Data_Checks!$A:$A,3+1)) -> 8 | B7: =IF(INDEX(Data_Checks!$B:$B,3+1)="","",INDEX(Data_Checks!$B:$B,3+1)) -> Gateway statement matches our logs | C7: =IF(INDEX(Data_Checks!$C:$C,3+1)="","",INDEX(Data_Checks!$C:$C,3+1)) -> openrouter 2027-01 | D7: =IF(INDEX(Data_Checks!$D:$D,3+1)="","",INDEX(Data_Checks!$D:$D,3+1)) -> 314743752869 | E7: =IF(INDEX(Data_Checks!$E:$E,3+1)="","",INDEX(Data_Checks!$E:$E,3+1)) -> 306560000000 | F7: =IF(INDEX(Data_Checks!$F:$F,3+1)="","",INDEX(Data_Checks!$F:$F,3+1)) -> -326.53174 | G7: =IF(INDEX(Data_Checks!$G:$G,3+1)="","",INDEX(Data_Checks!$G:$G,3+1)) -> FLAG | H7: =IF(INDEX(Data_Checks!$H:$H,3+1)="","",INDEX(Data_Checks!$H:$H,3+1)) -> Statement is -2.6% vs our logs
A8: =IF(INDEX(Data_Checks!$A:$A,4+1)="","",INDEX(Data_Checks!$A:$A,4+1)) -> 10 | B8: =IF(INDEX(Data_Checks!$B:$B,4+1)="","",INDEX(Data_Checks!$B:$B,4+1)) -> Enterprise usage below commitment | C8: =IF(INDEX(Data_Checks!$C:$C,4+1)="","",INDEX(Data_Checks!$C:$C,4+1)) -> Halcyon Games 2026-12 | D8: =IF(INDEX(Data_Checks!$D:$D,4+1)="","",INDEX(Data_Checks!$D:$D,4+1)) -> 15000 | E8: =IF(INDEX(Data_Checks!$E:$E,4+1)="","",INDEX(Data_Checks!$E:$E,4+1)) -> 9731.6831 | F8: =IF(INDEX(Data_Checks!$F:$F,4+1)="","",INDEX(Data_Checks!$F:$F,4+1)) -> 5268.3169 | G8: =IF(INDEX(Data_Checks!$G:$G,4+1)="","",INDEX(Data_Checks!$G:$G,4+1)) -> INFO | H8: =IF(INDEX(Data_Checks!$H:$H,4+1)="","",INDEX(Data_Checks!$H:$H,4+1)) -> Usage at 65.0% of commitment; true-up owed. Revenue is protected this month; renewal is the risk.
A9: =IF(INDEX(Data_Checks!$A:$A,5+1)="","",INDEX(Data_Checks!$A:$A,5+1)) -> 10 | B9: =IF(INDEX(Data_Checks!$B:$B,5+1)="","",INDEX(Data_Checks!$B:$B,5+1)) -> Enterprise usage below commitment | C9: =IF(INDEX(Data_Checks!$C:$C,5+1)="","",INDEX(Data_Checks!$C:$C,5+1)) -> Ledgerline Payments 2026-11 | D9: =IF(INDEX(Data_Checks!$D:$D,5+1)="","",INDEX(Data_Checks!$D:$D,5+1)) -> 40000 | E9: =IF(INDEX(Data_Checks!$E:$E,5+1)="","",INDEX(Data_Checks!$E:$E,5+1)) -> 26079.212 | F9: =IF(INDEX(Data_Checks!$F:$F,5+1)="","",INDEX(Data_Checks!$F:$F,5+1)) -> 13920.788 | G9: =IF(INDEX(Data_Checks!$G:$G,5+1)="","",INDEX(Data_Checks!$G:$G,5+1)) -> INFO | H9: =IF(INDEX(Data_Checks!$H:$H,5+1)="","",INDEX(Data_Checks!$H:$H,5+1)) -> Usage at 65.0% of commitment; true-up owed. Revenue is protected this month; renewal is the risk.
A10: =IF(INDEX(Data_Checks!$A:$A,6+1)="","",INDEX(Data_Checks!$A:$A,6+1)) -> 10 | B10: =IF(INDEX(Data_Checks!$B:$B,6+1)="","",INDEX(Data_Checks!$B:$B,6+1)) -> Enterprise usage below commitment | C10: =IF(INDEX(Data_Checks!$C:$C,6+1)="","",INDEX(Data_Checks!$C:$C,6+1)) -> Meridian Legal 2027-01 | D10: =IF(INDEX(Data_Checks!$D:$D,6+1)="","",INDEX(Data_Checks!$D:$D,6+1)) -> 12500 | E10: =IF(INDEX(Data_Checks!$E:$E,6+1)="","",INDEX(Data_Checks!$E:$E,6+1)) -> 5834.6763 | F10: =IF(INDEX(Data_Checks!$F:$F,6+1)="","",INDEX(Data_Checks!$F:$F,6+1)) -> 6665.3237 | G10: =IF(INDEX(Data_Checks!$G:$G,6+1)="","",INDEX(Data_Checks!$G:$G,6+1)) -> INFO | H10: =IF(INDEX(Data_Checks!$H:$H,6+1)="","",INDEX(Data_Checks!$H:$H,6+1)) -> Usage at 47.0% of commitment; true-up owed. Revenue is protected this month; renewal is the risk.
A11: =IF(INDEX(Data_Checks!$A:$A,7+1)="","",INDEX(Data_Checks!$A:$A,7+1)) -> 10 | B11: =IF(INDEX(Data_Checks!$B:$B,7+1)="","",INDEX(Data_Checks!$B:$B,7+1)) -> Enterprise usage below commitment | C11: =IF(INDEX(Data_Checks!$C:$C,7+1)="","",INDEX(Data_Checks!$C:$C,7+1)) -> Meridian Legal 2027-02 | D11: =IF(INDEX(Data_Checks!$D:$D,7+1)="","",INDEX(Data_Checks!$D:$D,7+1)) -> 12500 | E11: =IF(INDEX(Data_Checks!$E:$E,7+1)="","",INDEX(Data_Checks!$E:$E,7+1)) -> 8675.3028 | F11: =IF(INDEX(Data_Checks!$F:$F,7+1)="","",INDEX(Data_Checks!$F:$F,7+1)) -> 3824.6972 | G11: =IF(INDEX(Data_Checks!$G:$G,7+1)="","",INDEX(Data_Checks!$G:$G,7+1)) -> INFO | H11: =IF(INDEX(Data_Checks!$H:$H,7+1)="","",INDEX(Data_Checks!$H:$H,7+1)) -> Usage at 69.0% of commitment; true-up owed. Revenue is protected this month; renewal is the risk.
A12: =IF(INDEX(Data_Checks!$A:$A,8+1)="","",INDEX(Data_Checks!$A:$A,8+1)) -> 10 | B12: =IF(INDEX(Data_Checks!$B:$B,8+1)="","",INDEX(Data_Checks!$B:$B,8+1)) -> Enterprise usage below commitment | C12: =IF(INDEX(Data_Checks!$C:$C,8+1)="","",INDEX(Data_Checks!$C:$C,8+1)) -> Northwind Insurance 2026-12 | D12: =IF(INDEX(Data_Checks!$D:$D,8+1)="","",INDEX(Data_Checks!$D:$D,8+1)) -> 20000 | E12: =IF(INDEX(Data_Checks!$E:$E,8+1)="","",INDEX(Data_Checks!$E:$E,8+1)) -> 7777.388 | F12: =IF(INDEX(Data_Checks!$F:$F,8+1)="","",INDEX(Data_Checks!$F:$F,8+1)) -> 12222.612 | G12: =IF(INDEX(Data_Checks!$G:$G,8+1)="","",INDEX(Data_Checks!$G:$G,8+1)) -> INFO | H12: =IF(INDEX(Data_Checks!$H:$H,8+1)="","",INDEX(Data_Checks!$H:$H,8+1)) -> Usage at 39.0% of commitment; true-up owed. Revenue is protected this month; renewal is the risk.
A13: =IF(INDEX(Data_Checks!$A:$A,9+1)="","",INDEX(Data_Checks!$A:$A,9+1)) -> 10 | B13: =IF(INDEX(Data_Checks!$B:$B,9+1)="","",INDEX(Data_Checks!$B:$B,9+1)) -> Enterprise usage below commitment | C13: =IF(INDEX(Data_Checks!$C:$C,9+1)="","",INDEX(Data_Checks!$C:$C,9+1)) -> Northwind Insurance 2027-01 | D13: =IF(INDEX(Data_Checks!$D:$D,9+1)="","",INDEX(Data_Checks!$D:$D,9+1)) -> 20000 | E13: =IF(INDEX(Data_Checks!$E:$E,9+1)="","",INDEX(Data_Checks!$E:$E,9+1)) -> 9624.0229 | F13: =IF(INDEX(Data_Checks!$F:$F,9+1)="","",INDEX(Data_Checks!$F:$F,9+1)) -> 10375.977 | G13: =IF(INDEX(Data_Checks!$G:$G,9+1)="","",INDEX(Data_Checks!$G:$G,9+1)) -> INFO | H13: =IF(INDEX(Data_Checks!$H:$H,9+1)="","",INDEX(Data_Checks!$H:$H,9+1)) -> Usage at 48.0% of commitment; true-up owed. Revenue is protected this month; renewal is the risk.
A14: =IF(INDEX(Data_Checks!$A:$A,10+1)="","",INDEX(Data_Checks!$A:$A,10+1)) -> 10 | B14: =IF(INDEX(Data_Checks!$B:$B,10+1)="","",INDEX(Data_Checks!$B:$B,10+1)) -> Enterprise usage below commitment | C14: =IF(INDEX(Data_Checks!$C:$C,10+1)="","",INDEX(Data_Checks!$C:$C,10+1)) -> Northwind Insurance 2027-02 | D14: =IF(INDEX(Data_Checks!$D:$D,10+1)="","",INDEX(Data_Checks!$D:$D,10+1)) -> 20000 | E14: =IF(INDEX(Data_Checks!$E:$E,10+1)="","",INDEX(Data_Checks!$E:$E,10+1)) -> 9112.6607 | F14: =IF(INDEX(Data_Checks!$F:$F,10+1)="","",INDEX(Data_Checks!$F:$F,10+1)) -> 10887.339 | G14: =IF(INDEX(Data_Checks!$G:$G,10+1)="","",INDEX(Data_Checks!$G:$G,10+1)) -> INFO | H14: =IF(INDEX(Data_Checks!$H:$H,10+1)="","",INDEX(Data_Checks!$H:$H,10+1)) -> Usage at 46.0% of commitment; true-up owed. Revenue is protected this month; renewal is the risk.
A15: =IF(INDEX(Data_Checks!$A:$A,11+1)="","",INDEX(Data_Checks!$A:$A,11+1)) -> 10 | B15: =IF(INDEX(Data_Checks!$B:$B,11+1)="","",INDEX(Data_Checks!$B:$B,11+1)) -> Enterprise usage below commitment | C15: =IF(INDEX(Data_Checks!$C:$C,11+1)="","",INDEX(Data_Checks!$C:$C,11+1)) -> Sable Research 2027-02 | D15: =IF(INDEX(Data_Checks!$D:$D,11+1)="","",INDEX(Data_Checks!$D:$D,11+1)) -> 17500 | E15: =IF(INDEX(Data_Checks!$E:$E,11+1)="","",INDEX(Data_Checks!$E:$E,11+1)) -> 12418.124 | F15: =IF(INDEX(Data_Checks!$F:$F,11+1)="","",INDEX(Data_Checks!$F:$F,11+1)) -> 5081.8763 | G15: =IF(INDEX(Data_Checks!$G:$G,11+1)="","",INDEX(Data_Checks!$G:$G,11+1)) -> INFO | H15: =IF(INDEX(Data_Checks!$H:$H,11+1)="","",INDEX(Data_Checks!$H:$H,11+1)) -> Usage at 71.0% of commitment; true-up owed. Revenue is protected this month; renewal is the risk.
A16: =IF(INDEX(Data_Checks!$A:$A,12+1)="","",INDEX(Data_Checks!$A:$A,12+1)) -> 1 | B16: =IF(INDEX(Data_Checks!$B:$B,12+1)="","",INDEX(Data_Checks!$B:$B,12+1)) -> No duplicate request IDs in call logs | C16: =IF(INDEX(Data_Checks!$C:$C,12+1)="","",INDEX(Data_Checks!$C:$C,12+1)) -> all calls to close | D16: =IF(INDEX(Data_Checks!$D:$D,12+1)="","",INDEX(Data_Checks!$D:$D,12+1)) -> 0 | E16: =IF(INDEX(Data_Checks!$E:$E,12+1)="","",INDEX(Data_Checks!$E:$E,12+1)) | F16: =IF(INDEX(Data_Checks!$F:$F,12+1)="","",INDEX(Data_Checks!$F:$F,12+1)) -> 0 | G16: =IF(INDEX(Data_Checks!$G:$G,12+1)="","",INDEX(Data_Checks!$G:$G,12+1)) -> SKIP | H16: =IF(INDEX(Data_Checks!$H:$H,12+1)="","",INDEX(Data_Checks!$H:$H,12+1)) -> Needs call-level logs with request_id
A17: =IF(INDEX(Data_Checks!$A:$A,13+1)="","",INDEX(Data_Checks!$A:$A,13+1)) -> 2 | B17: =IF(INDEX(Data_Checks!$B:$B,13+1)="","",INDEX(Data_Checks!$B:$B,13+1)) -> No missing days in usage data | C17: =IF(INDEX(Data_Checks!$C:$C,13+1)="","",INDEX(Data_Checks!$C:$C,13+1)) -> 2026-09-15 to 2027-02-28 | D17: =IF(INDEX(Data_Checks!$D:$D,13+1)="","",INDEX(Data_Checks!$D:$D,13+1)) -> 167 | E17: =IF(INDEX(Data_Checks!$E:$E,13+1)="","",INDEX(Data_Checks!$E:$E,13+1)) -> 167 | F17: =IF(INDEX(Data_Checks!$F:$F,13+1)="","",INDEX(Data_Checks!$F:$F,13+1)) -> 0 | G17: =IF(INDEX(Data_Checks!$G:$G,13+1)="","",INDEX(Data_Checks!$G:$G,13+1)) -> PASS | H17: =IF(INDEX(Data_Checks!$H:$H,13+1)="","",INDEX(Data_Checks!$H:$H,13+1)) -> Days with usage vs days in period. A gap usually means a failed export, not a quiet day.
A18: =IF(INDEX(Data_Checks!$A:$A,14+1)="","",INDEX(Data_Checks!$A:$A,14+1)) -> 3 | B18: =IF(INDEX(Data_Checks!$B:$B,14+1)="","",INDEX(Data_Checks!$B:$B,14+1)) -> All usage belongs to a known account | C18: =IF(INDEX(Data_Checks!$C:$C,14+1)="","",INDEX(Data_Checks!$C:$C,14+1)) -> reporting window | D18: =IF(INDEX(Data_Checks!$D:$D,14+1)="","",INDEX(Data_Checks!$D:$D,14+1)) -> 0 | E18: =IF(INDEX(Data_Checks!$E:$E,14+1)="","",INDEX(Data_Checks!$E:$E,14+1)) -> 0 | F18: =IF(INDEX(Data_Checks!$F:$F,14+1)="","",INDEX(Data_Checks!$F:$F,14+1)) -> 0 | G18: =IF(INDEX(Data_Checks!$G:$G,14+1)="","",INDEX(Data_Checks!$G:$G,14+1)) -> PASS | H18: =IF(INDEX(Data_Checks!$H:$H,14+1)="","",INDEX(Data_Checks!$H:$H,14+1)) -> 0 account IDs in usage are missing from the accounts source
A19: =IF(INDEX(Data_Checks!$A:$A,15+1)="","",INDEX(Data_Checks!$A:$A,15+1)) -> 4 | B19: =IF(INDEX(Data_Checks!$B:$B,15+1)="","",INDEX(Data_Checks!$B:$B,15+1)) -> Billed tokens tie to billable usage | C19: =IF(INDEX(Data_Checks!$C:$C,15+1)="","",INDEX(Data_Checks!$C:$C,15+1)) -> 2026-09 | D19: =IF(INDEX(Data_Checks!$D:$D,15+1)="","",INDEX(Data_Checks!$D:$D,15+1)) -> 3100670156 | E19: =IF(INDEX(Data_Checks!$E:$E,15+1)="","",INDEX(Data_Checks!$E:$E,15+1)) -> 3100670156 | F19: =IF(INDEX(Data_Checks!$F:$F,15+1)="","",INDEX(Data_Checks!$F:$F,15+1)) -> 0 | G19: =IF(INDEX(Data_Checks!$G:$G,15+1)="","",INDEX(Data_Checks!$G:$G,15+1)) -> PASS | H19: =IF(INDEX(Data_Checks!$H:$H,15+1)="","",INDEX(Data_Checks!$H:$H,15+1)) -> 0 accounts billed for a different number of tokens than billable usage
A20: =IF(INDEX(Data_Checks!$A:$A,16+1)="","",INDEX(Data_Checks!$A:$A,16+1)) -> 4 | B20: =IF(INDEX(Data_Checks!$B:$B,16+1)="","",INDEX(Data_Checks!$B:$B,16+1)) -> Billed tokens tie to billable usage | C20: =IF(INDEX(Data_Checks!$C:$C,16+1)="","",INDEX(Data_Checks!$C:$C,16+1)) -> 2026-10 | D20: =IF(INDEX(Data_Checks!$D:$D,16+1)="","",INDEX(Data_Checks!$D:$D,16+1)) -> 620098291596 | E20: =IF(INDEX(Data_Checks!$E:$E,16+1)="","",INDEX(Data_Checks!$E:$E,16+1)) -> 620098291596 | F20: =IF(INDEX(Data_Checks!$F:$F,16+1)="","",INDEX(Data_Checks!$F:$F,16+1)) -> 0 | G20: =IF(INDEX(Data_Checks!$G:$G,16+1)="","",INDEX(Data_Checks!$G:$G,16+1)) -> PASS | H20: =IF(INDEX(Data_Checks!$H:$H,16+1)="","",INDEX(Data_Checks!$H:$H,16+1)) -> 0 accounts billed for a different number of tokens than billable usage
A21: =IF(INDEX(Data_Checks!$A:$A,17+1)="","",INDEX(Data_Checks!$A:$A,17+1)) -> 4 | B21: =IF(INDEX(Data_Checks!$B:$B,17+1)="","",INDEX(Data_Checks!$B:$B,17+1)) -> Billed tokens tie to billable usage | C21: =IF(INDEX(Data_Checks!$C:$C,17+1)="","",INDEX(Data_Checks!$C:$C,17+1)) -> 2026-11 | D21: =IF(INDEX(Data_Checks!$D:$D,17+1)="","",INDEX(Data_Checks!$D:$D,17+1)) -> 2026111033189 | E21: =IF(INDEX(Data_Checks!$E:$E,17+1)="","",INDEX(Data_Checks!$E:$E,17+1)) -> 2026111033189 | F21: =IF(INDEX(Data_Checks!$F:$F,17+1)="","",INDEX(Data_Checks!$F:$F,17+1)) -> 0 | G21: =IF(INDEX(Data_Checks!$G:$G,17+1)="","",INDEX(Data_Checks!$G:$G,17+1)) -> PASS | H21: =IF(INDEX(Data_Checks!$H:$H,17+1)="","",INDEX(Data_Checks!$H:$H,17+1)) -> 0 accounts billed for a different number of tokens than billable usage
A22: =IF(INDEX(Data_Checks!$A:$A,18+1)="","",INDEX(Data_Checks!$A:$A,18+1)) -> 4 | B22: =IF(INDEX(Data_Checks!$B:$B,18+1)="","",INDEX(Data_Checks!$B:$B,18+1)) -> Billed tokens tie to billable usage | C22: =IF(INDEX(Data_Checks!$C:$C,18+1)="","",INDEX(Data_Checks!$C:$C,18+1)) -> 2027-01 | D22: =IF(INDEX(Data_Checks!$D:$D,18+1)="","",INDEX(Data_Checks!$D:$D,18+1)) -> 4910016675784 | E22: =IF(INDEX(Data_Checks!$E:$E,18+1)="","",INDEX(Data_Checks!$E:$E,18+1)) -> 4910016675784 | F22: =IF(INDEX(Data_Checks!$F:$F,18+1)="","",INDEX(Data_Checks!$F:$F,18+1)) -> 0 | G22: =IF(INDEX(Data_Checks!$G:$G,18+1)="","",INDEX(Data_Checks!$G:$G,18+1)) -> PASS | H22: =IF(INDEX(Data_Checks!$H:$H,18+1)="","",INDEX(Data_Checks!$H:$H,18+1)) -> 0 accounts billed for a different number of tokens than billable usage
A23: =IF(INDEX(Data_Checks!$A:$A,19+1)="","",INDEX(Data_Checks!$A:$A,19+1)) -> 4 | B23: =IF(INDEX(Data_Checks!$B:$B,19+1)="","",INDEX(Data_Checks!$B:$B,19+1)) -> Billed tokens tie to billable usage | C23: =IF(INDEX(Data_Checks!$C:$C,19+1)="","",INDEX(Data_Checks!$C:$C,19+1)) -> 2027-02 | D23: =IF(INDEX(Data_Checks!$D:$D,19+1)="","",INDEX(Data_Checks!$D:$D,19+1)) -> 5198170656463 | E23: =IF(INDEX(Data_Checks!$E:$E,19+1)="","",INDEX(Data_Checks!$E:$E,19+1)) -> 5198170656463 | F23: =IF(INDEX(Data_Checks!$F:$F,19+1)="","",INDEX(Data_Checks!$F:$F,19+1)) -> 0 | G23: =IF(INDEX(Data_Checks!$G:$G,19+1)="","",INDEX(Data_Checks!$G:$G,19+1)) -> PASS | H23: =IF(INDEX(Data_Checks!$H:$H,19+1)="","",INDEX(Data_Checks!$H:$H,19+1)) -> 0 accounts billed for a different number of tokens than billable usage
A24: =IF(INDEX(Data_Checks!$A:$A,20+1)="","",INDEX(Data_Checks!$A:$A,20+1)) -> 5 | B24: =IF(INDEX(Data_Checks!$B:$B,20+1)="","",INDEX(Data_Checks!$B:$B,20+1)) -> Every account with revenue has an invoice | C24: =IF(INDEX(Data_Checks!$C:$C,20+1)="","",INDEX(Data_Checks!$C:$C,20+1)) -> reporting window | D24: =IF(INDEX(Data_Checks!$D:$D,20+1)="","",INDEX(Data_Checks!$D:$D,20+1)) -> 0 | E24: =IF(INDEX(Data_Checks!$E:$E,20+1)="","",INDEX(Data_Checks!$E:$E,20+1)) -> 0 | F24: =IF(INDEX(Data_Checks!$F:$F,20+1)="","",INDEX(Data_Checks!$F:$F,20+1)) -> 0 | G24: =IF(INDEX(Data_Checks!$G:$G,20+1)="","",INDEX(Data_Checks!$G:$G,20+1)) -> PASS | H24: =IF(INDEX(Data_Checks!$H:$H,20+1)="","",INDEX(Data_Checks!$H:$H,20+1)) -> Every account with chargeable usage has an invoice
A25: =IF(INDEX(Data_Checks!$A:$A,21+1)="","",INDEX(Data_Checks!$A:$A,21+1)) -> 6 | B25: =IF(INDEX(Data_Checks!$B:$B,21+1)="","",INDEX(Data_Checks!$B:$B,21+1)) -> Invoices use the right unit price | C25: =IF(INDEX(Data_Checks!$C:$C,21+1)="","",INDEX(Data_Checks!$C:$C,21+1)) -> 2026-09 | D25: =IF(INDEX(Data_Checks!$D:$D,21+1)="","",INDEX(Data_Checks!$D:$D,21+1)) -> 8.0009597 | E25: =IF(INDEX(Data_Checks!$E:$E,21+1)="","",INDEX(Data_Checks!$E:$E,21+1)) -> 8 | F25: =IF(INDEX(Data_Checks!$F:$F,21+1)="","",INDEX(Data_Checks!$F:$F,21+1)) -> -0.000959722 | G25: =IF(INDEX(Data_Checks!$G:$G,21+1)="","",INDEX(Data_Checks!$G:$G,21+1)) -> PASS | H25: =IF(INDEX(Data_Checks!$H:$H,21+1)="","",INDEX(Data_Checks!$H:$H,21+1)) -> All invoices at the expected price
A26: =IF(INDEX(Data_Checks!$A:$A,22+1)="","",INDEX(Data_Checks!$A:$A,22+1)) -> 6 | B26: =IF(INDEX(Data_Checks!$B:$B,22+1)="","",INDEX(Data_Checks!$B:$B,22+1)) -> Invoices use the right unit price | C26: =IF(INDEX(Data_Checks!$C:$C,22+1)="","",INDEX(Data_Checks!$C:$C,22+1)) -> 2026-10 | D26: =IF(INDEX(Data_Checks!$D:$D,22+1)="","",INDEX(Data_Checks!$D:$D,22+1)) -> 21735.129 | E26: =IF(INDEX(Data_Checks!$E:$E,22+1)="","",INDEX(Data_Checks!$E:$E,22+1)) -> 21735.14 | F26: =IF(INDEX(Data_Checks!$F:$F,22+1)="","",INDEX(Data_Checks!$F:$F,22+1)) -> 0.010682876 | G26: =IF(INDEX(Data_Checks!$G:$G,22+1)="","",INDEX(Data_Checks!$G:$G,22+1)) -> PASS | H26: =IF(INDEX(Data_Checks!$H:$H,22+1)="","",INDEX(Data_Checks!$H:$H,22+1)) -> All invoices at the expected price
A27: =IF(INDEX(Data_Checks!$A:$A,23+1)="","",INDEX(Data_Checks!$A:$A,23+1)) -> 6 | B27: =IF(INDEX(Data_Checks!$B:$B,23+1)="","",INDEX(Data_Checks!$B:$B,23+1)) -> Invoices use the right unit price | C27: =IF(INDEX(Data_Checks!$C:$C,23+1)="","",INDEX(Data_Checks!$C:$C,23+1)) -> 2026-11 | D27: =IF(INDEX(Data_Checks!$D:$D,23+1)="","",INDEX(Data_Checks!$D:$D,23+1)) -> 71340.136 | E27: =IF(INDEX(Data_Checks!$E:$E,23+1)="","",INDEX(Data_Checks!$E:$E,23+1)) -> 71340.12 | F27: =IF(INDEX(Data_Checks!$F:$F,23+1)="","",INDEX(Data_Checks!$F:$F,23+1)) -> -0.015676633 | G27: =IF(INDEX(Data_Checks!$G:$G,23+1)="","",INDEX(Data_Checks!$G:$G,23+1)) -> PASS | H27: =IF(INDEX(Data_Checks!$H:$H,23+1)="","",INDEX(Data_Checks!$H:$H,23+1)) -> All invoices at the expected price
A28: =IF(INDEX(Data_Checks!$A:$A,24+1)="","",INDEX(Data_Checks!$A:$A,24+1)) -> 6 | B28: =IF(INDEX(Data_Checks!$B:$B,24+1)="","",INDEX(Data_Checks!$B:$B,24+1)) -> Invoices use the right unit price | C28: =IF(INDEX(Data_Checks!$C:$C,24+1)="","",INDEX(Data_Checks!$C:$C,24+1)) -> 2026-12 | D28: =IF(INDEX(Data_Checks!$D:$D,24+1)="","",INDEX(Data_Checks!$D:$D,24+1)) -> 137442.99 | E28: =IF(INDEX(Data_Checks!$E:$E,24+1)="","",INDEX(Data_Checks!$E:$E,24+1)) -> 137443.02 | F28: =IF(INDEX(Data_Checks!$F:$F,24+1)="","",INDEX(Data_Checks!$F:$F,24+1)) -> 0.02820446 | G28: =IF(INDEX(Data_Checks!$G:$G,24+1)="","",INDEX(Data_Checks!$G:$G,24+1)) -> PASS | H28: =IF(INDEX(Data_Checks!$H:$H,24+1)="","",INDEX(Data_Checks!$H:$H,24+1)) -> All invoices at the expected price
A29: =IF(INDEX(Data_Checks!$A:$A,25+1)="","",INDEX(Data_Checks!$A:$A,25+1)) -> 6 | B29: =IF(INDEX(Data_Checks!$B:$B,25+1)="","",INDEX(Data_Checks!$B:$B,25+1)) -> Invoices use the right unit price | C29: =IF(INDEX(Data_Checks!$C:$C,25+1)="","",INDEX(Data_Checks!$C:$C,25+1)) -> 2027-02 | D29: =IF(INDEX(Data_Checks!$D:$D,25+1)="","",INDEX(Data_Checks!$D:$D,25+1)) -> 186569.48 | E29: =IF(INDEX(Data_Checks!$E:$E,25+1)="","",INDEX(Data_Checks!$E:$E,25+1)) -> 186569.45 | F29: =IF(INDEX(Data_Checks!$F:$F,25+1)="","",INDEX(Data_Checks!$F:$F,25+1)) -> -0.026268446 | G29: =IF(INDEX(Data_Checks!$G:$G,25+1)="","",INDEX(Data_Checks!$G:$G,25+1)) -> PASS | H29: =IF(INDEX(Data_Checks!$H:$H,25+1)="","",INDEX(Data_Checks!$H:$H,25+1)) -> All invoices at the expected price
A30: =IF(INDEX(Data_Checks!$A:$A,26+1)="","",INDEX(Data_Checks!$A:$A,26+1)) -> 7 | B30: =IF(INDEX(Data_Checks!$B:$B,26+1)="","",INDEX(Data_Checks!$B:$B,26+1)) -> Free credit used stays within each account's grant | C30: =IF(INDEX(Data_Checks!$C:$C,26+1)="","",INDEX(Data_Checks!$C:$C,26+1)) -> all accounts | D30: =IF(INDEX(Data_Checks!$D:$D,26+1)="","",INDEX(Data_Checks!$D:$D,26+1)) -> 5 | E30: =IF(INDEX(Data_Checks!$E:$E,26+1)="","",INDEX(Data_Checks!$E:$E,26+1)) -> 5 | F30: =IF(INDEX(Data_Checks!$F:$F,26+1)="","",INDEX(Data_Checks!$F:$F,26+1)) -> 0 | G30: =IF(INDEX(Data_Checks!$G:$G,26+1)="","",INDEX(Data_Checks!$G:$G,26+1)) -> PASS | H30: =IF(INDEX(Data_Checks!$H:$H,26+1)="","",INDEX(Data_Checks!$H:$H,26+1)) -> 0 accounts used more free credit than granted
A31: =IF(INDEX(Data_Checks!$A:$A,27+1)="","",INDEX(Data_Checks!$A:$A,27+1)) -> 8 | B31: =IF(INDEX(Data_Checks!$B:$B,27+1)="","",INDEX(Data_Checks!$B:$B,27+1)) -> Gateway statement matches our logs | C31: =IF(INDEX(Data_Checks!$C:$C,27+1)="","",INDEX(Data_Checks!$C:$C,27+1)) -> digitalocean 2026-09 | D31: =IF(INDEX(Data_Checks!$D:$D,27+1)="","",INDEX(Data_Checks!$D:$D,27+1)) -> 426469684 | E31: =IF(INDEX(Data_Checks!$E:$E,27+1)="","",INDEX(Data_Checks!$E:$E,27+1)) -> 426000000 | F31: =IF(INDEX(Data_Checks!$F:$F,27+1)="","",INDEX(Data_Checks!$F:$F,27+1)) -> -0.01814859 | G31: =IF(INDEX(Data_Checks!$G:$G,27+1)="","",INDEX(Data_Checks!$G:$G,27+1)) -> PASS | H31: =IF(INDEX(Data_Checks!$H:$H,27+1)="","",INDEX(Data_Checks!$H:$H,27+1)) -> Statement is -0.11% vs our logs
A32: =IF(INDEX(Data_Checks!$A:$A,28+1)="","",INDEX(Data_Checks!$A:$A,28+1)) -> 8 | B32: =IF(INDEX(Data_Checks!$B:$B,28+1)="","",INDEX(Data_Checks!$B:$B,28+1)) -> Gateway statement matches our logs | C32: =IF(INDEX(Data_Checks!$C:$C,28+1)="","",INDEX(Data_Checks!$C:$C,28+1)) -> digitalocean 2026-10 | D32: =IF(INDEX(Data_Checks!$D:$D,28+1)="","",INDEX(Data_Checks!$D:$D,28+1)) -> 1055669350 | E32: =IF(INDEX(Data_Checks!$E:$E,28+1)="","",INDEX(Data_Checks!$E:$E,28+1)) -> 1056000000 | F32: =IF(INDEX(Data_Checks!$F:$F,28+1)="","",INDEX(Data_Checks!$F:$F,28+1)) -> 0.012776316 | G32: =IF(INDEX(Data_Checks!$G:$G,28+1)="","",INDEX(Data_Checks!$G:$G,28+1)) -> PASS | H32: =IF(INDEX(Data_Checks!$H:$H,28+1)="","",INDEX(Data_Checks!$H:$H,28+1)) -> Statement is 0.03% vs our logs
A33: =IF(INDEX(Data_Checks!$A:$A,29+1)="","",INDEX(Data_Checks!$A:$A,29+1)) -> 8 | B33: =IF(INDEX(Data_Checks!$B:$B,29+1)="","",INDEX(Data_Checks!$B:$B,29+1)) -> Gateway statement matches our logs | C33: =IF(INDEX(Data_Checks!$C:$C,29+1)="","",INDEX(Data_Checks!$C:$C,29+1)) -> digitalocean 2026-11 | D33: =IF(INDEX(Data_Checks!$D:$D,29+1)="","",INDEX(Data_Checks!$D:$D,29+1)) -> 2114605799 | E33: =IF(INDEX(Data_Checks!$E:$E,29+1)="","",INDEX(Data_Checks!$E:$E,29+1)) -> 2115000000 | F33: =IF(INDEX(Data_Checks!$F:$F,29+1)="","",INDEX(Data_Checks!$F:$F,29+1)) -> 0.015231927 | G33: =IF(INDEX(Data_Checks!$G:$G,29+1)="","",INDEX(Data_Checks!$G:$G,29+1)) -> PASS | H33: =IF(INDEX(Data_Checks!$H:$H,29+1)="","",INDEX(Data_Checks!$H:$H,29+1)) -> Statement is 0.02% vs our logs
A34: =IF(INDEX(Data_Checks!$A:$A,30+1)="","",INDEX(Data_Checks!$A:$A,30+1)) -> 8 | B34: =IF(INDEX(Data_Checks!$B:$B,30+1)="","",INDEX(Data_Checks!$B:$B,30+1)) -> Gateway statement matches our logs | C34: =IF(INDEX(Data_Checks!$C:$C,30+1)="","",INDEX(Data_Checks!$C:$C,30+1)) -> digitalocean 2026-12 | D34: =IF(INDEX(Data_Checks!$D:$D,30+1)="","",INDEX(Data_Checks!$D:$D,30+1)) -> 7466089971 | E34: =IF(INDEX(Data_Checks!$E:$E,30+1)="","",INDEX(Data_Checks!$E:$E,30+1)) -> 7466000000 | F34: =IF(INDEX(Data_Checks!$F:$F,30+1)="","",INDEX(Data_Checks!$F:$F,30+1)) -> -0.0034764794 | G34: =IF(INDEX(Data_Checks!$G:$G,30+1)="","",INDEX(Data_Checks!$G:$G,30+1)) -> PASS | H34: =IF(INDEX(Data_Checks!$H:$H,30+1)="","",INDEX(Data_Checks!$H:$H,30+1)) -> Statement is -0.0% vs our logs
A35: =IF(INDEX(Data_Checks!$A:$A,31+1)="","",INDEX(Data_Checks!$A:$A,31+1)) -> 8 | B35: =IF(INDEX(Data_Checks!$B:$B,31+1)="","",INDEX(Data_Checks!$B:$B,31+1)) -> Gateway statement matches our logs | C35: =IF(INDEX(Data_Checks!$C:$C,31+1)="","",INDEX(Data_Checks!$C:$C,31+1)) -> digitalocean 2027-01 | D35: =IF(INDEX(Data_Checks!$D:$D,31+1)="","",INDEX(Data_Checks!$D:$D,31+1)) -> 12737283801 | E35: =IF(INDEX(Data_Checks!$E:$E,31+1)="","",INDEX(Data_Checks!$E:$E,31+1)) -> 12737000000 | F35: =IF(INDEX(Data_Checks!$F:$F,31+1)="","",INDEX(Data_Checks!$F:$F,31+1)) -> -0.010966071 | G35: =IF(INDEX(Data_Checks!$G:$G,31+1)="","",INDEX(Data_Checks!$G:$G,31+1)) -> PASS | H35: =IF(INDEX(Data_Checks!$H:$H,31+1)="","",INDEX(Data_Checks!$H:$H,31+1)) -> Statement is -0.0% vs our logs
A36: =IF(INDEX(Data_Checks!$A:$A,32+1)="","",INDEX(Data_Checks!$A:$A,32+1)) -> 8 | B36: =IF(INDEX(Data_Checks!$B:$B,32+1)="","",INDEX(Data_Checks!$B:$B,32+1)) -> Gateway statement matches our logs | C36: =IF(INDEX(Data_Checks!$C:$C,32+1)="","",INDEX(Data_Checks!$C:$C,32+1)) -> digitalocean 2027-02 | D36: =IF(INDEX(Data_Checks!$D:$D,32+1)="","",INDEX(Data_Checks!$D:$D,32+1)) -> 14986734199 | E36: =IF(INDEX(Data_Checks!$E:$E,32+1)="","",INDEX(Data_Checks!$E:$E,32+1)) -> 14987000000 | F36: =IF(INDEX(Data_Checks!$F:$F,32+1)="","",INDEX(Data_Checks!$F:$F,32+1)) -> 0.010270551 | G36: =IF(INDEX(Data_Checks!$G:$G,32+1)="","",INDEX(Data_Checks!$G:$G,32+1)) -> PASS | H36: =IF(INDEX(Data_Checks!$H:$H,32+1)="","",INDEX(Data_Checks!$H:$H,32+1)) -> Statement is 0.0% vs our logs
A37: =IF(INDEX(Data_Checks!$A:$A,33+1)="","",INDEX(Data_Checks!$A:$A,33+1)) -> 8 | B37: =IF(INDEX(Data_Checks!$B:$B,33+1)="","",INDEX(Data_Checks!$B:$B,33+1)) -> Gateway statement matches our logs | C37: =IF(INDEX(Data_Checks!$C:$C,33+1)="","",INDEX(Data_Checks!$C:$C,33+1)) -> openrouter 2026-09 | D37: =IF(INDEX(Data_Checks!$D:$D,33+1)="","",INDEX(Data_Checks!$D:$D,33+1)) -> 1226175518 | E37: =IF(INDEX(Data_Checks!$E:$E,33+1)="","",INDEX(Data_Checks!$E:$E,33+1)) -> 1226000000 | F37: =IF(INDEX(Data_Checks!$F:$F,33+1)="","",INDEX(Data_Checks!$F:$F,33+1)) -> -0.0070031682 | G37: =IF(INDEX(Data_Checks!$G:$G,33+1)="","",INDEX(Data_Checks!$G:$G,33+1)) -> PASS | H37: =IF(INDEX(Data_Checks!$H:$H,33+1)="","",INDEX(Data_Checks!$H:$H,33+1)) -> Statement is -0.01% vs our logs
A38: =IF(INDEX(Data_Checks!$A:$A,34+1)="","",INDEX(Data_Checks!$A:$A,34+1)) -> 8 | B38: =IF(INDEX(Data_Checks!$B:$B,34+1)="","",INDEX(Data_Checks!$B:$B,34+1)) -> Gateway statement matches our logs | C38: =IF(INDEX(Data_Checks!$C:$C,34+1)="","",INDEX(Data_Checks!$C:$C,34+1)) -> openrouter 2026-10 | D38: =IF(INDEX(Data_Checks!$D:$D,34+1)="","",INDEX(Data_Checks!$D:$D,34+1)) -> 10059494302 | E38: =IF(INDEX(Data_Checks!$E:$E,34+1)="","",INDEX(Data_Checks!$E:$E,34+1)) -> 10059000000 | F38: =IF(INDEX(Data_Checks!$F:$F,34+1)="","",INDEX(Data_Checks!$F:$F,34+1)) -> -0.01972265 | G38: =IF(INDEX(Data_Checks!$G:$G,34+1)="","",INDEX(Data_Checks!$G:$G,34+1)) -> PASS | H38: =IF(INDEX(Data_Checks!$H:$H,34+1)="","",INDEX(Data_Checks!$H:$H,34+1)) -> Statement is -0.0% vs our logs
A39: =IF(INDEX(Data_Checks!$A:$A,35+1)="","",INDEX(Data_Checks!$A:$A,35+1)) -> 8 | B39: =IF(INDEX(Data_Checks!$B:$B,35+1)="","",INDEX(Data_Checks!$B:$B,35+1)) -> Gateway statement matches our logs | C39: =IF(INDEX(Data_Checks!$C:$C,35+1)="","",INDEX(Data_Checks!$C:$C,35+1)) -> openrouter 2026-11 | D39: =IF(INDEX(Data_Checks!$D:$D,35+1)="","",INDEX(Data_Checks!$D:$D,35+1)) -> 46369863095 | E39: =IF(INDEX(Data_Checks!$E:$E,35+1)="","",INDEX(Data_Checks!$E:$E,35+1)) -> 46370000000 | F39: =IF(INDEX(Data_Checks!$F:$F,35+1)="","",INDEX(Data_Checks!$F:$F,35+1)) -> 0.0054625095 | G39: =IF(INDEX(Data_Checks!$G:$G,35+1)="","",INDEX(Data_Checks!$G:$G,35+1)) -> PASS | H39: =IF(INDEX(Data_Checks!$H:$H,35+1)="","",INDEX(Data_Checks!$H:$H,35+1)) -> Statement is 0.0% vs our logs
A40: =IF(INDEX(Data_Checks!$A:$A,36+1)="","",INDEX(Data_Checks!$A:$A,36+1)) -> 8 | B40: =IF(INDEX(Data_Checks!$B:$B,36+1)="","",INDEX(Data_Checks!$B:$B,36+1)) -> Gateway statement matches our logs | C40: =IF(INDEX(Data_Checks!$C:$C,36+1)="","",INDEX(Data_Checks!$C:$C,36+1)) -> openrouter 2026-12 | D40: =IF(INDEX(Data_Checks!$D:$D,36+1)="","",INDEX(Data_Checks!$D:$D,36+1)) -> 165493359479 | E40: =IF(INDEX(Data_Checks!$E:$E,36+1)="","",INDEX(Data_Checks!$E:$E,36+1)) -> 165493000000 | F40: =IF(INDEX(Data_Checks!$F:$F,36+1)="","",INDEX(Data_Checks!$F:$F,36+1)) -> -0.014343212 | G40: =IF(INDEX(Data_Checks!$G:$G,36+1)="","",INDEX(Data_Checks!$G:$G,36+1)) -> PASS | H40: =IF(INDEX(Data_Checks!$H:$H,36+1)="","",INDEX(Data_Checks!$H:$H,36+1)) -> Statement is -0.0% vs our logs
A41: =IF(INDEX(Data_Checks!$A:$A,37+1)="","",INDEX(Data_Checks!$A:$A,37+1)) -> 8 | B41: =IF(INDEX(Data_Checks!$B:$B,37+1)="","",INDEX(Data_Checks!$B:$B,37+1)) -> Gateway statement matches our logs | C41: =IF(INDEX(Data_Checks!$C:$C,37+1)="","",INDEX(Data_Checks!$C:$C,37+1)) -> openrouter 2027-02 | D41: =IF(INDEX(Data_Checks!$D:$D,37+1)="","",INDEX(Data_Checks!$D:$D,37+1)) -> 370518908817 | E41: =IF(INDEX(Data_Checks!$E:$E,37+1)="","",INDEX(Data_Checks!$E:$E,37+1)) -> 370519000000 | F41: =IF(INDEX(Data_Checks!$F:$F,37+1)="","",INDEX(Data_Checks!$F:$F,37+1)) -> 0.0036382017 | G41: =IF(INDEX(Data_Checks!$G:$G,37+1)="","",INDEX(Data_Checks!$G:$G,37+1)) -> PASS | H41: =IF(INDEX(Data_Checks!$H:$H,37+1)="","",INDEX(Data_Checks!$H:$H,37+1)) -> Statement is 0.0% vs our logs
A42: =IF(INDEX(Data_Checks!$A:$A,38+1)="","",INDEX(Data_Checks!$A:$A,38+1)) -> 8 | B42: =IF(INDEX(Data_Checks!$B:$B,38+1)="","",INDEX(Data_Checks!$B:$B,38+1)) -> Gateway statement matches our logs | C42: =IF(INDEX(Data_Checks!$C:$C,38+1)="","",INDEX(Data_Checks!$C:$C,38+1)) -> vercel 2026-09 | D42: =IF(INDEX(Data_Checks!$D:$D,38+1)="","",INDEX(Data_Checks!$D:$D,38+1)) -> 2516245521 | E42: =IF(INDEX(Data_Checks!$E:$E,38+1)="","",INDEX(Data_Checks!$E:$E,38+1)) -> 2516000000 | F42: =IF(INDEX(Data_Checks!$F:$F,38+1)="","",INDEX(Data_Checks!$F:$F,38+1)) -> -0.0097962879 | G42: =IF(INDEX(Data_Checks!$G:$G,38+1)="","",INDEX(Data_Checks!$G:$G,38+1)) -> PASS | H42: =IF(INDEX(Data_Checks!$H:$H,38+1)="","",INDEX(Data_Checks!$H:$H,38+1)) -> Statement is -0.01% vs our logs
A43: =IF(INDEX(Data_Checks!$A:$A,39+1)="","",INDEX(Data_Checks!$A:$A,39+1)) -> 8 | B43: =IF(INDEX(Data_Checks!$B:$B,39+1)="","",INDEX(Data_Checks!$B:$B,39+1)) -> Gateway statement matches our logs | C43: =IF(INDEX(Data_Checks!$C:$C,39+1)="","",INDEX(Data_Checks!$C:$C,39+1)) -> vercel 2026-10 | D43: =IF(INDEX(Data_Checks!$D:$D,39+1)="","",INDEX(Data_Checks!$D:$D,39+1)) -> 16337845301 | E43: =IF(INDEX(Data_Checks!$E:$E,39+1)="","",INDEX(Data_Checks!$E:$E,39+1)) -> 16338000000 | F43: =IF(INDEX(Data_Checks!$F:$F,39+1)="","",INDEX(Data_Checks!$F:$F,39+1)) -> 0.0061724901 | G43: =IF(INDEX(Data_Checks!$G:$G,39+1)="","",INDEX(Data_Checks!$G:$G,39+1)) -> PASS | H43: =IF(INDEX(Data_Checks!$H:$H,39+1)="","",INDEX(Data_Checks!$H:$H,39+1)) -> Statement is 0.0% vs our logs
A44: =IF(INDEX(Data_Checks!$A:$A,40+1)="","",INDEX(Data_Checks!$A:$A,40+1)) -> 8 | B44: =IF(INDEX(Data_Checks!$B:$B,40+1)="","",INDEX(Data_Checks!$B:$B,40+1)) -> Gateway statement matches our logs | C44: =IF(INDEX(Data_Checks!$C:$C,40+1)="","",INDEX(Data_Checks!$C:$C,40+1)) -> vercel 2026-11 | D44: =IF(INDEX(Data_Checks!$D:$D,40+1)="","",INDEX(Data_Checks!$D:$D,40+1)) -> 113741699989 | E44: =IF(INDEX(Data_Checks!$E:$E,40+1)="","",INDEX(Data_Checks!$E:$E,40+1)) -> 113742000000 | F44: =IF(INDEX(Data_Checks!$F:$F,40+1)="","",INDEX(Data_Checks!$F:$F,40+1)) -> 0.011970439 | G44: =IF(INDEX(Data_Checks!$G:$G,40+1)="","",INDEX(Data_Checks!$G:$G,40+1)) -> PASS | H44: =IF(INDEX(Data_Checks!$H:$H,40+1)="","",INDEX(Data_Checks!$H:$H,40+1)) -> Statement is 0.0% vs our logs
A45: =IF(INDEX(Data_Checks!$A:$A,41+1)="","",INDEX(Data_Checks!$A:$A,41+1)) -> 8 | B45: =IF(INDEX(Data_Checks!$B:$B,41+1)="","",INDEX(Data_Checks!$B:$B,41+1)) -> Gateway statement matches our logs | C45: =IF(INDEX(Data_Checks!$C:$C,41+1)="","",INDEX(Data_Checks!$C:$C,41+1)) -> vercel 2026-12 | D45: =IF(INDEX(Data_Checks!$D:$D,41+1)="","",INDEX(Data_Checks!$D:$D,41+1)) -> 319660762488 | E45: =IF(INDEX(Data_Checks!$E:$E,41+1)="","",INDEX(Data_Checks!$E:$E,41+1)) -> 319661000000 | F45: =IF(INDEX(Data_Checks!$F:$F,41+1)="","",INDEX(Data_Checks!$F:$F,41+1)) -> 0.0094767288 | G45: =IF(INDEX(Data_Checks!$G:$G,41+1)="","",INDEX(Data_Checks!$G:$G,41+1)) -> PASS | H45: =IF(INDEX(Data_Checks!$H:$H,41+1)="","",INDEX(Data_Checks!$H:$H,41+1)) -> Statement is 0.0% vs our logs
A46: =IF(INDEX(Data_Checks!$A:$A,42+1)="","",INDEX(Data_Checks!$A:$A,42+1)) -> 8 | B46: =IF(INDEX(Data_Checks!$B:$B,42+1)="","",INDEX(Data_Checks!$B:$B,42+1)) -> Gateway statement matches our logs | C46: =IF(INDEX(Data_Checks!$C:$C,42+1)="","",INDEX(Data_Checks!$C:$C,42+1)) -> vercel 2027-01 | D46: =IF(INDEX(Data_Checks!$D:$D,42+1)="","",INDEX(Data_Checks!$D:$D,42+1)) -> 410116582141 | E46: =IF(INDEX(Data_Checks!$E:$E,42+1)="","",INDEX(Data_Checks!$E:$E,42+1)) -> 410117000000 | F46: =IF(INDEX(Data_Checks!$F:$F,42+1)="","",INDEX(Data_Checks!$F:$F,42+1)) -> 0.016672574 | G46: =IF(INDEX(Data_Checks!$G:$G,42+1)="","",INDEX(Data_Checks!$G:$G,42+1)) -> PASS | H46: =IF(INDEX(Data_Checks!$H:$H,42+1)="","",INDEX(Data_Checks!$H:$H,42+1)) -> Statement is 0.0% vs our logs
A47: =IF(INDEX(Data_Checks!$A:$A,43+1)="","",INDEX(Data_Checks!$A:$A,43+1)) -> 8 | B47: =IF(INDEX(Data_Checks!$B:$B,43+1)="","",INDEX(Data_Checks!$B:$B,43+1)) -> Gateway statement matches our logs | C47: =IF(INDEX(Data_Checks!$C:$C,43+1)="","",INDEX(Data_Checks!$C:$C,43+1)) -> vercel 2027-02 | D47: =IF(INDEX(Data_Checks!$D:$D,43+1)="","",INDEX(Data_Checks!$D:$D,43+1)) -> 456562117440 | E47: =IF(INDEX(Data_Checks!$E:$E,43+1)="","",INDEX(Data_Checks!$E:$E,43+1)) -> 456562000000 | F47: =IF(INDEX(Data_Checks!$F:$F,43+1)="","",INDEX(Data_Checks!$F:$F,43+1)) -> -0.004685856 | G47: =IF(INDEX(Data_Checks!$G:$G,43+1)="","",INDEX(Data_Checks!$G:$G,43+1)) -> PASS | H47: =IF(INDEX(Data_Checks!$H:$H,43+1)="","",INDEX(Data_Checks!$H:$H,43+1)) -> Statement is -0.0% vs our logs
A48: =IF(INDEX(Data_Checks!$A:$A,44+1)="","",INDEX(Data_Checks!$A:$A,44+1)) -> 9 | B48: =IF(INDEX(Data_Checks!$B:$B,44+1)="","",INDEX(Data_Checks!$B:$B,44+1)) -> Gateway remittance = gross less agreed fee | C48: =IF(INDEX(Data_Checks!$C:$C,44+1)="","",INDEX(Data_Checks!$C:$C,44+1)) -> digitalocean 2026-09 | D48: =IF(INDEX(Data_Checks!$D:$D,44+1)="","",INDEX(Data_Checks!$D:$D,44+1)) -> 16.4588 | E48: =IF(INDEX(Data_Checks!$E:$E,44+1)="","",INDEX(Data_Checks!$E:$E,44+1)) -> 16.46 | F48: =IF(INDEX(Data_Checks!$F:$F,44+1)="","",INDEX(Data_Checks!$F:$F,44+1)) -> 0.0012 | G48: =IF(INDEX(Data_Checks!$G:$G,44+1)="","",INDEX(Data_Checks!$G:$G,44+1)) -> PASS | H48: =IF(INDEX(Data_Checks!$H:$H,44+1)="","",INDEX(Data_Checks!$H:$H,44+1)) -> Agreed fee 8.0% (config), statement fee 8.0%
A49: =IF(INDEX(Data_Checks!$A:$A,45+1)="","",INDEX(Data_Checks!$A:$A,45+1)) -> 9 | B49: =IF(INDEX(Data_Checks!$B:$B,45+1)="","",INDEX(Data_Checks!$B:$B,45+1)) -> Gateway remittance = gross less agreed fee | C49: =IF(INDEX(Data_Checks!$C:$C,45+1)="","",INDEX(Data_Checks!$C:$C,45+1)) -> digitalocean 2026-10 | D49: =IF(INDEX(Data_Checks!$D:$D,45+1)="","",INDEX(Data_Checks!$D:$D,45+1)) -> 40.802 | E49: =IF(INDEX(Data_Checks!$E:$E,45+1)="","",INDEX(Data_Checks!$E:$E,45+1)) -> 40.8 | F49: =IF(INDEX(Data_Checks!$F:$F,45+1)="","",INDEX(Data_Checks!$F:$F,45+1)) -> -0.002 | G49: =IF(INDEX(Data_Checks!$G:$G,45+1)="","",INDEX(Data_Checks!$G:$G,45+1)) -> PASS | H49: =IF(INDEX(Data_Checks!$H:$H,45+1)="","",INDEX(Data_Checks!$H:$H,45+1)) -> Agreed fee 8.0% (config), statement fee 8.0%
A50: =IF(INDEX(Data_Checks!$A:$A,46+1)="","",INDEX(Data_Checks!$A:$A,46+1)) -> 9 | B50: =IF(INDEX(Data_Checks!$B:$B,46+1)="","",INDEX(Data_Checks!$B:$B,46+1)) -> Gateway remittance = gross less agreed fee | C50: =IF(INDEX(Data_Checks!$C:$C,46+1)="","",INDEX(Data_Checks!$C:$C,46+1)) -> digitalocean 2026-11 | D50: =IF(INDEX(Data_Checks!$D:$D,46+1)="","",INDEX(Data_Checks!$D:$D,46+1)) -> 81.7236 | E50: =IF(INDEX(Data_Checks!$E:$E,46+1)="","",INDEX(Data_Checks!$E:$E,46+1)) -> 81.72 | F50: =IF(INDEX(Data_Checks!$F:$F,46+1)="","",INDEX(Data_Checks!$F:$F,46+1)) -> -0.0036 | G50: =IF(INDEX(Data_Checks!$G:$G,46+1)="","",INDEX(Data_Checks!$G:$G,46+1)) -> PASS | H50: =IF(INDEX(Data_Checks!$H:$H,46+1)="","",INDEX(Data_Checks!$H:$H,46+1)) -> Agreed fee 8.0% (config), statement fee 8.0%
A51: =IF(INDEX(Data_Checks!$A:$A,47+1)="","",INDEX(Data_Checks!$A:$A,47+1)) -> 9 | B51: =IF(INDEX(Data_Checks!$B:$B,47+1)="","",INDEX(Data_Checks!$B:$B,47+1)) -> Gateway remittance = gross less agreed fee | C51: =IF(INDEX(Data_Checks!$C:$C,47+1)="","",INDEX(Data_Checks!$C:$C,47+1)) -> digitalocean 2026-12 | D51: =IF(INDEX(Data_Checks!$D:$D,47+1)="","",INDEX(Data_Checks!$D:$D,47+1)) -> 288.4844 | E51: =IF(INDEX(Data_Checks!$E:$E,47+1)="","",INDEX(Data_Checks!$E:$E,47+1)) -> 288.48 | F51: =IF(INDEX(Data_Checks!$F:$F,47+1)="","",INDEX(Data_Checks!$F:$F,47+1)) -> -0.0044 | G51: =IF(INDEX(Data_Checks!$G:$G,47+1)="","",INDEX(Data_Checks!$G:$G,47+1)) -> PASS | H51: =IF(INDEX(Data_Checks!$H:$H,47+1)="","",INDEX(Data_Checks!$H:$H,47+1)) -> Agreed fee 8.0% (config), statement fee 8.0%
A52: =IF(INDEX(Data_Checks!$A:$A,48+1)="","",INDEX(Data_Checks!$A:$A,48+1)) -> 9 | B52: =IF(INDEX(Data_Checks!$B:$B,48+1)="","",INDEX(Data_Checks!$B:$B,48+1)) -> Gateway remittance = gross less agreed fee | C52: =IF(INDEX(Data_Checks!$C:$C,48+1)="","",INDEX(Data_Checks!$C:$C,48+1)) -> digitalocean 2027-01 | D52: =IF(INDEX(Data_Checks!$D:$D,48+1)="","",INDEX(Data_Checks!$D:$D,48+1)) -> 492.154 | E52: =IF(INDEX(Data_Checks!$E:$E,48+1)="","",INDEX(Data_Checks!$E:$E,48+1)) -> 492.15 | F52: =IF(INDEX(Data_Checks!$F:$F,48+1)="","",INDEX(Data_Checks!$F:$F,48+1)) -> -0.004 | G52: =IF(INDEX(Data_Checks!$G:$G,48+1)="","",INDEX(Data_Checks!$G:$G,48+1)) -> PASS | H52: =IF(INDEX(Data_Checks!$H:$H,48+1)="","",INDEX(Data_Checks!$H:$H,48+1)) -> Agreed fee 8.0% (config), statement fee 8.0%
A53: =IF(INDEX(Data_Checks!$A:$A,49+1)="","",INDEX(Data_Checks!$A:$A,49+1)) -> 9 | B53: =IF(INDEX(Data_Checks!$B:$B,49+1)="","",INDEX(Data_Checks!$B:$B,49+1)) -> Gateway remittance = gross less agreed fee | C53: =IF(INDEX(Data_Checks!$C:$C,49+1)="","",INDEX(Data_Checks!$C:$C,49+1)) -> digitalocean 2027-02 | D53: =IF(INDEX(Data_Checks!$D:$D,49+1)="","",INDEX(Data_Checks!$D:$D,49+1)) -> 579.094 | E53: =IF(INDEX(Data_Checks!$E:$E,49+1)="","",INDEX(Data_Checks!$E:$E,49+1)) -> 579.09 | F53: =IF(INDEX(Data_Checks!$F:$F,49+1)="","",INDEX(Data_Checks!$F:$F,49+1)) -> -0.004 | G53: =IF(INDEX(Data_Checks!$G:$G,49+1)="","",INDEX(Data_Checks!$G:$G,49+1)) -> PASS | H53: =IF(INDEX(Data_Checks!$H:$H,49+1)="","",INDEX(Data_Checks!$H:$H,49+1)) -> Agreed fee 8.0% (config), statement fee 8.0%
A54: =IF(INDEX(Data_Checks!$A:$A,50+1)="","",INDEX(Data_Checks!$A:$A,50+1)) -> 9 | B54: =IF(INDEX(Data_Checks!$B:$B,50+1)="","",INDEX(Data_Checks!$B:$B,50+1)) -> Gateway remittance = gross less agreed fee | C54: =IF(INDEX(Data_Checks!$C:$C,50+1)="","",INDEX(Data_Checks!$C:$C,50+1)) -> openrouter 2026-09 | D54: =IF(INDEX(Data_Checks!$D:$D,50+1)="","",INDEX(Data_Checks!$D:$D,50+1)) -> 48.9155 | E54: =IF(INDEX(Data_Checks!$E:$E,50+1)="","",INDEX(Data_Checks!$E:$E,50+1)) -> 48.92 | F54: =IF(INDEX(Data_Checks!$F:$F,50+1)="","",INDEX(Data_Checks!$F:$F,50+1)) -> 0.0045 | G54: =IF(INDEX(Data_Checks!$G:$G,50+1)="","",INDEX(Data_Checks!$G:$G,50+1)) -> PASS | H54: =IF(INDEX(Data_Checks!$H:$H,50+1)="","",INDEX(Data_Checks!$H:$H,50+1)) -> Agreed fee 5.0% (config), statement fee 5.0%
A55: =IF(INDEX(Data_Checks!$A:$A,51+1)="","",INDEX(Data_Checks!$A:$A,51+1)) -> 9 | B55: =IF(INDEX(Data_Checks!$B:$B,51+1)="","",INDEX(Data_Checks!$B:$B,51+1)) -> Gateway remittance = gross less agreed fee | C55: =IF(INDEX(Data_Checks!$C:$C,51+1)="","",INDEX(Data_Checks!$C:$C,51+1)) -> openrouter 2026-10 | D55: =IF(INDEX(Data_Checks!$D:$D,51+1)="","",INDEX(Data_Checks!$D:$D,51+1)) -> 401.356 | E55: =IF(INDEX(Data_Checks!$E:$E,51+1)="","",INDEX(Data_Checks!$E:$E,51+1)) -> 401.36 | F55: =IF(INDEX(Data_Checks!$F:$F,51+1)="","",INDEX(Data_Checks!$F:$F,51+1)) -> 0.004 | G55: =IF(INDEX(Data_Checks!$G:$G,51+1)="","",INDEX(Data_Checks!$G:$G,51+1)) -> PASS | H55: =IF(INDEX(Data_Checks!$H:$H,51+1)="","",INDEX(Data_Checks!$H:$H,51+1)) -> Agreed fee 5.0% (config), statement fee 5.0%
A56: =IF(INDEX(Data_Checks!$A:$A,52+1)="","",INDEX(Data_Checks!$A:$A,52+1)) -> 9 | B56: =IF(INDEX(Data_Checks!$B:$B,52+1)="","",INDEX(Data_Checks!$B:$B,52+1)) -> Gateway remittance = gross less agreed fee | C56: =IF(INDEX(Data_Checks!$C:$C,52+1)="","",INDEX(Data_Checks!$C:$C,52+1)) -> openrouter 2026-11 | D56: =IF(INDEX(Data_Checks!$D:$D,52+1)="","",INDEX(Data_Checks!$D:$D,52+1)) -> 1850.163 | E56: =IF(INDEX(Data_Checks!$E:$E,52+1)="","",INDEX(Data_Checks!$E:$E,52+1)) -> 1850.16 | F56: =IF(INDEX(Data_Checks!$F:$F,52+1)="","",INDEX(Data_Checks!$F:$F,52+1)) -> -0.003 | G56: =IF(INDEX(Data_Checks!$G:$G,52+1)="","",INDEX(Data_Checks!$G:$G,52+1)) -> PASS | H56: =IF(INDEX(Data_Checks!$H:$H,52+1)="","",INDEX(Data_Checks!$H:$H,52+1)) -> Agreed fee 5.0% (config), statement fee 5.0%
A57: =IF(INDEX(Data_Checks!$A:$A,53+1)="","",INDEX(Data_Checks!$A:$A,53+1)) -> 9 | B57: =IF(INDEX(Data_Checks!$B:$B,53+1)="","",INDEX(Data_Checks!$B:$B,53+1)) -> Gateway remittance = gross less agreed fee | C57: =IF(INDEX(Data_Checks!$C:$C,53+1)="","",INDEX(Data_Checks!$C:$C,53+1)) -> openrouter 2026-12 | D57: =IF(INDEX(Data_Checks!$D:$D,53+1)="","",INDEX(Data_Checks!$D:$D,53+1)) -> 6603.1745 | E57: =IF(INDEX(Data_Checks!$E:$E,53+1)="","",INDEX(Data_Checks!$E:$E,53+1)) -> 6603.17 | F57: =IF(INDEX(Data_Checks!$F:$F,53+1)="","",INDEX(Data_Checks!$F:$F,53+1)) -> -0.0045 | G57: =IF(INDEX(Data_Checks!$G:$G,53+1)="","",INDEX(Data_Checks!$G:$G,53+1)) -> PASS | H57: =IF(INDEX(Data_Checks!$H:$H,53+1)="","",INDEX(Data_Checks!$H:$H,53+1)) -> Agreed fee 5.0% (config), statement fee 5.0%
A58: =IF(INDEX(Data_Checks!$A:$A,54+1)="","",INDEX(Data_Checks!$A:$A,54+1)) -> 9 | B58: =IF(INDEX(Data_Checks!$B:$B,54+1)="","",INDEX(Data_Checks!$B:$B,54+1)) -> Gateway remittance = gross less agreed fee | C58: =IF(INDEX(Data_Checks!$C:$C,54+1)="","",INDEX(Data_Checks!$C:$C,54+1)) -> openrouter 2027-01 | D58: =IF(INDEX(Data_Checks!$D:$D,54+1)="","",INDEX(Data_Checks!$D:$D,54+1)) -> 12231.744 | E58: =IF(INDEX(Data_Checks!$E:$E,54+1)="","",INDEX(Data_Checks!$E:$E,54+1)) -> 12231.74 | F58: =IF(INDEX(Data_Checks!$F:$F,54+1)="","",INDEX(Data_Checks!$F:$F,54+1)) -> -0.004 | G58: =IF(INDEX(Data_Checks!$G:$G,54+1)="","",INDEX(Data_Checks!$G:$G,54+1)) -> PASS | H58: =IF(INDEX(Data_Checks!$H:$H,54+1)="","",INDEX(Data_Checks!$H:$H,54+1)) -> Agreed fee 5.0% (config), statement fee 5.0%
A59: =IF(INDEX(Data_Checks!$A:$A,55+1)="","",INDEX(Data_Checks!$A:$A,55+1)) -> 9 | B59: =IF(INDEX(Data_Checks!$B:$B,55+1)="","",INDEX(Data_Checks!$B:$B,55+1)) -> Gateway remittance = gross less agreed fee | C59: =IF(INDEX(Data_Checks!$C:$C,55+1)="","",INDEX(Data_Checks!$C:$C,55+1)) -> openrouter 2027-02 | D59: =IF(INDEX(Data_Checks!$D:$D,55+1)="","",INDEX(Data_Checks!$D:$D,55+1)) -> 14783.71 | E59: =IF(INDEX(Data_Checks!$E:$E,55+1)="","",INDEX(Data_Checks!$E:$E,55+1)) -> 14783.71 | F59: =IF(INDEX(Data_Checks!$F:$F,55+1)="","",INDEX(Data_Checks!$F:$F,55+1)) -> 0 | G59: =IF(INDEX(Data_Checks!$G:$G,55+1)="","",INDEX(Data_Checks!$G:$G,55+1)) -> PASS | H59: =IF(INDEX(Data_Checks!$H:$H,55+1)="","",INDEX(Data_Checks!$H:$H,55+1)) -> Agreed fee 5.0% (config), statement fee 5.0%
A60: =IF(INDEX(Data_Checks!$A:$A,56+1)="","",INDEX(Data_Checks!$A:$A,56+1)) -> 9 | B60: =IF(INDEX(Data_Checks!$B:$B,56+1)="","",INDEX(Data_Checks!$B:$B,56+1)) -> Gateway remittance = gross less agreed fee | C60: =IF(INDEX(Data_Checks!$C:$C,56+1)="","",INDEX(Data_Checks!$C:$C,56+1)) -> vercel 2026-09 | D60: =IF(INDEX(Data_Checks!$D:$D,56+1)="","",INDEX(Data_Checks!$D:$D,56+1)) -> 100.3865 | E60: =IF(INDEX(Data_Checks!$E:$E,56+1)="","",INDEX(Data_Checks!$E:$E,56+1)) -> 100.39 | F60: =IF(INDEX(Data_Checks!$F:$F,56+1)="","",INDEX(Data_Checks!$F:$F,56+1)) -> 0.0035 | G60: =IF(INDEX(Data_Checks!$G:$G,56+1)="","",INDEX(Data_Checks!$G:$G,56+1)) -> PASS | H60: =IF(INDEX(Data_Checks!$H:$H,56+1)="","",INDEX(Data_Checks!$H:$H,56+1)) -> Agreed fee 5.0% (config), statement fee 5.0%
A61: =IF(INDEX(Data_Checks!$A:$A,57+1)="","",INDEX(Data_Checks!$A:$A,57+1)) -> 9 | B61: =IF(INDEX(Data_Checks!$B:$B,57+1)="","",INDEX(Data_Checks!$B:$B,57+1)) -> Gateway remittance = gross less agreed fee | C61: =IF(INDEX(Data_Checks!$C:$C,57+1)="","",INDEX(Data_Checks!$C:$C,57+1)) -> vercel 2026-10 | D61: =IF(INDEX(Data_Checks!$D:$D,57+1)="","",INDEX(Data_Checks!$D:$D,57+1)) -> 651.89 | E61: =IF(INDEX(Data_Checks!$E:$E,57+1)="","",INDEX(Data_Checks!$E:$E,57+1)) -> 651.89 | F61: =IF(INDEX(Data_Checks!$F:$F,57+1)="","",INDEX(Data_Checks!$F:$F,57+1)) -> 0 | G61: =IF(INDEX(Data_Checks!$G:$G,57+1)="","",INDEX(Data_Checks!$G:$G,57+1)) -> PASS | H61: =IF(INDEX(Data_Checks!$H:$H,57+1)="","",INDEX(Data_Checks!$H:$H,57+1)) -> Agreed fee 5.0% (config), statement fee 5.0%
A62: =IF(INDEX(Data_Checks!$A:$A,58+1)="","",INDEX(Data_Checks!$A:$A,58+1)) -> 9 | B62: =IF(INDEX(Data_Checks!$B:$B,58+1)="","",INDEX(Data_Checks!$B:$B,58+1)) -> Gateway remittance = gross less agreed fee | C62: =IF(INDEX(Data_Checks!$C:$C,58+1)="","",INDEX(Data_Checks!$C:$C,58+1)) -> vercel 2026-11 | D62: =IF(INDEX(Data_Checks!$D:$D,58+1)="","",INDEX(Data_Checks!$D:$D,58+1)) -> 4538.302 | E62: =IF(INDEX(Data_Checks!$E:$E,58+1)="","",INDEX(Data_Checks!$E:$E,58+1)) -> 4538.3 | F62: =IF(INDEX(Data_Checks!$F:$F,58+1)="","",INDEX(Data_Checks!$F:$F,58+1)) -> -0.002 | G62: =IF(INDEX(Data_Checks!$G:$G,58+1)="","",INDEX(Data_Checks!$G:$G,58+1)) -> PASS | H62: =IF(INDEX(Data_Checks!$H:$H,58+1)="","",INDEX(Data_Checks!$H:$H,58+1)) -> Agreed fee 5.0% (config), statement fee 5.0%
A63: =IF(INDEX(Data_Checks!$A:$A,59+1)="","",INDEX(Data_Checks!$A:$A,59+1)) -> 9 | B63: =IF(INDEX(Data_Checks!$B:$B,59+1)="","",INDEX(Data_Checks!$B:$B,59+1)) -> Gateway remittance = gross less agreed fee | C63: =IF(INDEX(Data_Checks!$C:$C,59+1)="","",INDEX(Data_Checks!$C:$C,59+1)) -> vercel 2026-12 | D63: =IF(INDEX(Data_Checks!$D:$D,59+1)="","",INDEX(Data_Checks!$D:$D,59+1)) -> 12754.472 | E63: =IF(INDEX(Data_Checks!$E:$E,59+1)="","",INDEX(Data_Checks!$E:$E,59+1)) -> 12754.47 | F63: =IF(INDEX(Data_Checks!$F:$F,59+1)="","",INDEX(Data_Checks!$F:$F,59+1)) -> -0.002 | G63: =IF(INDEX(Data_Checks!$G:$G,59+1)="","",INDEX(Data_Checks!$G:$G,59+1)) -> PASS | H63: =IF(INDEX(Data_Checks!$H:$H,59+1)="","",INDEX(Data_Checks!$H:$H,59+1)) -> Agreed fee 5.0% (config), statement fee 5.0%
A64: =IF(INDEX(Data_Checks!$A:$A,60+1)="","",INDEX(Data_Checks!$A:$A,60+1)) -> 9 | B64: =IF(INDEX(Data_Checks!$B:$B,60+1)="","",INDEX(Data_Checks!$B:$B,60+1)) -> Gateway remittance = gross less agreed fee | C64: =IF(INDEX(Data_Checks!$C:$C,60+1)="","",INDEX(Data_Checks!$C:$C,60+1)) -> vercel 2027-01 | D64: =IF(INDEX(Data_Checks!$D:$D,60+1)="","",INDEX(Data_Checks!$D:$D,60+1)) -> 16363.665 | E64: =IF(INDEX(Data_Checks!$E:$E,60+1)="","",INDEX(Data_Checks!$E:$E,60+1)) -> 16363.66 | F64: =IF(INDEX(Data_Checks!$F:$F,60+1)="","",INDEX(Data_Checks!$F:$F,60+1)) -> -0.0045 | G64: =IF(INDEX(Data_Checks!$G:$G,60+1)="","",INDEX(Data_Checks!$G:$G,60+1)) -> PASS | H64: =IF(INDEX(Data_Checks!$H:$H,60+1)="","",INDEX(Data_Checks!$H:$H,60+1)) -> Agreed fee 5.0% (config), statement fee 5.0%
A65: =IF(INDEX(Data_Checks!$A:$A,61+1)="","",INDEX(Data_Checks!$A:$A,61+1)) -> 9 | B65: =IF(INDEX(Data_Checks!$B:$B,61+1)="","",INDEX(Data_Checks!$B:$B,61+1)) -> Gateway remittance = gross less agreed fee | C65: =IF(INDEX(Data_Checks!$C:$C,61+1)="","",INDEX(Data_Checks!$C:$C,61+1)) -> vercel 2027-02 | D65: =IF(INDEX(Data_Checks!$D:$D,61+1)="","",INDEX(Data_Checks!$D:$D,61+1)) -> 18216.82 | E65: =IF(INDEX(Data_Checks!$E:$E,61+1)="","",INDEX(Data_Checks!$E:$E,61+1)) -> 18216.82 | F65: =IF(INDEX(Data_Checks!$F:$F,61+1)="","",INDEX(Data_Checks!$F:$F,61+1)) -> 3.6379788e-12 | G65: =IF(INDEX(Data_Checks!$G:$G,61+1)="","",INDEX(Data_Checks!$G:$G,61+1)) -> PASS | H65: =IF(INDEX(Data_Checks!$H:$H,61+1)="","",INDEX(Data_Checks!$H:$H,61+1)) -> Agreed fee 5.0% (config), statement fee 5.0%
A66: =IF(INDEX(Data_Checks!$A:$A,62+1)="","",INDEX(Data_Checks!$A:$A,62+1)) -> 11 | B66: =IF(INDEX(Data_Checks!$B:$B,62+1)="","",INDEX(Data_Checks!$B:$B,62+1)) -> Top-3 customer concentration | C66: =IF(INDEX(Data_Checks!$C:$C,62+1)="","",INDEX(Data_Checks!$C:$C,62+1)) -> 2027-02 | D66: =IF(INDEX(Data_Checks!$D:$D,62+1)="","",INDEX(Data_Checks!$D:$D,62+1)) -> 0.5 | E66: =IF(INDEX(Data_Checks!$E:$E,62+1)="","",INDEX(Data_Checks!$E:$E,62+1)) -> 0.4624076 | F66: =IF(INDEX(Data_Checks!$F:$F,62+1)="","",INDEX(Data_Checks!$F:$F,62+1)) -> 0 | G66: =IF(INDEX(Data_Checks!$G:$G,62+1)="","",INDEX(Data_Checks!$G:$G,62+1)) -> PASS | H66: =IF(INDEX(Data_Checks!$H:$H,62+1)="","",INDEX(Data_Checks!$H:$H,62+1)) -> Top 3 accounts = 46.0% of net revenue
A67: =IF(INDEX(Data_Checks!$A:$A,63+1)="","",INDEX(Data_Checks!$A:$A,63+1)) -> 12 | B67: =IF(INDEX(Data_Checks!$B:$B,63+1)="","",INDEX(Data_Checks!$B:$B,63+1)) -> Use case known for most usage | C67: =IF(INDEX(Data_Checks!$C:$C,63+1)="","",INDEX(Data_Checks!$C:$C,63+1)) -> 2027-02 | D67: =IF(INDEX(Data_Checks!$D:$D,63+1)="","",INDEX(Data_Checks!$D:$D,63+1)) -> 0.2 | E67: =IF(INDEX(Data_Checks!$E:$E,63+1)="","",INDEX(Data_Checks!$E:$E,63+1)) -> 0 | F67: =IF(INDEX(Data_Checks!$F:$F,63+1)="","",INDEX(Data_Checks!$F:$F,63+1)) -> 0 | G67: =IF(INDEX(Data_Checks!$G:$G,63+1)="","",INDEX(Data_Checks!$G:$G,63+1)) -> PASS | H67: =IF(INDEX(Data_Checks!$H:$H,63+1)="","",INDEX(Data_Checks!$H:$H,63+1)) -> Share of tokens with no label and no inferred use case
A68: =IF(INDEX(Data_Checks!$A:$A,64+1)="","",INDEX(Data_Checks!$A:$A,64+1)) | B68: =IF(INDEX(Data_Checks!$B:$B,64+1)="","",INDEX(Data_Checks!$B:$B,64+1)) | C68: =IF(INDEX(Data_Checks!$C:$C,64+1)="","",INDEX(Data_Checks!$C:$C,64+1)) | D68: =IF(INDEX(Data_Checks!$D:$D,64+1)="","",INDEX(Data_Checks!$D:$D,64+1)) | E68: =IF(INDEX(Data_Checks!$E:$E,64+1)="","",INDEX(Data_Checks!$E:$E,64+1)) | F68: =IF(INDEX(Data_Checks!$F:$F,64+1)="","",INDEX(Data_Checks!$F:$F,64+1)) | G68: =IF(INDEX(Data_Checks!$G:$G,64+1)="","",INDEX(Data_Checks!$G:$G,64+1)) | H68: =IF(INDEX(Data_Checks!$H:$H,64+1)="","",INDEX(Data_Checks!$H:$H,64+1))
A69: =IF(INDEX(Data_Checks!$A:$A,65+1)="","",INDEX(Data_Checks!$A:$A,65+1)) | B69: =IF(INDEX(Data_Checks!$B:$B,65+1)="","",INDEX(Data_Checks!$B:$B,65+1)) | C69: =IF(INDEX(Data_Checks!$C:$C,65+1)="","",INDEX(Data_Checks!$C:$C,65+1)) | D69: =IF(INDEX(Data_Checks!$D:$D,65+1)="","",INDEX(Data_Checks!$D:$D,65+1)) | E69: =IF(INDEX(Data_Checks!$E:$E,65+1)="","",INDEX(Data_Checks!$E:$E,65+1)) | F69: =IF(INDEX(Data_Checks!$F:$F,65+1)="","",INDEX(Data_Checks!$F:$F,65+1)) | G69: =IF(INDEX(Data_Checks!$G:$G,65+1)="","",INDEX(Data_Checks!$G:$G,65+1)) | H69: =IF(INDEX(Data_Checks!$H:$H,65+1)="","",INDEX(Data_Checks!$H:$H,65+1))
A70: =IF(INDEX(Data_Checks!$A:$A,66+1)="","",INDEX(Data_Checks!$A:$A,66+1)) | B70: =IF(INDEX(Data_Checks!$B:$B,66+1)="","",INDEX(Data_Checks!$B:$B,66+1)) | C70: =IF(INDEX(Data_Checks!$C:$C,66+1)="","",INDEX(Data_Checks!$C:$C,66+1)) | D70: =IF(INDEX(Data_Checks!$D:$D,66+1)="","",INDEX(Data_Checks!$D:$D,66+1)) | E70: =IF(INDEX(Data_Checks!$E:$E,66+1)="","",INDEX(Data_Checks!$E:$E,66+1)) | F70: =IF(INDEX(Data_Checks!$F:$F,66+1)="","",INDEX(Data_Checks!$F:$F,66+1)) | G70: =IF(INDEX(Data_Checks!$G:$G,66+1)="","",INDEX(Data_Checks!$G:$G,66+1)) | H70: =IF(INDEX(Data_Checks!$H:$H,66+1)="","",INDEX(Data_Checks!$H:$H,66+1))
A71: =IF(INDEX(Data_Checks!$A:$A,67+1)="","",INDEX(Data_Checks!$A:$A,67+1)) | B71: =IF(INDEX(Data_Checks!$B:$B,67+1)="","",INDEX(Data_Checks!$B:$B,67+1)) | C71: =IF(INDEX(Data_Checks!$C:$C,67+1)="","",INDEX(Data_Checks!$C:$C,67+1)) | D71: =IF(INDEX(Data_Checks!$D:$D,67+1)="","",INDEX(Data_Checks!$D:$D,67+1)) | E71: =IF(INDEX(Data_Checks!$E:$E,67+1)="","",INDEX(Data_Checks!$E:$E,67+1)) | F71: =IF(INDEX(Data_Checks!$F:$F,67+1)="","",INDEX(Data_Checks!$F:$F,67+1)) | G71: =IF(INDEX(Data_Checks!$G:$G,67+1)="","",INDEX(Data_Checks!$G:$G,67+1)) | H71: =IF(INDEX(Data_Checks!$H:$H,67+1)="","",INDEX(Data_Checks!$H:$H,67+1))
A72: =IF(INDEX(Data_Checks!$A:$A,68+1)="","",INDEX(Data_Checks!$A:$A,68+1)) | B72: =IF(INDEX(Data_Checks!$B:$B,68+1)="","",INDEX(Data_Checks!$B:$B,68+1)) | C72: =IF(INDEX(Data_Checks!$C:$C,68+1)="","",INDEX(Data_Checks!$C:$C,68+1)) | D72: =IF(INDEX(Data_Checks!$D:$D,68+1)="","",INDEX(Data_Checks!$D:$D,68+1)) | E72: =IF(INDEX(Data_Checks!$E:$E,68+1)="","",INDEX(Data_Checks!$E:$E,68+1)) | F72: =IF(INDEX(Data_Checks!$F:$F,68+1)="","",INDEX(Data_Checks!$F:$F,68+1)) | G72: =IF(INDEX(Data_Checks!$G:$G,68+1)="","",INDEX(Data_Checks!$G:$G,68+1)) | H72: =IF(INDEX(Data_Checks!$H:$H,68+1)="","",INDEX(Data_Checks!$H:$H,68+1))
A73: =IF(INDEX(Data_Checks!$A:$A,69+1)="","",INDEX(Data_Checks!$A:$A,69+1)) | B73: =IF(INDEX(Data_Checks!$B:$B,69+1)="","",INDEX(Data_Checks!$B:$B,69+1)) | C73: =IF(INDEX(Data_Checks!$C:$C,69+1)="","",INDEX(Data_Checks!$C:$C,69+1)) | D73: =IF(INDEX(Data_Checks!$D:$D,69+1)="","",INDEX(Data_Checks!$D:$D,69+1)) | E73: =IF(INDEX(Data_Checks!$E:$E,69+1)="","",INDEX(Data_Checks!$E:$E,69+1)) | F73: =IF(INDEX(Data_Checks!$F:$F,69+1)="","",INDEX(Data_Checks!$F:$F,69+1)) | G73: =IF(INDEX(Data_Checks!$G:$G,69+1)="","",INDEX(Data_Checks!$G:$G,69+1)) | H73: =IF(INDEX(Data_Checks!$H:$H,69+1)="","",INDEX(Data_Checks!$H:$H,69+1))
A74: =IF(INDEX(Data_Checks!$A:$A,70+1)="","",INDEX(Data_Checks!$A:$A,70+1)) | B74: =IF(INDEX(Data_Checks!$B:$B,70+1)="","",INDEX(Data_Checks!$B:$B,70+1)) | C74: =IF(INDEX(Data_Checks!$C:$C,70+1)="","",INDEX(Data_Checks!$C:$C,70+1)) | D74: =IF(INDEX(Data_Checks!$D:$D,70+1)="","",INDEX(Data_Checks!$D:$D,70+1)) | E74: =IF(INDEX(Data_Checks!$E:$E,70+1)="","",INDEX(Data_Checks!$E:$E,70+1)) | F74: =IF(INDEX(Data_Checks!$F:$F,70+1)="","",INDEX(Data_Checks!$F:$F,70+1)) | G74: =IF(INDEX(Data_Checks!$G:$G,70+1)="","",INDEX(Data_Checks!$G:$G,70+1)) | H74: =IF(INDEX(Data_Checks!$H:$H,70+1)="","",INDEX(Data_Checks!$H:$H,70+1))
A75: =IF(INDEX(Data_Checks!$A:$A,71+1)="","",INDEX(Data_Checks!$A:$A,71+1)) | B75: =IF(INDEX(Data_Checks!$B:$B,71+1)="","",INDEX(Data_Checks!$B:$B,71+1)) | C75: =IF(INDEX(Data_Checks!$C:$C,71+1)="","",INDEX(Data_Checks!$C:$C,71+1)) | D75: =IF(INDEX(Data_Checks!$D:$D,71+1)="","",INDEX(Data_Checks!$D:$D,71+1)) | E75: =IF(INDEX(Data_Checks!$E:$E,71+1)="","",INDEX(Data_Checks!$E:$E,71+1)) | F75: =IF(INDEX(Data_Checks!$F:$F,71+1)="","",INDEX(Data_Checks!$F:$F,71+1)) | G75: =IF(INDEX(Data_Checks!$G:$G,71+1)="","",INDEX(Data_Checks!$G:$G,71+1)) | H75: =IF(INDEX(Data_Checks!$H:$H,71+1)="","",INDEX(Data_Checks!$H:$H,71+1))
A76: =IF(INDEX(Data_Checks!$A:$A,72+1)="","",INDEX(Data_Checks!$A:$A,72+1)) | B76: =IF(INDEX(Data_Checks!$B:$B,72+1)="","",INDEX(Data_Checks!$B:$B,72+1)) | C76: =IF(INDEX(Data_Checks!$C:$C,72+1)="","",INDEX(Data_Checks!$C:$C,72+1)) | D76: =IF(INDEX(Data_Checks!$D:$D,72+1)="","",INDEX(Data_Checks!$D:$D,72+1)) | E76: =IF(INDEX(Data_Checks!$E:$E,72+1)="","",INDEX(Data_Checks!$E:$E,72+1)) | F76: =IF(INDEX(Data_Checks!$F:$F,72+1)="","",INDEX(Data_Checks!$F:$F,72+1)) | G76: =IF(INDEX(Data_Checks!$G:$G,72+1)="","",INDEX(Data_Checks!$G:$G,72+1)) | H76: =IF(INDEX(Data_Checks!$H:$H,72+1)="","",INDEX(Data_Checks!$H:$H,72+1))
A77: =IF(INDEX(Data_Checks!$A:$A,73+1)="","",INDEX(Data_Checks!$A:$A,73+1)) | B77: =IF(INDEX(Data_Checks!$B:$B,73+1)="","",INDEX(Data_Checks!$B:$B,73+1)) | C77: =IF(INDEX(Data_Checks!$C:$C,73+1)="","",INDEX(Data_Checks!$C:$C,73+1)) | D77: =IF(INDEX(Data_Checks!$D:$D,73+1)="","",INDEX(Data_Checks!$D:$D,73+1)) | E77: =IF(INDEX(Data_Checks!$E:$E,73+1)="","",INDEX(Data_Checks!$E:$E,73+1)) | F77: =IF(INDEX(Data_Checks!$F:$F,73+1)="","",INDEX(Data_Checks!$F:$F,73+1)) | G77: =IF(INDEX(Data_Checks!$G:$G,73+1)="","",INDEX(Data_Checks!$G:$G,73+1)) | H77: =IF(INDEX(Data_Checks!$H:$H,73+1)="","",INDEX(Data_Checks!$H:$H,73+1))
A78: =IF(INDEX(Data_Checks!$A:$A,74+1)="","",INDEX(Data_Checks!$A:$A,74+1)) | B78: =IF(INDEX(Data_Checks!$B:$B,74+1)="","",INDEX(Data_Checks!$B:$B,74+1)) | C78: =IF(INDEX(Data_Checks!$C:$C,74+1)="","",INDEX(Data_Checks!$C:$C,74+1)) | D78: =IF(INDEX(Data_Checks!$D:$D,74+1)="","",INDEX(Data_Checks!$D:$D,74+1)) | E78: =IF(INDEX(Data_Checks!$E:$E,74+1)="","",INDEX(Data_Checks!$E:$E,74+1)) | F78: =IF(INDEX(Data_Checks!$F:$F,74+1)="","",INDEX(Data_Checks!$F:$F,74+1)) | G78: =IF(INDEX(Data_Checks!$G:$G,74+1)="","",INDEX(Data_Checks!$G:$G,74+1)) | H78: =IF(INDEX(Data_Checks!$H:$H,74+1)="","",INDEX(Data_Checks!$H:$H,74+1))
A79: =IF(INDEX(Data_Checks!$A:$A,75+1)="","",INDEX(Data_Checks!$A:$A,75+1)) | B79: =IF(INDEX(Data_Checks!$B:$B,75+1)="","",INDEX(Data_Checks!$B:$B,75+1)) | C79: =IF(INDEX(Data_Checks!$C:$C,75+1)="","",INDEX(Data_Checks!$C:$C,75+1)) | D79: =IF(INDEX(Data_Checks!$D:$D,75+1)="","",INDEX(Data_Checks!$D:$D,75+1)) | E79: =IF(INDEX(Data_Checks!$E:$E,75+1)="","",INDEX(Data_Checks!$E:$E,75+1)) | F79: =IF(INDEX(Data_Checks!$F:$F,75+1)="","",INDEX(Data_Checks!$F:$F,75+1)) | G79: =IF(INDEX(Data_Checks!$G:$G,75+1)="","",INDEX(Data_Checks!$G:$G,75+1)) | H79: =IF(INDEX(Data_Checks!$H:$H,75+1)="","",INDEX(Data_Checks!$H:$H,75+1))
A80: =IF(INDEX(Data_Checks!$A:$A,76+1)="","",INDEX(Data_Checks!$A:$A,76+1)) | B80: =IF(INDEX(Data_Checks!$B:$B,76+1)="","",INDEX(Data_Checks!$B:$B,76+1)) | C80: =IF(INDEX(Data_Checks!$C:$C,76+1)="","",INDEX(Data_Checks!$C:$C,76+1)) | D80: =IF(INDEX(Data_Checks!$D:$D,76+1)="","",INDEX(Data_Checks!$D:$D,76+1)) | E80: =IF(INDEX(Data_Checks!$E:$E,76+1)="","",INDEX(Data_Checks!$E:$E,76+1)) | F80: =IF(INDEX(Data_Checks!$F:$F,76+1)="","",INDEX(Data_Checks!$F:$F,76+1)) | G80: =IF(INDEX(Data_Checks!$G:$G,76+1)="","",INDEX(Data_Checks!$G:$G,76+1)) | H80: =IF(INDEX(Data_Checks!$H:$H,76+1)="","",INDEX(Data_Checks!$H:$H,76+1))
A81: =IF(INDEX(Data_Checks!$A:$A,77+1)="","",INDEX(Data_Checks!$A:$A,77+1)) | B81: =IF(INDEX(Data_Checks!$B:$B,77+1)="","",INDEX(Data_Checks!$B:$B,77+1)) | C81: =IF(INDEX(Data_Checks!$C:$C,77+1)="","",INDEX(Data_Checks!$C:$C,77+1)) | D81: =IF(INDEX(Data_Checks!$D:$D,77+1)="","",INDEX(Data_Checks!$D:$D,77+1)) | E81: =IF(INDEX(Data_Checks!$E:$E,77+1)="","",INDEX(Data_Checks!$E:$E,77+1)) | F81: =IF(INDEX(Data_Checks!$F:$F,77+1)="","",INDEX(Data_Checks!$F:$F,77+1)) | G81: =IF(INDEX(Data_Checks!$G:$G,77+1)="","",INDEX(Data_Checks!$G:$G,77+1)) | H81: =IF(INDEX(Data_Checks!$H:$H,77+1)="","",INDEX(Data_Checks!$H:$H,77+1))
A82: =IF(INDEX(Data_Checks!$A:$A,78+1)="","",INDEX(Data_Checks!$A:$A,78+1)) | B82: =IF(INDEX(Data_Checks!$B:$B,78+1)="","",INDEX(Data_Checks!$B:$B,78+1)) | C82: =IF(INDEX(Data_Checks!$C:$C,78+1)="","",INDEX(Data_Checks!$C:$C,78+1)) | D82: =IF(INDEX(Data_Checks!$D:$D,78+1)="","",INDEX(Data_Checks!$D:$D,78+1)) | E82: =IF(INDEX(Data_Checks!$E:$E,78+1)="","",INDEX(Data_Checks!$E:$E,78+1)) | F82: =IF(INDEX(Data_Checks!$F:$F,78+1)="","",INDEX(Data_Checks!$F:$F,78+1)) | G82: =IF(INDEX(Data_Checks!$G:$G,78+1)="","",INDEX(Data_Checks!$G:$G,78+1)) | H82: =IF(INDEX(Data_Checks!$H:$H,78+1)="","",INDEX(Data_Checks!$H:$H,78+1))
A83: =IF(INDEX(Data_Checks!$A:$A,79+1)="","",INDEX(Data_Checks!$A:$A,79+1)) | B83: =IF(INDEX(Data_Checks!$B:$B,79+1)="","",INDEX(Data_Checks!$B:$B,79+1)) | C83: =IF(INDEX(Data_Checks!$C:$C,79+1)="","",INDEX(Data_Checks!$C:$C,79+1)) | D83: =IF(INDEX(Data_Checks!$D:$D,79+1)="","",INDEX(Data_Checks!$D:$D,79+1)) | E83: =IF(INDEX(Data_Checks!$E:$E,79+1)="","",INDEX(Data_Checks!$E:$E,79+1)) | F83: =IF(INDEX(Data_Checks!$F:$F,79+1)="","",INDEX(Data_Checks!$F:$F,79+1)) | G83: =IF(INDEX(Data_Checks!$G:$G,79+1)="","",INDEX(Data_Checks!$G:$G,79+1)) | H83: =IF(INDEX(Data_Checks!$H:$H,79+1)="","",INDEX(Data_Checks!$H:$H,79+1))
A84: =IF(INDEX(Data_Checks!$A:$A,80+1)="","",INDEX(Data_Checks!$A:$A,80+1)) | B84: =IF(INDEX(Data_Checks!$B:$B,80+1)="","",INDEX(Data_Checks!$B:$B,80+1)) | C84: =IF(INDEX(Data_Checks!$C:$C,80+1)="","",INDEX(Data_Checks!$C:$C,80+1)) | D84: =IF(INDEX(Data_Checks!$D:$D,80+1)="","",INDEX(Data_Checks!$D:$D,80+1)) | E84: =IF(INDEX(Data_Checks!$E:$E,80+1)="","",INDEX(Data_Checks!$E:$E,80+1)) | F84: =IF(INDEX(Data_Checks!$F:$F,80+1)="","",INDEX(Data_Checks!$F:$F,80+1)) | G84: =IF(INDEX(Data_Checks!$G:$G,80+1)="","",INDEX(Data_Checks!$G:$G,80+1)) | H84: =IF(INDEX(Data_Checks!$H:$H,80+1)="","",INDEX(Data_Checks!$H:$H,80+1))
A85: =IF(INDEX(Data_Checks!$A:$A,81+1)="","",INDEX(Data_Checks!$A:$A,81+1)) | B85: =IF(INDEX(Data_Checks!$B:$B,81+1)="","",INDEX(Data_Checks!$B:$B,81+1)) | C85: =IF(INDEX(Data_Checks!$C:$C,81+1)="","",INDEX(Data_Checks!$C:$C,81+1)) | D85: =IF(INDEX(Data_Checks!$D:$D,81+1)="","",INDEX(Data_Checks!$D:$D,81+1)) | E85: =IF(INDEX(Data_Checks!$E:$E,81+1)="","",INDEX(Data_Checks!$E:$E,81+1)) | F85: =IF(INDEX(Data_Checks!$F:$F,81+1)="","",INDEX(Data_Checks!$F:$F,81+1)) | G85: =IF(INDEX(Data_Checks!$G:$G,81+1)="","",INDEX(Data_Checks!$G:$G,81+1)) | H85: =IF(INDEX(Data_Checks!$H:$H,81+1)="","",INDEX(Data_Checks!$H:$H,81+1))
A86: =IF(INDEX(Data_Checks!$A:$A,82+1)="","",INDEX(Data_Checks!$A:$A,82+1)) | B86: =IF(INDEX(Data_Checks!$B:$B,82+1)="","",INDEX(Data_Checks!$B:$B,82+1)) | C86: =IF(INDEX(Data_Checks!$C:$C,82+1)="","",INDEX(Data_Checks!$C:$C,82+1)) | D86: =IF(INDEX(Data_Checks!$D:$D,82+1)="","",INDEX(Data_Checks!$D:$D,82+1)) | E86: =IF(INDEX(Data_Checks!$E:$E,82+1)="","",INDEX(Data_Checks!$E:$E,82+1)) | F86: =IF(INDEX(Data_Checks!$F:$F,82+1)="","",INDEX(Data_Checks!$F:$F,82+1)) | G86: =IF(INDEX(Data_Checks!$G:$G,82+1)="","",INDEX(Data_Checks!$G:$G,82+1)) | H86: =IF(INDEX(Data_Checks!$H:$H,82+1)="","",INDEX(Data_Checks!$H:$H,82+1))
A87: =IF(INDEX(Data_Checks!$A:$A,83+1)="","",INDEX(Data_Checks!$A:$A,83+1)) | B87: =IF(INDEX(Data_Checks!$B:$B,83+1)="","",INDEX(Data_Checks!$B:$B,83+1)) | C87: =IF(INDEX(Data_Checks!$C:$C,83+1)="","",INDEX(Data_Checks!$C:$C,83+1)) | D87: =IF(INDEX(Data_Checks!$D:$D,83+1)="","",INDEX(Data_Checks!$D:$D,83+1)) | E87: =IF(INDEX(Data_Checks!$E:$E,83+1)="","",INDEX(Data_Checks!$E:$E,83+1)) | F87: =IF(INDEX(Data_Checks!$F:$F,83+1)="","",INDEX(Data_Checks!$F:$F,83+1)) | G87: =IF(INDEX(Data_Checks!$G:$G,83+1)="","",INDEX(Data_Checks!$G:$G,83+1)) | H87: =IF(INDEX(Data_Checks!$H:$H,83+1)="","",INDEX(Data_Checks!$H:$H,83+1))
A88: =IF(INDEX(Data_Checks!$A:$A,84+1)="","",INDEX(Data_Checks!$A:$A,84+1)) | B88: =IF(INDEX(Data_Checks!$B:$B,84+1)="","",INDEX(Data_Checks!$B:$B,84+1)) | C88: =IF(INDEX(Data_Checks!$C:$C,84+1)="","",INDEX(Data_Checks!$C:$C,84+1)) | D88: =IF(INDEX(Data_Checks!$D:$D,84+1)="","",INDEX(Data_Checks!$D:$D,84+1)) | E88: =IF(INDEX(Data_Checks!$E:$E,84+1)="","",INDEX(Data_Checks!$E:$E,84+1)) | F88: =IF(INDEX(Data_Checks!$F:$F,84+1)="","",INDEX(Data_Checks!$F:$F,84+1)) | G88: =IF(INDEX(Data_Checks!$G:$G,84+1)="","",INDEX(Data_Checks!$G:$G,84+1)) | H88: =IF(INDEX(Data_Checks!$H:$H,84+1)="","",INDEX(Data_Checks!$H:$H,84+1))
A89: =IF(INDEX(Data_Checks!$A:$A,85+1)="","",INDEX(Data_Checks!$A:$A,85+1)) | B89: =IF(INDEX(Data_Checks!$B:$B,85+1)="","",INDEX(Data_Checks!$B:$B,85+1)) | C89: =IF(INDEX(Data_Checks!$C:$C,85+1)="","",INDEX(Data_Checks!$C:$C,85+1)) | D89: =IF(INDEX(Data_Checks!$D:$D,85+1)="","",INDEX(Data_Checks!$D:$D,85+1)) | E89: =IF(INDEX(Data_Checks!$E:$E,85+1)="","",INDEX(Data_Checks!$E:$E,85+1)) | F89: =IF(INDEX(Data_Checks!$F:$F,85+1)="","",INDEX(Data_Checks!$F:$F,85+1)) | G89: =IF(INDEX(Data_Checks!$G:$G,85+1)="","",INDEX(Data_Checks!$G:$G,85+1)) | H89: =IF(INDEX(Data_Checks!$H:$H,85+1)="","",INDEX(Data_Checks!$H:$H,85+1))
A90: =IF(INDEX(Data_Checks!$A:$A,86+1)="","",INDEX(Data_Checks!$A:$A,86+1)) | B90: =IF(INDEX(Data_Checks!$B:$B,86+1)="","",INDEX(Data_Checks!$B:$B,86+1)) | C90: =IF(INDEX(Data_Checks!$C:$C,86+1)="","",INDEX(Data_Checks!$C:$C,86+1)) | D90: =IF(INDEX(Data_Checks!$D:$D,86+1)="","",INDEX(Data_Checks!$D:$D,86+1)) | E90: =IF(INDEX(Data_Checks!$E:$E,86+1)="","",INDEX(Data_Checks!$E:$E,86+1)) | F90: =IF(INDEX(Data_Checks!$F:$F,86+1)="","",INDEX(Data_Checks!$F:$F,86+1)) | G90: =IF(INDEX(Data_Checks!$G:$G,86+1)="","",INDEX(Data_Checks!$G:$G,86+1)) | H90: =IF(INDEX(Data_Checks!$H:$H,86+1)="","",INDEX(Data_Checks!$H:$H,86+1))
A91: =IF(INDEX(Data_Checks!$A:$A,87+1)="","",INDEX(Data_Checks!$A:$A,87+1)) | B91: =IF(INDEX(Data_Checks!$B:$B,87+1)="","",INDEX(Data_Checks!$B:$B,87+1)) | C91: =IF(INDEX(Data_Checks!$C:$C,87+1)="","",INDEX(Data_Checks!$C:$C,87+1)) | D91: =IF(INDEX(Data_Checks!$D:$D,87+1)="","",INDEX(Data_Checks!$D:$D,87+1)) | E91: =IF(INDEX(Data_Checks!$E:$E,87+1)="","",INDEX(Data_Checks!$E:$E,87+1)) | F91: =IF(INDEX(Data_Checks!$F:$F,87+1)="","",INDEX(Data_Checks!$F:$F,87+1)) | G91: =IF(INDEX(Data_Checks!$G:$G,87+1)="","",INDEX(Data_Checks!$G:$G,87+1)) | H91: =IF(INDEX(Data_Checks!$H:$H,87+1)="","",INDEX(Data_Checks!$H:$H,87+1))
A92: =IF(INDEX(Data_Checks!$A:$A,88+1)="","",INDEX(Data_Checks!$A:$A,88+1)) | B92: =IF(INDEX(Data_Checks!$B:$B,88+1)="","",INDEX(Data_Checks!$B:$B,88+1)) | C92: =IF(INDEX(Data_Checks!$C:$C,88+1)="","",INDEX(Data_Checks!$C:$C,88+1)) | D92: =IF(INDEX(Data_Checks!$D:$D,88+1)="","",INDEX(Data_Checks!$D:$D,88+1)) | E92: =IF(INDEX(Data_Checks!$E:$E,88+1)="","",INDEX(Data_Checks!$E:$E,88+1)) | F92: =IF(INDEX(Data_Checks!$F:$F,88+1)="","",INDEX(Data_Checks!$F:$F,88+1)) | G92: =IF(INDEX(Data_Checks!$G:$G,88+1)="","",INDEX(Data_Checks!$G:$G,88+1)) | H92: =IF(INDEX(Data_Checks!$H:$H,88+1)="","",INDEX(Data_Checks!$H:$H,88+1))
A93: =IF(INDEX(Data_Checks!$A:$A,89+1)="","",INDEX(Data_Checks!$A:$A,89+1)) | B93: =IF(INDEX(Data_Checks!$B:$B,89+1)="","",INDEX(Data_Checks!$B:$B,89+1)) | C93: =IF(INDEX(Data_Checks!$C:$C,89+1)="","",INDEX(Data_Checks!$C:$C,89+1)) | D93: =IF(INDEX(Data_Checks!$D:$D,89+1)="","",INDEX(Data_Checks!$D:$D,89+1)) | E93: =IF(INDEX(Data_Checks!$E:$E,89+1)="","",INDEX(Data_Checks!$E:$E,89+1)) | F93: =IF(INDEX(Data_Checks!$F:$F,89+1)="","",INDEX(Data_Checks!$F:$F,89+1)) | G93: =IF(INDEX(Data_Checks!$G:$G,89+1)="","",INDEX(Data_Checks!$G:$G,89+1)) | H93: =IF(INDEX(Data_Checks!$H:$H,89+1)="","",INDEX(Data_Checks!$H:$H,89+1))
A94: =IF(INDEX(Data_Checks!$A:$A,90+1)="","",INDEX(Data_Checks!$A:$A,90+1)) | B94: =IF(INDEX(Data_Checks!$B:$B,90+1)="","",INDEX(Data_Checks!$B:$B,90+1)) | C94: =IF(INDEX(Data_Checks!$C:$C,90+1)="","",INDEX(Data_Checks!$C:$C,90+1)) | D94: =IF(INDEX(Data_Checks!$D:$D,90+1)="","",INDEX(Data_Checks!$D:$D,90+1)) | E94: =IF(INDEX(Data_Checks!$E:$E,90+1)="","",INDEX(Data_Checks!$E:$E,90+1)) | F94: =IF(INDEX(Data_Checks!$F:$F,90+1)="","",INDEX(Data_Checks!$F:$F,90+1)) | G94: =IF(INDEX(Data_Checks!$G:$G,90+1)="","",INDEX(Data_Checks!$G:$G,90+1)) | H94: =IF(INDEX(Data_Checks!$H:$H,90+1)="","",INDEX(Data_Checks!$H:$H,90+1))
A95: =IF(INDEX(Data_Checks!$A:$A,91+1)="","",INDEX(Data_Checks!$A:$A,91+1)) | B95: =IF(INDEX(Data_Checks!$B:$B,91+1)="","",INDEX(Data_Checks!$B:$B,91+1)) | C95: =IF(INDEX(Data_Checks!$C:$C,91+1)="","",INDEX(Data_Checks!$C:$C,91+1)) | D95: =IF(INDEX(Data_Checks!$D:$D,91+1)="","",INDEX(Data_Checks!$D:$D,91+1)) | E95: =IF(INDEX(Data_Checks!$E:$E,91+1)="","",INDEX(Data_Checks!$E:$E,91+1)) | F95: =IF(INDEX(Data_Checks!$F:$F,91+1)="","",INDEX(Data_Checks!$F:$F,91+1)) | G95: =IF(INDEX(Data_Checks!$G:$G,91+1)="","",INDEX(Data_Checks!$G:$G,91+1)) | H95: =IF(INDEX(Data_Checks!$H:$H,91+1)="","",INDEX(Data_Checks!$H:$H,91+1))
A96: =IF(INDEX(Data_Checks!$A:$A,92+1)="","",INDEX(Data_Checks!$A:$A,92+1)) | B96: =IF(INDEX(Data_Checks!$B:$B,92+1)="","",INDEX(Data_Checks!$B:$B,92+1)) | C96: =IF(INDEX(Data_Checks!$C:$C,92+1)="","",INDEX(Data_Checks!$C:$C,92+1)) | D96: =IF(INDEX(Data_Checks!$D:$D,92+1)="","",INDEX(Data_Checks!$D:$D,92+1)) | E96: =IF(INDEX(Data_Checks!$E:$E,92+1)="","",INDEX(Data_Checks!$E:$E,92+1)) | F96: =IF(INDEX(Data_Checks!$F:$F,92+1)="","",INDEX(Data_Checks!$F:$F,92+1)) | G96: =IF(INDEX(Data_Checks!$G:$G,92+1)="","",INDEX(Data_Checks!$G:$G,92+1)) | H96: =IF(INDEX(Data_Checks!$H:$H,92+1)="","",INDEX(Data_Checks!$H:$H,92+1))
A97: =IF(INDEX(Data_Checks!$A:$A,93+1)="","",INDEX(Data_Checks!$A:$A,93+1)) | B97: =IF(INDEX(Data_Checks!$B:$B,93+1)="","",INDEX(Data_Checks!$B:$B,93+1)) | C97: =IF(INDEX(Data_Checks!$C:$C,93+1)="","",INDEX(Data_Checks!$C:$C,93+1)) | D97: =IF(INDEX(Data_Checks!$D:$D,93+1)="","",INDEX(Data_Checks!$D:$D,93+1)) | E97: =IF(INDEX(Data_Checks!$E:$E,93+1)="","",INDEX(Data_Checks!$E:$E,93+1)) | F97: =IF(INDEX(Data_Checks!$F:$F,93+1)="","",INDEX(Data_Checks!$F:$F,93+1)) | G97: =IF(INDEX(Data_Checks!$G:$G,93+1)="","",INDEX(Data_Checks!$G:$G,93+1)) | H97: =IF(INDEX(Data_Checks!$H:$H,93+1)="","",INDEX(Data_Checks!$H:$H,93+1))
A98: =IF(INDEX(Data_Checks!$A:$A,94+1)="","",INDEX(Data_Checks!$A:$A,94+1)) | B98: =IF(INDEX(Data_Checks!$B:$B,94+1)="","",INDEX(Data_Checks!$B:$B,94+1)) | C98: =IF(INDEX(Data_Checks!$C:$C,94+1)="","",INDEX(Data_Checks!$C:$C,94+1)) | D98: =IF(INDEX(Data_Checks!$D:$D,94+1)="","",INDEX(Data_Checks!$D:$D,94+1)) | E98: =IF(INDEX(Data_Checks!$E:$E,94+1)="","",INDEX(Data_Checks!$E:$E,94+1)) | F98: =IF(INDEX(Data_Checks!$F:$F,94+1)="","",INDEX(Data_Checks!$F:$F,94+1)) | G98: =IF(INDEX(Data_Checks!$G:$G,94+1)="","",INDEX(Data_Checks!$G:$G,94+1)) | H98: =IF(INDEX(Data_Checks!$H:$H,94+1)="","",INDEX(Data_Checks!$H:$H,94+1))
A99: =IF(INDEX(Data_Checks!$A:$A,95+1)="","",INDEX(Data_Checks!$A:$A,95+1)) | B99: =IF(INDEX(Data_Checks!$B:$B,95+1)="","",INDEX(Data_Checks!$B:$B,95+1)) | C99: =IF(INDEX(Data_Checks!$C:$C,95+1)="","",INDEX(Data_Checks!$C:$C,95+1)) | D99: =IF(INDEX(Data_Checks!$D:$D,95+1)="","",INDEX(Data_Checks!$D:$D,95+1)) | E99: =IF(INDEX(Data_Checks!$E:$E,95+1)="","",INDEX(Data_Checks!$E:$E,95+1)) | F99: =IF(INDEX(Data_Checks!$F:$F,95+1)="","",INDEX(Data_Checks!$F:$F,95+1)) | G99: =IF(INDEX(Data_Checks!$G:$G,95+1)="","",INDEX(Data_Checks!$G:$G,95+1)) | H99: =IF(INDEX(Data_Checks!$H:$H,95+1)="","",INDEX(Data_Checks!$H:$H,95+1))
A100: =IF(INDEX(Data_Checks!$A:$A,96+1)="","",INDEX(Data_Checks!$A:$A,96+1)) | B100: =IF(INDEX(Data_Checks!$B:$B,96+1)="","",INDEX(Data_Checks!$B:$B,96+1)) | C100: =IF(INDEX(Data_Checks!$C:$C,96+1)="","",INDEX(Data_Checks!$C:$C,96+1)) | D100: =IF(INDEX(Data_Checks!$D:$D,96+1)="","",INDEX(Data_Checks!$D:$D,96+1)) | E100: =IF(INDEX(Data_Checks!$E:$E,96+1)="","",INDEX(Data_Checks!$E:$E,96+1)) | F100: =IF(INDEX(Data_Checks!$F:$F,96+1)="","",INDEX(Data_Checks!$F:$F,96+1)) | G100: =IF(INDEX(Data_Checks!$G:$G,96+1)="","",INDEX(Data_Checks!$G:$G,96+1)) | H100: =IF(INDEX(Data_Checks!$H:$H,96+1)="","",INDEX(Data_Checks!$H:$H,96+1))
A101: =IF(INDEX(Data_Checks!$A:$A,97+1)="","",INDEX(Data_Checks!$A:$A,97+1)) | B101: =IF(INDEX(Data_Checks!$B:$B,97+1)="","",INDEX(Data_Checks!$B:$B,97+1)) | C101: =IF(INDEX(Data_Checks!$C:$C,97+1)="","",INDEX(Data_Checks!$C:$C,97+1)) | D101: =IF(INDEX(Data_Checks!$D:$D,97+1)="","",INDEX(Data_Checks!$D:$D,97+1)) | E101: =IF(INDEX(Data_Checks!$E:$E,97+1)="","",INDEX(Data_Checks!$E:$E,97+1)) | F101: =IF(INDEX(Data_Checks!$F:$F,97+1)="","",INDEX(Data_Checks!$F:$F,97+1)) | G101: =IF(INDEX(Data_Checks!$G:$G,97+1)="","",INDEX(Data_Checks!$G:$G,97+1)) | H101: =IF(INDEX(Data_Checks!$H:$H,97+1)="","",INDEX(Data_Checks!$H:$H,97+1))
...

Sheet Monthly
A1: =Data_Params!$B$14&" | Usage and revenue by month" -> Example Co (synthetic data) | Usage and revenue by month
A2: Formulas only: every number reads the Data_ sheets. Tokens in billions, $ in thousands.
A4: Line | B4: =EDATE(Data_Params!$B$3,0) -> 46082 | C4: =EDATE(Data_Params!$B$3,1) -> 46113 | D4: =EDATE(Data_Params!$B$3,2) -> 46143 | E4: =EDATE(Data_Params!$B$3,3) -> 46174 | F4: =EDATE(Data_Params!$B$3,4) -> 46204 | G4: =EDATE(Data_Params!$B$3,5) -> 46235 | H4: =EDATE(Data_Params!$B$3,6) -> 46266 | I4: =EDATE(Data_Params!$B$3,7) -> 46296 | J4: =EDATE(Data_Params!$B$3,8) -> 46327 | K4: =EDATE(Data_Params!$B$3,9) -> 46357 | L4: =EDATE(Data_Params!$B$3,10) -> 46388 | M4: =EDATE(Data_Params!$B$3,11) -> 46419
A5: Billable tokens (B)
A6: Enterprise | B6: =SUMIFS(Data_Monthly!$F:$F,Data_Monthly!$A:$A,B$4,Data_Monthly!$B:$B,"enterprise")/1000000000 -> 0 | C6: =SUMIFS(Data_Monthly!$F:$F,Data_Monthly!$A:$A,C$4,Data_Monthly!$B:$B,"enterprise")/1000000000 -> 0 | D6: =SUMIFS(Data_Monthly!$F:$F,Data_Monthly!$A:$A,D$4,Data_Monthly!$B:$B,"enterprise")/1000000000 -> 0 | E6: =SUMIFS(Data_Monthly!$F:$F,Data_Monthly!$A:$A,E$4,Data_Monthly!$B:$B,"enterprise")/1000000000 -> 0 | F6: =SUMIFS(Data_Monthly!$F:$F,Data_Monthly!$A:$A,F$4,Data_Monthly!$B:$B,"enterprise")/1000000000 -> 0 | G6: =SUMIFS(Data_Monthly!$F:$F,Data_Monthly!$A:$A,G$4,Data_Monthly!$B:$B,"enterprise")/1000000000 -> 0 | H6: =SUMIFS(Data_Monthly!$F:$F,Data_Monthly!$A:$A,H$4,Data_Monthly!$B:$B,"enterprise")/1000000000 -> 0 | I6: =SUMIFS(Data_Monthly!$F:$F,Data_Monthly!$A:$A,I$4,Data_Monthly!$B:$B,"enterprise")/1000000000 -> 584.37278 | ... M6: =SUMIFS(Data_Monthly!$F:$F,Data_Monthly!$A:$A,M$4,Data_Monthly!$B:$B,"enterprise")/1000000000 -> 4615.8421
A7: Self-serve | B7: =SUMIFS(Data_Monthly!$F:$F,Data_Monthly!$A:$A,B$4,Data_Monthly!$B:$B,"self_serve")/1000000000 -> 0 | C7: =SUMIFS(Data_Monthly!$F:$F,Data_Monthly!$A:$A,C$4,Data_Monthly!$B:$B,"self_serve")/1000000000 -> 0 | D7: =SUMIFS(Data_Monthly!$F:$F,Data_Monthly!$A:$A,D$4,Data_Monthly!$B:$B,"self_serve")/1000000000 -> 0 | E7: =SUMIFS(Data_Monthly!$F:$F,Data_Monthly!$A:$A,E$4,Data_Monthly!$B:$B,"self_serve")/1000000000 -> 0 | F7: =SUMIFS(Data_Monthly!$F:$F,Data_Monthly!$A:$A,F$4,Data_Monthly!$B:$B,"self_serve")/1000000000 -> 0 | G7: =SUMIFS(Data_Monthly!$F:$F,Data_Monthly!$A:$A,G$4,Data_Monthly!$B:$B,"self_serve")/1000000000 -> 0 | H7: =SUMIFS(Data_Monthly!$F:$F,Data_Monthly!$A:$A,H$4,Data_Monthly!$B:$B,"self_serve")/1000000000 -> 6.0433854 | I7: =SUMIFS(Data_Monthly!$F:$F,Data_Monthly!$A:$A,I$4,Data_Monthly!$B:$B,"self_serve")/1000000000 -> 53.119027 | ... M7: =SUMIFS(Data_Monthly!$F:$F,Data_Monthly!$A:$A,M$4,Data_Monthly!$B:$B,"self_serve")/1000000000 -> 1053.8774
A8: Gateways that don't pass customer IDs | B8: =SUMIFS(Data_Monthly!$F:$F,Data_Monthly!$A:$A,B$4,Data_Monthly!$B:$B,"gateway_aggregate")/1000000000 -> 0 | C8: =SUMIFS(Data_Monthly!$F:$F,Data_Monthly!$A:$A,C$4,Data_Monthly!$B:$B,"gateway_aggregate")/1000000000 -> 0 | D8: =SUMIFS(Data_Monthly!$F:$F,Data_Monthly!$A:$A,D$4,Data_Monthly!$B:$B,"gateway_aggregate")/1000000000 -> 0 | E8: =SUMIFS(Data_Monthly!$F:$F,Data_Monthly!$A:$A,E$4,Data_Monthly!$B:$B,"gateway_aggregate")/1000000000 -> 0 | F8: =SUMIFS(Data_Monthly!$F:$F,Data_Monthly!$A:$A,F$4,Data_Monthly!$B:$B,"gateway_aggregate")/1000000000 -> 0 | G8: =SUMIFS(Data_Monthly!$F:$F,Data_Monthly!$A:$A,G$4,Data_Monthly!$B:$B,"gateway_aggregate")/1000000000 -> 0 | H8: =SUMIFS(Data_Monthly!$F:$F,Data_Monthly!$A:$A,H$4,Data_Monthly!$B:$B,"gateway_aggregate")/1000000000 -> 1.2261755 | I8: =SUMIFS(Data_Monthly!$F:$F,Data_Monthly!$A:$A,I$4,Data_Monthly!$B:$B,"gateway_aggregate")/1000000000 -> 10.059494 | ... M8: =SUMIFS(Data_Monthly!$F:$F,Data_Monthly!$A:$A,M$4,Data_Monthly!$B:$B,"gateway_aggregate")/1000000000 -> 370.51891
A9: Unmatched accounts (fix the accounts source) | B9: =SUMIFS(Data_Monthly!$F:$F,Data_Monthly!$A:$A,B$4,Data_Monthly!$B:$B,"unmatched")/1000000000 -> 0 | C9: =SUMIFS(Data_Monthly!$F:$F,Data_Monthly!$A:$A,C$4,Data_Monthly!$B:$B,"unmatched")/1000000000 -> 0 | D9: =SUMIFS(Data_Monthly!$F:$F,Data_Monthly!$A:$A,D$4,Data_Monthly!$B:$B,"unmatched")/1000000000 -> 0 | E9: =SUMIFS(Data_Monthly!$F:$F,Data_Monthly!$A:$A,E$4,Data_Monthly!$B:$B,"unmatched")/1000000000 -> 0 | F9: =SUMIFS(Data_Monthly!$F:$F,Data_Monthly!$A:$A,F$4,Data_Monthly!$B:$B,"unmatched")/1000000000 -> 0 | G9: =SUMIFS(Data_Monthly!$F:$F,Data_Monthly!$A:$A,G$4,Data_Monthly!$B:$B,"unmatched")/1000000000 -> 0 | H9: =SUMIFS(Data_Monthly!$F:$F,Data_Monthly!$A:$A,H$4,Data_Monthly!$B:$B,"unmatched")/1000000000 -> 0 | I9: =SUMIFS(Data_Monthly!$F:$F,Data_Monthly!$A:$A,I$4,Data_Monthly!$B:$B,"unmatched")/1000000000 -> 0 | ... M9: =SUMIFS(Data_Monthly!$F:$F,Data_Monthly!$A:$A,M$4,Data_Monthly!$B:$B,"unmatched")/1000000000 -> 0
A10: Total billable tokens | B10: =SUM(B6:B9) -> 0 | C10: =SUM(C6:C9) -> 0 | D10: =SUM(D6:D9) -> 0 | E10: =SUM(E6:E9) -> 0 | F10: =SUM(F6:F9) -> 0 | G10: =SUM(G6:G9) -> 0 | H10: =SUM(H6:H9) -> 7.2695609 | I10: =SUM(I6:I9) -> 647.5513 | ... M10: =SUM(M6:M9) -> 6040.2384
A11: Days of data in month | B11: =SUMIFS(Data_Months!$B:$B,Data_Months!$A:$A,B$4) -> 31 | C11: =SUMIFS(Data_Months!$B:$B,Data_Months!$A:$A,C$4) -> 30 | D11: =SUMIFS(Data_Months!$B:$B,Data_Months!$A:$A,D$4) -> 31 | E11: =SUMIFS(Data_Months!$B:$B,Data_Months!$A:$A,E$4) -> 30 | F11: =SUMIFS(Data_Months!$B:$B,Data_Months!$A:$A,F$4) -> 31 | G11: =SUMIFS(Data_Months!$B:$B,Data_Months!$A:$A,G$4) -> 31 | H11: =SUMIFS(Data_Months!$B:$B,Data_Months!$A:$A,H$4) -> 16 | I11: =SUMIFS(Data_Months!$B:$B,Data_Months!$A:$A,I$4) -> 31 | ... M11: =SUMIFS(Data_Months!$B:$B,Data_Months!$A:$A,M$4) -> 28
A12: Tokens per day (B) | B12: =IF(B11=0,0,B10/B11) -> 0 | C12: =IF(C11=0,0,C10/C11) -> 0 | D12: =IF(D11=0,0,D10/D11) -> 0 | E12: =IF(E11=0,0,E10/E11) -> 0 | F12: =IF(F11=0,0,F10/F11) -> 0 | G12: =IF(G11=0,0,G10/G11) -> 0 | H12: =IF(H11=0,0,H10/H11) -> 0.45434755 | I12: =IF(I11=0,0,I10/I11) -> 20.888752 | ... M12: =IF(M11=0,0,M10/M11) -> 215.7228
A13: Enterprise, per day | B13: =IF(B11=0,0,B6/B11) -> 0 | C13: =IF(C11=0,0,C6/C11) -> 0 | D13: =IF(D11=0,0,D6/D11) -> 0 | E13: =IF(E11=0,0,E6/E11) -> 0 | F13: =IF(F11=0,0,F6/F11) -> 0 | G13: =IF(G11=0,0,G6/G11) -> 0 | H13: =IF(H11=0,0,H6/H11) -> 0 | I13: =IF(I11=0,0,I6/I11) -> 18.850735 | ... M13: =IF(M11=0,0,M6/M11) -> 164.85151
A14: Self-serve, per day | B14: =IF(B11=0,0,B7/B11) -> 0 | C14: =IF(C11=0,0,C7/C11) -> 0 | D14: =IF(D11=0,0,D7/D11) -> 0 | E14: =IF(E11=0,0,E7/E11) -> 0 | F14: =IF(F11=0,0,F7/F11) -> 0 | G14: =IF(G11=0,0,G7/G11) -> 0 | H14: =IF(H11=0,0,H7/H11) -> 0.37771159 | I14: =IF(I11=0,0,I7/I11) -> 1.713517 | ... M14: =IF(M11=0,0,M7/M11) -> 37.638477
A15: Gateways that don't pass customer IDs, per day | B15: =IF(B11=0,0,B8/B11) -> 0 | C15: =IF(C11=0,0,C8/C11) -> 0 | D15: =IF(D11=0,0,D8/D11) -> 0 | E15: =IF(E11=0,0,E8/E11) -> 0 | F15: =IF(F11=0,0,F8/F11) -> 0 | G15: =IF(G11=0,0,G8/G11) -> 0 | H15: =IF(H11=0,0,H8/H11) -> 0.07663597 | I15: =IF(I11=0,0,I8/I11) -> 0.32449982 | ... M15: =IF(M11=0,0,M8/M11) -> 13.232818
A16: Growth in tokens per day vs prior month | C16: =IF(B12=0,0,C12/B12-1) -> 0 | D16: =IF(C12=0,0,D12/C12-1) -> 0 | E16: =IF(D12=0,0,E12/D12-1) -> 0 | F16: =IF(E12=0,0,F12/E12-1) -> 0 | G16: =IF(F12=0,0,G12/F12-1) -> 0 | H16: =IF(G12=0,0,H12/G12-1) -> 0 | I16: =IF(H12=0,0,I12/H12-1) -> 44.97527 | J16: =IF(I12=0,0,J12/I12-1) -> 2.4920504 | ... M16: =IF(L12=0,0,M12/L12-1) -> 0.18411182
A18: Billable tokens by channel (B)
A19: =IF(INDEX(Data_Lists!$B:$B,1+1)="","",INDEX(Data_Lists!$B:$B,1+1)) -> direct | B19: =IF($A19="","",SUMIFS(Data_Monthly!$F:$F,Data_Monthly!$A:$A,B$4,Data_Monthly!$C:$C,$A19)/1000000000) -> 0 | C19: =IF($A19="","",SUMIFS(Data_Monthly!$F:$F,Data_Monthly!$A:$A,C$4,Data_Monthly!$C:$C,$A19)/1000000000) -> 0 | D19: =IF($A19="","",SUMIFS(Data_Monthly!$F:$F,Data_Monthly!$A:$A,D$4,Data_Monthly!$C:$C,$A19)/1000000000) -> 0 | E19: =IF($A19="","",SUMIFS(Data_Monthly!$F:$F,Data_Monthly!$A:$A,E$4,Data_Monthly!$C:$C,$A19)/1000000000) -> 0 | F19: =IF($A19="","",SUMIFS(Data_Monthly!$F:$F,Data_Monthly!$A:$A,F$4,Data_Monthly!$C:$C,$A19)/1000000000) -> 0 | G19: =IF($A19="","",SUMIFS(Data_Monthly!$F:$F,Data_Monthly!$A:$A,G$4,Data_Monthly!$C:$C,$A19)/1000000000) -> 0 | H19: =IF($A19="","",SUMIFS(Data_Monthly!$F:$F,Data_Monthly!$A:$A,H$4,Data_Monthly!$C:$C,$A19)/1000000000) -> 3.1006702 | I19: =IF($A19="","",SUMIFS(Data_Monthly!$F:$F,Data_Monthly!$A:$A,I$4,Data_Monthly!$C:$C,$A19)/1000000000) -> 620.09829 | ... M19: =IF($A19="","",SUMIFS(Data_Monthly!$F:$F,Data_Monthly!$A:$A,M$4,Data_Monthly!$C:$C,$A19)/1000000000) -> 5198.1707
A20: =IF(INDEX(Data_Lists!$B:$B,2+1)="","",INDEX(Data_Lists!$B:$B,2+1)) -> vercel | B20: =IF($A20="","",SUMIFS(Data_Monthly!$F:$F,Data_Monthly!$A:$A,B$4,Data_Monthly!$C:$C,$A20)/1000000000) -> 0 | C20: =IF($A20="","",SUMIFS(Data_Monthly!$F:$F,Data_Monthly!$A:$A,C$4,Data_Monthly!$C:$C,$A20)/1000000000) -> 0 | D20: =IF($A20="","",SUMIFS(Data_Monthly!$F:$F,Data_Monthly!$A:$A,D$4,Data_Monthly!$C:$C,$A20)/1000000000) -> 0 | E20: =IF($A20="","",SUMIFS(Data_Monthly!$F:$F,Data_Monthly!$A:$A,E$4,Data_Monthly!$C:$C,$A20)/1000000000) -> 0 | F20: =IF($A20="","",SUMIFS(Data_Monthly!$F:$F,Data_Monthly!$A:$A,F$4,Data_Monthly!$C:$C,$A20)/1000000000) -> 0 | G20: =IF($A20="","",SUMIFS(Data_Monthly!$F:$F,Data_Monthly!$A:$A,G$4,Data_Monthly!$C:$C,$A20)/1000000000) -> 0 | H20: =IF($A20="","",SUMIFS(Data_Monthly!$F:$F,Data_Monthly!$A:$A,H$4,Data_Monthly!$C:$C,$A20)/1000000000) -> 2.5162455 | I20: =IF($A20="","",SUMIFS(Data_Monthly!$F:$F,Data_Monthly!$A:$A,I$4,Data_Monthly!$C:$C,$A20)/1000000000) -> 16.337845 | ... M20: =IF($A20="","",SUMIFS(Data_Monthly!$F:$F,Data_Monthly!$A:$A,M$4,Data_Monthly!$C:$C,$A20)/1000000000) -> 456.56212
A21: =IF(INDEX(Data_Lists!$B:$B,3+1)="","",INDEX(Data_Lists!$B:$B,3+1)) -> openrouter | B21: =IF($A21="","",SUMIFS(Data_Monthly!$F:$F,Data_Monthly!$A:$A,B$4,Data_Monthly!$C:$C,$A21)/1000000000) -> 0 | C21: =IF($A21="","",SUMIFS(Data_Monthly!$F:$F,Data_Monthly!$A:$A,C$4,Data_Monthly!$C:$C,$A21)/1000000000) -> 0 | D21: =IF($A21="","",SUMIFS(Data_Monthly!$F:$F,Data_Monthly!$A:$A,D$4,Data_Monthly!$C:$C,$A21)/1000000000) -> 0 | E21: =IF($A21="","",SUMIFS(Data_Monthly!$F:$F,Data_Monthly!$A:$A,E$4,Data_Monthly!$C:$C,$A21)/1000000000) -> 0 | F21: =IF($A21="","",SUMIFS(Data_Monthly!$F:$F,Data_Monthly!$A:$A,F$4,Data_Monthly!$C:$C,$A21)/1000000000) -> 0 | G21: =IF($A21="","",SUMIFS(Data_Monthly!$F:$F,Data_Monthly!$A:$A,G$4,Data_Monthly!$C:$C,$A21)/1000000000) -> 0 | H21: =IF($A21="","",SUMIFS(Data_Monthly!$F:$F,Data_Monthly!$A:$A,H$4,Data_Monthly!$C:$C,$A21)/1000000000) -> 1.2261755 | I21: =IF($A21="","",SUMIFS(Data_Monthly!$F:$F,Data_Monthly!$A:$A,I$4,Data_Monthly!$C:$C,$A21)/1000000000) -> 10.059494 | ... M21: =IF($A21="","",SUMIFS(Data_Monthly!$F:$F,Data_Monthly!$A:$A,M$4,Data_Monthly!$C:$C,$A21)/1000000000) -> 370.51891
A22: =IF(INDEX(Data_Lists!$B:$B,4+1)="","",INDEX(Data_Lists!$B:$B,4+1)) -> digitalocean | B22: =IF($A22="","",SUMIFS(Data_Monthly!$F:$F,Data_Monthly!$A:$A,B$4,Data_Monthly!$C:$C,$A22)/1000000000) -> 0 | C22: =IF($A22="","",SUMIFS(Data_Monthly!$F:$F,Data_Monthly!$A:$A,C$4,Data_Monthly!$C:$C,$A22)/1000000000) -> 0 | D22: =IF($A22="","",SUMIFS(Data_Monthly!$F:$F,Data_Monthly!$A:$A,D$4,Data_Monthly!$C:$C,$A22)/1000000000) -> 0 | E22: =IF($A22="","",SUMIFS(Data_Monthly!$F:$F,Data_Monthly!$A:$A,E$4,Data_Monthly!$C:$C,$A22)/1000000000) -> 0 | F22: =IF($A22="","",SUMIFS(Data_Monthly!$F:$F,Data_Monthly!$A:$A,F$4,Data_Monthly!$C:$C,$A22)/1000000000) -> 0 | G22: =IF($A22="","",SUMIFS(Data_Monthly!$F:$F,Data_Monthly!$A:$A,G$4,Data_Monthly!$C:$C,$A22)/1000000000) -> 0 | H22: =IF($A22="","",SUMIFS(Data_Monthly!$F:$F,Data_Monthly!$A:$A,H$4,Data_Monthly!$C:$C,$A22)/1000000000) -> 0.42646968 | I22: =IF($A22="","",SUMIFS(Data_Monthly!$F:$F,Data_Monthly!$A:$A,I$4,Data_Monthly!$C:$C,$A22)/1000000000) -> 1.0556694 | ... M22: =IF($A22="","",SUMIFS(Data_Monthly!$F:$F,Data_Monthly!$A:$A,M$4,Data_Monthly!$C:$C,$A22)/1000000000) -> 14.986734
A23: =IF(INDEX(Data_Lists!$B:$B,5+1)="","",INDEX(Data_Lists!$B:$B,5+1)) | B23: =IF($A23="","",SUMIFS(Data_Monthly!$F:$F,Data_Monthly!$A:$A,B$4,Data_Monthly!$C:$C,$A23)/1000000000) | C23: =IF($A23="","",SUMIFS(Data_Monthly!$F:$F,Data_Monthly!$A:$A,C$4,Data_Monthly!$C:$C,$A23)/1000000000) | D23: =IF($A23="","",SUMIFS(Data_Monthly!$F:$F,Data_Monthly!$A:$A,D$4,Data_Monthly!$C:$C,$A23)/1000000000) | E23: =IF($A23="","",SUMIFS(Data_Monthly!$F:$F,Data_Monthly!$A:$A,E$4,Data_Monthly!$C:$C,$A23)/1000000000) | F23: =IF($A23="","",SUMIFS(Data_Monthly!$F:$F,Data_Monthly!$A:$A,F$4,Data_Monthly!$C:$C,$A23)/1000000000) | G23: =IF($A23="","",SUMIFS(Data_Monthly!$F:$F,Data_Monthly!$A:$A,G$4,Data_Monthly!$C:$C,$A23)/1000000000) | H23: =IF($A23="","",SUMIFS(Data_Monthly!$F:$F,Data_Monthly!$A:$A,H$4,Data_Monthly!$C:$C,$A23)/1000000000) | I23: =IF($A23="","",SUMIFS(Data_Monthly!$F:$F,Data_Monthly!$A:$A,I$4,Data_Monthly!$C:$C,$A23)/1000000000) | ... M23: =IF($A23="","",SUMIFS(Data_Monthly!$F:$F,Data_Monthly!$A:$A,M$4,Data_Monthly!$C:$C,$A23)/1000000000)
A24: =IF(INDEX(Data_Lists!$B:$B,6+1)="","",INDEX(Data_Lists!$B:$B,6+1)) | B24: =IF($A24="","",SUMIFS(Data_Monthly!$F:$F,Data_Monthly!$A:$A,B$4,Data_Monthly!$C:$C,$A24)/1000000000) | C24: =IF($A24="","",SUMIFS(Data_Monthly!$F:$F,Data_Monthly!$A:$A,C$4,Data_Monthly!$C:$C,$A24)/1000000000) | D24: =IF($A24="","",SUMIFS(Data_Monthly!$F:$F,Data_Monthly!$A:$A,D$4,Data_Monthly!$C:$C,$A24)/1000000000) | E24: =IF($A24="","",SUMIFS(Data_Monthly!$F:$F,Data_Monthly!$A:$A,E$4,Data_Monthly!$C:$C,$A24)/1000000000) | F24: =IF($A24="","",SUMIFS(Data_Monthly!$F:$F,Data_Monthly!$A:$A,F$4,Data_Monthly!$C:$C,$A24)/1000000000) | G24: =IF($A24="","",SUMIFS(Data_Monthly!$F:$F,Data_Monthly!$A:$A,G$4,Data_Monthly!$C:$C,$A24)/1000000000) | H24: =IF($A24="","",SUMIFS(Data_Monthly!$F:$F,Data_Monthly!$A:$A,H$4,Data_Monthly!$C:$C,$A24)/1000000000) | I24: =IF($A24="","",SUMIFS(Data_Monthly!$F:$F,Data_Monthly!$A:$A,I$4,Data_Monthly!$C:$C,$A24)/1000000000) | ... M24: =IF($A24="","",SUMIFS(Data_Monthly!$F:$F,Data_Monthly!$A:$A,M$4,Data_Monthly!$C:$C,$A24)/1000000000)
A25: =IF(INDEX(Data_Lists!$B:$B,7+1)="","",INDEX(Data_Lists!$B:$B,7+1)) | B25: =IF($A25="","",SUMIFS(Data_Monthly!$F:$F,Data_Monthly!$A:$A,B$4,Data_Monthly!$C:$C,$A25)/1000000000) | C25: =IF($A25="","",SUMIFS(Data_Monthly!$F:$F,Data_Monthly!$A:$A,C$4,Data_Monthly!$C:$C,$A25)/1000000000) | D25: =IF($A25="","",SUMIFS(Data_Monthly!$F:$F,Data_Monthly!$A:$A,D$4,Data_Monthly!$C:$C,$A25)/1000000000) | E25: =IF($A25="","",SUMIFS(Data_Monthly!$F:$F,Data_Monthly!$A:$A,E$4,Data_Monthly!$C:$C,$A25)/1000000000) | F25: =IF($A25="","",SUMIFS(Data_Monthly!$F:$F,Data_Monthly!$A:$A,F$4,Data_Monthly!$C:$C,$A25)/1000000000) | G25: =IF($A25="","",SUMIFS(Data_Monthly!$F:$F,Data_Monthly!$A:$A,G$4,Data_Monthly!$C:$C,$A25)/1000000000) | H25: =IF($A25="","",SUMIFS(Data_Monthly!$F:$F,Data_Monthly!$A:$A,H$4,Data_Monthly!$C:$C,$A25)/1000000000) | I25: =IF($A25="","",SUMIFS(Data_Monthly!$F:$F,Data_Monthly!$A:$A,I$4,Data_Monthly!$C:$C,$A25)/1000000000) | ... M25: =IF($A25="","",SUMIFS(Data_Monthly!$F:$F,Data_Monthly!$A:$A,M$4,Data_Monthly!$C:$C,$A25)/1000000000)
A26: =IF(INDEX(Data_Lists!$B:$B,8+1)="","",INDEX(Data_Lists!$B:$B,8+1)) | B26: =IF($A26="","",SUMIFS(Data_Monthly!$F:$F,Data_Monthly!$A:$A,B$4,Data_Monthly!$C:$C,$A26)/1000000000) | C26: =IF($A26="","",SUMIFS(Data_Monthly!$F:$F,Data_Monthly!$A:$A,C$4,Data_Monthly!$C:$C,$A26)/1000000000) | D26: =IF($A26="","",SUMIFS(Data_Monthly!$F:$F,Data_Monthly!$A:$A,D$4,Data_Monthly!$C:$C,$A26)/1000000000) | E26: =IF($A26="","",SUMIFS(Data_Monthly!$F:$F,Data_Monthly!$A:$A,E$4,Data_Monthly!$C:$C,$A26)/1000000000) | F26: =IF($A26="","",SUMIFS(Data_Monthly!$F:$F,Data_Monthly!$A:$A,F$4,Data_Monthly!$C:$C,$A26)/1000000000) | G26: =IF($A26="","",SUMIFS(Data_Monthly!$F:$F,Data_Monthly!$A:$A,G$4,Data_Monthly!$C:$C,$A26)/1000000000) | H26: =IF($A26="","",SUMIFS(Data_Monthly!$F:$F,Data_Monthly!$A:$A,H$4,Data_Monthly!$C:$C,$A26)/1000000000) | I26: =IF($A26="","",SUMIFS(Data_Monthly!$F:$F,Data_Monthly!$A:$A,I$4,Data_Monthly!$C:$C,$A26)/1000000000) | ... M26: =IF($A26="","",SUMIFS(Data_Monthly!$F:$F,Data_Monthly!$A:$A,M$4,Data_Monthly!$C:$C,$A26)/1000000000)
A28: Net revenue ($k)
A29: Enterprise | B29: =SUMIFS(Data_Monthly!$L:$L,Data_Monthly!$A:$A,B$4,Data_Monthly!$B:$B,"enterprise")/1000 -> 0 | C29: =SUMIFS(Data_Monthly!$L:$L,Data_Monthly!$A:$A,C$4,Data_Monthly!$B:$B,"enterprise")/1000 -> 0 | D29: =SUMIFS(Data_Monthly!$L:$L,Data_Monthly!$A:$A,D$4,Data_Monthly!$B:$B,"enterprise")/1000 -> 0 | E29: =SUMIFS(Data_Monthly!$L:$L,Data_Monthly!$A:$A,E$4,Data_Monthly!$B:$B,"enterprise")/1000 -> 0 | F29: =SUMIFS(Data_Monthly!$L:$L,Data_Monthly!$A:$A,F$4,Data_Monthly!$B:$B,"enterprise")/1000 -> 0 | G29: =SUMIFS(Data_Monthly!$L:$L,Data_Monthly!$A:$A,G$4,Data_Monthly!$B:$B,"enterprise")/1000 -> 0 | H29: =SUMIFS(Data_Monthly!$L:$L,Data_Monthly!$A:$A,H$4,Data_Monthly!$B:$B,"enterprise")/1000 -> 0 | I29: =SUMIFS(Data_Monthly!$L:$L,Data_Monthly!$A:$A,I$4,Data_Monthly!$B:$B,"enterprise")/1000 -> 51.935484 | ... M29: =SUMIFS(Data_Monthly!$L:$L,Data_Monthly!$A:$A,M$4,Data_Monthly!$B:$B,"enterprise")/1000 -> 190.11559
A30: Self-serve | B30: =SUMIFS(Data_Monthly!$L:$L,Data_Monthly!$A:$A,B$4,Data_Monthly!$B:$B,"self_serve")/1000 -> 0 | C30: =SUMIFS(Data_Monthly!$L:$L,Data_Monthly!$A:$A,C$4,Data_Monthly!$B:$B,"self_serve")/1000 -> 0 | D30: =SUMIFS(Data_Monthly!$L:$L,Data_Monthly!$A:$A,D$4,Data_Monthly!$B:$B,"self_serve")/1000 -> 0 | E30: =SUMIFS(Data_Monthly!$L:$L,Data_Monthly!$A:$A,E$4,Data_Monthly!$B:$B,"self_serve")/1000 -> 0 | F30: =SUMIFS(Data_Monthly!$L:$L,Data_Monthly!$A:$A,F$4,Data_Monthly!$B:$B,"self_serve")/1000 -> 0 | G30: =SUMIFS(Data_Monthly!$L:$L,Data_Monthly!$A:$A,G$4,Data_Monthly!$B:$B,"self_serve")/1000 -> 0 | H30: =SUMIFS(Data_Monthly!$L:$L,Data_Monthly!$A:$A,H$4,Data_Monthly!$B:$B,"self_serve")/1000 -> 0.12487794 | I30: =SUMIFS(Data_Monthly!$L:$L,Data_Monthly!$A:$A,I$4,Data_Monthly!$B:$B,"self_serve")/1000 -> 1.9118088 | ... M30: =SUMIFS(Data_Monthly!$L:$L,Data_Monthly!$A:$A,M$4,Data_Monthly!$B:$B,"self_serve")/1000 -> 42.805857
A31: Gateways that don't pass customer IDs | B31: =SUMIFS(Data_Monthly!$L:$L,Data_Monthly!$A:$A,B$4,Data_Monthly!$B:$B,"gateway_aggregate")/1000 -> 0 | C31: =SUMIFS(Data_Monthly!$L:$L,Data_Monthly!$A:$A,C$4,Data_Monthly!$B:$B,"gateway_aggregate")/1000 -> 0 | D31: =SUMIFS(Data_Monthly!$L:$L,Data_Monthly!$A:$A,D$4,Data_Monthly!$B:$B,"gateway_aggregate")/1000 -> 0 | E31: =SUMIFS(Data_Monthly!$L:$L,Data_Monthly!$A:$A,E$4,Data_Monthly!$B:$B,"gateway_aggregate")/1000 -> 0 | F31: =SUMIFS(Data_Monthly!$L:$L,Data_Monthly!$A:$A,F$4,Data_Monthly!$B:$B,"gateway_aggregate")/1000 -> 0 | G31: =SUMIFS(Data_Monthly!$L:$L,Data_Monthly!$A:$A,G$4,Data_Monthly!$B:$B,"gateway_aggregate")/1000 -> 0 | H31: =SUMIFS(Data_Monthly!$L:$L,Data_Monthly!$A:$A,H$4,Data_Monthly!$B:$B,"gateway_aggregate")/1000 -> 0.048924403 | I31: =SUMIFS(Data_Monthly!$L:$L,Data_Monthly!$A:$A,I$4,Data_Monthly!$B:$B,"gateway_aggregate")/1000 -> 0.40137382 | ... M31: =SUMIFS(Data_Monthly!$L:$L,Data_Monthly!$A:$A,M$4,Data_Monthly!$B:$B,"gateway_aggregate")/1000 -> 14.783704
A32: Unmatched accounts (fix the accounts source) | B32: =SUMIFS(Data_Monthly!$L:$L,Data_Monthly!$A:$A,B$4,Data_Monthly!$B:$B,"unmatched")/1000 -> 0 | C32: =SUMIFS(Data_Monthly!$L:$L,Data_Monthly!$A:$A,C$4,Data_Monthly!$B:$B,"unmatched")/1000 -> 0 | D32: =SUMIFS(Data_Monthly!$L:$L,Data_Monthly!$A:$A,D$4,Data_Monthly!$B:$B,"unmatched")/1000 -> 0 | E32: =SUMIFS(Data_Monthly!$L:$L,Data_Monthly!$A:$A,E$4,Data_Monthly!$B:$B,"unmatched")/1000 -> 0 | F32: =SUMIFS(Data_Monthly!$L:$L,Data_Monthly!$A:$A,F$4,Data_Monthly!$B:$B,"unmatched")/1000 -> 0 | G32: =SUMIFS(Data_Monthly!$L:$L,Data_Monthly!$A:$A,G$4,Data_Monthly!$B:$B,"unmatched")/1000 -> 0 | H32: =SUMIFS(Data_Monthly!$L:$L,Data_Monthly!$A:$A,H$4,Data_Monthly!$B:$B,"unmatched")/1000 -> 0 | I32: =SUMIFS(Data_Monthly!$L:$L,Data_Monthly!$A:$A,I$4,Data_Monthly!$B:$B,"unmatched")/1000 -> 0 | ... M32: =SUMIFS(Data_Monthly!$L:$L,Data_Monthly!$A:$A,M$4,Data_Monthly!$B:$B,"unmatched")/1000 -> 0
A33: Manual adjustments (Overrides tab) | B33: =SUMIFS(Overrides!$G$46:$G$75,Overrides!$F$46:$F$75,B$4)/1000 -> 0 | C33: =SUMIFS(Overrides!$G$46:$G$75,Overrides!$F$46:$F$75,C$4)/1000 -> 0 | D33: =SUMIFS(Overrides!$G$46:$G$75,Overrides!$F$46:$F$75,D$4)/1000 -> 0 | E33: =SUMIFS(Overrides!$G$46:$G$75,Overrides!$F$46:$F$75,E$4)/1000 -> 0 | F33: =SUMIFS(Overrides!$G$46:$G$75,Overrides!$F$46:$F$75,F$4)/1000 -> 0 | G33: =SUMIFS(Overrides!$G$46:$G$75,Overrides!$F$46:$F$75,G$4)/1000 -> 0 | H33: =SUMIFS(Overrides!$G$46:$G$75,Overrides!$F$46:$F$75,H$4)/1000 -> 0 | I33: =SUMIFS(Overrides!$G$46:$G$75,Overrides!$F$46:$F$75,I$4)/1000 -> 0 | ... M33: =SUMIFS(Overrides!$G$46:$G$75,Overrides!$F$46:$F$75,M$4)/1000 -> 0
A34: Total net revenue | B34: =SUM(B29:B33) -> 0 | C34: =SUM(C29:C33) -> 0 | D34: =SUM(D29:D33) -> 0 | E34: =SUM(E29:E33) -> 0 | F34: =SUM(F29:F33) -> 0 | G34: =SUM(G29:G33) -> 0 | H34: =SUM(H29:H33) -> 0.17380235 | I34: =SUM(I29:I33) -> 54.248666 | ... M34: =SUM(M29:M33) -> 247.70515
A35: of which enterprise true-ups | B35: =SUMIFS(Data_Monthly!$K:$K,Data_Monthly!$A:$A,B$4)/1000 -> 0 | C35: =SUMIFS(Data_Monthly!$K:$K,Data_Monthly!$A:$A,C$4)/1000 -> 0 | D35: =SUMIFS(Data_Monthly!$K:$K,Data_Monthly!$A:$A,D$4)/1000 -> 0 | E35: =SUMIFS(Data_Monthly!$K:$K,Data_Monthly!$A:$A,E$4)/1000 -> 0 | F35: =SUMIFS(Data_Monthly!$K:$K,Data_Monthly!$A:$A,F$4)/1000 -> 0 | G35: =SUMIFS(Data_Monthly!$K:$K,Data_Monthly!$A:$A,G$4)/1000 -> 0 | H35: =SUMIFS(Data_Monthly!$K:$K,Data_Monthly!$A:$A,H$4)/1000 -> 0 | I35: =SUMIFS(Data_Monthly!$K:$K,Data_Monthly!$A:$A,I$4)/1000 -> 31.419492 | ... M35: =SUMIFS(Data_Monthly!$K:$K,Data_Monthly!$A:$A,M$4)/1000 -> 27.556058
A36: Annualized run-rate ($k) | B36: =IF(B11=0,0,B34/B11*365) -> 0 | C36: =IF(C11=0,0,C34/C11*365) -> 0 | D36: =IF(D11=0,0,D34/D11*365) -> 0 | E36: =IF(E11=0,0,E34/E11*365) -> 0 | F36: =IF(F11=0,0,F34/F11*365) -> 0 | G36: =IF(G11=0,0,G34/G11*365) -> 0 | H36: =IF(H11=0,0,H34/H11*365) -> 3.9648661 | I36: =IF(I11=0,0,I34/I11*365) -> 638.7343 | ... M36: =IF(M11=0,0,M34/M11*365) -> 3229.0135
A37: Enterprise share of net revenue | B37: =IF(B34=0,0,B29/B34) -> 0 | C37: =IF(C34=0,0,C29/C34) -> 0 | D37: =IF(D34=0,0,D29/D34) -> 0 | E37: =IF(E34=0,0,E29/E34) -> 0 | F37: =IF(F34=0,0,F29/F34) -> 0 | G37: =IF(G34=0,0,G29/G34) -> 0 | H37: =IF(H34=0,0,H29/H34) -> 0 | I37: =IF(I34=0,0,I29/I34) -> 0.95735964 | ... M37: =IF(M34=0,0,M29/M34) -> 0.76750761
A38: Realized net price per M tokens ($) | B38: =IF(B10=0,0,B34/B10) -> 0 | C38: =IF(C10=0,0,C34/C10) -> 0 | D38: =IF(D10=0,0,D34/D10) -> 0 | E38: =IF(E10=0,0,E34/E10) -> 0 | F38: =IF(F10=0,0,F34/F10) -> 0 | G38: =IF(G10=0,0,G34/G10) -> 0 | H38: =IF(H10=0,0,H34/H10) -> 0.023908232 | I38: =IF(I10=0,0,I34/I10) -> 0.083775087 | ... M38: =IF(M10=0,0,M34/M10) -> 0.041009167
A40: Other lines
A41: List value of tokens ($k) | B41: =SUMIFS(Data_Monthly!$I:$I,Data_Monthly!$A:$A,B$4)/1000 -> 0 | C41: =SUMIFS(Data_Monthly!$I:$I,Data_Monthly!$A:$A,C$4)/1000 -> 0 | D41: =SUMIFS(Data_Monthly!$I:$I,Data_Monthly!$A:$A,D$4)/1000 -> 0 | E41: =SUMIFS(Data_Monthly!$I:$I,Data_Monthly!$A:$A,E$4)/1000 -> 0 | F41: =SUMIFS(Data_Monthly!$I:$I,Data_Monthly!$A:$A,F$4)/1000 -> 0 | G41: =SUMIFS(Data_Monthly!$I:$I,Data_Monthly!$A:$A,G$4)/1000 -> 0 | H41: =SUMIFS(Data_Monthly!$I:$I,Data_Monthly!$A:$A,H$4)/1000 -> 0.30532156 | I41: =SUMIFS(Data_Monthly!$I:$I,Data_Monthly!$A:$A,I$4)/1000 -> 27.197155 | ... M41: =SUMIFS(Data_Monthly!$I:$I,Data_Monthly!$A:$A,M$4)/1000 -> 253.69001
A42: Free credit used ($k) | B42: =SUMIFS(Data_Monthly!$H:$H,Data_Monthly!$A:$A,B$4)/1000 -> 0 | C42: =SUMIFS(Data_Monthly!$H:$H,Data_Monthly!$A:$A,C$4)/1000 -> 0 | D42: =SUMIFS(Data_Monthly!$H:$H,Data_Monthly!$A:$A,D$4)/1000 -> 0 | E42: =SUMIFS(Data_Monthly!$H:$H,Data_Monthly!$A:$A,E$4)/1000 -> 0 | F42: =SUMIFS(Data_Monthly!$H:$H,Data_Monthly!$A:$A,F$4)/1000 -> 0 | G42: =SUMIFS(Data_Monthly!$H:$H,Data_Monthly!$A:$A,G$4)/1000 -> 0 | H42: =SUMIFS(Data_Monthly!$H:$H,Data_Monthly!$A:$A,H$4)/1000 -> 0.12222719 | I42: =SUMIFS(Data_Monthly!$H:$H,Data_Monthly!$A:$A,I$4)/1000 -> 0.28133383 | ... M42: =SUMIFS(Data_Monthly!$H:$H,Data_Monthly!$A:$A,M$4)/1000 -> 0.447856
A43: Gateway fees ($k) | B43: =SUMIFS(Data_Monthly!$M:$M,Data_Monthly!$A:$A,B$4)/1000 -> 0 | C43: =SUMIFS(Data_Monthly!$M:$M,Data_Monthly!$A:$A,C$4)/1000 -> 0 | D43: =SUMIFS(Data_Monthly!$M:$M,Data_Monthly!$A:$A,D$4)/1000 -> 0 | E43: =SUMIFS(Data_Monthly!$M:$M,Data_Monthly!$A:$A,E$4)/1000 -> 0 | F43: =SUMIFS(Data_Monthly!$M:$M,Data_Monthly!$A:$A,F$4)/1000 -> 0 | G43: =SUMIFS(Data_Monthly!$M:$M,Data_Monthly!$A:$A,G$4)/1000 -> 0 | H43: =SUMIFS(Data_Monthly!$M:$M,Data_Monthly!$A:$A,H$4)/1000 -> 0.0092920223 | I43: =SUMIFS(Data_Monthly!$M:$M,Data_Monthly!$A:$A,I$4)/1000 -> 0.058981462 | ... M43: =SUMIFS(Data_Monthly!$M:$M,Data_Monthly!$A:$A,M$4)/1000 -> 1.7872256
A44: Active accounts (gateways counted once) | B44: =SUMIFS(Data_Monthly!$D:$D,Data_Monthly!$A:$A,B$4) -> 0 | C44: =SUMIFS(Data_Monthly!$D:$D,Data_Monthly!$A:$A,C$4) -> 0 | D44: =SUMIFS(Data_Monthly!$D:$D,Data_Monthly!$A:$A,D$4) -> 0 | E44: =SUMIFS(Data_Monthly!$D:$D,Data_Monthly!$A:$A,E$4) -> 0 | F44: =SUMIFS(Data_Monthly!$D:$D,Data_Monthly!$A:$A,F$4) -> 0 | G44: =SUMIFS(Data_Monthly!$D:$D,Data_Monthly!$A:$A,G$4) -> 0 | H44: =SUMIFS(Data_Monthly!$D:$D,Data_Monthly!$A:$A,H$4) -> 205 | I44: =SUMIFS(Data_Monthly!$D:$D,Data_Monthly!$A:$A,I$4) -> 386 | ... M44: =SUMIFS(Data_Monthly!$D:$D,Data_Monthly!$A:$A,M$4) -> 680
A45: Paying accounts | B45: =SUMIFS(Data_Monthly!$E:$E,Data_Monthly!$A:$A,B$4) -> 0 | C45: =SUMIFS(Data_Monthly!$E:$E,Data_Monthly!$A:$A,C$4) -> 0 | D45: =SUMIFS(Data_Monthly!$E:$E,Data_Monthly!$A:$A,D$4) -> 0 | E45: =SUMIFS(Data_Monthly!$E:$E,Data_Monthly!$A:$A,E$4) -> 0 | F45: =SUMIFS(Data_Monthly!$E:$E,Data_Monthly!$A:$A,F$4) -> 0 | G45: =SUMIFS(Data_Monthly!$E:$E,Data_Monthly!$A:$A,G$4) -> 0 | H45: =SUMIFS(Data_Monthly!$E:$E,Data_Monthly!$A:$A,H$4) -> 99 | I45: =SUMIFS(Data_Monthly!$E:$E,Data_Monthly!$A:$A,I$4) -> 209 | ... M45: =SUMIFS(Data_Monthly!$E:$E,Data_Monthly!$A:$A,M$4) -> 421
A46: Failed calls as % of all calls (not billed) | B46: =IF(SUMIFS(Data_Reliability!$B:$B,Data_Reliability!$A:$A,B$4)+SUMIFS(Data_Reliability!$C:$C,Data_Reliability!$A:$A,B$4)=0,0,SUMIFS(Data_Reliability!$C:$C,Data_Reliability!$A:$A,B$4)/(SUMIFS(Data_Reliability!$B:$B,Data_Reliability!$A:$A,B$4)+SUMIFS(Data_Reliability!$C:$C,Data_Reliability!$A:$A,B$4))) -> 0 | C46: =IF(SUMIFS(Data_Reliability!$B:$B,Data_Reliability!$A:$A,C$4)+SUMIFS(Data_Reliability!$C:$C,Data_Reliability!$A:$A,C$4)=0,0,SUMIFS(Data_Reliability!$C:$C,Data_Reliability!$A:$A,C$4)/(SUMIFS(Data_Reliability!$B:$B,Data_Reliability!$A:$A,C$4)+SUMIFS(Data_Reliability!$C:$C,Data_Reliability!$A:$A,C$4))) -> 0 | D46: =IF(SUMIFS(Data_Reliability!$B:$B,Data_Reliability!$A:$A,D$4)+SUMIFS(Data_Reliability!$C:$C,Data_Reliability!$A:$A,D$4)=0,0,SUMIFS(Data_Reliability!$C:$C,Data_Reliability!$A:$A,D$4)/(SUMIFS(Data_Reliability!$B:$B,Data_Reliability!$A:$A,D$4)+SUMIFS(Data_Reliability!$C:$C,Data_Reliability!$A:$A,D$4))) -> 0 | E46: =IF(SUMIFS(Data_Reliability!$B:$B,Data_Reliability!$A:$A,E$4)+SUMIFS(Data_Reliability!$C:$C,Data_Reliability!$A:$A,E$4)=0,0,SUMIFS(Data_Reliability!$C:$C,Data_Reliability!$A:$A,E$4)/(SUMIFS(Data_Reliability!$B:$B,Data_Reliability!$A:$A,E$4)+SUMIFS(Data_Reliability!$C:$C,Data_Reliability!$A:$A,E$4))) -> 0 | F46: =IF(SUMIFS(Data_Reliability!$B:$B,Data_Reliability!$A:$A,F$4)+SUMIFS(Data_Reliability!$C:$C,Data_Reliability!$A:$A,F$4)=0,0,SUMIFS(Data_Reliability!$C:$C,Data_Reliability!$A:$A,F$4)/(SUMIFS(Data_Reliability!$B:$B,Data_Reliability!$A:$A,F$4)+SUMIFS(Data_Reliability!$C:$C,Data_Reliability!$A:$A,F$4))) -> 0 | G46: =IF(SUMIFS(Data_Reliability!$B:$B,Data_Reliability!$A:$A,G$4)+SUMIFS(Data_Reliability!$C:$C,Data_Reliability!$A:$A,G$4)=0,0,SUMIFS(Data_Reliability!$C:$C,Data_Reliability!$A:$A,G$4)/(SUMIFS(Data_Reliability!$B:$B,Data_Reliability!$A:$A,G$4)+SUMIFS(Data_Reliability!$C:$C,Data_Reliability!$A:$A,G$4))) -> 0 | H46: =IF(SUMIFS(Data_Reliability!$B:$B,Data_Reliability!$A:$A,H$4)+SUMIFS(Data_Reliability!$C:$C,Data_Reliability!$A:$A,H$4)=0,0,SUMIFS(Data_Reliability!$C:$C,Data_Reliability!$A:$A,H$4)/(SUMIFS(Data_Reliability!$B:$B,Data_Reliability!$A:$A,H$4)+SUMIFS(Data_Reliability!$C:$C,Data_Reliability!$A:$A,H$4))) -> 0.0037498935 | I46: =IF(SUMIFS(Data_Reliability!$B:$B,Data_Reliability!$A:$A,I$4)+SUMIFS(Data_Reliability!$C:$C,Data_Reliability!$A:$A,I$4)=0,0,SUMIFS(Data_Reliability!$C:$C,Data_Reliability!$A:$A,I$4)/(SUMIFS(Data_Reliability!$B:$B,Data_Reliability!$A:$A,I$4)+SUMIFS(Data_Reliability!$C:$C,Data_Reliability!$A:$A,I$4))) -> 0.0058980202 | ... M46: =IF(SUMIFS(Data_Reliability!$B:$B,Data_Reliability!$A:$A,M$4)+SUMIFS(Data_Reliability!$C:$C,Data_Reliability!$A:$A,M$4)=0,0,SUMIFS(Data_Reliability!$C:$C,Data_Reliability!$A:$A,M$4)/(SUMIFS(Data_Reliability!$B:$B,Data_Reliability!$A:$A,M$4)+SUMIFS(Data_Reliability!$C:$C,Data_Reliability!$A:$A,M$4))) -> 0.0059398741

Sheet UseCases
A1: =Data_Params!$B$14&" | Where usage comes from" -> Example Co (synthetic data) | Where usage comes from
A2: Use case from the customer's project label when mapped (label_map), otherwise inferred from traffic shape (sql/20_use_case_rules.sql).
A4: Use case (B tokens) | B4: =EDATE(Data_Params!$B$3,0) -> 46082 | C4: =EDATE(Data_Params!$B$3,1) -> 46113 | D4: =EDATE(Data_Params!$B$3,2) -> 46143 | E4: =EDATE(Data_Params!$B$3,3) -> 46174 | F4: =EDATE(Data_Params!$B$3,4) -> 46204 | G4: =EDATE(Data_Params!$B$3,5) -> 46235 | H4: =EDATE(Data_Params!$B$3,6) -> 46266 | I4: =EDATE(Data_Params!$B$3,7) -> 46296 | J4: =EDATE(Data_Params!$B$3,8) -> 46327 | K4: =EDATE(Data_Params!$B$3,9) -> 46357 | L4: =EDATE(Data_Params!$B$3,10) -> 46388 | M4: =EDATE(Data_Params!$B$3,11) -> 46419 | N4: Share of latest month | O4: From label, latest month
A5: =IF(INDEX(Data_Lists!$C:$C,1+1)="","",INDEX(Data_Lists!$C:$C,1+1)) -> fraud_triage | B5: =IF($A5="","",SUMIFS(Data_UseCase!$C:$C,Data_UseCase!$A:$A,B$4,Data_UseCase!$B:$B,$A5)/1000000000) -> 0 | C5: =IF($A5="","",SUMIFS(Data_UseCase!$C:$C,Data_UseCase!$A:$A,C$4,Data_UseCase!$B:$B,$A5)/1000000000) -> 0 | D5: =IF($A5="","",SUMIFS(Data_UseCase!$C:$C,Data_UseCase!$A:$A,D$4,Data_UseCase!$B:$B,$A5)/1000000000) -> 0 | E5: =IF($A5="","",SUMIFS(Data_UseCase!$C:$C,Data_UseCase!$A:$A,E$4,Data_UseCase!$B:$B,$A5)/1000000000) -> 0 | F5: =IF($A5="","",SUMIFS(Data_UseCase!$C:$C,Data_UseCase!$A:$A,F$4,Data_UseCase!$B:$B,$A5)/1000000000) -> 0 | G5: =IF($A5="","",SUMIFS(Data_UseCase!$C:$C,Data_UseCase!$A:$A,G$4,Data_UseCase!$B:$B,$A5)/1000000000) -> 0 | H5: =IF($A5="","",SUMIFS(Data_UseCase!$C:$C,Data_UseCase!$A:$A,H$4,Data_UseCase!$B:$B,$A5)/1000000000) -> 0.26967756 | I5: =IF($A5="","",SUMIFS(Data_UseCase!$C:$C,Data_UseCase!$A:$A,I$4,Data_UseCase!$B:$B,$A5)/1000000000) -> 140.06946 | ... M5: =IF($A5="","",SUMIFS(Data_UseCase!$C:$C,Data_UseCase!$A:$A,M$4,Data_UseCase!$B:$B,$A5)/1000000000) -> 1147.9804 | N5: =IF($A5="","",IF(M$20=0,0,M5/M$20)) -> 0.19005547 | O5: =IF(OR($A5="",N(M5)=0),"",SUMIFS(Data_UseCase!$D:$D,Data_UseCase!$A:$A,M$4,Data_UseCase!$B:$B,$A5)/1000000000/M5) -> 0.93921252
A6: =IF(INDEX(Data_Lists!$C:$C,2+1)="","",INDEX(Data_Lists!$C:$C,2+1)) -> llm_guardrails | B6: =IF($A6="","",SUMIFS(Data_UseCase!$C:$C,Data_UseCase!$A:$A,B$4,Data_UseCase!$B:$B,$A6)/1000000000) -> 0 | C6: =IF($A6="","",SUMIFS(Data_UseCase!$C:$C,Data_UseCase!$A:$A,C$4,Data_UseCase!$B:$B,$A6)/1000000000) -> 0 | D6: =IF($A6="","",SUMIFS(Data_UseCase!$C:$C,Data_UseCase!$A:$A,D$4,Data_UseCase!$B:$B,$A6)/1000000000) -> 0 | E6: =IF($A6="","",SUMIFS(Data_UseCase!$C:$C,Data_UseCase!$A:$A,E$4,Data_UseCase!$B:$B,$A6)/1000000000) -> 0 | F6: =IF($A6="","",SUMIFS(Data_UseCase!$C:$C,Data_UseCase!$A:$A,F$4,Data_UseCase!$B:$B,$A6)/1000000000) -> 0 | G6: =IF($A6="","",SUMIFS(Data_UseCase!$C:$C,Data_UseCase!$A:$A,G$4,Data_UseCase!$B:$B,$A6)/1000000000) -> 0 | H6: =IF($A6="","",SUMIFS(Data_UseCase!$C:$C,Data_UseCase!$A:$A,H$4,Data_UseCase!$B:$B,$A6)/1000000000) -> 1.0938073 | I6: =IF($A6="","",SUMIFS(Data_UseCase!$C:$C,Data_UseCase!$A:$A,I$4,Data_UseCase!$B:$B,$A6)/1000000000) -> 258.77162 | ... M6: =IF($A6="","",SUMIFS(Data_UseCase!$C:$C,Data_UseCase!$A:$A,M$4,Data_UseCase!$B:$B,$A6)/1000000000) -> 1080.0574 | N6: =IF($A6="","",IF(M$20=0,0,M6/M$20)) -> 0.1788104 | O6: =IF(OR($A6="",N(M6)=0),"",SUMIFS(Data_UseCase!$D:$D,Data_UseCase!$A:$A,M$4,Data_UseCase!$B:$B,$A6)/1000000000/M6) -> 0.12546205
A7: =IF(INDEX(Data_Lists!$C:$C,3+1)="","",INDEX(Data_Lists!$C:$C,3+1)) -> model_routing | B7: =IF($A7="","",SUMIFS(Data_UseCase!$C:$C,Data_UseCase!$A:$A,B$4,Data_UseCase!$B:$B,$A7)/1000000000) -> 0 | C7: =IF($A7="","",SUMIFS(Data_UseCase!$C:$C,Data_UseCase!$A:$A,C$4,Data_UseCase!$B:$B,$A7)/1000000000) -> 0 | D7: =IF($A7="","",SUMIFS(Data_UseCase!$C:$C,Data_UseCase!$A:$A,D$4,Data_UseCase!$B:$B,$A7)/1000000000) -> 0 | E7: =IF($A7="","",SUMIFS(Data_UseCase!$C:$C,Data_UseCase!$A:$A,E$4,Data_UseCase!$B:$B,$A7)/1000000000) -> 0 | F7: =IF($A7="","",SUMIFS(Data_UseCase!$C:$C,Data_UseCase!$A:$A,F$4,Data_UseCase!$B:$B,$A7)/1000000000) -> 0 | G7: =IF($A7="","",SUMIFS(Data_UseCase!$C:$C,Data_UseCase!$A:$A,G$4,Data_UseCase!$B:$B,$A7)/1000000000) -> 0 | H7: =IF($A7="","",SUMIFS(Data_UseCase!$C:$C,Data_UseCase!$A:$A,H$4,Data_UseCase!$B:$B,$A7)/1000000000) -> 1.1992365 | I7: =IF($A7="","",SUMIFS(Data_UseCase!$C:$C,Data_UseCase!$A:$A,I$4,Data_UseCase!$B:$B,$A7)/1000000000) -> 176.62998 | ... M7: =IF($A7="","",SUMIFS(Data_UseCase!$C:$C,Data_UseCase!$A:$A,M$4,Data_UseCase!$B:$B,$A7)/1000000000) -> 618.14796 | N7: =IF($A7="","",IF(M$20=0,0,M7/M$20)) -> 0.10233834 | O7: =IF(OR($A7="",N(M7)=0),"",SUMIFS(Data_UseCase!$D:$D,Data_UseCase!$A:$A,M$4,Data_UseCase!$B:$B,$A7)/1000000000/M7) -> 0.82329277
A8: =IF(INDEX(Data_Lists!$C:$C,4+1)="","",INDEX(Data_Lists!$C:$C,4+1)) -> data_enrichment | B8: =IF($A8="","",SUMIFS(Data_UseCase!$C:$C,Data_UseCase!$A:$A,B$4,Data_UseCase!$B:$B,$A8)/1000000000) -> 0 | C8: =IF($A8="","",SUMIFS(Data_UseCase!$C:$C,Data_UseCase!$A:$A,C$4,Data_UseCase!$B:$B,$A8)/1000000000) -> 0 | D8: =IF($A8="","",SUMIFS(Data_UseCase!$C:$C,Data_UseCase!$A:$A,D$4,Data_UseCase!$B:$B,$A8)/1000000000) -> 0 | E8: =IF($A8="","",SUMIFS(Data_UseCase!$C:$C,Data_UseCase!$A:$A,E$4,Data_UseCase!$B:$B,$A8)/1000000000) -> 0 | F8: =IF($A8="","",SUMIFS(Data_UseCase!$C:$C,Data_UseCase!$A:$A,F$4,Data_UseCase!$B:$B,$A8)/1000000000) -> 0 | G8: =IF($A8="","",SUMIFS(Data_UseCase!$C:$C,Data_UseCase!$A:$A,G$4,Data_UseCase!$B:$B,$A8)/1000000000) -> 0 | H8: =IF($A8="","",SUMIFS(Data_UseCase!$C:$C,Data_UseCase!$A:$A,H$4,Data_UseCase!$B:$B,$A8)/1000000000) -> 0.33531424 | I8: =IF($A8="","",SUMIFS(Data_UseCase!$C:$C,Data_UseCase!$A:$A,I$4,Data_UseCase!$B:$B,$A8)/1000000000) -> 5.8071945 | ... M8: =IF($A8="","",SUMIFS(Data_UseCase!$C:$C,Data_UseCase!$A:$A,M$4,Data_UseCase!$B:$B,$A8)/1000000000) -> 1012.2493 | N8: =IF($A8="","",IF(M$20=0,0,M8/M$20)) -> 0.16758433 | O8: =IF(OR($A8="",N(M8)=0),"",SUMIFS(Data_UseCase!$D:$D,Data_UseCase!$A:$A,M$4,Data_UseCase!$B:$B,$A8)/1000000000/M8) -> 0.94985246
A9: =IF(INDEX(Data_Lists!$C:$C,5+1)="","",INDEX(Data_Lists!$C:$C,5+1)) -> moderation | B9: =IF($A9="","",SUMIFS(Data_UseCase!$C:$C,Data_UseCase!$A:$A,B$4,Data_UseCase!$B:$B,$A9)/1000000000) -> 0 | C9: =IF($A9="","",SUMIFS(Data_UseCase!$C:$C,Data_UseCase!$A:$A,C$4,Data_UseCase!$B:$B,$A9)/1000000000) -> 0 | D9: =IF($A9="","",SUMIFS(Data_UseCase!$C:$C,Data_UseCase!$A:$A,D$4,Data_UseCase!$B:$B,$A9)/1000000000) -> 0 | E9: =IF($A9="","",SUMIFS(Data_UseCase!$C:$C,Data_UseCase!$A:$A,E$4,Data_UseCase!$B:$B,$A9)/1000000000) -> 0 | F9: =IF($A9="","",SUMIFS(Data_UseCase!$C:$C,Data_UseCase!$A:$A,F$4,Data_UseCase!$B:$B,$A9)/1000000000) -> 0 | G9: =IF($A9="","",SUMIFS(Data_UseCase!$C:$C,Data_UseCase!$A:$A,G$4,Data_UseCase!$B:$B,$A9)/1000000000) -> 0 | H9: =IF($A9="","",SUMIFS(Data_UseCase!$C:$C,Data_UseCase!$A:$A,H$4,Data_UseCase!$B:$B,$A9)/1000000000) -> 1.0075728 | I9: =IF($A9="","",SUMIFS(Data_UseCase!$C:$C,Data_UseCase!$A:$A,I$4,Data_UseCase!$B:$B,$A9)/1000000000) -> 4.5176457 | ... M9: =IF($A9="","",SUMIFS(Data_UseCase!$C:$C,Data_UseCase!$A:$A,M$4,Data_UseCase!$B:$B,$A9)/1000000000) -> 757.1875 | N9: =IF($A9="","",IF(M$20=0,0,M9/M$20)) -> 0.12535722 | O9: =IF(OR($A9="",N(M9)=0),"",SUMIFS(Data_UseCase!$D:$D,Data_UseCase!$A:$A,M$4,Data_UseCase!$B:$B,$A9)/1000000000/M9) -> 0.93890056
A10: =IF(INDEX(Data_Lists!$C:$C,6+1)="","",INDEX(Data_Lists!$C:$C,6+1)) -> doc_classification | B10: =IF($A10="","",SUMIFS(Data_UseCase!$C:$C,Data_UseCase!$A:$A,B$4,Data_UseCase!$B:$B,$A10)/1000000000) -> 0 | C10: =IF($A10="","",SUMIFS(Data_UseCase!$C:$C,Data_UseCase!$A:$A,C$4,Data_UseCase!$B:$B,$A10)/1000000000) -> 0 | D10: =IF($A10="","",SUMIFS(Data_UseCase!$C:$C,Data_UseCase!$A:$A,D$4,Data_UseCase!$B:$B,$A10)/1000000000) -> 0 | E10: =IF($A10="","",SUMIFS(Data_UseCase!$C:$C,Data_UseCase!$A:$A,E$4,Data_UseCase!$B:$B,$A10)/1000000000) -> 0 | F10: =IF($A10="","",SUMIFS(Data_UseCase!$C:$C,Data_UseCase!$A:$A,F$4,Data_UseCase!$B:$B,$A10)/1000000000) -> 0 | G10: =IF($A10="","",SUMIFS(Data_UseCase!$C:$C,Data_UseCase!$A:$A,G$4,Data_UseCase!$B:$B,$A10)/1000000000) -> 0 | H10: =IF($A10="","",SUMIFS(Data_UseCase!$C:$C,Data_UseCase!$A:$A,H$4,Data_UseCase!$B:$B,$A10)/1000000000) -> 0.33287943 | I10: =IF($A10="","",SUMIFS(Data_UseCase!$C:$C,Data_UseCase!$A:$A,I$4,Data_UseCase!$B:$B,$A10)/1000000000) -> 28.958846 | ... M10: =IF($A10="","",SUMIFS(Data_UseCase!$C:$C,Data_UseCase!$A:$A,M$4,Data_UseCase!$B:$B,$A10)/1000000000) -> 558.15022 | N10: =IF($A10="","",IF(M$20=0,0,M10/M$20)) -> 0.09240533 | O10: =IF(OR($A10="",N(M10)=0),"",SUMIFS(Data_UseCase!$D:$D,Data_UseCase!$A:$A,M$4,Data_UseCase!$B:$B,$A10)/1000000000/M10) -> 0.97581507
A11: =IF(INDEX(Data_Lists!$C:$C,7+1)="","",INDEX(Data_Lists!$C:$C,7+1)) -> ticket_routing | B11: =IF($A11="","",SUMIFS(Data_UseCase!$C:$C,Data_UseCase!$A:$A,B$4,Data_UseCase!$B:$B,$A11)/1000000000) -> 0 | C11: =IF($A11="","",SUMIFS(Data_UseCase!$C:$C,Data_UseCase!$A:$A,C$4,Data_UseCase!$B:$B,$A11)/1000000000) -> 0 | D11: =IF($A11="","",SUMIFS(Data_UseCase!$C:$C,Data_UseCase!$A:$A,D$4,Data_UseCase!$B:$B,$A11)/1000000000) -> 0 | E11: =IF($A11="","",SUMIFS(Data_UseCase!$C:$C,Data_UseCase!$A:$A,E$4,Data_UseCase!$B:$B,$A11)/1000000000) -> 0 | F11: =IF($A11="","",SUMIFS(Data_UseCase!$C:$C,Data_UseCase!$A:$A,F$4,Data_UseCase!$B:$B,$A11)/1000000000) -> 0 | G11: =IF($A11="","",SUMIFS(Data_UseCase!$C:$C,Data_UseCase!$A:$A,G$4,Data_UseCase!$B:$B,$A11)/1000000000) -> 0 | H11: =IF($A11="","",SUMIFS(Data_UseCase!$C:$C,Data_UseCase!$A:$A,H$4,Data_UseCase!$B:$B,$A11)/1000000000) -> 0.47096489 | I11: =IF($A11="","",SUMIFS(Data_UseCase!$C:$C,Data_UseCase!$A:$A,I$4,Data_UseCase!$B:$B,$A11)/1000000000) -> 8.2682297 | ... M11: =IF($A11="","",SUMIFS(Data_UseCase!$C:$C,Data_UseCase!$A:$A,M$4,Data_UseCase!$B:$B,$A11)/1000000000) -> 393.82933 | N11: =IF($A11="","",IF(M$20=0,0,M11/M$20)) -> 0.065200958 | O11: =IF(OR($A11="",N(M11)=0),"",SUMIFS(Data_UseCase!$D:$D,Data_UseCase!$A:$A,M$4,Data_UseCase!$B:$B,$A11)/1000000000/M11) -> 0.90163041
A12: =IF(INDEX(Data_Lists!$C:$C,8+1)="","",INDEX(Data_Lists!$C:$C,8+1)) -> rag_rerank | B12: =IF($A12="","",SUMIFS(Data_UseCase!$C:$C,Data_UseCase!$A:$A,B$4,Data_UseCase!$B:$B,$A12)/1000000000) -> 0 | C12: =IF($A12="","",SUMIFS(Data_UseCase!$C:$C,Data_UseCase!$A:$A,C$4,Data_UseCase!$B:$B,$A12)/1000000000) -> 0 | D12: =IF($A12="","",SUMIFS(Data_UseCase!$C:$C,Data_UseCase!$A:$A,D$4,Data_UseCase!$B:$B,$A12)/1000000000) -> 0 | E12: =IF($A12="","",SUMIFS(Data_UseCase!$C:$C,Data_UseCase!$A:$A,E$4,Data_UseCase!$B:$B,$A12)/1000000000) -> 0 | F12: =IF($A12="","",SUMIFS(Data_UseCase!$C:$C,Data_UseCase!$A:$A,F$4,Data_UseCase!$B:$B,$A12)/1000000000) -> 0 | G12: =IF($A12="","",SUMIFS(Data_UseCase!$C:$C,Data_UseCase!$A:$A,G$4,Data_UseCase!$B:$B,$A12)/1000000000) -> 0 | H12: =IF($A12="","",SUMIFS(Data_UseCase!$C:$C,Data_UseCase!$A:$A,H$4,Data_UseCase!$B:$B,$A12)/1000000000) -> 1.0603484 | I12: =IF($A12="","",SUMIFS(Data_UseCase!$C:$C,Data_UseCase!$A:$A,I$4,Data_UseCase!$B:$B,$A12)/1000000000) -> 4.4554084 | ... M12: =IF($A12="","",SUMIFS(Data_UseCase!$C:$C,Data_UseCase!$A:$A,M$4,Data_UseCase!$B:$B,$A12)/1000000000) -> 313.40323 | N12: =IF($A12="","",IF(M$20=0,0,M12/M$20)) -> 0.051885904 | O12: =IF(OR($A12="",N(M12)=0),"",SUMIFS(Data_UseCase!$D:$D,Data_UseCase!$A:$A,M$4,Data_UseCase!$B:$B,$A12)/1000000000/M12) -> 0.050893381
A13: =IF(INDEX(Data_Lists!$C:$C,9+1)="","",INDEX(Data_Lists!$C:$C,9+1)) -> ci_lint | B13: =IF($A13="","",SUMIFS(Data_UseCase!$C:$C,Data_UseCase!$A:$A,B$4,Data_UseCase!$B:$B,$A13)/1000000000) -> 0 | C13: =IF($A13="","",SUMIFS(Data_UseCase!$C:$C,Data_UseCase!$A:$A,C$4,Data_UseCase!$B:$B,$A13)/1000000000) -> 0 | D13: =IF($A13="","",SUMIFS(Data_UseCase!$C:$C,Data_UseCase!$A:$A,D$4,Data_UseCase!$B:$B,$A13)/1000000000) -> 0 | E13: =IF($A13="","",SUMIFS(Data_UseCase!$C:$C,Data_UseCase!$A:$A,E$4,Data_UseCase!$B:$B,$A13)/1000000000) -> 0 | F13: =IF($A13="","",SUMIFS(Data_UseCase!$C:$C,Data_UseCase!$A:$A,F$4,Data_UseCase!$B:$B,$A13)/1000000000) -> 0 | G13: =IF($A13="","",SUMIFS(Data_UseCase!$C:$C,Data_UseCase!$A:$A,G$4,Data_UseCase!$B:$B,$A13)/1000000000) -> 0 | H13: =IF($A13="","",SUMIFS(Data_UseCase!$C:$C,Data_UseCase!$A:$A,H$4,Data_UseCase!$B:$B,$A13)/1000000000) -> 1.0307572 | I13: =IF($A13="","",SUMIFS(Data_UseCase!$C:$C,Data_UseCase!$A:$A,I$4,Data_UseCase!$B:$B,$A13)/1000000000) -> 18.275089 | ... M13: =IF($A13="","",SUMIFS(Data_UseCase!$C:$C,Data_UseCase!$A:$A,M$4,Data_UseCase!$B:$B,$A13)/1000000000) -> 69.144671 | N13: =IF($A13="","",IF(M$20=0,0,M13/M$20)) -> 0.011447341 | O13: =IF(OR($A13="",N(M13)=0),"",SUMIFS(Data_UseCase!$D:$D,Data_UseCase!$A:$A,M$4,Data_UseCase!$B:$B,$A13)/1000000000/M13) -> 0.25617491
A14: =IF(INDEX(Data_Lists!$C:$C,10+1)="","",INDEX(Data_Lists!$C:$C,10+1)) -> lead_scoring | B14: =IF($A14="","",SUMIFS(Data_UseCase!$C:$C,Data_UseCase!$A:$A,B$4,Data_UseCase!$B:$B,$A14)/1000000000) -> 0 | C14: =IF($A14="","",SUMIFS(Data_UseCase!$C:$C,Data_UseCase!$A:$A,C$4,Data_UseCase!$B:$B,$A14)/1000000000) -> 0 | D14: =IF($A14="","",SUMIFS(Data_UseCase!$C:$C,Data_UseCase!$A:$A,D$4,Data_UseCase!$B:$B,$A14)/1000000000) -> 0 | E14: =IF($A14="","",SUMIFS(Data_UseCase!$C:$C,Data_UseCase!$A:$A,E$4,Data_UseCase!$B:$B,$A14)/1000000000) -> 0 | F14: =IF($A14="","",SUMIFS(Data_UseCase!$C:$C,Data_UseCase!$A:$A,F$4,Data_UseCase!$B:$B,$A14)/1000000000) -> 0 | G14: =IF($A14="","",SUMIFS(Data_UseCase!$C:$C,Data_UseCase!$A:$A,G$4,Data_UseCase!$B:$B,$A14)/1000000000) -> 0 | H14: =IF($A14="","",SUMIFS(Data_UseCase!$C:$C,Data_UseCase!$A:$A,H$4,Data_UseCase!$B:$B,$A14)/1000000000) -> 0.46900246 | I14: =IF($A14="","",SUMIFS(Data_UseCase!$C:$C,Data_UseCase!$A:$A,I$4,Data_UseCase!$B:$B,$A14)/1000000000) -> 1.797828 | ... M14: =IF($A14="","",SUMIFS(Data_UseCase!$C:$C,Data_UseCase!$A:$A,M$4,Data_UseCase!$B:$B,$A14)/1000000000) -> 90.088401 | N14: =IF($A14="","",IF(M$20=0,0,M14/M$20)) -> 0.014914709 | O14: =IF(OR($A14="",N(M14)=0),"",SUMIFS(Data_UseCase!$D:$D,Data_UseCase!$A:$A,M$4,Data_UseCase!$B:$B,$A14)/1000000000/M14) -> 0.53521262
A15: =IF(INDEX(Data_Lists!$C:$C,11+1)="","",INDEX(Data_Lists!$C:$C,11+1)) | B15: =IF($A15="","",SUMIFS(Data_UseCase!$C:$C,Data_UseCase!$A:$A,B$4,Data_UseCase!$B:$B,$A15)/1000000000) | C15: =IF($A15="","",SUMIFS(Data_UseCase!$C:$C,Data_UseCase!$A:$A,C$4,Data_UseCase!$B:$B,$A15)/1000000000) | D15: =IF($A15="","",SUMIFS(Data_UseCase!$C:$C,Data_UseCase!$A:$A,D$4,Data_UseCase!$B:$B,$A15)/1000000000) | E15: =IF($A15="","",SUMIFS(Data_UseCase!$C:$C,Data_UseCase!$A:$A,E$4,Data_UseCase!$B:$B,$A15)/1000000000) | F15: =IF($A15="","",SUMIFS(Data_UseCase!$C:$C,Data_UseCase!$A:$A,F$4,Data_UseCase!$B:$B,$A15)/1000000000) | G15: =IF($A15="","",SUMIFS(Data_UseCase!$C:$C,Data_UseCase!$A:$A,G$4,Data_UseCase!$B:$B,$A15)/1000000000) | H15: =IF($A15="","",SUMIFS(Data_UseCase!$C:$C,Data_UseCase!$A:$A,H$4,Data_UseCase!$B:$B,$A15)/1000000000) | I15: =IF($A15="","",SUMIFS(Data_UseCase!$C:$C,Data_UseCase!$A:$A,I$4,Data_UseCase!$B:$B,$A15)/1000000000) | ... M15: =IF($A15="","",SUMIFS(Data_UseCase!$C:$C,Data_UseCase!$A:$A,M$4,Data_UseCase!$B:$B,$A15)/1000000000) | N15: =IF($A15="","",IF(M$20=0,0,M15/M$20)) | O15: =IF(OR($A15="",N(M15)=0),"",SUMIFS(Data_UseCase!$D:$D,Data_UseCase!$A:$A,M$4,Data_UseCase!$B:$B,$A15)/1000000000/M15)
A16: =IF(INDEX(Data_Lists!$C:$C,12+1)="","",INDEX(Data_Lists!$C:$C,12+1)) | B16: =IF($A16="","",SUMIFS(Data_UseCase!$C:$C,Data_UseCase!$A:$A,B$4,Data_UseCase!$B:$B,$A16)/1000000000) | C16: =IF($A16="","",SUMIFS(Data_UseCase!$C:$C,Data_UseCase!$A:$A,C$4,Data_UseCase!$B:$B,$A16)/1000000000) | D16: =IF($A16="","",SUMIFS(Data_UseCase!$C:$C,Data_UseCase!$A:$A,D$4,Data_UseCase!$B:$B,$A16)/1000000000) | E16: =IF($A16="","",SUMIFS(Data_UseCase!$C:$C,Data_UseCase!$A:$A,E$4,Data_UseCase!$B:$B,$A16)/1000000000) | F16: =IF($A16="","",SUMIFS(Data_UseCase!$C:$C,Data_UseCase!$A:$A,F$4,Data_UseCase!$B:$B,$A16)/1000000000) | G16: =IF($A16="","",SUMIFS(Data_UseCase!$C:$C,Data_UseCase!$A:$A,G$4,Data_UseCase!$B:$B,$A16)/1000000000) | H16: =IF($A16="","",SUMIFS(Data_UseCase!$C:$C,Data_UseCase!$A:$A,H$4,Data_UseCase!$B:$B,$A16)/1000000000) | I16: =IF($A16="","",SUMIFS(Data_UseCase!$C:$C,Data_UseCase!$A:$A,I$4,Data_UseCase!$B:$B,$A16)/1000000000) | ... M16: =IF($A16="","",SUMIFS(Data_UseCase!$C:$C,Data_UseCase!$A:$A,M$4,Data_UseCase!$B:$B,$A16)/1000000000) | N16: =IF($A16="","",IF(M$20=0,0,M16/M$20)) | O16: =IF(OR($A16="",N(M16)=0),"",SUMIFS(Data_UseCase!$D:$D,Data_UseCase!$A:$A,M$4,Data_UseCase!$B:$B,$A16)/1000000000/M16)
A17: =IF(INDEX(Data_Lists!$C:$C,13+1)="","",INDEX(Data_Lists!$C:$C,13+1)) | B17: =IF($A17="","",SUMIFS(Data_UseCase!$C:$C,Data_UseCase!$A:$A,B$4,Data_UseCase!$B:$B,$A17)/1000000000) | C17: =IF($A17="","",SUMIFS(Data_UseCase!$C:$C,Data_UseCase!$A:$A,C$4,Data_UseCase!$B:$B,$A17)/1000000000) | D17: =IF($A17="","",SUMIFS(Data_UseCase!$C:$C,Data_UseCase!$A:$A,D$4,Data_UseCase!$B:$B,$A17)/1000000000) | E17: =IF($A17="","",SUMIFS(Data_UseCase!$C:$C,Data_UseCase!$A:$A,E$4,Data_UseCase!$B:$B,$A17)/1000000000) | F17: =IF($A17="","",SUMIFS(Data_UseCase!$C:$C,Data_UseCase!$A:$A,F$4,Data_UseCase!$B:$B,$A17)/1000000000) | G17: =IF($A17="","",SUMIFS(Data_UseCase!$C:$C,Data_UseCase!$A:$A,G$4,Data_UseCase!$B:$B,$A17)/1000000000) | H17: =IF($A17="","",SUMIFS(Data_UseCase!$C:$C,Data_UseCase!$A:$A,H$4,Data_UseCase!$B:$B,$A17)/1000000000) | I17: =IF($A17="","",SUMIFS(Data_UseCase!$C:$C,Data_UseCase!$A:$A,I$4,Data_UseCase!$B:$B,$A17)/1000000000) | ... M17: =IF($A17="","",SUMIFS(Data_UseCase!$C:$C,Data_UseCase!$A:$A,M$4,Data_UseCase!$B:$B,$A17)/1000000000) | N17: =IF($A17="","",IF(M$20=0,0,M17/M$20)) | O17: =IF(OR($A17="",N(M17)=0),"",SUMIFS(Data_UseCase!$D:$D,Data_UseCase!$A:$A,M$4,Data_UseCase!$B:$B,$A17)/1000000000/M17)
A18: =IF(INDEX(Data_Lists!$C:$C,14+1)="","",INDEX(Data_Lists!$C:$C,14+1)) | B18: =IF($A18="","",SUMIFS(Data_UseCase!$C:$C,Data_UseCase!$A:$A,B$4,Data_UseCase!$B:$B,$A18)/1000000000) | C18: =IF($A18="","",SUMIFS(Data_UseCase!$C:$C,Data_UseCase!$A:$A,C$4,Data_UseCase!$B:$B,$A18)/1000000000) | D18: =IF($A18="","",SUMIFS(Data_UseCase!$C:$C,Data_UseCase!$A:$A,D$4,Data_UseCase!$B:$B,$A18)/1000000000) | E18: =IF($A18="","",SUMIFS(Data_UseCase!$C:$C,Data_UseCase!$A:$A,E$4,Data_UseCase!$B:$B,$A18)/1000000000) | F18: =IF($A18="","",SUMIFS(Data_UseCase!$C:$C,Data_UseCase!$A:$A,F$4,Data_UseCase!$B:$B,$A18)/1000000000) | G18: =IF($A18="","",SUMIFS(Data_UseCase!$C:$C,Data_UseCase!$A:$A,G$4,Data_UseCase!$B:$B,$A18)/1000000000) | H18: =IF($A18="","",SUMIFS(Data_UseCase!$C:$C,Data_UseCase!$A:$A,H$4,Data_UseCase!$B:$B,$A18)/1000000000) | I18: =IF($A18="","",SUMIFS(Data_UseCase!$C:$C,Data_UseCase!$A:$A,I$4,Data_UseCase!$B:$B,$A18)/1000000000) | ... M18: =IF($A18="","",SUMIFS(Data_UseCase!$C:$C,Data_UseCase!$A:$A,M$4,Data_UseCase!$B:$B,$A18)/1000000000) | N18: =IF($A18="","",IF(M$20=0,0,M18/M$20)) | O18: =IF(OR($A18="",N(M18)=0),"",SUMIFS(Data_UseCase!$D:$D,Data_UseCase!$A:$A,M$4,Data_UseCase!$B:$B,$A18)/1000000000/M18)
A19: =IF(INDEX(Data_Lists!$C:$C,15+1)="","",INDEX(Data_Lists!$C:$C,15+1)) | B19: =IF($A19="","",SUMIFS(Data_UseCase!$C:$C,Data_UseCase!$A:$A,B$4,Data_UseCase!$B:$B,$A19)/1000000000) | C19: =IF($A19="","",SUMIFS(Data_UseCase!$C:$C,Data_UseCase!$A:$A,C$4,Data_UseCase!$B:$B,$A19)/1000000000) | D19: =IF($A19="","",SUMIFS(Data_UseCase!$C:$C,Data_UseCase!$A:$A,D$4,Data_UseCase!$B:$B,$A19)/1000000000) | E19: =IF($A19="","",SUMIFS(Data_UseCase!$C:$C,Data_UseCase!$A:$A,E$4,Data_UseCase!$B:$B,$A19)/1000000000) | F19: =IF($A19="","",SUMIFS(Data_UseCase!$C:$C,Data_UseCase!$A:$A,F$4,Data_UseCase!$B:$B,$A19)/1000000000) | G19: =IF($A19="","",SUMIFS(Data_UseCase!$C:$C,Data_UseCase!$A:$A,G$4,Data_UseCase!$B:$B,$A19)/1000000000) | H19: =IF($A19="","",SUMIFS(Data_UseCase!$C:$C,Data_UseCase!$A:$A,H$4,Data_UseCase!$B:$B,$A19)/1000000000) | I19: =IF($A19="","",SUMIFS(Data_UseCase!$C:$C,Data_UseCase!$A:$A,I$4,Data_UseCase!$B:$B,$A19)/1000000000) | ... M19: =IF($A19="","",SUMIFS(Data_UseCase!$C:$C,Data_UseCase!$A:$A,M$4,Data_UseCase!$B:$B,$A19)/1000000000) | N19: =IF($A19="","",IF(M$20=0,0,M19/M$20)) | O19: =IF(OR($A19="",N(M19)=0),"",SUMIFS(Data_UseCase!$D:$D,Data_UseCase!$A:$A,M$4,Data_UseCase!$B:$B,$A19)/1000000000/M19)
A20: Total | B20: =SUM(B5:B19) -> 0 | C20: =SUM(C5:C19) -> 0 | D20: =SUM(D5:D19) -> 0 | E20: =SUM(E5:E19) -> 0 | F20: =SUM(F5:F19) -> 0 | G20: =SUM(G5:G19) -> 0 | H20: =SUM(H5:H19) -> 7.2695609 | I20: =SUM(I5:I19) -> 647.5513 | ... M20: =SUM(M5:M19) -> 6040.2384
A22: How reliable is the inferred use case? Rules scored on traffic whose label we know
A23: Use case | B23: Labelled tokens (B) | C23: Inferred correctly (B) | D23: Accuracy
A24: =IF(INDEX(Data_InferenceAcc!$A:$A,1+1)="","",INDEX(Data_InferenceAcc!$A:$A,1+1)) -> fraud_triage | B24: =IF($A24="","",INDEX(Data_InferenceAcc!$B:$B,1+1)/1000000000) -> 4213.0561 | C24: =IF($A24="","",INDEX(Data_InferenceAcc!$C:$C,1+1)/1000000000) -> 4205.3341 | D24: =IF(OR($A24="",N(B24)=0),"",C24/B24) -> 0.99816713
A25: =IF(INDEX(Data_InferenceAcc!$A:$A,2+1)="","",INDEX(Data_InferenceAcc!$A:$A,2+1)) -> model_routing | B25: =IF($A25="","",INDEX(Data_InferenceAcc!$B:$B,2+1)/1000000000) -> 2133.5729 | C25: =IF($A25="","",INDEX(Data_InferenceAcc!$C:$C,2+1)/1000000000) -> 2131.37 | D25: =IF(OR($A25="",N(B25)=0),"",C25/B25) -> 0.99896752
A26: =IF(INDEX(Data_InferenceAcc!$A:$A,3+1)="","",INDEX(Data_InferenceAcc!$A:$A,3+1)) -> data_enrichment | B26: =IF($A26="","",INDEX(Data_InferenceAcc!$B:$B,3+1)/1000000000) -> 1898.256 | C26: =IF($A26="","",INDEX(Data_InferenceAcc!$C:$C,3+1)/1000000000) -> 1898.256 | D26: =IF(OR($A26="",N(B26)=0),"",C26/B26) -> 1
A27: =IF(INDEX(Data_InferenceAcc!$A:$A,4+1)="","",INDEX(Data_InferenceAcc!$A:$A,4+1)) -> moderation | B27: =IF($A27="","",INDEX(Data_InferenceAcc!$B:$B,4+1)/1000000000) -> 1822.3818 | C27: =IF($A27="","",INDEX(Data_InferenceAcc!$C:$C,4+1)/1000000000) -> 409.43825 | D27: =IF(OR($A27="",N(B27)=0),"",C27/B27) -> 0.22467205
A28: =IF(INDEX(Data_InferenceAcc!$A:$A,5+1)="","",INDEX(Data_InferenceAcc!$A:$A,5+1)) -> doc_classification | B28: =IF($A28="","",INDEX(Data_InferenceAcc!$B:$B,5+1)/1000000000) -> 1651.1577 | C28: =IF($A28="","",INDEX(Data_InferenceAcc!$C:$C,5+1)/1000000000) -> 1651.1577 | D28: =IF(OR($A28="",N(B28)=0),"",C28/B28) -> 1
A29: =IF(INDEX(Data_InferenceAcc!$A:$A,6+1)="","",INDEX(Data_InferenceAcc!$A:$A,6+1)) -> ticket_routing | B29: =IF($A29="","",INDEX(Data_InferenceAcc!$B:$B,6+1)/1000000000) -> 1093.0234 | C29: =IF($A29="","",INDEX(Data_InferenceAcc!$C:$C,6+1)/1000000000) -> 1053.6078 | D29: =IF(OR($A29="",N(B29)=0),"",C29/B29) -> 0.963939
A30: =IF(INDEX(Data_InferenceAcc!$A:$A,7+1)="","",INDEX(Data_InferenceAcc!$A:$A,7+1)) -> llm_guardrails | B30: =IF($A30="","",INDEX(Data_InferenceAcc!$B:$B,7+1)/1000000000) -> 285.8711 | C30: =IF($A30="","",INDEX(Data_InferenceAcc!$C:$C,7+1)/1000000000) -> 285.67657 | D30: =IF(OR($A30="",N(B30)=0),"",C30/B30) -> 0.9993195
A31: =IF(INDEX(Data_InferenceAcc!$A:$A,8+1)="","",INDEX(Data_InferenceAcc!$A:$A,8+1)) -> ci_lint | B31: =IF($A31="","",INDEX(Data_InferenceAcc!$B:$B,8+1)/1000000000) -> 73.709984 | C31: =IF($A31="","",INDEX(Data_InferenceAcc!$C:$C,8+1)/1000000000) -> 73.709984 | D31: =IF(OR($A31="",N(B31)=0),"",C31/B31) -> 1
A32: =IF(INDEX(Data_InferenceAcc!$A:$A,9+1)="","",INDEX(Data_InferenceAcc!$A:$A,9+1)) -> lead_scoring | B32: =IF($A32="","",INDEX(Data_InferenceAcc!$B:$B,9+1)/1000000000) -> 70.291049 | C32: =IF($A32="","",INDEX(Data_InferenceAcc!$C:$C,9+1)/1000000000) -> 64.507301 | D32: =IF(OR($A32="",N(B32)=0),"",C32/B32) -> 0.91771715
A33: =IF(INDEX(Data_InferenceAcc!$A:$A,10+1)="","",INDEX(Data_InferenceAcc!$A:$A,10+1)) -> rag_rerank | B33: =IF($A33="","",INDEX(Data_InferenceAcc!$B:$B,10+1)/1000000000) -> 45.303246 | C33: =IF($A33="","",INDEX(Data_InferenceAcc!$C:$C,10+1)/1000000000) -> 41.678495 | D33: =IF(OR($A33="",N(B33)=0),"",C33/B33) -> 0.91998914
A34: =IF(INDEX(Data_InferenceAcc!$A:$A,11+1)="","",INDEX(Data_InferenceAcc!$A:$A,11+1)) | B34: =IF($A34="","",INDEX(Data_InferenceAcc!$B:$B,11+1)/1000000000) | C34: =IF($A34="","",INDEX(Data_InferenceAcc!$C:$C,11+1)/1000000000) | D34: =IF(OR($A34="",N(B34)=0),"",C34/B34)
A35: =IF(INDEX(Data_InferenceAcc!$A:$A,12+1)="","",INDEX(Data_InferenceAcc!$A:$A,12+1)) | B35: =IF($A35="","",INDEX(Data_InferenceAcc!$B:$B,12+1)/1000000000) | C35: =IF($A35="","",INDEX(Data_InferenceAcc!$C:$C,12+1)/1000000000) | D35: =IF(OR($A35="",N(B35)=0),"",C35/B35)
A36: =IF(INDEX(Data_InferenceAcc!$A:$A,13+1)="","",INDEX(Data_InferenceAcc!$A:$A,13+1)) | B36: =IF($A36="","",INDEX(Data_InferenceAcc!$B:$B,13+1)/1000000000) | C36: =IF($A36="","",INDEX(Data_InferenceAcc!$C:$C,13+1)/1000000000) | D36: =IF(OR($A36="",N(B36)=0),"",C36/B36)
A37: =IF(INDEX(Data_InferenceAcc!$A:$A,14+1)="","",INDEX(Data_InferenceAcc!$A:$A,14+1)) | B37: =IF($A37="","",INDEX(Data_InferenceAcc!$B:$B,14+1)/1000000000) | C37: =IF($A37="","",INDEX(Data_InferenceAcc!$C:$C,14+1)/1000000000) | D37: =IF(OR($A37="",N(B37)=0),"",C37/B37)
A38: =IF(INDEX(Data_InferenceAcc!$A:$A,15+1)="","",INDEX(Data_InferenceAcc!$A:$A,15+1)) | B38: =IF($A38="","",INDEX(Data_InferenceAcc!$B:$B,15+1)/1000000000) | C38: =IF($A38="","",INDEX(Data_InferenceAcc!$C:$C,15+1)/1000000000) | D38: =IF(OR($A38="",N(B38)=0),"",C38/B38)
A39: All labelled traffic | B39: =SUM(B24:B38) -> 13286.623 | C39: =SUM(C24:C38) -> 11814.736 | D39: =IF(B39=0,"no labelled traffic",C39/B39) -> 0.88922039
A41: Low accuracy means the rules in sql/20_use_case_rules.sql don't fit your traffic yet. Recalibrate them, or map more labels.

Sheet Cohorts
A1: =Data_Params!$B$14&" | Self-serve cohorts" -> Example Co (synthetic data) | Self-serve cohorts
A2: Accounts grouped by signup month. Tokens per day (B) so partial months compare fairly. Older cohorts are combined on the Forecast tab.
A4: Signup cohort | B4: Signups | C4: Added payment method | D4: Month 0 | E4: Month 1 | F4: Month 2 | G4: Month 3 | H4: Month 4 | I4: Month 5 | J4: Month 6 | K4: Month 7 | L4: Month 8 | M4: Month 9 | N4: Month 10 | O4: Month 11
A5: =EDATE(Data_Params!$B$3,0) -> 46082 | B5: =SUMIFS(Data_Signups!$B:$B,Data_Signups!$A:$A,$A5) -> 0 | C5: =IF(SUMIFS(Data_Signups!$D:$D,Data_Signups!$A:$A,$A5)=0,"n/a",SUMIFS(Data_Signups!$C:$C,Data_Signups!$A:$A,$A5)) -> n/a | D5: =SUMIFS(Data_Cohort!$C:$C,Data_Cohort!$A:$A,$A5,Data_Cohort!$B:$B,0)/MAX(1,SUMIFS(Data_Months!$B:$B,Data_Months!$A:$A,EDATE($A5,0)))/1000000000 -> 0 | E5: =SUMIFS(Data_Cohort!$C:$C,Data_Cohort!$A:$A,$A5,Data_Cohort!$B:$B,1)/MAX(1,SUMIFS(Data_Months!$B:$B,Data_Months!$A:$A,EDATE($A5,1)))/1000000000 -> 0 | F5: =SUMIFS(Data_Cohort!$C:$C,Data_Cohort!$A:$A,$A5,Data_Cohort!$B:$B,2)/MAX(1,SUMIFS(Data_Months!$B:$B,Data_Months!$A:$A,EDATE($A5,2)))/1000000000 -> 0 | G5: =SUMIFS(Data_Cohort!$C:$C,Data_Cohort!$A:$A,$A5,Data_Cohort!$B:$B,3)/MAX(1,SUMIFS(Data_Months!$B:$B,Data_Months!$A:$A,EDATE($A5,3)))/1000000000 -> 0 | H5: =SUMIFS(Data_Cohort!$C:$C,Data_Cohort!$A:$A,$A5,Data_Cohort!$B:$B,4)/MAX(1,SUMIFS(Data_Months!$B:$B,Data_Months!$A:$A,EDATE($A5,4)))/1000000000 -> 0 | I5: =SUMIFS(Data_Cohort!$C:$C,Data_Cohort!$A:$A,$A5,Data_Cohort!$B:$B,5)/MAX(1,SUMIFS(Data_Months!$B:$B,Data_Months!$A:$A,EDATE($A5,5)))/1000000000 -> 0 | J5: =SUMIFS(Data_Cohort!$C:$C,Data_Cohort!$A:$A,$A5,Data_Cohort!$B:$B,6)/MAX(1,SUMIFS(Data_Months!$B:$B,Data_Months!$A:$A,EDATE($A5,6)))/1000000000 -> 0 | K5: =SUMIFS(Data_Cohort!$C:$C,Data_Cohort!$A:$A,$A5,Data_Cohort!$B:$B,7)/MAX(1,SUMIFS(Data_Months!$B:$B,Data_Months!$A:$A,EDATE($A5,7)))/1000000000 -> 0 | L5: =SUMIFS(Data_Cohort!$C:$C,Data_Cohort!$A:$A,$A5,Data_Cohort!$B:$B,8)/MAX(1,SUMIFS(Data_Months!$B:$B,Data_Months!$A:$A,EDATE($A5,8)))/1000000000 -> 0 | M5: =SUMIFS(Data_Cohort!$C:$C,Data_Cohort!$A:$A,$A5,Data_Cohort!$B:$B,9)/MAX(1,SUMIFS(Data_Months!$B:$B,Data_Months!$A:$A,EDATE($A5,9)))/1000000000 -> 0 | N5: =SUMIFS(Data_Cohort!$C:$C,Data_Cohort!$A:$A,$A5,Data_Cohort!$B:$B,10)/MAX(1,SUMIFS(Data_Months!$B:$B,Data_Months!$A:$A,EDATE($A5,10)))/1000000000 -> 0 | O5: =SUMIFS(Data_Cohort!$C:$C,Data_Cohort!$A:$A,$A5,Data_Cohort!$B:$B,11)/MAX(1,SUMIFS(Data_Months!$B:$B,Data_Months!$A:$A,EDATE($A5,11)))/1000000000 -> 0
A6: =EDATE(Data_Params!$B$3,1) -> 46113 | B6: =SUMIFS(Data_Signups!$B:$B,Data_Signups!$A:$A,$A6) -> 0 | C6: =IF(SUMIFS(Data_Signups!$D:$D,Data_Signups!$A:$A,$A6)=0,"n/a",SUMIFS(Data_Signups!$C:$C,Data_Signups!$A:$A,$A6)) -> n/a | D6: =SUMIFS(Data_Cohort!$C:$C,Data_Cohort!$A:$A,$A6,Data_Cohort!$B:$B,0)/MAX(1,SUMIFS(Data_Months!$B:$B,Data_Months!$A:$A,EDATE($A6,0)))/1000000000 -> 0 | E6: =SUMIFS(Data_Cohort!$C:$C,Data_Cohort!$A:$A,$A6,Data_Cohort!$B:$B,1)/MAX(1,SUMIFS(Data_Months!$B:$B,Data_Months!$A:$A,EDATE($A6,1)))/1000000000 -> 0 | F6: =SUMIFS(Data_Cohort!$C:$C,Data_Cohort!$A:$A,$A6,Data_Cohort!$B:$B,2)/MAX(1,SUMIFS(Data_Months!$B:$B,Data_Months!$A:$A,EDATE($A6,2)))/1000000000 -> 0 | G6: =SUMIFS(Data_Cohort!$C:$C,Data_Cohort!$A:$A,$A6,Data_Cohort!$B:$B,3)/MAX(1,SUMIFS(Data_Months!$B:$B,Data_Months!$A:$A,EDATE($A6,3)))/1000000000 -> 0 | H6: =SUMIFS(Data_Cohort!$C:$C,Data_Cohort!$A:$A,$A6,Data_Cohort!$B:$B,4)/MAX(1,SUMIFS(Data_Months!$B:$B,Data_Months!$A:$A,EDATE($A6,4)))/1000000000 -> 0 | I6: =SUMIFS(Data_Cohort!$C:$C,Data_Cohort!$A:$A,$A6,Data_Cohort!$B:$B,5)/MAX(1,SUMIFS(Data_Months!$B:$B,Data_Months!$A:$A,EDATE($A6,5)))/1000000000 -> 0 | J6: =SUMIFS(Data_Cohort!$C:$C,Data_Cohort!$A:$A,$A6,Data_Cohort!$B:$B,6)/MAX(1,SUMIFS(Data_Months!$B:$B,Data_Months!$A:$A,EDATE($A6,6)))/1000000000 -> 0 | K6: =SUMIFS(Data_Cohort!$C:$C,Data_Cohort!$A:$A,$A6,Data_Cohort!$B:$B,7)/MAX(1,SUMIFS(Data_Months!$B:$B,Data_Months!$A:$A,EDATE($A6,7)))/1000000000 -> 0 | L6: =SUMIFS(Data_Cohort!$C:$C,Data_Cohort!$A:$A,$A6,Data_Cohort!$B:$B,8)/MAX(1,SUMIFS(Data_Months!$B:$B,Data_Months!$A:$A,EDATE($A6,8)))/1000000000 -> 0 | M6: =SUMIFS(Data_Cohort!$C:$C,Data_Cohort!$A:$A,$A6,Data_Cohort!$B:$B,9)/MAX(1,SUMIFS(Data_Months!$B:$B,Data_Months!$A:$A,EDATE($A6,9)))/1000000000 -> 0 | N6: =SUMIFS(Data_Cohort!$C:$C,Data_Cohort!$A:$A,$A6,Data_Cohort!$B:$B,10)/MAX(1,SUMIFS(Data_Months!$B:$B,Data_Months!$A:$A,EDATE($A6,10)))/1000000000 -> 0
A7: =EDATE(Data_Params!$B$3,2) -> 46143 | B7: =SUMIFS(Data_Signups!$B:$B,Data_Signups!$A:$A,$A7) -> 0 | C7: =IF(SUMIFS(Data_Signups!$D:$D,Data_Signups!$A:$A,$A7)=0,"n/a",SUMIFS(Data_Signups!$C:$C,Data_Signups!$A:$A,$A7)) -> n/a | D7: =SUMIFS(Data_Cohort!$C:$C,Data_Cohort!$A:$A,$A7,Data_Cohort!$B:$B,0)/MAX(1,SUMIFS(Data_Months!$B:$B,Data_Months!$A:$A,EDATE($A7,0)))/1000000000 -> 0 | E7: =SUMIFS(Data_Cohort!$C:$C,Data_Cohort!$A:$A,$A7,Data_Cohort!$B:$B,1)/MAX(1,SUMIFS(Data_Months!$B:$B,Data_Months!$A:$A,EDATE($A7,1)))/1000000000 -> 0 | F7: =SUMIFS(Data_Cohort!$C:$C,Data_Cohort!$A:$A,$A7,Data_Cohort!$B:$B,2)/MAX(1,SUMIFS(Data_Months!$B:$B,Data_Months!$A:$A,EDATE($A7,2)))/1000000000 -> 0 | G7: =SUMIFS(Data_Cohort!$C:$C,Data_Cohort!$A:$A,$A7,Data_Cohort!$B:$B,3)/MAX(1,SUMIFS(Data_Months!$B:$B,Data_Months!$A:$A,EDATE($A7,3)))/1000000000 -> 0 | H7: =SUMIFS(Data_Cohort!$C:$C,Data_Cohort!$A:$A,$A7,Data_Cohort!$B:$B,4)/MAX(1,SUMIFS(Data_Months!$B:$B,Data_Months!$A:$A,EDATE($A7,4)))/1000000000 -> 0 | I7: =SUMIFS(Data_Cohort!$C:$C,Data_Cohort!$A:$A,$A7,Data_Cohort!$B:$B,5)/MAX(1,SUMIFS(Data_Months!$B:$B,Data_Months!$A:$A,EDATE($A7,5)))/1000000000 -> 0 | J7: =SUMIFS(Data_Cohort!$C:$C,Data_Cohort!$A:$A,$A7,Data_Cohort!$B:$B,6)/MAX(1,SUMIFS(Data_Months!$B:$B,Data_Months!$A:$A,EDATE($A7,6)))/1000000000 -> 0 | K7: =SUMIFS(Data_Cohort!$C:$C,Data_Cohort!$A:$A,$A7,Data_Cohort!$B:$B,7)/MAX(1,SUMIFS(Data_Months!$B:$B,Data_Months!$A:$A,EDATE($A7,7)))/1000000000 -> 0 | L7: =SUMIFS(Data_Cohort!$C:$C,Data_Cohort!$A:$A,$A7,Data_Cohort!$B:$B,8)/MAX(1,SUMIFS(Data_Months!$B:$B,Data_Months!$A:$A,EDATE($A7,8)))/1000000000 -> 0 | M7: =SUMIFS(Data_Cohort!$C:$C,Data_Cohort!$A:$A,$A7,Data_Cohort!$B:$B,9)/MAX(1,SUMIFS(Data_Months!$B:$B,Data_Months!$A:$A,EDATE($A7,9)))/1000000000 -> 0
A8: =EDATE(Data_Params!$B$3,3) -> 46174 | B8: =SUMIFS(Data_Signups!$B:$B,Data_Signups!$A:$A,$A8) -> 0 | C8: =IF(SUMIFS(Data_Signups!$D:$D,Data_Signups!$A:$A,$A8)=0,"n/a",SUMIFS(Data_Signups!$C:$C,Data_Signups!$A:$A,$A8)) -> n/a | D8: =SUMIFS(Data_Cohort!$C:$C,Data_Cohort!$A:$A,$A8,Data_Cohort!$B:$B,0)/MAX(1,SUMIFS(Data_Months!$B:$B,Data_Months!$A:$A,EDATE($A8,0)))/1000000000 -> 0 | E8: =SUMIFS(Data_Cohort!$C:$C,Data_Cohort!$A:$A,$A8,Data_Cohort!$B:$B,1)/MAX(1,SUMIFS(Data_Months!$B:$B,Data_Months!$A:$A,EDATE($A8,1)))/1000000000 -> 0 | F8: =SUMIFS(Data_Cohort!$C:$C,Data_Cohort!$A:$A,$A8,Data_Cohort!$B:$B,2)/MAX(1,SUMIFS(Data_Months!$B:$B,Data_Months!$A:$A,EDATE($A8,2)))/1000000000 -> 0 | G8: =SUMIFS(Data_Cohort!$C:$C,Data_Cohort!$A:$A,$A8,Data_Cohort!$B:$B,3)/MAX(1,SUMIFS(Data_Months!$B:$B,Data_Months!$A:$A,EDATE($A8,3)))/1000000000 -> 0 | H8: =SUMIFS(Data_Cohort!$C:$C,Data_Cohort!$A:$A,$A8,Data_Cohort!$B:$B,4)/MAX(1,SUMIFS(Data_Months!$B:$B,Data_Months!$A:$A,EDATE($A8,4)))/1000000000 -> 0 | I8: =SUMIFS(Data_Cohort!$C:$C,Data_Cohort!$A:$A,$A8,Data_Cohort!$B:$B,5)/MAX(1,SUMIFS(Data_Months!$B:$B,Data_Months!$A:$A,EDATE($A8,5)))/1000000000 -> 0 | J8: =SUMIFS(Data_Cohort!$C:$C,Data_Cohort!$A:$A,$A8,Data_Cohort!$B:$B,6)/MAX(1,SUMIFS(Data_Months!$B:$B,Data_Months!$A:$A,EDATE($A8,6)))/1000000000 -> 0 | K8: =SUMIFS(Data_Cohort!$C:$C,Data_Cohort!$A:$A,$A8,Data_Cohort!$B:$B,7)/MAX(1,SUMIFS(Data_Months!$B:$B,Data_Months!$A:$A,EDATE($A8,7)))/1000000000 -> 0 | L8: =SUMIFS(Data_Cohort!$C:$C,Data_Cohort!$A:$A,$A8,Data_Cohort!$B:$B,8)/MAX(1,SUMIFS(Data_Months!$B:$B,Data_Months!$A:$A,EDATE($A8,8)))/1000000000 -> 0
A9: =EDATE(Data_Params!$B$3,4) -> 46204 | B9: =SUMIFS(Data_Signups!$B:$B,Data_Signups!$A:$A,$A9) -> 0 | C9: =IF(SUMIFS(Data_Signups!$D:$D,Data_Signups!$A:$A,$A9)=0,"n/a",SUMIFS(Data_Signups!$C:$C,Data_Signups!$A:$A,$A9)) -> n/a | D9: =SUMIFS(Data_Cohort!$C:$C,Data_Cohort!$A:$A,$A9,Data_Cohort!$B:$B,0)/MAX(1,SUMIFS(Data_Months!$B:$B,Data_Months!$A:$A,EDATE($A9,0)))/1000000000 -> 0 | E9: =SUMIFS(Data_Cohort!$C:$C,Data_Cohort!$A:$A,$A9,Data_Cohort!$B:$B,1)/MAX(1,SUMIFS(Data_Months!$B:$B,Data_Months!$A:$A,EDATE($A9,1)))/1000000000 -> 0 | F9: =SUMIFS(Data_Cohort!$C:$C,Data_Cohort!$A:$A,$A9,Data_Cohort!$B:$B,2)/MAX(1,SUMIFS(Data_Months!$B:$B,Data_Months!$A:$A,EDATE($A9,2)))/1000000000 -> 0 | G9: =SUMIFS(Data_Cohort!$C:$C,Data_Cohort!$A:$A,$A9,Data_Cohort!$B:$B,3)/MAX(1,SUMIFS(Data_Months!$B:$B,Data_Months!$A:$A,EDATE($A9,3)))/1000000000 -> 0 | H9: =SUMIFS(Data_Cohort!$C:$C,Data_Cohort!$A:$A,$A9,Data_Cohort!$B:$B,4)/MAX(1,SUMIFS(Data_Months!$B:$B,Data_Months!$A:$A,EDATE($A9,4)))/1000000000 -> 0 | I9: =SUMIFS(Data_Cohort!$C:$C,Data_Cohort!$A:$A,$A9,Data_Cohort!$B:$B,5)/MAX(1,SUMIFS(Data_Months!$B:$B,Data_Months!$A:$A,EDATE($A9,5)))/1000000000 -> 0 | J9: =SUMIFS(Data_Cohort!$C:$C,Data_Cohort!$A:$A,$A9,Data_Cohort!$B:$B,6)/MAX(1,SUMIFS(Data_Months!$B:$B,Data_Months!$A:$A,EDATE($A9,6)))/1000000000 -> 0 | K9: =SUMIFS(Data_Cohort!$C:$C,Data_Cohort!$A:$A,$A9,Data_Cohort!$B:$B,7)/MAX(1,SUMIFS(Data_Months!$B:$B,Data_Months!$A:$A,EDATE($A9,7)))/1000000000 -> 0
A10: =EDATE(Data_Params!$B$3,5) -> 46235 | B10: =SUMIFS(Data_Signups!$B:$B,Data_Signups!$A:$A,$A10) -> 0 | C10: =IF(SUMIFS(Data_Signups!$D:$D,Data_Signups!$A:$A,$A10)=0,"n/a",SUMIFS(Data_Signups!$C:$C,Data_Signups!$A:$A,$A10)) -> n/a | D10: =SUMIFS(Data_Cohort!$C:$C,Data_Cohort!$A:$A,$A10,Data_Cohort!$B:$B,0)/MAX(1,SUMIFS(Data_Months!$B:$B,Data_Months!$A:$A,EDATE($A10,0)))/1000000000 -> 0 | E10: =SUMIFS(Data_Cohort!$C:$C,Data_Cohort!$A:$A,$A10,Data_Cohort!$B:$B,1)/MAX(1,SUMIFS(Data_Months!$B:$B,Data_Months!$A:$A,EDATE($A10,1)))/1000000000 -> 0 | F10: =SUMIFS(Data_Cohort!$C:$C,Data_Cohort!$A:$A,$A10,Data_Cohort!$B:$B,2)/MAX(1,SUMIFS(Data_Months!$B:$B,Data_Months!$A:$A,EDATE($A10,2)))/1000000000 -> 0 | G10: =SUMIFS(Data_Cohort!$C:$C,Data_Cohort!$A:$A,$A10,Data_Cohort!$B:$B,3)/MAX(1,SUMIFS(Data_Months!$B:$B,Data_Months!$A:$A,EDATE($A10,3)))/1000000000 -> 0 | H10: =SUMIFS(Data_Cohort!$C:$C,Data_Cohort!$A:$A,$A10,Data_Cohort!$B:$B,4)/MAX(1,SUMIFS(Data_Months!$B:$B,Data_Months!$A:$A,EDATE($A10,4)))/1000000000 -> 0 | I10: =SUMIFS(Data_Cohort!$C:$C,Data_Cohort!$A:$A,$A10,Data_Cohort!$B:$B,5)/MAX(1,SUMIFS(Data_Months!$B:$B,Data_Months!$A:$A,EDATE($A10,5)))/1000000000 -> 0 | J10: =SUMIFS(Data_Cohort!$C:$C,Data_Cohort!$A:$A,$A10,Data_Cohort!$B:$B,6)/MAX(1,SUMIFS(Data_Months!$B:$B,Data_Months!$A:$A,EDATE($A10,6)))/1000000000 -> 0
A11: =EDATE(Data_Params!$B$3,6) -> 46266 | B11: =SUMIFS(Data_Signups!$B:$B,Data_Signups!$A:$A,$A11) -> 204 | C11: =IF(SUMIFS(Data_Signups!$D:$D,Data_Signups!$A:$A,$A11)=0,"n/a",SUMIFS(Data_Signups!$C:$C,Data_Signups!$A:$A,$A11)) -> 26 | D11: =SUMIFS(Data_Cohort!$C:$C,Data_Cohort!$A:$A,$A11,Data_Cohort!$B:$B,0)/MAX(1,SUMIFS(Data_Months!$B:$B,Data_Months!$A:$A,EDATE($A11,0)))/1000000000 -> 0.37771159 | E11: =SUMIFS(Data_Cohort!$C:$C,Data_Cohort!$A:$A,$A11,Data_Cohort!$B:$B,1)/MAX(1,SUMIFS(Data_Months!$B:$B,Data_Months!$A:$A,EDATE($A11,1)))/1000000000 -> 0.72591047 | F11: =SUMIFS(Data_Cohort!$C:$C,Data_Cohort!$A:$A,$A11,Data_Cohort!$B:$B,2)/MAX(1,SUMIFS(Data_Months!$B:$B,Data_Months!$A:$A,EDATE($A11,2)))/1000000000 -> 1.829924 | G11: =SUMIFS(Data_Cohort!$C:$C,Data_Cohort!$A:$A,$A11,Data_Cohort!$B:$B,3)/MAX(1,SUMIFS(Data_Months!$B:$B,Data_Months!$A:$A,EDATE($A11,3)))/1000000000 -> 2.0855666 | H11: =SUMIFS(Data_Cohort!$C:$C,Data_Cohort!$A:$A,$A11,Data_Cohort!$B:$B,4)/MAX(1,SUMIFS(Data_Months!$B:$B,Data_Months!$A:$A,EDATE($A11,4)))/1000000000 -> 2.067955 | I11: =SUMIFS(Data_Cohort!$C:$C,Data_Cohort!$A:$A,$A11,Data_Cohort!$B:$B,5)/MAX(1,SUMIFS(Data_Months!$B:$B,Data_Months!$A:$A,EDATE($A11,5)))/1000000000 -> 2.0303645
A12: =EDATE(Data_Params!$B$3,7) -> 46296 | B12: =SUMIFS(Data_Signups!$B:$B,Data_Signups!$A:$A,$A12) -> 302 | C12: =IF(SUMIFS(Data_Signups!$D:$D,Data_Signups!$A:$A,$A12)=0,"n/a",SUMIFS(Data_Signups!$C:$C,Data_Signups!$A:$A,$A12)) -> 41 | D12: =SUMIFS(Data_Cohort!$C:$C,Data_Cohort!$A:$A,$A12,Data_Cohort!$B:$B,0)/MAX(1,SUMIFS(Data_Months!$B:$B,Data_Months!$A:$A,EDATE($A12,0)))/1000000000 -> 0.98760653 | E12: =SUMIFS(Data_Cohort!$C:$C,Data_Cohort!$A:$A,$A12,Data_Cohort!$B:$B,1)/MAX(1,SUMIFS(Data_Months!$B:$B,Data_Months!$A:$A,EDATE($A12,1)))/1000000000 -> 6.2196472 | F12: =SUMIFS(Data_Cohort!$C:$C,Data_Cohort!$A:$A,$A12,Data_Cohort!$B:$B,2)/MAX(1,SUMIFS(Data_Months!$B:$B,Data_Months!$A:$A,EDATE($A12,2)))/1000000000 -> 14.807998 | G12: =SUMIFS(Data_Cohort!$C:$C,Data_Cohort!$A:$A,$A12,Data_Cohort!$B:$B,3)/MAX(1,SUMIFS(Data_Months!$B:$B,Data_Months!$A:$A,EDATE($A12,3)))/1000000000 -> 15.792116 | H12: =SUMIFS(Data_Cohort!$C:$C,Data_Cohort!$A:$A,$A12,Data_Cohort!$B:$B,4)/MAX(1,SUMIFS(Data_Months!$B:$B,Data_Months!$A:$A,EDATE($A12,4)))/1000000000 -> 16.518878
A13: =EDATE(Data_Params!$B$3,8) -> 46327 | B13: =SUMIFS(Data_Signups!$B:$B,Data_Signups!$A:$A,$A13) -> 349 | C13: =IF(SUMIFS(Data_Signups!$D:$D,Data_Signups!$A:$A,$A13)=0,"n/a",SUMIFS(Data_Signups!$C:$C,Data_Signups!$A:$A,$A13)) -> 45 | D13: =SUMIFS(Data_Cohort!$C:$C,Data_Cohort!$A:$A,$A13,Data_Cohort!$B:$B,0)/MAX(1,SUMIFS(Data_Months!$B:$B,Data_Months!$A:$A,EDATE($A13,0)))/1000000000 -> 0.47871638 | E13: =SUMIFS(Data_Cohort!$C:$C,Data_Cohort!$A:$A,$A13,Data_Cohort!$B:$B,1)/MAX(1,SUMIFS(Data_Months!$B:$B,Data_Months!$A:$A,EDATE($A13,1)))/1000000000 -> 2.6466131 | F13: =SUMIFS(Data_Cohort!$C:$C,Data_Cohort!$A:$A,$A13,Data_Cohort!$B:$B,2)/MAX(1,SUMIFS(Data_Months!$B:$B,Data_Months!$A:$A,EDATE($A13,2)))/1000000000 -> 5.6457811 | G13: =SUMIFS(Data_Cohort!$C:$C,Data_Cohort!$A:$A,$A13,Data_Cohort!$B:$B,3)/MAX(1,SUMIFS(Data_Months!$B:$B,Data_Months!$A:$A,EDATE($A13,3)))/1000000000 -> 5.9159471
A14: =EDATE(Data_Params!$B$3,9) -> 46357 | B14: =SUMIFS(Data_Signups!$B:$B,Data_Signups!$A:$A,$A14) -> 335 | C14: =IF(SUMIFS(Data_Signups!$D:$D,Data_Signups!$A:$A,$A14)=0,"n/a",SUMIFS(Data_Signups!$C:$C,Data_Signups!$A:$A,$A14)) -> 41 | D14: =SUMIFS(Data_Cohort!$C:$C,Data_Cohort!$A:$A,$A14,Data_Cohort!$B:$B,0)/MAX(1,SUMIFS(Data_Months!$B:$B,Data_Months!$A:$A,EDATE($A14,0)))/1000000000 -> 0.6552221 | E14: =SUMIFS(Data_Cohort!$C:$C,Data_Cohort!$A:$A,$A14,Data_Cohort!$B:$B,1)/MAX(1,SUMIFS(Data_Months!$B:$B,Data_Months!$A:$A,EDATE($A14,1)))/1000000000 -> 3.1784264 | F14: =SUMIFS(Data_Cohort!$C:$C,Data_Cohort!$A:$A,$A14,Data_Cohort!$B:$B,2)/MAX(1,SUMIFS(Data_Months!$B:$B,Data_Months!$A:$A,EDATE($A14,2)))/1000000000 -> 5.8827266
A15: =EDATE(Data_Params!$B$3,10) -> 46388 | B15: =SUMIFS(Data_Signups!$B:$B,Data_Signups!$A:$A,$A15) -> 385 | C15: =IF(SUMIFS(Data_Signups!$D:$D,Data_Signups!$A:$A,$A15)=0,"n/a",SUMIFS(Data_Signups!$C:$C,Data_Signups!$A:$A,$A15)) -> 53 | D15: =SUMIFS(Data_Cohort!$C:$C,Data_Cohort!$A:$A,$A15,Data_Cohort!$B:$B,0)/MAX(1,SUMIFS(Data_Months!$B:$B,Data_Months!$A:$A,EDATE($A15,0)))/1000000000 -> 1.4209448 | E15: =SUMIFS(Data_Cohort!$C:$C,Data_Cohort!$A:$A,$A15,Data_Cohort!$B:$B,1)/MAX(1,SUMIFS(Data_Months!$B:$B,Data_Months!$A:$A,EDATE($A15,1)))/1000000000 -> 6.1576996
A16: =EDATE(Data_Params!$B$3,11) -> 46419 | B16: =SUMIFS(Data_Signups!$B:$B,Data_Signups!$A:$A,$A16) -> 441 | C16: =IF(SUMIFS(Data_Signups!$D:$D,Data_Signups!$A:$A,$A16)=0,"n/a",SUMIFS(Data_Signups!$C:$C,Data_Signups!$A:$A,$A16)) -> 66 | D16: =SUMIFS(Data_Cohort!$C:$C,Data_Cohort!$A:$A,$A16,Data_Cohort!$B:$B,0)/MAX(1,SUMIFS(Data_Months!$B:$B,Data_Months!$A:$A,EDATE($A16,0)))/1000000000 -> 1.1328616
A18: Active accounts as % of signups (retention)
A19: Signup cohort | B19: Signups | D19: Month 0 | E19: Month 1 | F19: Month 2 | G19: Month 3 | H19: Month 4 | I19: Month 5 | J19: Month 6 | K19: Month 7 | L19: Month 8 | M19: Month 9 | N19: Month 10 | O19: Month 11
A20: =A5 -> 46082 | B20: =B5 -> 0 | D20: =IF($B20=0,"",SUMIFS(Data_Cohort!$D:$D,Data_Cohort!$A:$A,$A20,Data_Cohort!$B:$B,0)/$B20) | E20: =IF($B20=0,"",SUMIFS(Data_Cohort!$D:$D,Data_Cohort!$A:$A,$A20,Data_Cohort!$B:$B,1)/$B20) | F20: =IF($B20=0,"",SUMIFS(Data_Cohort!$D:$D,Data_Cohort!$A:$A,$A20,Data_Cohort!$B:$B,2)/$B20) | G20: =IF($B20=0,"",SUMIFS(Data_Cohort!$D:$D,Data_Cohort!$A:$A,$A20,Data_Cohort!$B:$B,3)/$B20) | H20: =IF($B20=0,"",SUMIFS(Data_Cohort!$D:$D,Data_Cohort!$A:$A,$A20,Data_Cohort!$B:$B,4)/$B20) | I20: =IF($B20=0,"",SUMIFS(Data_Cohort!$D:$D,Data_Cohort!$A:$A,$A20,Data_Cohort!$B:$B,5)/$B20) | J20: =IF($B20=0,"",SUMIFS(Data_Cohort!$D:$D,Data_Cohort!$A:$A,$A20,Data_Cohort!$B:$B,6)/$B20) | K20: =IF($B20=0,"",SUMIFS(Data_Cohort!$D:$D,Data_Cohort!$A:$A,$A20,Data_Cohort!$B:$B,7)/$B20) | L20: =IF($B20=0,"",SUMIFS(Data_Cohort!$D:$D,Data_Cohort!$A:$A,$A20,Data_Cohort!$B:$B,8)/$B20) | M20: =IF($B20=0,"",SUMIFS(Data_Cohort!$D:$D,Data_Cohort!$A:$A,$A20,Data_Cohort!$B:$B,9)/$B20) | N20: =IF($B20=0,"",SUMIFS(Data_Cohort!$D:$D,Data_Cohort!$A:$A,$A20,Data_Cohort!$B:$B,10)/$B20) | O20: =IF($B20=0,"",SUMIFS(Data_Cohort!$D:$D,Data_Cohort!$A:$A,$A20,Data_Cohort!$B:$B,11)/$B20)
A21: =A6 -> 46113 | B21: =B6 -> 0 | D21: =IF($B21=0,"",SUMIFS(Data_Cohort!$D:$D,Data_Cohort!$A:$A,$A21,Data_Cohort!$B:$B,0)/$B21) | E21: =IF($B21=0,"",SUMIFS(Data_Cohort!$D:$D,Data_Cohort!$A:$A,$A21,Data_Cohort!$B:$B,1)/$B21) | F21: =IF($B21=0,"",SUMIFS(Data_Cohort!$D:$D,Data_Cohort!$A:$A,$A21,Data_Cohort!$B:$B,2)/$B21) | G21: =IF($B21=0,"",SUMIFS(Data_Cohort!$D:$D,Data_Cohort!$A:$A,$A21,Data_Cohort!$B:$B,3)/$B21) | H21: =IF($B21=0,"",SUMIFS(Data_Cohort!$D:$D,Data_Cohort!$A:$A,$A21,Data_Cohort!$B:$B,4)/$B21) | I21: =IF($B21=0,"",SUMIFS(Data_Cohort!$D:$D,Data_Cohort!$A:$A,$A21,Data_Cohort!$B:$B,5)/$B21) | J21: =IF($B21=0,"",SUMIFS(Data_Cohort!$D:$D,Data_Cohort!$A:$A,$A21,Data_Cohort!$B:$B,6)/$B21) | K21: =IF($B21=0,"",SUMIFS(Data_Cohort!$D:$D,Data_Cohort!$A:$A,$A21,Data_Cohort!$B:$B,7)/$B21) | L21: =IF($B21=0,"",SUMIFS(Data_Cohort!$D:$D,Data_Cohort!$A:$A,$A21,Data_Cohort!$B:$B,8)/$B21) | M21: =IF($B21=0,"",SUMIFS(Data_Cohort!$D:$D,Data_Cohort!$A:$A,$A21,Data_Cohort!$B:$B,9)/$B21) | N21: =IF($B21=0,"",SUMIFS(Data_Cohort!$D:$D,Data_Cohort!$A:$A,$A21,Data_Cohort!$B:$B,10)/$B21)
A22: =A7 -> 46143 | B22: =B7 -> 0 | D22: =IF($B22=0,"",SUMIFS(Data_Cohort!$D:$D,Data_Cohort!$A:$A,$A22,Data_Cohort!$B:$B,0)/$B22) | E22: =IF($B22=0,"",SUMIFS(Data_Cohort!$D:$D,Data_Cohort!$A:$A,$A22,Data_Cohort!$B:$B,1)/$B22) | F22: =IF($B22=0,"",SUMIFS(Data_Cohort!$D:$D,Data_Cohort!$A:$A,$A22,Data_Cohort!$B:$B,2)/$B22) | G22: =IF($B22=0,"",SUMIFS(Data_Cohort!$D:$D,Data_Cohort!$A:$A,$A22,Data_Cohort!$B:$B,3)/$B22) | H22: =IF($B22=0,"",SUMIFS(Data_Cohort!$D:$D,Data_Cohort!$A:$A,$A22,Data_Cohort!$B:$B,4)/$B22) | I22: =IF($B22=0,"",SUMIFS(Data_Cohort!$D:$D,Data_Cohort!$A:$A,$A22,Data_Cohort!$B:$B,5)/$B22) | J22: =IF($B22=0,"",SUMIFS(Data_Cohort!$D:$D,Data_Cohort!$A:$A,$A22,Data_Cohort!$B:$B,6)/$B22) | K22: =IF($B22=0,"",SUMIFS(Data_Cohort!$D:$D,Data_Cohort!$A:$A,$A22,Data_Cohort!$B:$B,7)/$B22) | L22: =IF($B22=0,"",SUMIFS(Data_Cohort!$D:$D,Data_Cohort!$A:$A,$A22,Data_Cohort!$B:$B,8)/$B22) | M22: =IF($B22=0,"",SUMIFS(Data_Cohort!$D:$D,Data_Cohort!$A:$A,$A22,Data_Cohort!$B:$B,9)/$B22)
A23: =A8 -> 46174 | B23: =B8 -> 0 | D23: =IF($B23=0,"",SUMIFS(Data_Cohort!$D:$D,Data_Cohort!$A:$A,$A23,Data_Cohort!$B:$B,0)/$B23) | E23: =IF($B23=0,"",SUMIFS(Data_Cohort!$D:$D,Data_Cohort!$A:$A,$A23,Data_Cohort!$B:$B,1)/$B23) | F23: =IF($B23=0,"",SUMIFS(Data_Cohort!$D:$D,Data_Cohort!$A:$A,$A23,Data_Cohort!$B:$B,2)/$B23) | G23: =IF($B23=0,"",SUMIFS(Data_Cohort!$D:$D,Data_Cohort!$A:$A,$A23,Data_Cohort!$B:$B,3)/$B23) | H23: =IF($B23=0,"",SUMIFS(Data_Cohort!$D:$D,Data_Cohort!$A:$A,$A23,Data_Cohort!$B:$B,4)/$B23) | I23: =IF($B23=0,"",SUMIFS(Data_Cohort!$D:$D,Data_Cohort!$A:$A,$A23,Data_Cohort!$B:$B,5)/$B23) | J23: =IF($B23=0,"",SUMIFS(Data_Cohort!$D:$D,Data_Cohort!$A:$A,$A23,Data_Cohort!$B:$B,6)/$B23) | K23: =IF($B23=0,"",SUMIFS(Data_Cohort!$D:$D,Data_Cohort!$A:$A,$A23,Data_Cohort!$B:$B,7)/$B23) | L23: =IF($B23=0,"",SUMIFS(Data_Cohort!$D:$D,Data_Cohort!$A:$A,$A23,Data_Cohort!$B:$B,8)/$B23)
A24: =A9 -> 46204 | B24: =B9 -> 0 | D24: =IF($B24=0,"",SUMIFS(Data_Cohort!$D:$D,Data_Cohort!$A:$A,$A24,Data_Cohort!$B:$B,0)/$B24) | E24: =IF($B24=0,"",SUMIFS(Data_Cohort!$D:$D,Data_Cohort!$A:$A,$A24,Data_Cohort!$B:$B,1)/$B24) | F24: =IF($B24=0,"",SUMIFS(Data_Cohort!$D:$D,Data_Cohort!$A:$A,$A24,Data_Cohort!$B:$B,2)/$B24) | G24: =IF($B24=0,"",SUMIFS(Data_Cohort!$D:$D,Data_Cohort!$A:$A,$A24,Data_Cohort!$B:$B,3)/$B24) | H24: =IF($B24=0,"",SUMIFS(Data_Cohort!$D:$D,Data_Cohort!$A:$A,$A24,Data_Cohort!$B:$B,4)/$B24) | I24: =IF($B24=0,"",SUMIFS(Data_Cohort!$D:$D,Data_Cohort!$A:$A,$A24,Data_Cohort!$B:$B,5)/$B24) | J24: =IF($B24=0,"",SUMIFS(Data_Cohort!$D:$D,Data_Cohort!$A:$A,$A24,Data_Cohort!$B:$B,6)/$B24) | K24: =IF($B24=0,"",SUMIFS(Data_Cohort!$D:$D,Data_Cohort!$A:$A,$A24,Data_Cohort!$B:$B,7)/$B24)
A25: =A10 -> 46235 | B25: =B10 -> 0 | D25: =IF($B25=0,"",SUMIFS(Data_Cohort!$D:$D,Data_Cohort!$A:$A,$A25,Data_Cohort!$B:$B,0)/$B25) | E25: =IF($B25=0,"",SUMIFS(Data_Cohort!$D:$D,Data_Cohort!$A:$A,$A25,Data_Cohort!$B:$B,1)/$B25) | F25: =IF($B25=0,"",SUMIFS(Data_Cohort!$D:$D,Data_Cohort!$A:$A,$A25,Data_Cohort!$B:$B,2)/$B25) | G25: =IF($B25=0,"",SUMIFS(Data_Cohort!$D:$D,Data_Cohort!$A:$A,$A25,Data_Cohort!$B:$B,3)/$B25) | H25: =IF($B25=0,"",SUMIFS(Data_Cohort!$D:$D,Data_Cohort!$A:$A,$A25,Data_Cohort!$B:$B,4)/$B25) | I25: =IF($B25=0,"",SUMIFS(Data_Cohort!$D:$D,Data_Cohort!$A:$A,$A25,Data_Cohort!$B:$B,5)/$B25) | J25: =IF($B25=0,"",SUMIFS(Data_Cohort!$D:$D,Data_Cohort!$A:$A,$A25,Data_Cohort!$B:$B,6)/$B25)
A26: =A11 -> 46266 | B26: =B11 -> 204 | D26: =IF($B26=0,"",SUMIFS(Data_Cohort!$D:$D,Data_Cohort!$A:$A,$A26,Data_Cohort!$B:$B,0)/$B26) -> 1 | E26: =IF($B26=0,"",SUMIFS(Data_Cohort!$D:$D,Data_Cohort!$A:$A,$A26,Data_Cohort!$B:$B,1)/$B26) -> 0.39705882 | F26: =IF($B26=0,"",SUMIFS(Data_Cohort!$D:$D,Data_Cohort!$A:$A,$A26,Data_Cohort!$B:$B,2)/$B26) -> 0.12254902 | G26: =IF($B26=0,"",SUMIFS(Data_Cohort!$D:$D,Data_Cohort!$A:$A,$A26,Data_Cohort!$B:$B,3)/$B26) -> 0.12254902 | H26: =IF($B26=0,"",SUMIFS(Data_Cohort!$D:$D,Data_Cohort!$A:$A,$A26,Data_Cohort!$B:$B,4)/$B26) -> 0.11764706 | I26: =IF($B26=0,"",SUMIFS(Data_Cohort!$D:$D,Data_Cohort!$A:$A,$A26,Data_Cohort!$B:$B,5)/$B26) -> 0.10294118
A27: =A12 -> 46296 | B27: =B12 -> 302 | D27: =IF($B27=0,"",SUMIFS(Data_Cohort!$D:$D,Data_Cohort!$A:$A,$A27,Data_Cohort!$B:$B,0)/$B27) -> 1 | E27: =IF($B27=0,"",SUMIFS(Data_Cohort!$D:$D,Data_Cohort!$A:$A,$A27,Data_Cohort!$B:$B,1)/$B27) -> 0.22847682 | F27: =IF($B27=0,"",SUMIFS(Data_Cohort!$D:$D,Data_Cohort!$A:$A,$A27,Data_Cohort!$B:$B,2)/$B27) -> 0.12582781 | G27: =IF($B27=0,"",SUMIFS(Data_Cohort!$D:$D,Data_Cohort!$A:$A,$A27,Data_Cohort!$B:$B,3)/$B27) -> 0.12251656 | H27: =IF($B27=0,"",SUMIFS(Data_Cohort!$D:$D,Data_Cohort!$A:$A,$A27,Data_Cohort!$B:$B,4)/$B27) -> 0.11589404
A28: =A13 -> 46327 | B28: =B13 -> 349 | D28: =IF($B28=0,"",SUMIFS(Data_Cohort!$D:$D,Data_Cohort!$A:$A,$A28,Data_Cohort!$B:$B,0)/$B28) -> 1 | E28: =IF($B28=0,"",SUMIFS(Data_Cohort!$D:$D,Data_Cohort!$A:$A,$A28,Data_Cohort!$B:$B,1)/$B28) -> 0.26074499 | F28: =IF($B28=0,"",SUMIFS(Data_Cohort!$D:$D,Data_Cohort!$A:$A,$A28,Data_Cohort!$B:$B,2)/$B28) -> 0.12893983 | G28: =IF($B28=0,"",SUMIFS(Data_Cohort!$D:$D,Data_Cohort!$A:$A,$A28,Data_Cohort!$B:$B,3)/$B28) -> 0.11461318
A29: =A14 -> 46357 | B29: =B14 -> 335 | D29: =IF($B29=0,"",SUMIFS(Data_Cohort!$D:$D,Data_Cohort!$A:$A,$A29,Data_Cohort!$B:$B,0)/$B29) -> 1 | E29: =IF($B29=0,"",SUMIFS(Data_Cohort!$D:$D,Data_Cohort!$A:$A,$A29,Data_Cohort!$B:$B,1)/$B29) -> 0.22985075 | F29: =IF($B29=0,"",SUMIFS(Data_Cohort!$D:$D,Data_Cohort!$A:$A,$A29,Data_Cohort!$B:$B,2)/$B29) -> 0.11641791
A30: =A15 -> 46388 | B30: =B15 -> 385 | D30: =IF($B30=0,"",SUMIFS(Data_Cohort!$D:$D,Data_Cohort!$A:$A,$A30,Data_Cohort!$B:$B,0)/$B30) -> 1 | E30: =IF($B30=0,"",SUMIFS(Data_Cohort!$D:$D,Data_Cohort!$A:$A,$A30,Data_Cohort!$B:$B,1)/$B30) -> 0.24675325
A31: =A16 -> 46419 | B31: =B16 -> 441 | D31: =IF($B31=0,"",SUMIFS(Data_Cohort!$D:$D,Data_Cohort!$A:$A,$A31,Data_Cohort!$B:$B,0)/$B31) -> 1
A33: Read across a row to follow one cohort; read down a column to compare cohorts at the same age.

Sheet Enterprise
A1: =Data_Params!$B$14&" | Enterprise: usage vs commitment" -> Example Co (synthetic data) | Enterprise: usage vs commitment
A2: Contracts live at the close (Data_Contracts) and usage revenue by month (Data_EntMonth). True-up = commitment minus usage when usage falls short.
A4: Customer | B4: Start | C4: End | D4: Monthly commit ($) | E4: Price ($/M) | F4: Latest month vs commit | G4: Latest month true-up ($) | H4: =EDATE(Data_Params!$B$3,0) -> 46082 | I4: =EDATE(Data_Params!$B$3,1) -> 46113 | J4: =EDATE(Data_Params!$B$3,2) -> 46143 | K4: =EDATE(Data_Params!$B$3,3) -> 46174 | L4: =EDATE(Data_Params!$B$3,4) -> 46204 | M4: =EDATE(Data_Params!$B$3,5) -> 46235 | N4: =EDATE(Data_Params!$B$3,6) -> 46266 | O4: =EDATE(Data_Params!$B$3,7) -> 46296 | P4: =EDATE(Data_Params!$B$3,8) -> 46327 | Q4: =EDATE(Data_Params!$B$3,9) -> 46357 | R4: =EDATE(Data_Params!$B$3,10) -> 46388 | S4: =EDATE(Data_Params!$B$3,11) -> 46419
A5: =IF(INDEX(Data_Contracts!$A:$A,1+1)="","",INDEX(Data_Contracts!$A:$A,1+1)) -> Quanta Assist | B5: =IF(INDEX(Data_Contracts!$C:$C,1+1)="","",INDEX(Data_Contracts!$C:$C,1+1)) -> 46296 | C5: =IF(INDEX(Data_Contracts!$D:$D,1+1)="","",INDEX(Data_Contracts!$D:$D,1+1)) | D5: =IF(INDEX(Data_Contracts!$E:$E,1+1)="","",INDEX(Data_Contracts!$E:$E,1+1)) -> 30000 | E5: =IF(INDEX(Data_Contracts!$F:$F,1+1)="","",INDEX(Data_Contracts!$F:$F,1+1)) -> 0.0357 | F5: =IF(OR($A5="",N($D5)=0),"",S5/$D5) -> 1.3897156 | G5: =IF($A5="","",SUMIFS(Data_EntMonth!$F:$F,Data_EntMonth!$A:$A,$A5,Data_EntMonth!$B:$B,S$4)) -> 0 | H5: =IF($A5="","",SUMIFS(Data_EntMonth!$D:$D,Data_EntMonth!$A:$A,$A5,Data_EntMonth!$B:$B,H$4)) -> 0 | I5: =IF($A5="","",SUMIFS(Data_EntMonth!$D:$D,Data_EntMonth!$A:$A,$A5,Data_EntMonth!$B:$B,I$4)) -> 0 | J5: =IF($A5="","",SUMIFS(Data_EntMonth!$D:$D,Data_EntMonth!$A:$A,$A5,Data_EntMonth!$B:$B,J$4)) -> 0 | K5: =IF($A5="","",SUMIFS(Data_EntMonth!$D:$D,Data_EntMonth!$A:$A,$A5,Data_EntMonth!$B:$B,K$4)) -> 0 | L5: =IF($A5="","",SUMIFS(Data_EntMonth!$D:$D,Data_EntMonth!$A:$A,$A5,Data_EntMonth!$B:$B,L$4)) -> 0 | M5: =IF($A5="","",SUMIFS(Data_EntMonth!$D:$D,Data_EntMonth!$A:$A,$A5,Data_EntMonth!$B:$B,M$4)) -> 0 | N5: =IF($A5="","",SUMIFS(Data_EntMonth!$D:$D,Data_EntMonth!$A:$A,$A5,Data_EntMonth!$B:$B,N$4)) -> 0 | O5: =IF($A5="","",SUMIFS(Data_EntMonth!$D:$D,Data_EntMonth!$A:$A,$A5,Data_EntMonth!$B:$B,O$4)) -> 14978.126 | ... S5: =IF($A5="","",SUMIFS(Data_EntMonth!$D:$D,Data_EntMonth!$A:$A,$A5,Data_EntMonth!$B:$B,S$4)) -> 41691.469
A6: =IF(INDEX(Data_Contracts!$A:$A,2+1)="","",INDEX(Data_Contracts!$A:$A,2+1)) -> Ledgerline Payments | B6: =IF(INDEX(Data_Contracts!$C:$C,2+1)="","",INDEX(Data_Contracts!$C:$C,2+1)) -> 46310 | C6: =IF(INDEX(Data_Contracts!$D:$D,2+1)="","",INDEX(Data_Contracts!$D:$D,2+1)) | D6: =IF(INDEX(Data_Contracts!$E:$E,2+1)="","",INDEX(Data_Contracts!$E:$E,2+1)) -> 40000 | E6: =IF(INDEX(Data_Contracts!$F:$F,2+1)="","",INDEX(Data_Contracts!$F:$F,2+1)) -> 0.0336 | F6: =IF(OR($A6="",N($D6)=0),"",S6/$D6) -> 1.0693702 | G6: =IF($A6="","",SUMIFS(Data_EntMonth!$F:$F,Data_EntMonth!$A:$A,$A6,Data_EntMonth!$B:$B,S$4)) -> 0 | H6: =IF($A6="","",SUMIFS(Data_EntMonth!$D:$D,Data_EntMonth!$A:$A,$A6,Data_EntMonth!$B:$B,H$4)) -> 0 | I6: =IF($A6="","",SUMIFS(Data_EntMonth!$D:$D,Data_EntMonth!$A:$A,$A6,Data_EntMonth!$B:$B,I$4)) -> 0 | J6: =IF($A6="","",SUMIFS(Data_EntMonth!$D:$D,Data_EntMonth!$A:$A,$A6,Data_EntMonth!$B:$B,J$4)) -> 0 | K6: =IF($A6="","",SUMIFS(Data_EntMonth!$D:$D,Data_EntMonth!$A:$A,$A6,Data_EntMonth!$B:$B,K$4)) -> 0 | L6: =IF($A6="","",SUMIFS(Data_EntMonth!$D:$D,Data_EntMonth!$A:$A,$A6,Data_EntMonth!$B:$B,L$4)) -> 0 | M6: =IF($A6="","",SUMIFS(Data_EntMonth!$D:$D,Data_EntMonth!$A:$A,$A6,Data_EntMonth!$B:$B,M$4)) -> 0 | N6: =IF($A6="","",SUMIFS(Data_EntMonth!$D:$D,Data_EntMonth!$A:$A,$A6,Data_EntMonth!$B:$B,N$4)) -> 0 | O6: =IF($A6="","",SUMIFS(Data_EntMonth!$D:$D,Data_EntMonth!$A:$A,$A6,Data_EntMonth!$B:$B,O$4)) -> 5537.8654 | ... S6: =IF($A6="","",SUMIFS(Data_EntMonth!$D:$D,Data_EntMonth!$A:$A,$A6,Data_EntMonth!$B:$B,S$4)) -> 42774.81
A7: =IF(INDEX(Data_Contracts!$A:$A,3+1)="","",INDEX(Data_Contracts!$A:$A,3+1)) -> Northwind Insurance | B7: =IF(INDEX(Data_Contracts!$C:$C,3+1)="","",INDEX(Data_Contracts!$C:$C,3+1)) -> 46327 | C7: =IF(INDEX(Data_Contracts!$D:$D,3+1)="","",INDEX(Data_Contracts!$D:$D,3+1)) | D7: =IF(INDEX(Data_Contracts!$E:$E,3+1)="","",INDEX(Data_Contracts!$E:$E,3+1)) -> 20000 | E7: =IF(INDEX(Data_Contracts!$F:$F,3+1)="","",INDEX(Data_Contracts!$F:$F,3+1)) -> 0.0357 | F7: =IF(OR($A7="",N($D7)=0),"",S7/$D7) -> 0.45563304 | G7: =IF($A7="","",SUMIFS(Data_EntMonth!$F:$F,Data_EntMonth!$A:$A,$A7,Data_EntMonth!$B:$B,S$4)) -> 10887.339 | H7: =IF($A7="","",SUMIFS(Data_EntMonth!$D:$D,Data_EntMonth!$A:$A,$A7,Data_EntMonth!$B:$B,H$4)) -> 0 | I7: =IF($A7="","",SUMIFS(Data_EntMonth!$D:$D,Data_EntMonth!$A:$A,$A7,Data_EntMonth!$B:$B,I$4)) -> 0 | J7: =IF($A7="","",SUMIFS(Data_EntMonth!$D:$D,Data_EntMonth!$A:$A,$A7,Data_EntMonth!$B:$B,J$4)) -> 0 | K7: =IF($A7="","",SUMIFS(Data_EntMonth!$D:$D,Data_EntMonth!$A:$A,$A7,Data_EntMonth!$B:$B,K$4)) -> 0 | L7: =IF($A7="","",SUMIFS(Data_EntMonth!$D:$D,Data_EntMonth!$A:$A,$A7,Data_EntMonth!$B:$B,L$4)) -> 0 | M7: =IF($A7="","",SUMIFS(Data_EntMonth!$D:$D,Data_EntMonth!$A:$A,$A7,Data_EntMonth!$B:$B,M$4)) -> 0 | N7: =IF($A7="","",SUMIFS(Data_EntMonth!$D:$D,Data_EntMonth!$A:$A,$A7,Data_EntMonth!$B:$B,N$4)) -> 0 | O7: =IF($A7="","",SUMIFS(Data_EntMonth!$D:$D,Data_EntMonth!$A:$A,$A7,Data_EntMonth!$B:$B,O$4)) -> 0 | ... S7: =IF($A7="","",SUMIFS(Data_EntMonth!$D:$D,Data_EntMonth!$A:$A,$A7,Data_EntMonth!$B:$B,S$4)) -> 9112.6607
A8: =IF(INDEX(Data_Contracts!$A:$A,4+1)="","",INDEX(Data_Contracts!$A:$A,4+1)) -> Halcyon Games | B8: =IF(INDEX(Data_Contracts!$C:$C,4+1)="","",INDEX(Data_Contracts!$C:$C,4+1)) -> 46341 | C8: =IF(INDEX(Data_Contracts!$D:$D,4+1)="","",INDEX(Data_Contracts!$D:$D,4+1)) | D8: =IF(INDEX(Data_Contracts!$E:$E,4+1)="","",INDEX(Data_Contracts!$E:$E,4+1)) -> 15000 | E8: =IF(INDEX(Data_Contracts!$F:$F,4+1)="","",INDEX(Data_Contracts!$F:$F,4+1)) -> 0.0378 | F8: =IF(OR($A8="",N($D8)=0),"",S8/$D8) -> 1.0383228 | G8: =IF($A8="","",SUMIFS(Data_EntMonth!$F:$F,Data_EntMonth!$A:$A,$A8,Data_EntMonth!$B:$B,S$4)) -> 0 | H8: =IF($A8="","",SUMIFS(Data_EntMonth!$D:$D,Data_EntMonth!$A:$A,$A8,Data_EntMonth!$B:$B,H$4)) -> 0 | I8: =IF($A8="","",SUMIFS(Data_EntMonth!$D:$D,Data_EntMonth!$A:$A,$A8,Data_EntMonth!$B:$B,I$4)) -> 0 | J8: =IF($A8="","",SUMIFS(Data_EntMonth!$D:$D,Data_EntMonth!$A:$A,$A8,Data_EntMonth!$B:$B,J$4)) -> 0 | K8: =IF($A8="","",SUMIFS(Data_EntMonth!$D:$D,Data_EntMonth!$A:$A,$A8,Data_EntMonth!$B:$B,K$4)) -> 0 | L8: =IF($A8="","",SUMIFS(Data_EntMonth!$D:$D,Data_EntMonth!$A:$A,$A8,Data_EntMonth!$B:$B,L$4)) -> 0 | M8: =IF($A8="","",SUMIFS(Data_EntMonth!$D:$D,Data_EntMonth!$A:$A,$A8,Data_EntMonth!$B:$B,M$4)) -> 0 | N8: =IF($A8="","",SUMIFS(Data_EntMonth!$D:$D,Data_EntMonth!$A:$A,$A8,Data_EntMonth!$B:$B,N$4)) -> 0 | O8: =IF($A8="","",SUMIFS(Data_EntMonth!$D:$D,Data_EntMonth!$A:$A,$A8,Data_EntMonth!$B:$B,O$4)) -> 0 | ... S8: =IF($A8="","",SUMIFS(Data_EntMonth!$D:$D,Data_EntMonth!$A:$A,$A8,Data_EntMonth!$B:$B,S$4)) -> 15574.842
A9: =IF(INDEX(Data_Contracts!$A:$A,5+1)="","",INDEX(Data_Contracts!$A:$A,5+1)) -> Cobalt Ads | B9: =IF(INDEX(Data_Contracts!$C:$C,5+1)="","",INDEX(Data_Contracts!$C:$C,5+1)) -> 46357 | C9: =IF(INDEX(Data_Contracts!$D:$D,5+1)="","",INDEX(Data_Contracts!$D:$D,5+1)) | D9: =IF(INDEX(Data_Contracts!$E:$E,5+1)="","",INDEX(Data_Contracts!$E:$E,5+1)) -> 25000 | E9: =IF(INDEX(Data_Contracts!$F:$F,5+1)="","",INDEX(Data_Contracts!$F:$F,5+1)) -> 0.0357 | F9: =IF(OR($A9="",N($D9)=0),"",S9/$D9) -> 1.2029785 | G9: =IF($A9="","",SUMIFS(Data_EntMonth!$F:$F,Data_EntMonth!$A:$A,$A9,Data_EntMonth!$B:$B,S$4)) -> 0 | H9: =IF($A9="","",SUMIFS(Data_EntMonth!$D:$D,Data_EntMonth!$A:$A,$A9,Data_EntMonth!$B:$B,H$4)) -> 0 | I9: =IF($A9="","",SUMIFS(Data_EntMonth!$D:$D,Data_EntMonth!$A:$A,$A9,Data_EntMonth!$B:$B,I$4)) -> 0 | J9: =IF($A9="","",SUMIFS(Data_EntMonth!$D:$D,Data_EntMonth!$A:$A,$A9,Data_EntMonth!$B:$B,J$4)) -> 0 | K9: =IF($A9="","",SUMIFS(Data_EntMonth!$D:$D,Data_EntMonth!$A:$A,$A9,Data_EntMonth!$B:$B,K$4)) -> 0 | L9: =IF($A9="","",SUMIFS(Data_EntMonth!$D:$D,Data_EntMonth!$A:$A,$A9,Data_EntMonth!$B:$B,L$4)) -> 0 | M9: =IF($A9="","",SUMIFS(Data_EntMonth!$D:$D,Data_EntMonth!$A:$A,$A9,Data_EntMonth!$B:$B,M$4)) -> 0 | N9: =IF($A9="","",SUMIFS(Data_EntMonth!$D:$D,Data_EntMonth!$A:$A,$A9,Data_EntMonth!$B:$B,N$4)) -> 0 | O9: =IF($A9="","",SUMIFS(Data_EntMonth!$D:$D,Data_EntMonth!$A:$A,$A9,Data_EntMonth!$B:$B,O$4)) -> 0 | ... S9: =IF($A9="","",SUMIFS(Data_EntMonth!$D:$D,Data_EntMonth!$A:$A,$A9,Data_EntMonth!$B:$B,S$4)) -> 30074.464
A10: =IF(INDEX(Data_Contracts!$A:$A,6+1)="","",INDEX(Data_Contracts!$A:$A,6+1)) -> Meridian Legal | B10: =IF(INDEX(Data_Contracts!$C:$C,6+1)="","",INDEX(Data_Contracts!$C:$C,6+1)) -> 46371 | C10: =IF(INDEX(Data_Contracts!$D:$D,6+1)="","",INDEX(Data_Contracts!$D:$D,6+1)) | D10: =IF(INDEX(Data_Contracts!$E:$E,6+1)="","",INDEX(Data_Contracts!$E:$E,6+1)) -> 12500 | E10: =IF(INDEX(Data_Contracts!$F:$F,6+1)="","",INDEX(Data_Contracts!$F:$F,6+1)) -> 0.0336 | F10: =IF(OR($A10="",N($D10)=0),"",S10/$D10) -> 0.69402423 | G10: =IF($A10="","",SUMIFS(Data_EntMonth!$F:$F,Data_EntMonth!$A:$A,$A10,Data_EntMonth!$B:$B,S$4)) -> 3824.6972 | H10: =IF($A10="","",SUMIFS(Data_EntMonth!$D:$D,Data_EntMonth!$A:$A,$A10,Data_EntMonth!$B:$B,H$4)) -> 0 | I10: =IF($A10="","",SUMIFS(Data_EntMonth!$D:$D,Data_EntMonth!$A:$A,$A10,Data_EntMonth!$B:$B,I$4)) -> 0 | J10: =IF($A10="","",SUMIFS(Data_EntMonth!$D:$D,Data_EntMonth!$A:$A,$A10,Data_EntMonth!$B:$B,J$4)) -> 0 | K10: =IF($A10="","",SUMIFS(Data_EntMonth!$D:$D,Data_EntMonth!$A:$A,$A10,Data_EntMonth!$B:$B,K$4)) -> 0 | L10: =IF($A10="","",SUMIFS(Data_EntMonth!$D:$D,Data_EntMonth!$A:$A,$A10,Data_EntMonth!$B:$B,L$4)) -> 0 | M10: =IF($A10="","",SUMIFS(Data_EntMonth!$D:$D,Data_EntMonth!$A:$A,$A10,Data_EntMonth!$B:$B,M$4)) -> 0 | N10: =IF($A10="","",SUMIFS(Data_EntMonth!$D:$D,Data_EntMonth!$A:$A,$A10,Data_EntMonth!$B:$B,N$4)) -> 0 | O10: =IF($A10="","",SUMIFS(Data_EntMonth!$D:$D,Data_EntMonth!$A:$A,$A10,Data_EntMonth!$B:$B,O$4)) -> 0 | ... S10: =IF($A10="","",SUMIFS(Data_EntMonth!$D:$D,Data_EntMonth!$A:$A,$A10,Data_EntMonth!$B:$B,S$4)) -> 8675.3028
A11: =IF(INDEX(Data_Contracts!$A:$A,7+1)="","",INDEX(Data_Contracts!$A:$A,7+1)) -> Sable Research | B11: =IF(INDEX(Data_Contracts!$C:$C,7+1)="","",INDEX(Data_Contracts!$C:$C,7+1)) -> 46388 | C11: =IF(INDEX(Data_Contracts!$D:$D,7+1)="","",INDEX(Data_Contracts!$D:$D,7+1)) | D11: =IF(INDEX(Data_Contracts!$E:$E,7+1)="","",INDEX(Data_Contracts!$E:$E,7+1)) -> 17500 | E11: =IF(INDEX(Data_Contracts!$F:$F,7+1)="","",INDEX(Data_Contracts!$F:$F,7+1)) -> 0.0357 | F11: =IF(OR($A11="",N($D11)=0),"",S11/$D11) -> 0.70960707 | G11: =IF($A11="","",SUMIFS(Data_EntMonth!$F:$F,Data_EntMonth!$A:$A,$A11,Data_EntMonth!$B:$B,S$4)) -> 5081.8763 | H11: =IF($A11="","",SUMIFS(Data_EntMonth!$D:$D,Data_EntMonth!$A:$A,$A11,Data_EntMonth!$B:$B,H$4)) -> 0 | I11: =IF($A11="","",SUMIFS(Data_EntMonth!$D:$D,Data_EntMonth!$A:$A,$A11,Data_EntMonth!$B:$B,I$4)) -> 0 | J11: =IF($A11="","",SUMIFS(Data_EntMonth!$D:$D,Data_EntMonth!$A:$A,$A11,Data_EntMonth!$B:$B,J$4)) -> 0 | K11: =IF($A11="","",SUMIFS(Data_EntMonth!$D:$D,Data_EntMonth!$A:$A,$A11,Data_EntMonth!$B:$B,K$4)) -> 0 | L11: =IF($A11="","",SUMIFS(Data_EntMonth!$D:$D,Data_EntMonth!$A:$A,$A11,Data_EntMonth!$B:$B,L$4)) -> 0 | M11: =IF($A11="","",SUMIFS(Data_EntMonth!$D:$D,Data_EntMonth!$A:$A,$A11,Data_EntMonth!$B:$B,M$4)) -> 0 | N11: =IF($A11="","",SUMIFS(Data_EntMonth!$D:$D,Data_EntMonth!$A:$A,$A11,Data_EntMonth!$B:$B,N$4)) -> 0 | O11: =IF($A11="","",SUMIFS(Data_EntMonth!$D:$D,Data_EntMonth!$A:$A,$A11,Data_EntMonth!$B:$B,O$4)) -> 0 | ... S11: =IF($A11="","",SUMIFS(Data_EntMonth!$D:$D,Data_EntMonth!$A:$A,$A11,Data_EntMonth!$B:$B,S$4)) -> 12418.124
A12: =IF(INDEX(Data_Contracts!$A:$A,8+1)="","",INDEX(Data_Contracts!$A:$A,8+1)) -> Brightpath Logistics | B12: =IF(INDEX(Data_Contracts!$C:$C,8+1)="","",INDEX(Data_Contracts!$C:$C,8+1)) -> 46419 | C12: =IF(INDEX(Data_Contracts!$D:$D,8+1)="","",INDEX(Data_Contracts!$D:$D,8+1)) | D12: =IF(INDEX(Data_Contracts!$E:$E,8+1)="","",INDEX(Data_Contracts!$E:$E,8+1)) -> 10000 | E12: =IF(INDEX(Data_Contracts!$F:$F,8+1)="","",INDEX(Data_Contracts!$F:$F,8+1)) -> 0.0378 | F12: =IF(OR($A12="",N($D12)=0),"",S12/$D12) -> 0.22378546 | G12: =IF($A12="","",SUMIFS(Data_EntMonth!$F:$F,Data_EntMonth!$A:$A,$A12,Data_EntMonth!$B:$B,S$4)) -> 7762.1454 | H12: =IF($A12="","",SUMIFS(Data_EntMonth!$D:$D,Data_EntMonth!$A:$A,$A12,Data_EntMonth!$B:$B,H$4)) -> 0 | I12: =IF($A12="","",SUMIFS(Data_EntMonth!$D:$D,Data_EntMonth!$A:$A,$A12,Data_EntMonth!$B:$B,I$4)) -> 0 | J12: =IF($A12="","",SUMIFS(Data_EntMonth!$D:$D,Data_EntMonth!$A:$A,$A12,Data_EntMonth!$B:$B,J$4)) -> 0 | K12: =IF($A12="","",SUMIFS(Data_EntMonth!$D:$D,Data_EntMonth!$A:$A,$A12,Data_EntMonth!$B:$B,K$4)) -> 0 | L12: =IF($A12="","",SUMIFS(Data_EntMonth!$D:$D,Data_EntMonth!$A:$A,$A12,Data_EntMonth!$B:$B,L$4)) -> 0 | M12: =IF($A12="","",SUMIFS(Data_EntMonth!$D:$D,Data_EntMonth!$A:$A,$A12,Data_EntMonth!$B:$B,M$4)) -> 0 | N12: =IF($A12="","",SUMIFS(Data_EntMonth!$D:$D,Data_EntMonth!$A:$A,$A12,Data_EntMonth!$B:$B,N$4)) -> 0 | O12: =IF($A12="","",SUMIFS(Data_EntMonth!$D:$D,Data_EntMonth!$A:$A,$A12,Data_EntMonth!$B:$B,O$4)) -> 0 | ... S12: =IF($A12="","",SUMIFS(Data_EntMonth!$D:$D,Data_EntMonth!$A:$A,$A12,Data_EntMonth!$B:$B,S$4)) -> 2237.8546
A13: =IF(INDEX(Data_Contracts!$A:$A,9+1)="","",INDEX(Data_Contracts!$A:$A,9+1)) | B13: =IF(INDEX(Data_Contracts!$C:$C,9+1)="","",INDEX(Data_Contracts!$C:$C,9+1)) | C13: =IF(INDEX(Data_Contracts!$D:$D,9+1)="","",INDEX(Data_Contracts!$D:$D,9+1)) | D13: =IF(INDEX(Data_Contracts!$E:$E,9+1)="","",INDEX(Data_Contracts!$E:$E,9+1)) | E13: =IF(INDEX(Data_Contracts!$F:$F,9+1)="","",INDEX(Data_Contracts!$F:$F,9+1)) | F13: =IF(OR($A13="",N($D13)=0),"",S13/$D13) | G13: =IF($A13="","",SUMIFS(Data_EntMonth!$F:$F,Data_EntMonth!$A:$A,$A13,Data_EntMonth!$B:$B,S$4)) | H13: =IF($A13="","",SUMIFS(Data_EntMonth!$D:$D,Data_EntMonth!$A:$A,$A13,Data_EntMonth!$B:$B,H$4)) | I13: =IF($A13="","",SUMIFS(Data_EntMonth!$D:$D,Data_EntMonth!$A:$A,$A13,Data_EntMonth!$B:$B,I$4)) | J13: =IF($A13="","",SUMIFS(Data_EntMonth!$D:$D,Data_EntMonth!$A:$A,$A13,Data_EntMonth!$B:$B,J$4)) | K13: =IF($A13="","",SUMIFS(Data_EntMonth!$D:$D,Data_EntMonth!$A:$A,$A13,Data_EntMonth!$B:$B,K$4)) | L13: =IF($A13="","",SUMIFS(Data_EntMonth!$D:$D,Data_EntMonth!$A:$A,$A13,Data_EntMonth!$B:$B,L$4)) | M13: =IF($A13="","",SUMIFS(Data_EntMonth!$D:$D,Data_EntMonth!$A:$A,$A13,Data_EntMonth!$B:$B,M$4)) | N13: =IF($A13="","",SUMIFS(Data_EntMonth!$D:$D,Data_EntMonth!$A:$A,$A13,Data_EntMonth!$B:$B,N$4)) | O13: =IF($A13="","",SUMIFS(Data_EntMonth!$D:$D,Data_EntMonth!$A:$A,$A13,Data_EntMonth!$B:$B,O$4)) | ... S13: =IF($A13="","",SUMIFS(Data_EntMonth!$D:$D,Data_EntMonth!$A:$A,$A13,Data_EntMonth!$B:$B,S$4))
A14: =IF(INDEX(Data_Contracts!$A:$A,10+1)="","",INDEX(Data_Contracts!$A:$A,10+1)) | B14: =IF(INDEX(Data_Contracts!$C:$C,10+1)="","",INDEX(Data_Contracts!$C:$C,10+1)) | C14: =IF(INDEX(Data_Contracts!$D:$D,10+1)="","",INDEX(Data_Contracts!$D:$D,10+1)) | D14: =IF(INDEX(Data_Contracts!$E:$E,10+1)="","",INDEX(Data_Contracts!$E:$E,10+1)) | E14: =IF(INDEX(Data_Contracts!$F:$F,10+1)="","",INDEX(Data_Contracts!$F:$F,10+1)) | F14: =IF(OR($A14="",N($D14)=0),"",S14/$D14) | G14: =IF($A14="","",SUMIFS(Data_EntMonth!$F:$F,Data_EntMonth!$A:$A,$A14,Data_EntMonth!$B:$B,S$4)) | H14: =IF($A14="","",SUMIFS(Data_EntMonth!$D:$D,Data_EntMonth!$A:$A,$A14,Data_EntMonth!$B:$B,H$4)) | I14: =IF($A14="","",SUMIFS(Data_EntMonth!$D:$D,Data_EntMonth!$A:$A,$A14,Data_EntMonth!$B:$B,I$4)) | J14: =IF($A14="","",SUMIFS(Data_EntMonth!$D:$D,Data_EntMonth!$A:$A,$A14,Data_EntMonth!$B:$B,J$4)) | K14: =IF($A14="","",SUMIFS(Data_EntMonth!$D:$D,Data_EntMonth!$A:$A,$A14,Data_EntMonth!$B:$B,K$4)) | L14: =IF($A14="","",SUMIFS(Data_EntMonth!$D:$D,Data_EntMonth!$A:$A,$A14,Data_EntMonth!$B:$B,L$4)) | M14: =IF($A14="","",SUMIFS(Data_EntMonth!$D:$D,Data_EntMonth!$A:$A,$A14,Data_EntMonth!$B:$B,M$4)) | N14: =IF($A14="","",SUMIFS(Data_EntMonth!$D:$D,Data_EntMonth!$A:$A,$A14,Data_EntMonth!$B:$B,N$4)) | O14: =IF($A14="","",SUMIFS(Data_EntMonth!$D:$D,Data_EntMonth!$A:$A,$A14,Data_EntMonth!$B:$B,O$4)) | ... S14: =IF($A14="","",SUMIFS(Data_EntMonth!$D:$D,Data_EntMonth!$A:$A,$A14,Data_EntMonth!$B:$B,S$4))
A15: =IF(INDEX(Data_Contracts!$A:$A,11+1)="","",INDEX(Data_Contracts!$A:$A,11+1)) | B15: =IF(INDEX(Data_Contracts!$C:$C,11+1)="","",INDEX(Data_Contracts!$C:$C,11+1)) | C15: =IF(INDEX(Data_Contracts!$D:$D,11+1)="","",INDEX(Data_Contracts!$D:$D,11+1)) | D15: =IF(INDEX(Data_Contracts!$E:$E,11+1)="","",INDEX(Data_Contracts!$E:$E,11+1)) | E15: =IF(INDEX(Data_Contracts!$F:$F,11+1)="","",INDEX(Data_Contracts!$F:$F,11+1)) | F15: =IF(OR($A15="",N($D15)=0),"",S15/$D15) | G15: =IF($A15="","",SUMIFS(Data_EntMonth!$F:$F,Data_EntMonth!$A:$A,$A15,Data_EntMonth!$B:$B,S$4)) | H15: =IF($A15="","",SUMIFS(Data_EntMonth!$D:$D,Data_EntMonth!$A:$A,$A15,Data_EntMonth!$B:$B,H$4)) | I15: =IF($A15="","",SUMIFS(Data_EntMonth!$D:$D,Data_EntMonth!$A:$A,$A15,Data_EntMonth!$B:$B,I$4)) | J15: =IF($A15="","",SUMIFS(Data_EntMonth!$D:$D,Data_EntMonth!$A:$A,$A15,Data_EntMonth!$B:$B,J$4)) | K15: =IF($A15="","",SUMIFS(Data_EntMonth!$D:$D,Data_EntMonth!$A:$A,$A15,Data_EntMonth!$B:$B,K$4)) | L15: =IF($A15="","",SUMIFS(Data_EntMonth!$D:$D,Data_EntMonth!$A:$A,$A15,Data_EntMonth!$B:$B,L$4)) | M15: =IF($A15="","",SUMIFS(Data_EntMonth!$D:$D,Data_EntMonth!$A:$A,$A15,Data_EntMonth!$B:$B,M$4)) | N15: =IF($A15="","",SUMIFS(Data_EntMonth!$D:$D,Data_EntMonth!$A:$A,$A15,Data_EntMonth!$B:$B,N$4)) | O15: =IF($A15="","",SUMIFS(Data_EntMonth!$D:$D,Data_EntMonth!$A:$A,$A15,Data_EntMonth!$B:$B,O$4)) | ... S15: =IF($A15="","",SUMIFS(Data_EntMonth!$D:$D,Data_EntMonth!$A:$A,$A15,Data_EntMonth!$B:$B,S$4))
A16: =IF(INDEX(Data_Contracts!$A:$A,12+1)="","",INDEX(Data_Contracts!$A:$A,12+1)) | B16: =IF(INDEX(Data_Contracts!$C:$C,12+1)="","",INDEX(Data_Contracts!$C:$C,12+1)) | C16: =IF(INDEX(Data_Contracts!$D:$D,12+1)="","",INDEX(Data_Contracts!$D:$D,12+1)) | D16: =IF(INDEX(Data_Contracts!$E:$E,12+1)="","",INDEX(Data_Contracts!$E:$E,12+1)) | E16: =IF(INDEX(Data_Contracts!$F:$F,12+1)="","",INDEX(Data_Contracts!$F:$F,12+1)) | F16: =IF(OR($A16="",N($D16)=0),"",S16/$D16) | G16: =IF($A16="","",SUMIFS(Data_EntMonth!$F:$F,Data_EntMonth!$A:$A,$A16,Data_EntMonth!$B:$B,S$4)) | H16: =IF($A16="","",SUMIFS(Data_EntMonth!$D:$D,Data_EntMonth!$A:$A,$A16,Data_EntMonth!$B:$B,H$4)) | I16: =IF($A16="","",SUMIFS(Data_EntMonth!$D:$D,Data_EntMonth!$A:$A,$A16,Data_EntMonth!$B:$B,I$4)) | J16: =IF($A16="","",SUMIFS(Data_EntMonth!$D:$D,Data_EntMonth!$A:$A,$A16,Data_EntMonth!$B:$B,J$4)) | K16: =IF($A16="","",SUMIFS(Data_EntMonth!$D:$D,Data_EntMonth!$A:$A,$A16,Data_EntMonth!$B:$B,K$4)) | L16: =IF($A16="","",SUMIFS(Data_EntMonth!$D:$D,Data_EntMonth!$A:$A,$A16,Data_EntMonth!$B:$B,L$4)) | M16: =IF($A16="","",SUMIFS(Data_EntMonth!$D:$D,Data_EntMonth!$A:$A,$A16,Data_EntMonth!$B:$B,M$4)) | N16: =IF($A16="","",SUMIFS(Data_EntMonth!$D:$D,Data_EntMonth!$A:$A,$A16,Data_EntMonth!$B:$B,N$4)) | O16: =IF($A16="","",SUMIFS(Data_EntMonth!$D:$D,Data_EntMonth!$A:$A,$A16,Data_EntMonth!$B:$B,O$4)) | ... S16: =IF($A16="","",SUMIFS(Data_EntMonth!$D:$D,Data_EntMonth!$A:$A,$A16,Data_EntMonth!$B:$B,S$4))
A17: =IF(INDEX(Data_Contracts!$A:$A,13+1)="","",INDEX(Data_Contracts!$A:$A,13+1)) | B17: =IF(INDEX(Data_Contracts!$C:$C,13+1)="","",INDEX(Data_Contracts!$C:$C,13+1)) | C17: =IF(INDEX(Data_Contracts!$D:$D,13+1)="","",INDEX(Data_Contracts!$D:$D,13+1)) | D17: =IF(INDEX(Data_Contracts!$E:$E,13+1)="","",INDEX(Data_Contracts!$E:$E,13+1)) | E17: =IF(INDEX(Data_Contracts!$F:$F,13+1)="","",INDEX(Data_Contracts!$F:$F,13+1)) | F17: =IF(OR($A17="",N($D17)=0),"",S17/$D17) | G17: =IF($A17="","",SUMIFS(Data_EntMonth!$F:$F,Data_EntMonth!$A:$A,$A17,Data_EntMonth!$B:$B,S$4)) | H17: =IF($A17="","",SUMIFS(Data_EntMonth!$D:$D,Data_EntMonth!$A:$A,$A17,Data_EntMonth!$B:$B,H$4)) | I17: =IF($A17="","",SUMIFS(Data_EntMonth!$D:$D,Data_EntMonth!$A:$A,$A17,Data_EntMonth!$B:$B,I$4)) | J17: =IF($A17="","",SUMIFS(Data_EntMonth!$D:$D,Data_EntMonth!$A:$A,$A17,Data_EntMonth!$B:$B,J$4)) | K17: =IF($A17="","",SUMIFS(Data_EntMonth!$D:$D,Data_EntMonth!$A:$A,$A17,Data_EntMonth!$B:$B,K$4)) | L17: =IF($A17="","",SUMIFS(Data_EntMonth!$D:$D,Data_EntMonth!$A:$A,$A17,Data_EntMonth!$B:$B,L$4)) | M17: =IF($A17="","",SUMIFS(Data_EntMonth!$D:$D,Data_EntMonth!$A:$A,$A17,Data_EntMonth!$B:$B,M$4)) | N17: =IF($A17="","",SUMIFS(Data_EntMonth!$D:$D,Data_EntMonth!$A:$A,$A17,Data_EntMonth!$B:$B,N$4)) | O17: =IF($A17="","",SUMIFS(Data_EntMonth!$D:$D,Data_EntMonth!$A:$A,$A17,Data_EntMonth!$B:$B,O$4)) | ... S17: =IF($A17="","",SUMIFS(Data_EntMonth!$D:$D,Data_EntMonth!$A:$A,$A17,Data_EntMonth!$B:$B,S$4))
A18: =IF(INDEX(Data_Contracts!$A:$A,14+1)="","",INDEX(Data_Contracts!$A:$A,14+1)) | B18: =IF(INDEX(Data_Contracts!$C:$C,14+1)="","",INDEX(Data_Contracts!$C:$C,14+1)) | C18: =IF(INDEX(Data_Contracts!$D:$D,14+1)="","",INDEX(Data_Contracts!$D:$D,14+1)) | D18: =IF(INDEX(Data_Contracts!$E:$E,14+1)="","",INDEX(Data_Contracts!$E:$E,14+1)) | E18: =IF(INDEX(Data_Contracts!$F:$F,14+1)="","",INDEX(Data_Contracts!$F:$F,14+1)) | F18: =IF(OR($A18="",N($D18)=0),"",S18/$D18) | G18: =IF($A18="","",SUMIFS(Data_EntMonth!$F:$F,Data_EntMonth!$A:$A,$A18,Data_EntMonth!$B:$B,S$4)) | H18: =IF($A18="","",SUMIFS(Data_EntMonth!$D:$D,Data_EntMonth!$A:$A,$A18,Data_EntMonth!$B:$B,H$4)) | I18: =IF($A18="","",SUMIFS(Data_EntMonth!$D:$D,Data_EntMonth!$A:$A,$A18,Data_EntMonth!$B:$B,I$4)) | J18: =IF($A18="","",SUMIFS(Data_EntMonth!$D:$D,Data_EntMonth!$A:$A,$A18,Data_EntMonth!$B:$B,J$4)) | K18: =IF($A18="","",SUMIFS(Data_EntMonth!$D:$D,Data_EntMonth!$A:$A,$A18,Data_EntMonth!$B:$B,K$4)) | L18: =IF($A18="","",SUMIFS(Data_EntMonth!$D:$D,Data_EntMonth!$A:$A,$A18,Data_EntMonth!$B:$B,L$4)) | M18: =IF($A18="","",SUMIFS(Data_EntMonth!$D:$D,Data_EntMonth!$A:$A,$A18,Data_EntMonth!$B:$B,M$4)) | N18: =IF($A18="","",SUMIFS(Data_EntMonth!$D:$D,Data_EntMonth!$A:$A,$A18,Data_EntMonth!$B:$B,N$4)) | O18: =IF($A18="","",SUMIFS(Data_EntMonth!$D:$D,Data_EntMonth!$A:$A,$A18,Data_EntMonth!$B:$B,O$4)) | ... S18: =IF($A18="","",SUMIFS(Data_EntMonth!$D:$D,Data_EntMonth!$A:$A,$A18,Data_EntMonth!$B:$B,S$4))
A19: =IF(INDEX(Data_Contracts!$A:$A,15+1)="","",INDEX(Data_Contracts!$A:$A,15+1)) | B19: =IF(INDEX(Data_Contracts!$C:$C,15+1)="","",INDEX(Data_Contracts!$C:$C,15+1)) | C19: =IF(INDEX(Data_Contracts!$D:$D,15+1)="","",INDEX(Data_Contracts!$D:$D,15+1)) | D19: =IF(INDEX(Data_Contracts!$E:$E,15+1)="","",INDEX(Data_Contracts!$E:$E,15+1)) | E19: =IF(INDEX(Data_Contracts!$F:$F,15+1)="","",INDEX(Data_Contracts!$F:$F,15+1)) | F19: =IF(OR($A19="",N($D19)=0),"",S19/$D19) | G19: =IF($A19="","",SUMIFS(Data_EntMonth!$F:$F,Data_EntMonth!$A:$A,$A19,Data_EntMonth!$B:$B,S$4)) | H19: =IF($A19="","",SUMIFS(Data_EntMonth!$D:$D,Data_EntMonth!$A:$A,$A19,Data_EntMonth!$B:$B,H$4)) | I19: =IF($A19="","",SUMIFS(Data_EntMonth!$D:$D,Data_EntMonth!$A:$A,$A19,Data_EntMonth!$B:$B,I$4)) | J19: =IF($A19="","",SUMIFS(Data_EntMonth!$D:$D,Data_EntMonth!$A:$A,$A19,Data_EntMonth!$B:$B,J$4)) | K19: =IF($A19="","",SUMIFS(Data_EntMonth!$D:$D,Data_EntMonth!$A:$A,$A19,Data_EntMonth!$B:$B,K$4)) | L19: =IF($A19="","",SUMIFS(Data_EntMonth!$D:$D,Data_EntMonth!$A:$A,$A19,Data_EntMonth!$B:$B,L$4)) | M19: =IF($A19="","",SUMIFS(Data_EntMonth!$D:$D,Data_EntMonth!$A:$A,$A19,Data_EntMonth!$B:$B,M$4)) | N19: =IF($A19="","",SUMIFS(Data_EntMonth!$D:$D,Data_EntMonth!$A:$A,$A19,Data_EntMonth!$B:$B,N$4)) | O19: =IF($A19="","",SUMIFS(Data_EntMonth!$D:$D,Data_EntMonth!$A:$A,$A19,Data_EntMonth!$B:$B,O$4)) | ... S19: =IF($A19="","",SUMIFS(Data_EntMonth!$D:$D,Data_EntMonth!$A:$A,$A19,Data_EntMonth!$B:$B,S$4))
A20: =IF(INDEX(Data_Contracts!$A:$A,16+1)="","",INDEX(Data_Contracts!$A:$A,16+1)) | B20: =IF(INDEX(Data_Contracts!$C:$C,16+1)="","",INDEX(Data_Contracts!$C:$C,16+1)) | C20: =IF(INDEX(Data_Contracts!$D:$D,16+1)="","",INDEX(Data_Contracts!$D:$D,16+1)) | D20: =IF(INDEX(Data_Contracts!$E:$E,16+1)="","",INDEX(Data_Contracts!$E:$E,16+1)) | E20: =IF(INDEX(Data_Contracts!$F:$F,16+1)="","",INDEX(Data_Contracts!$F:$F,16+1)) | F20: =IF(OR($A20="",N($D20)=0),"",S20/$D20) | G20: =IF($A20="","",SUMIFS(Data_EntMonth!$F:$F,Data_EntMonth!$A:$A,$A20,Data_EntMonth!$B:$B,S$4)) | H20: =IF($A20="","",SUMIFS(Data_EntMonth!$D:$D,Data_EntMonth!$A:$A,$A20,Data_EntMonth!$B:$B,H$4)) | I20: =IF($A20="","",SUMIFS(Data_EntMonth!$D:$D,Data_EntMonth!$A:$A,$A20,Data_EntMonth!$B:$B,I$4)) | J20: =IF($A20="","",SUMIFS(Data_EntMonth!$D:$D,Data_EntMonth!$A:$A,$A20,Data_EntMonth!$B:$B,J$4)) | K20: =IF($A20="","",SUMIFS(Data_EntMonth!$D:$D,Data_EntMonth!$A:$A,$A20,Data_EntMonth!$B:$B,K$4)) | L20: =IF($A20="","",SUMIFS(Data_EntMonth!$D:$D,Data_EntMonth!$A:$A,$A20,Data_EntMonth!$B:$B,L$4)) | M20: =IF($A20="","",SUMIFS(Data_EntMonth!$D:$D,Data_EntMonth!$A:$A,$A20,Data_EntMonth!$B:$B,M$4)) | N20: =IF($A20="","",SUMIFS(Data_EntMonth!$D:$D,Data_EntMonth!$A:$A,$A20,Data_EntMonth!$B:$B,N$4)) | O20: =IF($A20="","",SUMIFS(Data_EntMonth!$D:$D,Data_EntMonth!$A:$A,$A20,Data_EntMonth!$B:$B,O$4)) | ... S20: =IF($A20="","",SUMIFS(Data_EntMonth!$D:$D,Data_EntMonth!$A:$A,$A20,Data_EntMonth!$B:$B,S$4))
A21: =IF(INDEX(Data_Contracts!$A:$A,17+1)="","",INDEX(Data_Contracts!$A:$A,17+1)) | B21: =IF(INDEX(Data_Contracts!$C:$C,17+1)="","",INDEX(Data_Contracts!$C:$C,17+1)) | C21: =IF(INDEX(Data_Contracts!$D:$D,17+1)="","",INDEX(Data_Contracts!$D:$D,17+1)) | D21: =IF(INDEX(Data_Contracts!$E:$E,17+1)="","",INDEX(Data_Contracts!$E:$E,17+1)) | E21: =IF(INDEX(Data_Contracts!$F:$F,17+1)="","",INDEX(Data_Contracts!$F:$F,17+1)) | F21: =IF(OR($A21="",N($D21)=0),"",S21/$D21) | G21: =IF($A21="","",SUMIFS(Data_EntMonth!$F:$F,Data_EntMonth!$A:$A,$A21,Data_EntMonth!$B:$B,S$4)) | H21: =IF($A21="","",SUMIFS(Data_EntMonth!$D:$D,Data_EntMonth!$A:$A,$A21,Data_EntMonth!$B:$B,H$4)) | I21: =IF($A21="","",SUMIFS(Data_EntMonth!$D:$D,Data_EntMonth!$A:$A,$A21,Data_EntMonth!$B:$B,I$4)) | J21: =IF($A21="","",SUMIFS(Data_EntMonth!$D:$D,Data_EntMonth!$A:$A,$A21,Data_EntMonth!$B:$B,J$4)) | K21: =IF($A21="","",SUMIFS(Data_EntMonth!$D:$D,Data_EntMonth!$A:$A,$A21,Data_EntMonth!$B:$B,K$4)) | L21: =IF($A21="","",SUMIFS(Data_EntMonth!$D:$D,Data_EntMonth!$A:$A,$A21,Data_EntMonth!$B:$B,L$4)) | M21: =IF($A21="","",SUMIFS(Data_EntMonth!$D:$D,Data_EntMonth!$A:$A,$A21,Data_EntMonth!$B:$B,M$4)) | N21: =IF($A21="","",SUMIFS(Data_EntMonth!$D:$D,Data_EntMonth!$A:$A,$A21,Data_EntMonth!$B:$B,N$4)) | O21: =IF($A21="","",SUMIFS(Data_EntMonth!$D:$D,Data_EntMonth!$A:$A,$A21,Data_EntMonth!$B:$B,O$4)) | ... S21: =IF($A21="","",SUMIFS(Data_EntMonth!$D:$D,Data_EntMonth!$A:$A,$A21,Data_EntMonth!$B:$B,S$4))
A22: =IF(INDEX(Data_Contracts!$A:$A,18+1)="","",INDEX(Data_Contracts!$A:$A,18+1)) | B22: =IF(INDEX(Data_Contracts!$C:$C,18+1)="","",INDEX(Data_Contracts!$C:$C,18+1)) | C22: =IF(INDEX(Data_Contracts!$D:$D,18+1)="","",INDEX(Data_Contracts!$D:$D,18+1)) | D22: =IF(INDEX(Data_Contracts!$E:$E,18+1)="","",INDEX(Data_Contracts!$E:$E,18+1)) | E22: =IF(INDEX(Data_Contracts!$F:$F,18+1)="","",INDEX(Data_Contracts!$F:$F,18+1)) | F22: =IF(OR($A22="",N($D22)=0),"",S22/$D22) | G22: =IF($A22="","",SUMIFS(Data_EntMonth!$F:$F,Data_EntMonth!$A:$A,$A22,Data_EntMonth!$B:$B,S$4)) | H22: =IF($A22="","",SUMIFS(Data_EntMonth!$D:$D,Data_EntMonth!$A:$A,$A22,Data_EntMonth!$B:$B,H$4)) | I22: =IF($A22="","",SUMIFS(Data_EntMonth!$D:$D,Data_EntMonth!$A:$A,$A22,Data_EntMonth!$B:$B,I$4)) | J22: =IF($A22="","",SUMIFS(Data_EntMonth!$D:$D,Data_EntMonth!$A:$A,$A22,Data_EntMonth!$B:$B,J$4)) | K22: =IF($A22="","",SUMIFS(Data_EntMonth!$D:$D,Data_EntMonth!$A:$A,$A22,Data_EntMonth!$B:$B,K$4)) | L22: =IF($A22="","",SUMIFS(Data_EntMonth!$D:$D,Data_EntMonth!$A:$A,$A22,Data_EntMonth!$B:$B,L$4)) | M22: =IF($A22="","",SUMIFS(Data_EntMonth!$D:$D,Data_EntMonth!$A:$A,$A22,Data_EntMonth!$B:$B,M$4)) | N22: =IF($A22="","",SUMIFS(Data_EntMonth!$D:$D,Data_EntMonth!$A:$A,$A22,Data_EntMonth!$B:$B,N$4)) | O22: =IF($A22="","",SUMIFS(Data_EntMonth!$D:$D,Data_EntMonth!$A:$A,$A22,Data_EntMonth!$B:$B,O$4)) | ... S22: =IF($A22="","",SUMIFS(Data_EntMonth!$D:$D,Data_EntMonth!$A:$A,$A22,Data_EntMonth!$B:$B,S$4))
A23: =IF(INDEX(Data_Contracts!$A:$A,19+1)="","",INDEX(Data_Contracts!$A:$A,19+1)) | B23: =IF(INDEX(Data_Contracts!$C:$C,19+1)="","",INDEX(Data_Contracts!$C:$C,19+1)) | C23: =IF(INDEX(Data_Contracts!$D:$D,19+1)="","",INDEX(Data_Contracts!$D:$D,19+1)) | D23: =IF(INDEX(Data_Contracts!$E:$E,19+1)="","",INDEX(Data_Contracts!$E:$E,19+1)) | E23: =IF(INDEX(Data_Contracts!$F:$F,19+1)="","",INDEX(Data_Contracts!$F:$F,19+1)) | F23: =IF(OR($A23="",N($D23)=0),"",S23/$D23) | G23: =IF($A23="","",SUMIFS(Data_EntMonth!$F:$F,Data_EntMonth!$A:$A,$A23,Data_EntMonth!$B:$B,S$4)) | H23: =IF($A23="","",SUMIFS(Data_EntMonth!$D:$D,Data_EntMonth!$A:$A,$A23,Data_EntMonth!$B:$B,H$4)) | I23: =IF($A23="","",SUMIFS(Data_EntMonth!$D:$D,Data_EntMonth!$A:$A,$A23,Data_EntMonth!$B:$B,I$4)) | J23: =IF($A23="","",SUMIFS(Data_EntMonth!$D:$D,Data_EntMonth!$A:$A,$A23,Data_EntMonth!$B:$B,J$4)) | K23: =IF($A23="","",SUMIFS(Data_EntMonth!$D:$D,Data_EntMonth!$A:$A,$A23,Data_EntMonth!$B:$B,K$4)) | L23: =IF($A23="","",SUMIFS(Data_EntMonth!$D:$D,Data_EntMonth!$A:$A,$A23,Data_EntMonth!$B:$B,L$4)) | M23: =IF($A23="","",SUMIFS(Data_EntMonth!$D:$D,Data_EntMonth!$A:$A,$A23,Data_EntMonth!$B:$B,M$4)) | N23: =IF($A23="","",SUMIFS(Data_EntMonth!$D:$D,Data_EntMonth!$A:$A,$A23,Data_EntMonth!$B:$B,N$4)) | O23: =IF($A23="","",SUMIFS(Data_EntMonth!$D:$D,Data_EntMonth!$A:$A,$A23,Data_EntMonth!$B:$B,O$4)) | ... S23: =IF($A23="","",SUMIFS(Data_EntMonth!$D:$D,Data_EntMonth!$A:$A,$A23,Data_EntMonth!$B:$B,S$4))
A24: =IF(INDEX(Data_Contracts!$A:$A,20+1)="","",INDEX(Data_Contracts!$A:$A,20+1)) | B24: =IF(INDEX(Data_Contracts!$C:$C,20+1)="","",INDEX(Data_Contracts!$C:$C,20+1)) | C24: =IF(INDEX(Data_Contracts!$D:$D,20+1)="","",INDEX(Data_Contracts!$D:$D,20+1)) | D24: =IF(INDEX(Data_Contracts!$E:$E,20+1)="","",INDEX(Data_Contracts!$E:$E,20+1)) | E24: =IF(INDEX(Data_Contracts!$F:$F,20+1)="","",INDEX(Data_Contracts!$F:$F,20+1)) | F24: =IF(OR($A24="",N($D24)=0),"",S24/$D24) | G24: =IF($A24="","",SUMIFS(Data_EntMonth!$F:$F,Data_EntMonth!$A:$A,$A24,Data_EntMonth!$B:$B,S$4)) | H24: =IF($A24="","",SUMIFS(Data_EntMonth!$D:$D,Data_EntMonth!$A:$A,$A24,Data_EntMonth!$B:$B,H$4)) | I24: =IF($A24="","",SUMIFS(Data_EntMonth!$D:$D,Data_EntMonth!$A:$A,$A24,Data_EntMonth!$B:$B,I$4)) | J24: =IF($A24="","",SUMIFS(Data_EntMonth!$D:$D,Data_EntMonth!$A:$A,$A24,Data_EntMonth!$B:$B,J$4)) | K24: =IF($A24="","",SUMIFS(Data_EntMonth!$D:$D,Data_EntMonth!$A:$A,$A24,Data_EntMonth!$B:$B,K$4)) | L24: =IF($A24="","",SUMIFS(Data_EntMonth!$D:$D,Data_EntMonth!$A:$A,$A24,Data_EntMonth!$B:$B,L$4)) | M24: =IF($A24="","",SUMIFS(Data_EntMonth!$D:$D,Data_EntMonth!$A:$A,$A24,Data_EntMonth!$B:$B,M$4)) | N24: =IF($A24="","",SUMIFS(Data_EntMonth!$D:$D,Data_EntMonth!$A:$A,$A24,Data_EntMonth!$B:$B,N$4)) | O24: =IF($A24="","",SUMIFS(Data_EntMonth!$D:$D,Data_EntMonth!$A:$A,$A24,Data_EntMonth!$B:$B,O$4)) | ... S24: =IF($A24="","",SUMIFS(Data_EntMonth!$D:$D,Data_EntMonth!$A:$A,$A24,Data_EntMonth!$B:$B,S$4))
A25: =IF(INDEX(Data_Contracts!$A:$A,21+1)="","",INDEX(Data_Contracts!$A:$A,21+1)) | B25: =IF(INDEX(Data_Contracts!$C:$C,21+1)="","",INDEX(Data_Contracts!$C:$C,21+1)) | C25: =IF(INDEX(Data_Contracts!$D:$D,21+1)="","",INDEX(Data_Contracts!$D:$D,21+1)) | D25: =IF(INDEX(Data_Contracts!$E:$E,21+1)="","",INDEX(Data_Contracts!$E:$E,21+1)) | E25: =IF(INDEX(Data_Contracts!$F:$F,21+1)="","",INDEX(Data_Contracts!$F:$F,21+1)) | F25: =IF(OR($A25="",N($D25)=0),"",S25/$D25) | G25: =IF($A25="","",SUMIFS(Data_EntMonth!$F:$F,Data_EntMonth!$A:$A,$A25,Data_EntMonth!$B:$B,S$4)) | H25: =IF($A25="","",SUMIFS(Data_EntMonth!$D:$D,Data_EntMonth!$A:$A,$A25,Data_EntMonth!$B:$B,H$4)) | I25: =IF($A25="","",SUMIFS(Data_EntMonth!$D:$D,Data_EntMonth!$A:$A,$A25,Data_EntMonth!$B:$B,I$4)) | J25: =IF($A25="","",SUMIFS(Data_EntMonth!$D:$D,Data_EntMonth!$A:$A,$A25,Data_EntMonth!$B:$B,J$4)) | K25: =IF($A25="","",SUMIFS(Data_EntMonth!$D:$D,Data_EntMonth!$A:$A,$A25,Data_EntMonth!$B:$B,K$4)) | L25: =IF($A25="","",SUMIFS(Data_EntMonth!$D:$D,Data_EntMonth!$A:$A,$A25,Data_EntMonth!$B:$B,L$4)) | M25: =IF($A25="","",SUMIFS(Data_EntMonth!$D:$D,Data_EntMonth!$A:$A,$A25,Data_EntMonth!$B:$B,M$4)) | N25: =IF($A25="","",SUMIFS(Data_EntMonth!$D:$D,Data_EntMonth!$A:$A,$A25,Data_EntMonth!$B:$B,N$4)) | O25: =IF($A25="","",SUMIFS(Data_EntMonth!$D:$D,Data_EntMonth!$A:$A,$A25,Data_EntMonth!$B:$B,O$4)) | ... S25: =IF($A25="","",SUMIFS(Data_EntMonth!$D:$D,Data_EntMonth!$A:$A,$A25,Data_EntMonth!$B:$B,S$4))
A26: =IF(INDEX(Data_Contracts!$A:$A,22+1)="","",INDEX(Data_Contracts!$A:$A,22+1)) | B26: =IF(INDEX(Data_Contracts!$C:$C,22+1)="","",INDEX(Data_Contracts!$C:$C,22+1)) | C26: =IF(INDEX(Data_Contracts!$D:$D,22+1)="","",INDEX(Data_Contracts!$D:$D,22+1)) | D26: =IF(INDEX(Data_Contracts!$E:$E,22+1)="","",INDEX(Data_Contracts!$E:$E,22+1)) | E26: =IF(INDEX(Data_Contracts!$F:$F,22+1)="","",INDEX(Data_Contracts!$F:$F,22+1)) | F26: =IF(OR($A26="",N($D26)=0),"",S26/$D26) | G26: =IF($A26="","",SUMIFS(Data_EntMonth!$F:$F,Data_EntMonth!$A:$A,$A26,Data_EntMonth!$B:$B,S$4)) | H26: =IF($A26="","",SUMIFS(Data_EntMonth!$D:$D,Data_EntMonth!$A:$A,$A26,Data_EntMonth!$B:$B,H$4)) | I26: =IF($A26="","",SUMIFS(Data_EntMonth!$D:$D,Data_EntMonth!$A:$A,$A26,Data_EntMonth!$B:$B,I$4)) | J26: =IF($A26="","",SUMIFS(Data_EntMonth!$D:$D,Data_EntMonth!$A:$A,$A26,Data_EntMonth!$B:$B,J$4)) | K26: =IF($A26="","",SUMIFS(Data_EntMonth!$D:$D,Data_EntMonth!$A:$A,$A26,Data_EntMonth!$B:$B,K$4)) | L26: =IF($A26="","",SUMIFS(Data_EntMonth!$D:$D,Data_EntMonth!$A:$A,$A26,Data_EntMonth!$B:$B,L$4)) | M26: =IF($A26="","",SUMIFS(Data_EntMonth!$D:$D,Data_EntMonth!$A:$A,$A26,Data_EntMonth!$B:$B,M$4)) | N26: =IF($A26="","",SUMIFS(Data_EntMonth!$D:$D,Data_EntMonth!$A:$A,$A26,Data_EntMonth!$B:$B,N$4)) | O26: =IF($A26="","",SUMIFS(Data_EntMonth!$D:$D,Data_EntMonth!$A:$A,$A26,Data_EntMonth!$B:$B,O$4)) | ... S26: =IF($A26="","",SUMIFS(Data_EntMonth!$D:$D,Data_EntMonth!$A:$A,$A26,Data_EntMonth!$B:$B,S$4))
A27: =IF(INDEX(Data_Contracts!$A:$A,23+1)="","",INDEX(Data_Contracts!$A:$A,23+1)) | B27: =IF(INDEX(Data_Contracts!$C:$C,23+1)="","",INDEX(Data_Contracts!$C:$C,23+1)) | C27: =IF(INDEX(Data_Contracts!$D:$D,23+1)="","",INDEX(Data_Contracts!$D:$D,23+1)) | D27: =IF(INDEX(Data_Contracts!$E:$E,23+1)="","",INDEX(Data_Contracts!$E:$E,23+1)) | E27: =IF(INDEX(Data_Contracts!$F:$F,23+1)="","",INDEX(Data_Contracts!$F:$F,23+1)) | F27: =IF(OR($A27="",N($D27)=0),"",S27/$D27) | G27: =IF($A27="","",SUMIFS(Data_EntMonth!$F:$F,Data_EntMonth!$A:$A,$A27,Data_EntMonth!$B:$B,S$4)) | H27: =IF($A27="","",SUMIFS(Data_EntMonth!$D:$D,Data_EntMonth!$A:$A,$A27,Data_EntMonth!$B:$B,H$4)) | I27: =IF($A27="","",SUMIFS(Data_EntMonth!$D:$D,Data_EntMonth!$A:$A,$A27,Data_EntMonth!$B:$B,I$4)) | J27: =IF($A27="","",SUMIFS(Data_EntMonth!$D:$D,Data_EntMonth!$A:$A,$A27,Data_EntMonth!$B:$B,J$4)) | K27: =IF($A27="","",SUMIFS(Data_EntMonth!$D:$D,Data_EntMonth!$A:$A,$A27,Data_EntMonth!$B:$B,K$4)) | L27: =IF($A27="","",SUMIFS(Data_EntMonth!$D:$D,Data_EntMonth!$A:$A,$A27,Data_EntMonth!$B:$B,L$4)) | M27: =IF($A27="","",SUMIFS(Data_EntMonth!$D:$D,Data_EntMonth!$A:$A,$A27,Data_EntMonth!$B:$B,M$4)) | N27: =IF($A27="","",SUMIFS(Data_EntMonth!$D:$D,Data_EntMonth!$A:$A,$A27,Data_EntMonth!$B:$B,N$4)) | O27: =IF($A27="","",SUMIFS(Data_EntMonth!$D:$D,Data_EntMonth!$A:$A,$A27,Data_EntMonth!$B:$B,O$4)) | ... S27: =IF($A27="","",SUMIFS(Data_EntMonth!$D:$D,Data_EntMonth!$A:$A,$A27,Data_EntMonth!$B:$B,S$4))
A28: =IF(INDEX(Data_Contracts!$A:$A,24+1)="","",INDEX(Data_Contracts!$A:$A,24+1)) | B28: =IF(INDEX(Data_Contracts!$C:$C,24+1)="","",INDEX(Data_Contracts!$C:$C,24+1)) | C28: =IF(INDEX(Data_Contracts!$D:$D,24+1)="","",INDEX(Data_Contracts!$D:$D,24+1)) | D28: =IF(INDEX(Data_Contracts!$E:$E,24+1)="","",INDEX(Data_Contracts!$E:$E,24+1)) | E28: =IF(INDEX(Data_Contracts!$F:$F,24+1)="","",INDEX(Data_Contracts!$F:$F,24+1)) | F28: =IF(OR($A28="",N($D28)=0),"",S28/$D28) | G28: =IF($A28="","",SUMIFS(Data_EntMonth!$F:$F,Data_EntMonth!$A:$A,$A28,Data_EntMonth!$B:$B,S$4)) | H28: =IF($A28="","",SUMIFS(Data_EntMonth!$D:$D,Data_EntMonth!$A:$A,$A28,Data_EntMonth!$B:$B,H$4)) | I28: =IF($A28="","",SUMIFS(Data_EntMonth!$D:$D,Data_EntMonth!$A:$A,$A28,Data_EntMonth!$B:$B,I$4)) | J28: =IF($A28="","",SUMIFS(Data_EntMonth!$D:$D,Data_EntMonth!$A:$A,$A28,Data_EntMonth!$B:$B,J$4)) | K28: =IF($A28="","",SUMIFS(Data_EntMonth!$D:$D,Data_EntMonth!$A:$A,$A28,Data_EntMonth!$B:$B,K$4)) | L28: =IF($A28="","",SUMIFS(Data_EntMonth!$D:$D,Data_EntMonth!$A:$A,$A28,Data_EntMonth!$B:$B,L$4)) | M28: =IF($A28="","",SUMIFS(Data_EntMonth!$D:$D,Data_EntMonth!$A:$A,$A28,Data_EntMonth!$B:$B,M$4)) | N28: =IF($A28="","",SUMIFS(Data_EntMonth!$D:$D,Data_EntMonth!$A:$A,$A28,Data_EntMonth!$B:$B,N$4)) | O28: =IF($A28="","",SUMIFS(Data_EntMonth!$D:$D,Data_EntMonth!$A:$A,$A28,Data_EntMonth!$B:$B,O$4)) | ... S28: =IF($A28="","",SUMIFS(Data_EntMonth!$D:$D,Data_EntMonth!$A:$A,$A28,Data_EntMonth!$B:$B,S$4))
A29: =IF(INDEX(Data_Contracts!$A:$A,25+1)="","",INDEX(Data_Contracts!$A:$A,25+1)) | B29: =IF(INDEX(Data_Contracts!$C:$C,25+1)="","",INDEX(Data_Contracts!$C:$C,25+1)) | C29: =IF(INDEX(Data_Contracts!$D:$D,25+1)="","",INDEX(Data_Contracts!$D:$D,25+1)) | D29: =IF(INDEX(Data_Contracts!$E:$E,25+1)="","",INDEX(Data_Contracts!$E:$E,25+1)) | E29: =IF(INDEX(Data_Contracts!$F:$F,25+1)="","",INDEX(Data_Contracts!$F:$F,25+1)) | F29: =IF(OR($A29="",N($D29)=0),"",S29/$D29) | G29: =IF($A29="","",SUMIFS(Data_EntMonth!$F:$F,Data_EntMonth!$A:$A,$A29,Data_EntMonth!$B:$B,S$4)) | H29: =IF($A29="","",SUMIFS(Data_EntMonth!$D:$D,Data_EntMonth!$A:$A,$A29,Data_EntMonth!$B:$B,H$4)) | I29: =IF($A29="","",SUMIFS(Data_EntMonth!$D:$D,Data_EntMonth!$A:$A,$A29,Data_EntMonth!$B:$B,I$4)) | J29: =IF($A29="","",SUMIFS(Data_EntMonth!$D:$D,Data_EntMonth!$A:$A,$A29,Data_EntMonth!$B:$B,J$4)) | K29: =IF($A29="","",SUMIFS(Data_EntMonth!$D:$D,Data_EntMonth!$A:$A,$A29,Data_EntMonth!$B:$B,K$4)) | L29: =IF($A29="","",SUMIFS(Data_EntMonth!$D:$D,Data_EntMonth!$A:$A,$A29,Data_EntMonth!$B:$B,L$4)) | M29: =IF($A29="","",SUMIFS(Data_EntMonth!$D:$D,Data_EntMonth!$A:$A,$A29,Data_EntMonth!$B:$B,M$4)) | N29: =IF($A29="","",SUMIFS(Data_EntMonth!$D:$D,Data_EntMonth!$A:$A,$A29,Data_EntMonth!$B:$B,N$4)) | O29: =IF($A29="","",SUMIFS(Data_EntMonth!$D:$D,Data_EntMonth!$A:$A,$A29,Data_EntMonth!$B:$B,O$4)) | ... S29: =IF($A29="","",SUMIFS(Data_EntMonth!$D:$D,Data_EntMonth!$A:$A,$A29,Data_EntMonth!$B:$B,S$4))
A30: =IF(INDEX(Data_Contracts!$A:$A,26+1)="","",INDEX(Data_Contracts!$A:$A,26+1)) | B30: =IF(INDEX(Data_Contracts!$C:$C,26+1)="","",INDEX(Data_Contracts!$C:$C,26+1)) | C30: =IF(INDEX(Data_Contracts!$D:$D,26+1)="","",INDEX(Data_Contracts!$D:$D,26+1)) | D30: =IF(INDEX(Data_Contracts!$E:$E,26+1)="","",INDEX(Data_Contracts!$E:$E,26+1)) | E30: =IF(INDEX(Data_Contracts!$F:$F,26+1)="","",INDEX(Data_Contracts!$F:$F,26+1)) | F30: =IF(OR($A30="",N($D30)=0),"",S30/$D30) | G30: =IF($A30="","",SUMIFS(Data_EntMonth!$F:$F,Data_EntMonth!$A:$A,$A30,Data_EntMonth!$B:$B,S$4)) | H30: =IF($A30="","",SUMIFS(Data_EntMonth!$D:$D,Data_EntMonth!$A:$A,$A30,Data_EntMonth!$B:$B,H$4)) | I30: =IF($A30="","",SUMIFS(Data_EntMonth!$D:$D,Data_EntMonth!$A:$A,$A30,Data_EntMonth!$B:$B,I$4)) | J30: =IF($A30="","",SUMIFS(Data_EntMonth!$D:$D,Data_EntMonth!$A:$A,$A30,Data_EntMonth!$B:$B,J$4)) | K30: =IF($A30="","",SUMIFS(Data_EntMonth!$D:$D,Data_EntMonth!$A:$A,$A30,Data_EntMonth!$B:$B,K$4)) | L30: =IF($A30="","",SUMIFS(Data_EntMonth!$D:$D,Data_EntMonth!$A:$A,$A30,Data_EntMonth!$B:$B,L$4)) | M30: =IF($A30="","",SUMIFS(Data_EntMonth!$D:$D,Data_EntMonth!$A:$A,$A30,Data_EntMonth!$B:$B,M$4)) | N30: =IF($A30="","",SUMIFS(Data_EntMonth!$D:$D,Data_EntMonth!$A:$A,$A30,Data_EntMonth!$B:$B,N$4)) | O30: =IF($A30="","",SUMIFS(Data_EntMonth!$D:$D,Data_EntMonth!$A:$A,$A30,Data_EntMonth!$B:$B,O$4)) | ... S30: =IF($A30="","",SUMIFS(Data_EntMonth!$D:$D,Data_EntMonth!$A:$A,$A30,Data_EntMonth!$B:$B,S$4))
A31: =IF(INDEX(Data_Contracts!$A:$A,27+1)="","",INDEX(Data_Contracts!$A:$A,27+1)) | B31: =IF(INDEX(Data_Contracts!$C:$C,27+1)="","",INDEX(Data_Contracts!$C:$C,27+1)) | C31: =IF(INDEX(Data_Contracts!$D:$D,27+1)="","",INDEX(Data_Contracts!$D:$D,27+1)) | D31: =IF(INDEX(Data_Contracts!$E:$E,27+1)="","",INDEX(Data_Contracts!$E:$E,27+1)) | E31: =IF(INDEX(Data_Contracts!$F:$F,27+1)="","",INDEX(Data_Contracts!$F:$F,27+1)) | F31: =IF(OR($A31="",N($D31)=0),"",S31/$D31) | G31: =IF($A31="","",SUMIFS(Data_EntMonth!$F:$F,Data_EntMonth!$A:$A,$A31,Data_EntMonth!$B:$B,S$4)) | H31: =IF($A31="","",SUMIFS(Data_EntMonth!$D:$D,Data_EntMonth!$A:$A,$A31,Data_EntMonth!$B:$B,H$4)) | I31: =IF($A31="","",SUMIFS(Data_EntMonth!$D:$D,Data_EntMonth!$A:$A,$A31,Data_EntMonth!$B:$B,I$4)) | J31: =IF($A31="","",SUMIFS(Data_EntMonth!$D:$D,Data_EntMonth!$A:$A,$A31,Data_EntMonth!$B:$B,J$4)) | K31: =IF($A31="","",SUMIFS(Data_EntMonth!$D:$D,Data_EntMonth!$A:$A,$A31,Data_EntMonth!$B:$B,K$4)) | L31: =IF($A31="","",SUMIFS(Data_EntMonth!$D:$D,Data_EntMonth!$A:$A,$A31,Data_EntMonth!$B:$B,L$4)) | M31: =IF($A31="","",SUMIFS(Data_EntMonth!$D:$D,Data_EntMonth!$A:$A,$A31,Data_EntMonth!$B:$B,M$4)) | N31: =IF($A31="","",SUMIFS(Data_EntMonth!$D:$D,Data_EntMonth!$A:$A,$A31,Data_EntMonth!$B:$B,N$4)) | O31: =IF($A31="","",SUMIFS(Data_EntMonth!$D:$D,Data_EntMonth!$A:$A,$A31,Data_EntMonth!$B:$B,O$4)) | ... S31: =IF($A31="","",SUMIFS(Data_EntMonth!$D:$D,Data_EntMonth!$A:$A,$A31,Data_EntMonth!$B:$B,S$4))
A32: =IF(INDEX(Data_Contracts!$A:$A,28+1)="","",INDEX(Data_Contracts!$A:$A,28+1)) | B32: =IF(INDEX(Data_Contracts!$C:$C,28+1)="","",INDEX(Data_Contracts!$C:$C,28+1)) | C32: =IF(INDEX(Data_Contracts!$D:$D,28+1)="","",INDEX(Data_Contracts!$D:$D,28+1)) | D32: =IF(INDEX(Data_Contracts!$E:$E,28+1)="","",INDEX(Data_Contracts!$E:$E,28+1)) | E32: =IF(INDEX(Data_Contracts!$F:$F,28+1)="","",INDEX(Data_Contracts!$F:$F,28+1)) | F32: =IF(OR($A32="",N($D32)=0),"",S32/$D32) | G32: =IF($A32="","",SUMIFS(Data_EntMonth!$F:$F,Data_EntMonth!$A:$A,$A32,Data_EntMonth!$B:$B,S$4)) | H32: =IF($A32="","",SUMIFS(Data_EntMonth!$D:$D,Data_EntMonth!$A:$A,$A32,Data_EntMonth!$B:$B,H$4)) | I32: =IF($A32="","",SUMIFS(Data_EntMonth!$D:$D,Data_EntMonth!$A:$A,$A32,Data_EntMonth!$B:$B,I$4)) | J32: =IF($A32="","",SUMIFS(Data_EntMonth!$D:$D,Data_EntMonth!$A:$A,$A32,Data_EntMonth!$B:$B,J$4)) | K32: =IF($A32="","",SUMIFS(Data_EntMonth!$D:$D,Data_EntMonth!$A:$A,$A32,Data_EntMonth!$B:$B,K$4)) | L32: =IF($A32="","",SUMIFS(Data_EntMonth!$D:$D,Data_EntMonth!$A:$A,$A32,Data_EntMonth!$B:$B,L$4)) | M32: =IF($A32="","",SUMIFS(Data_EntMonth!$D:$D,Data_EntMonth!$A:$A,$A32,Data_EntMonth!$B:$B,M$4)) | N32: =IF($A32="","",SUMIFS(Data_EntMonth!$D:$D,Data_EntMonth!$A:$A,$A32,Data_EntMonth!$B:$B,N$4)) | O32: =IF($A32="","",SUMIFS(Data_EntMonth!$D:$D,Data_EntMonth!$A:$A,$A32,Data_EntMonth!$B:$B,O$4)) | ... S32: =IF($A32="","",SUMIFS(Data_EntMonth!$D:$D,Data_EntMonth!$A:$A,$A32,Data_EntMonth!$B:$B,S$4))
A33: =IF(INDEX(Data_Contracts!$A:$A,29+1)="","",INDEX(Data_Contracts!$A:$A,29+1)) | B33: =IF(INDEX(Data_Contracts!$C:$C,29+1)="","",INDEX(Data_Contracts!$C:$C,29+1)) | C33: =IF(INDEX(Data_Contracts!$D:$D,29+1)="","",INDEX(Data_Contracts!$D:$D,29+1)) | D33: =IF(INDEX(Data_Contracts!$E:$E,29+1)="","",INDEX(Data_Contracts!$E:$E,29+1)) | E33: =IF(INDEX(Data_Contracts!$F:$F,29+1)="","",INDEX(Data_Contracts!$F:$F,29+1)) | F33: =IF(OR($A33="",N($D33)=0),"",S33/$D33) | G33: =IF($A33="","",SUMIFS(Data_EntMonth!$F:$F,Data_EntMonth!$A:$A,$A33,Data_EntMonth!$B:$B,S$4)) | H33: =IF($A33="","",SUMIFS(Data_EntMonth!$D:$D,Data_EntMonth!$A:$A,$A33,Data_EntMonth!$B:$B,H$4)) | I33: =IF($A33="","",SUMIFS(Data_EntMonth!$D:$D,Data_EntMonth!$A:$A,$A33,Data_EntMonth!$B:$B,I$4)) | J33: =IF($A33="","",SUMIFS(Data_EntMonth!$D:$D,Data_EntMonth!$A:$A,$A33,Data_EntMonth!$B:$B,J$4)) | K33: =IF($A33="","",SUMIFS(Data_EntMonth!$D:$D,Data_EntMonth!$A:$A,$A33,Data_EntMonth!$B:$B,K$4)) | L33: =IF($A33="","",SUMIFS(Data_EntMonth!$D:$D,Data_EntMonth!$A:$A,$A33,Data_EntMonth!$B:$B,L$4)) | M33: =IF($A33="","",SUMIFS(Data_EntMonth!$D:$D,Data_EntMonth!$A:$A,$A33,Data_EntMonth!$B:$B,M$4)) | N33: =IF($A33="","",SUMIFS(Data_EntMonth!$D:$D,Data_EntMonth!$A:$A,$A33,Data_EntMonth!$B:$B,N$4)) | O33: =IF($A33="","",SUMIFS(Data_EntMonth!$D:$D,Data_EntMonth!$A:$A,$A33,Data_EntMonth!$B:$B,O$4)) | ... S33: =IF($A33="","",SUMIFS(Data_EntMonth!$D:$D,Data_EntMonth!$A:$A,$A33,Data_EntMonth!$B:$B,S$4))
